Workbook

Sheet README
A1: SLIC Scoring Workbook
A3: Purpose | B3: This workbook is the operational source of truth for the global SLIC city ranking. Enter or import data into Country_Context and City_Inputs, then review Scores, Leaderboard, Region_Comparison, and the Thai-specific scaffold.
A4: Official formula | B4: SLIC(c) = 0.25 Pressure + 0.22 Viability + 0.18 Capability + 0.15 Community + 0.20 Creative
A5: Disposable income term | B5: DI_ppp = ((gross_income x (1 - tax_rate)) - rent - utilities - transit - internet - food) / ppp_private_consumption
A6: Normalization | B6: Each scored input is winsorized at the 5th and 95th percentiles, then converted to a 0-100 score. Harmful variables such as crime, debt, suicide, PM2.5, and administrative friction are reverse-scored.
A7: Coverage rules | B7: A city is Ranked only when overall weighted coverage is at least 50% and every pillar clears the 35% minimum. Coverage grades: A >= 75%, B = 50-74%, C = 35-49%, below 35% = Watchlist.
A8: Source hierarchy | B8: Tier 1 city/metro official data > Tier 2 subnational official data > Tier 3 national and international official data > Tier 4 audited secondary and experimental layers.
A9: Doctrinal rule: safety | B9: Safety is scored by harm and victimization outcomes, never by camera count or visible control hardware.
A10: Doctrinal rule: tolerance | B10: Tolerance is scored through low-friction coexistence and real personal freedom, not symbolic branding proxies.
A11: Doctrinal rule: visitor flows | B11: Visitor flow is contextual only. It should be reviewed against crime, civic strain, and public-life quality rather than treated as an automatic positive.
A12: Country context | B12: GDP per capita PPP, GDP growth, Gini coefficient, PPP private consumption, and user-supplied tax rate are visible in Country_Context. GDP terms are capped context inputs, not headline determinants.
A13: How tax works | B13: Populate tax_rate_assumption in Country_Context as a decimal such as 0.18. City_Inputs pulls that value automatically into tax_rate_context and recomputes di_ppp_raw.
A14: Region comparison | B14: Region_Comparison summarizes ranked city counts and average scores by cohort so Europe, Asia, the Americas, Africa, the Middle East, and Oceania can be compared cleanly.
A15: Thai companion | B15: Thai_Ranking_Scaffold is a separate sheet for a Thailand-only ranking. It emphasizes province GDP per capita, pollution, hospitals, schools, infrastructure, income, longevity, and competitiveness.
A18: Coverage thresholds
A19: ranked_min_overall | B19: 0.5
A20: ranked_min_pillar | B20: 0.35
A21: grade_a_min | B21: 0.75
A22: grade_b_min | B22: 0.5
A23: grade_c_min | B23: 0.35
A26: Source tiers
A27: Tier 1 | B27: City and metro official data | C27: Open-data portals, utility regulators, transit feeds, hospital quality releases, and city statistical offices.
A28: Tier 2 | B28: State, province, and subnational official data | C28: Regional statistical offices, metropolitan observatories, and subnational administrative datasets.
A29: Tier 3 | B29: National and international official datasets | C29: World Bank, WHO, ILO, UNESCO UIS, OECD, WIPO, and WHO/UNICEF JMP.
A30: Tier 4 | B30: Audited secondary and experimental layers | C30: OpenAQ, M-Lab, social listening, crowdsourced cost layers, and city testimony with visible caveats.

Sheet Metric_Catalog
A1: metric_id | B1: metric_name | C1: pillar_id | D1: pillar_name | E1: pillar_weight | F1: metric_weight | G1: directionality | H1: scoring_role | I1: requiredness | J1: data_level | K1: source_priority | L1: workbook_input | M1: notes
A2: disposable_income_ppp | B2: Tax-adjusted PPP disposable income | C2: pressure | D2: Growth | E2: 25 | F2: 9 | G2: positive | H2: scored | I2: core | J2: city_or_metro_with_country_context | K2: Tier 1 city/metro > Tier 2 subnational > Tier 3 national/international > Tier 4 audited secondary | L2: di_ppp_raw | M2: Derived from gross income, tax, rent, utilities, transit, internet, food, and PPP private consumption.
A3: housing_burden | B3: Housing burden | C3: pressure | D3: Growth | E3: 25 | F3: 5 | G3: negative | H3: scored | I3: core | J3: city_or_metro | K3: Tier 1 city/metro > Tier 2 subnational > Tier 3 national/international > Tier 4 audited secondary | L3: housing_burden_raw | M3: Higher rent or housing cost share scores worse.
A4: household_debt_burden | B4: Household debt burden | C4: pressure | D4: Growth | E4: 25 | F4: 4 | G4: negative | H4: scored | I4: core | J4: city_with_country_proxy_fallback | K4: Tier 1 city/metro > Tier 2 subnational > Tier 3 country debt proxy > Tier 4 audited secondary | L4: household_debt_effective_raw | M4: Uses country proxy when city debt burden is unavailable.
A5: working_time_pressure | B5: Working time pressure | C5: pressure | D5: Growth | E5: 25 | F5: 4 | G5: negative | H5: scored | I5: core | J5: city_or_metro_with_subnational_fallback | K5: Tier 1 city/metro > Tier 2 subnational > Tier 3 ILO/national > Tier 4 audited secondary | L5: working_time_pressure_raw | M5: Higher weekly-hours and overwork prevalence score worse.
A6: suicide_mental_strain | B6: Suicide and severe mental strain | C6: pressure | D6: Growth | E6: 25 | F6: 5 | G6: negative | H6: scored | I6: core | J6: city_or_metro_with_subnational_fallback | K6: Tier 1 city/metro > Tier 2 subnational > Tier 3 WHO/national > Tier 4 audited secondary | L6: suicide_mental_strain_raw | M6: Lower suicide or equivalent severe-strain rates score better. Weight increased to 5 to better capture mental wellbeing burden.
A7: personal_safety | B7: Personal safety | C7: viability | D7: Viability | E7: 22 | F7: 5 | G7: negative | H7: scored | I7: core | J7: city_or_metro | K7: Tier 1 city/metro > Tier 2 subnational > Tier 3 national/international > Tier 4 audited secondary | L7: personal_safety_raw | M7: Enter a harm-and-victimization index or rate. Camera counts do not score.
A8: transit_access_commute | B8: Transit access and commute burden | C8: viability | D8: Viability | E8: 22 | F8: 5 | G8: positive | H8: scored | I8: core | J8: city_or_metro | K8: Tier 1 city/metro > Tier 2 GTFS/subnational > Tier 3 national/international > Tier 4 audited secondary | L8: transit_access_commute_raw | M8: Enter a composite where better access and lower burden push the value upward.
A9: clean_air | B9: Clean air | C9: viability | D9: Viability | E9: 22 | F9: 4 | G9: negative | H9: scored | I9: core | J9: city_or_metro | K9: Tier 1 city/metro > Tier 3 WHO/OpenAQ/national > Tier 4 audited secondary | L9: clean_air_raw | M9: Lower PM2.5 or pollution exposure scores better.
A10: water_sanitation_utility | B10: Water, sanitation, and utility reliability | C10: viability | D10: Viability | E10: 22 | F10: 4 | G10: positive | H10: scored | I10: core | J10: city_or_metro_with_country_fallback | K10: Tier 1 city/metro > Tier 2 subnational > Tier 3 JMP/national > Tier 4 audited secondary | L10: water_sanitation_utility_raw | M10: Enter a composite where safer access and higher reliability score better.
A11: digital_infrastructure | B11: Digital infrastructure | C11: viability | D11: Viability | E11: 22 | F11: 4 | G11: positive | H11: scored | I11: core | J11: city_or_metro_with_country_fallback | K11: Tier 1 city/metro > Tier 2 subnational > Tier 3 OECD/World Bank/M-Lab > Tier 4 audited secondary | L11: digital_infrastructure_raw | M11: Higher broadband quality, affordability, and fibre readiness score better.
A12: climate_sunlight_livability | B12: Climate and sunlight livability | C12: viability | D12: Viability | E12: 22 | F12: 5 | G12: positive | H12: scored | I12: core | J12: city_or_metro | K12: Tier 1 city/metro climate data > Tier 3 WMO/national > Tier 4 audited secondary | L12: climate_sunlight_livability_raw | M12: Composite of annual sunshine hours, temperature comfort (distance from 22C optimum), and extreme weather frequency. Penalizes both extreme darkness (Nordic winter) and extreme heat (Gulf/desert). Higher = more livable climate.
A13: healthcare_quality | B13: Healthcare quality | C13: capability | D13: Capability | E13: 18 | F13: 8 | G13: positive | H13: scored | I13: core | J13: city_or_metro_with_country_context | K13: Tier 1 city/metro > Tier 2 subnational > Tier 3 WHO/OECD/national > Tier 4 audited secondary | L13: healthcare_quality_raw | M13: Higher effective-care access and outcome quality score better.
... A27: birth_rate_optimism | B27: Birth rate and societal optimism | C27: community | D27: Community | E27: 15 | F27: 4 | G27: positive | H27: scored | I27: core | J27: country_proxy_or_city | K27: Tier 1 city/metro > Tier 3 national/international | L27: birth_rate_optimism_raw | M27: Total fertility rate or crude birth rate as proxy for societal optimism and family-friendliness.

Sheet City_Universe
A1: city_id | B1: display_name | C1: fua_name | D1: country | E1: cohort | F1: city_type | G1: manifest_status | H1: inclusion_rationale
A2: th-bangkok | B2: Bangkok | C2: Bangkok Metropolitan Region | D2: Thailand | E2: Southeast Asia | F2: primary | G2: locked | H2: User anchor and regional benchmark for hospitality, economic dynamism, and affordability-pressure tradeoffs.
A3: sg-singapore | B3: Singapore | C3: Singapore | D3: Singapore | E3: Southeast Asia | F3: primary | G3: locked | H3: Global convenience benchmark included to test how systems quality interacts with pressure, cost, and meaning.
A4: my-kuala-lumpur | B4: Kuala Lumpur | C4: Klang Valley | D4: Malaysia | E4: Southeast Asia | F4: primary | G4: locked | H4: User anchor and regional economic core with strong competitiveness, connectivity, and mixed affordability.
A5: id-jakarta | B5: Jakarta | C5: Jakarta Metropolitan Area | D5: Indonesia | E5: Southeast Asia | F5: primary | G5: provisional | H5: Necessary Southeast Asian benchmark for scale, competitiveness, and infrastructure-pressure tradeoffs.
A6: ph-makati | B6: Makati | C6: Metro Manila Core Business District | D6: Philippines | E6: Southeast Asia | F6: primary | G6: provisional | H6: Metro-core Philippine test case included for business density, services, and lived-affordability stress.
A7: my-george-town | B7: George Town | C7: Penang Conurbation | D7: Malaysia | E7: Southeast Asia | F7: secondary | G7: locked | H7: User anchor for semiconductor economy, cultural texture, and secondary-city livability.
A8: th-phuket | B8: Phuket | C8: Phuket Island Urban Area | D8: Thailand | E8: Southeast Asia | F8: secondary | G8: locked | H8: User anchor and tourism-livability stress test for cost, safety, and service quality.
A9: th-chiang-mai | B9: Chiang Mai | C9: Chiang Mai Metropolitan Area | D9: Thailand | E9: Southeast Asia | F9: secondary | G9: locked | H9: User anchor for creativity, secondary-city ambition, and lifestyle viability.
A10: my-kuching | B10: Kuching | C10: Greater Kuching | D10: Malaysia | E10: Southeast Asia | F10: secondary | G10: locked | H10: User anchor included as a calmer secondary-city comparator with strong everyday livability appeal.
A11: my-kota-kinabalu | B11: Kota Kinabalu | C11: Kota Kinabalu Urban Area | D11: Malaysia | E11: Southeast Asia | F11: secondary | G11: provisional | H11: User anchor — nature tourism, safety, and affordable livability on Borneo's coast.
A12: my-melaka | B12: Melaka | C12: Melaka Urban Area | D12: Malaysia | E12: Southeast Asia | F12: secondary | G12: provisional | H12: User anchor — deep cultural heritage, food scene, and underrated livability.
... A158: vu-port-vila | B158: Port Vila | C158: Greater Port Vila | D158: Vanuatu | E158: Oceania | F158: primary | G158: provisional | H158: Reserve Pacific capital comparator added for tourism, climate exposure, and utility-reliability benchmarking.

Sheet Country_Context
A1: country | B1: gdp_per_capita_ppp | C1: gdp_growth | D1: gini_coefficient | E1: ppp_private_consumption | F1: tax_rate_assumption | G1: household_debt_proxy | H1: source_url | I1: source_tier | J1: update_date | K1: notes
A2: Thailand | B2: 24712.07 | C2: 2.5418 | D2: 33.5 | E2: 10.945576 | F2: 0.152577 | G2: 115.1054 | H2: https://api.worldbank.org/v2/country/THA/indicator/NY.GDP.PCAP.PP.CD?format=json&mrv=30 | https://api.worldbank.org/v2/country/THA/indicator/NY.GDP.MKTP.KD.ZG?format=json&mrv=30 | https://api.worldbank.org/v2/country/THA/indicator/SI.POV.GINI?format=json&mrv=30 | +3 more | I2: Tier 3 | J2: 2024-12-31 | K2: providers=world_bank; fields=gdp_per_capita_ppp, gdp_growth, gini_coefficient, ppp_private_consumption; +2 additional fields
A3: Singapore | B3: 150689.3 | C3: 4.388 | E3: 1.04203 | F3: 0.141917 | G3: 129.1908 | H3: https://api.worldbank.org/v2/country/SGP/indicator/NY.GDP.PCAP.PP.CD?format=json&mrv=30 | https://api.worldbank.org/v2/country/SGP/indicator/NY.GDP.MKTP.KD.ZG?format=json&mrv=30 | https://api.worldbank.org/v2/country/SGP/indicator/PA.NUS.PRVT.PP?format=json&mrv=30 | +2 more | I3: Tier 3 | J3: 2024-12-31 | K3: providers=world_bank; fields=gdp_per_capita_ppp, gdp_growth, ppp_private_consumption, tax_rate_assumption; +1 additional fields
A4: Malaysia | B4: 38779.28 | C4: 5.1055 | D4: 40.7 | E4: 1.449227 | F4: 0.125648 | G4: 116.0773 | H4: https://api.worldbank.org/v2/country/MYS/indicator/NY.GDP.PCAP.PP.CD?format=json&mrv=30 | https://api.worldbank.org/v2/country/MYS/indicator/NY.GDP.MKTP.KD.ZG?format=json&mrv=30 | https://api.worldbank.org/v2/country/MYS/indicator/SI.POV.GINI?format=json&mrv=30 | +3 more | I4: Tier 3 | J4: 2024-12-31 | K4: providers=world_bank; fields=gdp_per_capita_ppp, gdp_growth, gini_coefficient, ppp_private_consumption; +2 additional fields
A5: Indonesia | B5: 16448.28 | C5: 5.0303 | D5: 34.9 | E5: 5104.9843 | F5: 0.110578 | G5: 31.7861 | H5: https://api.worldbank.org/v2/country/IDN/indicator/NY.GDP.PCAP.PP.CD?format=json&mrv=30 | https://api.worldbank.org/v2/country/IDN/indicator/NY.GDP.MKTP.KD.ZG?format=json&mrv=30 | https://api.worldbank.org/v2/country/IDN/indicator/SI.POV.GINI?format=json&mrv=30 | +3 more | I5: Tier 3 | J5: 2024-12-31 | K5: providers=world_bank; fields=gdp_per_capita_ppp, gdp_growth, gini_coefficient, ppp_private_consumption; +2 additional fields
A6: Philippines | B6: 11794.14 | C6: 5.692 | D6: 39.3 | E6: 20.743506 | F6: 0.141044 | G6: 49.8137 | H6: https://api.worldbank.org/v2/country/PHL/indicator/NY.GDP.PCAP.PP.CD?format=json&mrv=30 | https://api.worldbank.org/v2/country/PHL/indicator/NY.GDP.MKTP.KD.ZG?format=json&mrv=30 | https://api.worldbank.org/v2/country/PHL/indicator/SI.POV.GINI?format=json&mrv=30 | +3 more | I6: Tier 3 | J6: 2024-12-31 | K6: providers=world_bank; fields=gdp_per_capita_ppp, gdp_growth, gini_coefficient, ppp_private_consumption; +2 additional fields
A7: Taiwan | K7: Populate official country context inputs before ranking.
A8: South Korea | B8: 61051.35 | C8: 2.0036 | D8: 32.9 | E8: 872.46874 | F8: 0.145991 | G8: 160.3472 | H8: https://api.worldbank.org/v2/country/KOR/indicator/NY.GDP.PCAP.PP.CD?format=json&mrv=30 | https://api.worldbank.org/v2/country/KOR/indicator/NY.GDP.MKTP.KD.ZG?format=json&mrv=30 | https://api.worldbank.org/v2/country/KOR/indicator/SI.POV.GINI?format=json&mrv=30 | +3 more | I8: Tier 3 | J8: 2024-12-31 | K8: providers=world_bank; fields=gdp_per_capita_ppp, gdp_growth, gini_coefficient, ppp_private_consumption; +2 additional fields
A9: China | B9: 27104.87 | C9: 4.9774 | D9: 36 | E9: 3.550789 | F9: 0.076382 | G9: 194.166 | H9: https://api.worldbank.org/v2/country/CHN/indicator/NY.GDP.PCAP.PP.CD?format=json&mrv=30 | https://api.worldbank.org/v2/country/CHN/indicator/NY.GDP.MKTP.KD.ZG?format=json&mrv=30 | https://api.worldbank.org/v2/country/CHN/indicator/SI.POV.GINI?format=json&mrv=30 | +3 more | I9: Tier 3 | J9: 2024-12-31 | K9: providers=world_bank; fields=gdp_per_capita_ppp, gdp_growth, gini_coefficient, ppp_private_consumption; +2 additional fields
A10: Japan | B10: 52039.17 | C10: 0.1043 | D10: 32.3 | E10: 99.384798 | G10: 123.1289 | H10: https://api.worldbank.org/v2/country/JPN/indicator/NY.GDP.PCAP.PP.CD?format=json&mrv=30 | https://api.worldbank.org/v2/country/JPN/indicator/NY.GDP.MKTP.KD.ZG?format=json&mrv=30 | https://api.worldbank.org/v2/country/JPN/indicator/SI.POV.GINI?format=json&mrv=30 | +2 more | I10: Tier 3 | J10: 2024-12-31 | K10: providers=world_bank; fields=gdp_per_capita_ppp, gdp_growth, gini_coefficient, ppp_private_consumption; +1 additional fields
A11: India | B11: 11159.99 | C11: 6.4948 | D11: 25.5 | E11: 19.896916 | F11: 0.067344 | G11: 50.1422 | H11: https://api.worldbank.org/v2/country/IND/indicator/NY.GDP.PCAP.PP.CD?format=json&mrv=30 | https://api.worldbank.org/v2/country/IND/indicator/NY.GDP.MKTP.KD.ZG?format=json&mrv=30 | https://api.worldbank.org/v2/country/IND/indicator/SI.POV.GINI?format=json&mrv=30 | +3 more | I11: Tier 3 | J11: 2024-12-31 | K11: providers=world_bank; fields=gdp_per_capita_ppp, gdp_growth, gini_coefficient, ppp_private_consumption; +2 additional fields
A12: Sri Lanka | B12: 15632.59 | C12: 5.0087 | D12: 37.7 | E12: 87.489315 | F12: 0.099219 | G12: 46.8716 | H12: https://api.worldbank.org/v2/country/LKA/indicator/NY.GDP.PCAP.PP.CD?format=json&mrv=30 | https://api.worldbank.org/v2/country/LKA/indicator/NY.GDP.MKTP.KD.ZG?format=json&mrv=30 | https://api.worldbank.org/v2/country/LKA/indicator/SI.POV.GINI?format=json&mrv=30 | +3 more | I12: Tier 3 | J12: 2024-12-31 | K12: providers=world_bank; fields=gdp_per_capita_ppp, gdp_growth, gini_coefficient, ppp_private_consumption; +2 additional fields
A13: Bangladesh | B13: 9646.77 | C13: 4.2233 | D13: 30.9 | E13: 32.990539 | F13: 0.076424 | G13: 35.7061 | H13: https://api.worldbank.org/v2/country/BGD/indicator/NY.GDP.PCAP.PP.CD?format=json&mrv=30 | https://api.worldbank.org/v2/country/BGD/indicator/NY.GDP.MKTP.KD.ZG?format=json&mrv=30 | https://api.worldbank.org/v2/country/BGD/indicator/SI.POV.GINI?format=json&mrv=30 | +3 more | I13: Tier 3 | J13: 2024-12-31 | K13: providers=world_bank; fields=gdp_per_capita_ppp, gdp_growth, gini_coefficient, ppp_private_consumption; +2 additional fields
A14: Pakistan | B14: 6252.12 | C14: 3.049 | D14: 29.6 | E14: 64.860994 | G14: 11.3901 | H14: https://api.worldbank.org/v2/country/PAK/indicator/NY.GDP.PCAP.PP.CD?format=json&mrv=30 | https://api.worldbank.org/v2/country/PAK/indicator/NY.GDP.MKTP.KD.ZG?format=json&mrv=30 | https://api.worldbank.org/v2/country/PAK/indicator/SI.POV.GINI?format=json&mrv=30 | +2 more | I14: Tier 3 | J14: 2024-12-31 | K14: providers=world_bank; fields=gdp_per_capita_ppp, gdp_growth, gini_coefficient, ppp_private_consumption; +1 additional fields
A15: Nepal | B15: 5736.62 | C15: 3.6654 | D15: 30 | E15: 35.285741 | F15: 0.139449 | G15: 91.9385 | H15: https://api.worldbank.org/v2/country/NPL/indicator/NY.GDP.PCAP.PP.CD?format=json&mrv=30 | https://api.worldbank.org/v2/country/NPL/indicator/NY.GDP.MKTP.KD.ZG?format=json&mrv=30 | https://api.worldbank.org/v2/country/NPL/indicator/SI.POV.GINI?format=json&mrv=30 | +3 more | I15: Tier 3 | J15: 2024-12-31 | K15: providers=world_bank; fields=gdp_per_capita_ppp, gdp_growth, gini_coefficient, ppp_private_consumption; +2 additional fields
A16: Bhutan | B16: 16215.15 | C16: 4.6322 | D16: 28.5 | E16: 20.878112 | F16: 0.122846 | G16: 51.8935 | H16: https://api.worldbank.org/v2/country/BTN/indicator/NY.GDP.PCAP.PP.CD?format=json&mrv=30 | https://api.worldbank.org/v2/country/BTN/indicator/NY.GDP.MKTP.KD.ZG?format=json&mrv=30 | https://api.worldbank.org/v2/country/BTN/indicator/SI.POV.GINI?format=json&mrv=30 | +3 more | I16: Tier 3 | J16: 2024-12-31 | K16: providers=world_bank; fields=gdp_per_capita_ppp, gdp_growth, gini_coefficient, ppp_private_consumption; +2 additional fields
A17: Maldives | B17: 26182.78 | C17: 3.4944 | D17: 29.3 | E17: 9.455282 | F17: 0.194532 | G17: 31.5415 | H17: https://api.worldbank.org/v2/country/MDV/indicator/NY.GDP.PCAP.PP.CD?format=json&mrv=30 | https://api.worldbank.org/v2/country/MDV/indicator/NY.GDP.MKTP.KD.ZG?format=json&mrv=30 | https://api.worldbank.org/v2/country/MDV/indicator/SI.POV.GINI?format=json&mrv=30 | +3 more | I17: Tier 3 | J17: 2024-12-31 | K17: providers=world_bank; fields=gdp_per_capita_ppp, gdp_growth, gini_coefficient, ppp_private_consumption; +2 additional fields
A18: France | B18: 62556.92 | C18: 1.1905 | D18: 31.8 | E18: 0.716934 | F18: 0.23077 | G18: 103.9081 | H18: https://api.worldbank.org/v2/country/FRA/indicator/NY.GDP.PCAP.PP.CD?format=json&mrv=30 | https://api.worldbank.org/v2/country/FRA/indicator/NY.GDP.MKTP.KD.ZG?format=json&mrv=30 | https://api.worldbank.org/v2/country/FRA/indicator/SI.POV.GINI?format=json&mrv=30 | +3 more | I18: Tier 3 | J18: 2024-12-31 | K18: providers=world_bank; fields=gdp_per_capita_ppp, gdp_growth, gini_coefficient, ppp_private_consumption; +2 additional fields
A19: Austria | B19: 73911.44 | C19: -0.6591 | D19: 31.2 | E19: 0.720487 | F19: 0.256407 | G19: 81.4953 | H19: https://api.worldbank.org/v2/country/AUT/indicator/NY.GDP.PCAP.PP.CD?format=json&mrv=30 | https://api.worldbank.org/v2/country/AUT/indicator/NY.GDP.MKTP.KD.ZG?format=json&mrv=30 | https://api.worldbank.org/v2/country/AUT/indicator/SI.POV.GINI?format=json&mrv=30 | +3 more | I19: Tier 3 | J19: 2024-12-31 | K19: providers=world_bank; fields=gdp_per_capita_ppp, gdp_growth, gini_coefficient, ppp_private_consumption; +2 additional fields
A20: Switzerland | B20: 96497.69 | C20: 1.3023 | D20: 33.8 | E20: 1.062369 | F20: 0.090036 | G20: 170.3782 | H20: https://api.worldbank.org/v2/country/CHE/indicator/NY.GDP.PCAP.PP.CD?format=json&mrv=30 | https://api.worldbank.org/v2/country/CHE/indicator/NY.GDP.MKTP.KD.ZG?format=json&mrv=30 | https://api.worldbank.org/v2/country/CHE/indicator/SI.POV.GINI?format=json&mrv=30 | +3 more | I20: Tier 3 | J20: 2024-12-31 | K20: providers=world_bank; fields=gdp_per_capita_ppp, gdp_growth, gini_coefficient, ppp_private_consumption; +2 additional fields
A21: Netherlands | B21: 86173.63 | C21: 1.081 | D21: 25.7 | E21: 0.74195 | F21: 0.25254 | G21: 82.3297 | H21: https://api.worldbank.org/v2/country/NLD/indicator/NY.GDP.PCAP.PP.CD?format=json&mrv=30 | https://api.worldbank.org/v2/country/NLD/indicator/NY.GDP.MKTP.KD.ZG?format=json&mrv=30 | https://api.worldbank.org/v2/country/NLD/indicator/SI.POV.GINI?format=json&mrv=30 | +3 more | I21: Tier 3 | J21: 2024-12-31 | K21: providers=world_bank; fields=gdp_per_capita_ppp, gdp_growth, gini_coefficient, ppp_private_consumption; +2 additional fields
A22: Denmark | B22: 81878.23 | C22: 3.4778 | D22: 29.9 | E22: 6.764411 | F22: 0.315935 | G22: 144.0931 | H22: https://api.worldbank.org/v2/country/DNK/indicator/NY.GDP.PCAP.PP.CD?format=json&mrv=30 | https://api.worldbank.org/v2/country/DNK/indicator/NY.GDP.MKTP.KD.ZG?format=json&mrv=30 | https://api.worldbank.org/v2/country/DNK/indicator/SI.POV.GINI?format=json&mrv=30 | +3 more | I22: Tier 3 | J22: 2024-12-31 | K22: providers=world_bank; fields=gdp_per_capita_ppp, gdp_growth, gini_coefficient, ppp_private_consumption; +2 additional fields
A23: Italy | B23: 62014.27 | C23: 0.6927 | D23: 34.3 | E23: 0.625157 | F23: 0.24708 | G23: 59.3116 | H23: https://api.worldbank.org/v2/country/ITA/indicator/NY.GDP.PCAP.PP.CD?format=json&mrv=30 | https://api.worldbank.org/v2/country/ITA/indicator/NY.GDP.MKTP.KD.ZG?format=json&mrv=30 | https://api.worldbank.org/v2/country/ITA/indicator/SI.POV.GINI?format=json&mrv=30 | +3 more | I23: Tier 3 | J23: 2024-12-31 | K23: providers=world_bank; fields=gdp_per_capita_ppp, gdp_growth, gini_coefficient, ppp_private_consumption; +2 additional fields
A24: Portugal | B24: 51679.89 | C24: 2.1397 | D24: 33.9 | E24: 0.558749 | F24: 0.226188 | G24: 77.1375 | H24: https://api.worldbank.org/v2/country/PRT/indicator/NY.GDP.PCAP.PP.CD?format=json&mrv=30 | https://api.worldbank.org/v2/country/PRT/indicator/NY.GDP.MKTP.KD.ZG?format=json&mrv=30 | https://api.worldbank.org/v2/country/PRT/indicator/SI.POV.GINI?format=json&mrv=30 | +3 more | I24: Tier 3 | J24: 2024-12-31 | K24: providers=world_bank; fields=gdp_per_capita_ppp, gdp_growth, gini_coefficient, ppp_private_consumption; +2 additional fields
A25: Estonia | B25: 49968.71 | C25: -0.09 | D25: 30.7 | E25: 0.646078 | F25: 0.21329 | G25: 60.5329 | H25: https://api.worldbank.org/v2/country/EST/indicator/NY.GDP.PCAP.PP.CD?format=json&mrv=30 | https://api.worldbank.org/v2/country/EST/indicator/NY.GDP.MKTP.KD.ZG?format=json&mrv=30 | https://api.worldbank.org/v2/country/EST/indicator/SI.POV.GINI?format=json&mrv=30 | +3 more | I25: Tier 3 | J25: 2024-12-31 | K25: providers=world_bank; fields=gdp_per_capita_ppp, gdp_growth, gini_coefficient, ppp_private_consumption; +2 additional fields
A26: Finland | B26: 65378.38 | C26: 0.4162 | D26: 27.4 | E26: 0.788236 | F26: 0.253757 | G26: 90.8647 | H26: https://api.worldbank.org/v2/country/FIN/indicator/NY.GDP.PCAP.PP.CD?format=json&mrv=30 | https://api.worldbank.org/v2/country/FIN/indicator/NY.GDP.MKTP.KD.ZG?format=json&mrv=30 | https://api.worldbank.org/v2/country/FIN/indicator/SI.POV.GINI?format=json&mrv=30 | +3 more | I26: Tier 3 | J26: 2024-12-31 | K26: providers=world_bank; fields=gdp_per_capita_ppp, gdp_growth, gini_coefficient, ppp_private_consumption; +2 additional fields
... A37: Costa Rica | B37: 31106.76 | C37: 4.3212 | D37: 45.8 | E37: 328.04659 | F37: 0.139115 | G37: 50.9742 | H37: https://api.worldbank.org/v2/country/CRI/indicator/NY.GDP.PCAP.PP.CD?format=json&mrv=30 | https://api.worldbank.org/v2/country/CRI/indicator/NY.GDP.MKTP.KD.ZG?format=json&mrv=30 | https://api.worldbank.org/v2/country/CRI/indicator/SI.POV.GINI?format=json&mrv=30 | +3 more | I37: Tier 3 | J37: 2024-12-31 | K37: providers=world_bank; fields=gdp_per_capita_ppp, gdp_growth, gini_coefficient, ppp_private_consumption; +2 additional fields
A38: Puerto Rico | B38: 50247.85 | C38: 3.1771 | E38: 0.896932 | H38: https://api.worldbank.org/v2/country/PRI/indicator/NY.GDP.PCAP.PP.CD?format=json&mrv=30 | https://api.worldbank.org/v2/country/PRI/indicator/NY.GDP.MKTP.KD.ZG?format=json&mrv=30 | https://api.worldbank.org/v2/country/PRI/indicator/PA.NUS.PRVT.PP?format=json&mrv=30 | I38: Tier 3 | J38: 2024-12-31 | K38: providers=world_bank; fields=gdp_per_capita_ppp, gdp_growth, ppp_private_consumption
A39: Brazil | B39: 22338.48 | C39: 3.4193 | D39: 51.6 | E39: 2.524497 | F39: 0.154102 | G39: 75.6164 | H39: https://api.worldbank.org/v2/country/BRA/indicator/NY.GDP.PCAP.PP.CD?format=json&mrv=30 | https://api.worldbank.org/v2/country/BRA/indicator/NY.GDP.MKTP.KD.ZG?format=json&mrv=30 | https://api.worldbank.org/v2/country/BRA/indicator/SI.POV.GINI?format=json&mrv=30 | +3 more | I39: Tier 3 | J39: 2024-12-31 | K39: providers=world_bank; fields=gdp_per_capita_ppp, gdp_growth, gini_coefficient, ppp_private_consumption; +2 additional fields
A40: Argentina | B40: 30431.19 | C40: -1.3429 | D40: 42.4 | E40: 42.98624 | F40: 0.099289 | G40: 13.0788 | H40: https://api.worldbank.org/v2/country/ARG/indicator/NY.GDP.PCAP.PP.CD?format=json&mrv=30 | https://api.worldbank.org/v2/country/ARG/indicator/NY.GDP.MKTP.KD.ZG?format=json&mrv=30 | https://api.worldbank.org/v2/country/ARG/indicator/SI.POV.GINI?format=json&mrv=30 | +3 more | I40: Tier 3 | J40: 2024-12-31 | K40: providers=world_bank; fields=gdp_per_capita_ppp, gdp_growth, gini_coefficient, ppp_private_consumption; +2 additional fields
A41: Chile | B41: 36181.16 | C41: 2.6443 | D41: 43 | E41: 464.87603 | F41: 0.177194 | G41: 74.9355 | H41: https://api.worldbank.org/v2/country/CHL/indicator/NY.GDP.PCAP.PP.CD?format=json&mrv=30 | https://api.worldbank.org/v2/country/CHL/indicator/NY.GDP.MKTP.KD.ZG?format=json&mrv=30 | https://api.worldbank.org/v2/country/CHL/indicator/SI.POV.GINI?format=json&mrv=30 | +3 more | I41: Tier 3 | J41: 2024-12-31 | K41: providers=world_bank; fields=gdp_per_capita_ppp, gdp_growth, gini_coefficient, ppp_private_consumption; +2 additional fields
A42: Colombia | B42: 22349.44 | C42: 1.5983 | D42: 53.9 | E42: 1542.1938 | F42: 0.152812 | G42: 39.5117 | H42: https://api.worldbank.org/v2/country/COL/indicator/NY.GDP.PCAP.PP.CD?format=json&mrv=30 | https://api.worldbank.org/v2/country/COL/indicator/NY.GDP.MKTP.KD.ZG?format=json&mrv=30 | https://api.worldbank.org/v2/country/COL/indicator/SI.POV.GINI?format=json&mrv=30 | +3 more | I42: Tier 3 | J42: 2024-12-31 | K42: providers=world_bank; fields=gdp_per_capita_ppp, gdp_growth, gini_coefficient, ppp_private_consumption; +2 additional fields
A43: Peru | B43: 17802.42 | C43: 3.3039 | D43: 40.1 | E43: 1.94918 | F43: 0.159243 | G43: 45.668 | H43: https://api.worldbank.org/v2/country/PER/indicator/NY.GDP.PCAP.PP.CD?format=json&mrv=30 | https://api.worldbank.org/v2/country/PER/indicator/NY.GDP.MKTP.KD.ZG?format=json&mrv=30 | https://api.worldbank.org/v2/country/PER/indicator/SI.POV.GINI?format=json&mrv=30 | +3 more | I43: Tier 3 | J43: 2024-12-31 | K43: providers=world_bank; fields=gdp_per_capita_ppp, gdp_growth, gini_coefficient, ppp_private_consumption; +2 additional fields
A44: Uruguay | B44: 36417.87 | C44: 3.1083 | D44: 40 | E44: 29.298217 | F44: 0.181624 | G44: 31.0608 | H44: https://api.worldbank.org/v2/country/URY/indicator/NY.GDP.PCAP.PP.CD?format=json&mrv=30 | https://api.worldbank.org/v2/country/URY/indicator/NY.GDP.MKTP.KD.ZG?format=json&mrv=30 | https://api.worldbank.org/v2/country/URY/indicator/SI.POV.GINI?format=json&mrv=30 | +3 more | I44: Tier 3 | J44: 2024-12-31 | K44: providers=world_bank; fields=gdp_per_capita_ppp, gdp_growth, gini_coefficient, ppp_private_consumption; +2 additional fields
A45: United Arab Emirates | B45: 79228.74 | C45: 3.9918 | D45: 26.4 | E45: 2.56311 | F45: 0.006475 | G45: 67.9658 | H45: https://api.worldbank.org/v2/country/ARE/indicator/NY.GDP.PCAP.PP.CD?format=json&mrv=30 | https://api.worldbank.org/v2/country/ARE/indicator/NY.GDP.MKTP.KD.ZG?format=json&mrv=30 | https://api.worldbank.org/v2/country/ARE/indicator/SI.POV.GINI?format=json&mrv=30 | +3 more | I45: Tier 3 | J45: 2024-12-31 | K45: providers=world_bank; fields=gdp_per_capita_ppp, gdp_growth, gini_coefficient, ppp_private_consumption; +2 additional fields
A46: Qatar | B46: 126046.35 | C46: 2.3597 | D46: 35.1 | E46: 2.755487 | G46: 118.8652 | H46: https://api.worldbank.org/v2/country/QAT/indicator/NY.GDP.PCAP.PP.CD?format=json&mrv=30 | https://api.worldbank.org/v2/country/QAT/indicator/NY.GDP.MKTP.KD.ZG?format=json&mrv=30 | https://api.worldbank.org/v2/country/QAT/indicator/SI.POV.GINI?format=json&mrv=30 | +2 more | I46: Tier 3 | J46: 2024-12-31 | K46: providers=world_bank; fields=gdp_per_capita_ppp, gdp_growth, gini_coefficient, ppp_private_consumption; +1 additional fields
A47: Saudi Arabia | B47: 71375.37 | C47: 1.9965 | E47: 1.882361 | F47: 0.081847 | G47: 50.1376 | H47: https://api.worldbank.org/v2/country/SAU/indicator/NY.GDP.PCAP.PP.CD?format=json&mrv=30 | https://api.worldbank.org/v2/country/SAU/indicator/NY.GDP.MKTP.KD.ZG?format=json&mrv=30 | https://api.worldbank.org/v2/country/SAU/indicator/PA.NUS.PRVT.PP?format=json&mrv=30 | +2 more | I47: Tier 3 | J47: 2024-12-31 | K47: providers=world_bank; fields=gdp_per_capita_ppp, gdp_growth, ppp_private_consumption, tax_rate_assumption; +1 additional fields
A48: Israel | B48: 57235.78 | C48: 0.872 | D48: 37.9 | E48: 3.607983 | F48: 0.221364 | G48: 69.7497 | H48: https://api.worldbank.org/v2/country/ISR/indicator/NY.GDP.PCAP.PP.CD?format=json&mrv=30 | https://api.worldbank.org/v2/country/ISR/indicator/NY.GDP.MKTP.KD.ZG?format=json&mrv=30 | https://api.worldbank.org/v2/country/ISR/indicator/SI.POV.GINI?format=json&mrv=30 | +3 more | I48: Tier 3 | J48: 2024-12-31 | K48: providers=world_bank; fields=gdp_per_capita_ppp, gdp_growth, gini_coefficient, ppp_private_consumption; +2 additional fields
A49: Oman | B49: 41740.17 | C49: 1.6316 | E49: 0.184982 | G49: 59.7083 | H49: https://api.worldbank.org/v2/country/OMN/indicator/NY.GDP.PCAP.PP.CD?format=json&mrv=30 | https://api.worldbank.org/v2/country/OMN/indicator/NY.GDP.MKTP.KD.ZG?format=json&mrv=30 | https://api.worldbank.org/v2/country/OMN/indicator/PA.NUS.PRVT.PP?format=json&mrv=30 | +1 more | I49: Tier 3 | J49: 2024-12-31 | K49: providers=world_bank; fields=gdp_per_capita_ppp, gdp_growth, ppp_private_consumption, household_debt_proxy
A50: Bahrain | B50: 66941.24 | C50: 2.6038 | E50: 0.188671 | F50: 0.028232 | G50: 70.5501 | H50: https://api.worldbank.org/v2/country/BHR/indicator/NY.GDP.PCAP.PP.CD?format=json&mrv=30 | https://api.worldbank.org/v2/country/BHR/indicator/NY.GDP.MKTP.KD.ZG?format=json&mrv=30 | https://api.worldbank.org/v2/country/BHR/indicator/PA.NUS.PRVT.PP?format=json&mrv=30 | +2 more | I50: Tier 3 | J50: 2024-12-31 | K50: providers=world_bank; fields=gdp_per_capita_ppp, gdp_growth, ppp_private_consumption, tax_rate_assumption; +1 additional fields
A51: Kuwait | B51: 52443.6 | C51: -2.5601 | E51: 0.183789 | F51: 0.014924 | G51: 4.3975 | H51: https://api.worldbank.org/v2/country/KWT/indicator/NY.GDP.PCAP.PP.CD?format=json&mrv=30 | https://api.worldbank.org/v2/country/KWT/indicator/NY.GDP.MKTP.KD.ZG?format=json&mrv=30 | https://api.worldbank.org/v2/country/KWT/indicator/PA.NUS.PRVT.PP?format=json&mrv=30 | +2 more | I51: Tier 3 | J51: 2024-12-31 | K51: providers=world_bank; fields=gdp_per_capita_ppp, gdp_growth, ppp_private_consumption, tax_rate_assumption; +1 additional fields
A52: Jordan | B52: 10821.49 | C52: 2.4889 | D52: 33.7 | E52: 0.321203 | F52: 0.170491 | G52: 80.0729 | H52: https://api.worldbank.org/v2/country/JOR/indicator/NY.GDP.PCAP.PP.CD?format=json&mrv=30 | https://api.worldbank.org/v2/country/JOR/indicator/NY.GDP.MKTP.KD.ZG?format=json&mrv=30 | https://api.worldbank.org/v2/country/JOR/indicator/SI.POV.GINI?format=json&mrv=30 | +3 more | I52: Tier 3 | J52: 2024-12-31 | K52: providers=world_bank; fields=gdp_per_capita_ppp, gdp_growth, gini_coefficient, ppp_private_consumption; +2 additional fields
A53: South Africa | B53: 15456.2 | C53: 0.5348 | D53: 63 | E53: 7.701915 | F53: 0.254005 | G53: 57.4717 | H53: https://api.worldbank.org/v2/country/ZAF/indicator/NY.GDP.PCAP.PP.CD?format=json&mrv=30 | https://api.worldbank.org/v2/country/ZAF/indicator/NY.GDP.MKTP.KD.ZG?format=json&mrv=30 | https://api.worldbank.org/v2/country/ZAF/indicator/SI.POV.GINI?format=json&mrv=30 | +3 more | I53: Tier 3 | J53: 2024-12-31 | K53: providers=world_bank; fields=gdp_per_capita_ppp, gdp_growth, gini_coefficient, ppp_private_consumption; +2 additional fields
A54: Kenya | B54: 6644.13 | C54: 4.7247 | D54: 37.7 | E54: 44.391722 | F54: 0.140631 | G54: 31.7729 | H54: https://api.worldbank.org/v2/country/KEN/indicator/NY.GDP.PCAP.PP.CD?format=json&mrv=30 | https://api.worldbank.org/v2/country/KEN/indicator/NY.GDP.MKTP.KD.ZG?format=json&mrv=30 | https://api.worldbank.org/v2/country/KEN/indicator/SI.POV.GINI?format=json&mrv=30 | +3 more | I54: Tier 3 | J54: 2024-12-31 | K54: providers=world_bank; fields=gdp_per_capita_ppp, gdp_growth, gini_coefficient, ppp_private_consumption; +2 additional fields
A55: Rwanda | B55: 3710.86 | C55: 8.8907 | D55: 39.4 | E55: 361.39523 | F55: 0.135081 | G55: 22.5267 | H55: https://api.worldbank.org/v2/country/RWA/indicator/NY.GDP.PCAP.PP.CD?format=json&mrv=30 | https://api.worldbank.org/v2/country/RWA/indicator/NY.GDP.MKTP.KD.ZG?format=json&mrv=30 | https://api.worldbank.org/v2/country/RWA/indicator/SI.POV.GINI?format=json&mrv=30 | +3 more | I55: Tier 3 | J55: 2024-12-31 | K55: providers=world_bank; fields=gdp_per_capita_ppp, gdp_growth, gini_coefficient, ppp_private_consumption; +2 additional fields
A56: Morocco | B56: 10415.12 | C56: 3.7934 | D56: 39.5 | E56: 4.038145 | F56: 0.207439 | G56: 54.7741 | H56: https://api.worldbank.org/v2/country/MAR/indicator/NY.GDP.PCAP.PP.CD?format=json&mrv=30 | https://api.worldbank.org/v2/country/MAR/indicator/NY.GDP.MKTP.KD.ZG?format=json&mrv=30 | https://api.worldbank.org/v2/country/MAR/indicator/SI.POV.GINI?format=json&mrv=30 | +3 more | I56: Tier 3 | J56: 2024-12-31 | K56: providers=world_bank; fields=gdp_per_capita_ppp, gdp_growth, gini_coefficient, ppp_private_consumption; +2 additional fields
A57: Mauritius | B57: 31839.76 | C57: 4.9251 | D57: 36.8 | E57: 19.916335 | F57: 0.205324 | G57: 69.8221 | H57: https://api.worldbank.org/v2/country/MUS/indicator/NY.GDP.PCAP.PP.CD?format=json&mrv=30 | https://api.worldbank.org/v2/country/MUS/indicator/NY.GDP.MKTP.KD.ZG?format=json&mrv=30 | https://api.worldbank.org/v2/country/MUS/indicator/SI.POV.GINI?format=json&mrv=30 | +3 more | I57: Tier 3 | J57: 2024-12-31 | K57: providers=world_bank; fields=gdp_per_capita_ppp, gdp_growth, gini_coefficient, ppp_private_consumption; +2 additional fields
A58: Botswana | B58: 20538.13 | C58: -2.9899 | D58: 54.9 | E58: 5.312715 | F58: 0.224882 | G58: 32.8462 | H58: https://api.worldbank.org/v2/country/BWA/indicator/NY.GDP.PCAP.PP.CD?format=json&mrv=30 | https://api.worldbank.org/v2/country/BWA/indicator/NY.GDP.MKTP.KD.ZG?format=json&mrv=30 | https://api.worldbank.org/v2/country/BWA/indicator/SI.POV.GINI?format=json&mrv=30 | +3 more | I58: Tier 3 | J58: 2024-12-31 | K58: providers=world_bank; fields=gdp_per_capita_ppp, gdp_growth, gini_coefficient, ppp_private_consumption; +2 additional fields
A59: Namibia | B59: 11686.6 | C59: 3.7115 | D59: 59.1 | E59: 7.321244 | F59: 0.329629 | G59: 48.2075 | H59: https://api.worldbank.org/v2/country/NAM/indicator/NY.GDP.PCAP.PP.CD?format=json&mrv=30 | https://api.worldbank.org/v2/country/NAM/indicator/NY.GDP.MKTP.KD.ZG?format=json&mrv=30 | https://api.worldbank.org/v2/country/NAM/indicator/SI.POV.GINI?format=json&mrv=30 | +3 more | I59: Tier 3 | J59: 2024-12-31 | K59: providers=world_bank; fields=gdp_per_capita_ppp, gdp_growth, gini_coefficient, ppp_private_consumption; +2 additional fields
A60: Ghana | B60: 8020 | C60: 5.5905 | D60: 43.5 | E60: 4.721006 | F60: 0.122975 | G60: 8.6512 | H60: https://api.worldbank.org/v2/country/GHA/indicator/NY.GDP.PCAP.PP.CD?format=json&mrv=30 | https://api.worldbank.org/v2/country/GHA/indicator/NY.GDP.MKTP.KD.ZG?format=json&mrv=30 | https://api.worldbank.org/v2/country/GHA/indicator/SI.POV.GINI?format=json&mrv=30 | +3 more | I60: Tier 3 | J60: 2024-12-31 | K60: providers=world_bank; fields=gdp_per_capita_ppp, gdp_growth, gini_coefficient, ppp_private_consumption; +2 additional fields
A61: Senegal | B61: 5070.65 | C61: 6.0606 | D61: 36.2 | E61: 229.28096 | F61: 0.195371 | G61: 29.205 | H61: https://api.worldbank.org/v2/country/SEN/indicator/NY.GDP.PCAP.PP.CD?format=json&mrv=30 | https://api.worldbank.org/v2/country/SEN/indicator/NY.GDP.MKTP.KD.ZG?format=json&mrv=30 | https://api.worldbank.org/v2/country/SEN/indicator/SI.POV.GINI?format=json&mrv=30 | +3 more | I61: Tier 3 | J61: 2024-12-31 | K61: providers=world_bank; fields=gdp_per_capita_ppp, gdp_growth, gini_coefficient, ppp_private_consumption; +2 additional fields
A62: New Zealand | B62: 55551.14 | C62: 1.2886 | E62: 1.499938 | F62: 0.306678 | G62: 129.7971 | H62: https://api.worldbank.org/v2/country/NZL/indicator/NY.GDP.PCAP.PP.CD?format=json&mrv=30 | https://api.worldbank.org/v2/country/NZL/indicator/NY.GDP.MKTP.KD.ZG?format=json&mrv=30 | https://api.worldbank.org/v2/country/NZL/indicator/PA.NUS.PRVT.PP?format=json&mrv=30 | +2 more | I62: Tier 3 | J62: 2024-12-31 | K62: providers=world_bank; fields=gdp_per_capita_ppp, gdp_growth, ppp_private_consumption, tax_rate_assumption; +1 additional fields
A63: Australia | B63: 72111.18 | C63: 1.3734 | D63: 33.8 | E63: 1.427398 | F63: 0.235615 | G63: 129.3173 | H63: https://api.worldbank.org/v2/country/AUS/indicator/NY.GDP.PCAP.PP.CD?format=json&mrv=30 | https://api.worldbank.org/v2/country/AUS/indicator/NY.GDP.MKTP.KD.ZG?format=json&mrv=30 | https://api.worldbank.org/v2/country/AUS/indicator/SI.POV.GINI?format=json&mrv=30 | +3 more | I63: Tier 3 | J63: 2024-12-31 | K63: providers=world_bank; fields=gdp_per_capita_ppp, gdp_growth, gini_coefficient, ppp_private_consumption; +2 additional fields
A64: Fiji | B64: 15450.3 | C64: 3.5309 | D64: 30.7 | E64: 0.910728 | F64: 0.20538 | G64: 75.9993 | H64: https://api.worldbank.org/v2/country/FJI/indicator/NY.GDP.PCAP.PP.CD?format=json&mrv=30 | https://api.worldbank.org/v2/country/FJI/indicator/NY.GDP.MKTP.KD.ZG?format=json&mrv=30 | https://api.worldbank.org/v2/country/FJI/indicator/SI.POV.GINI?format=json&mrv=30 | +3 more | I64: Tier 3 | J64: 2024-12-31 | K64: providers=world_bank; fields=gdp_per_capita_ppp, gdp_growth, gini_coefficient, ppp_private_consumption; +2 additional fields
A65: Vietnam | K65: Populate official country context inputs before ranking.
A66: Cambodia | K66: Populate official country context inputs before ranking.
A67: Czechia | K67: Populate official country context inputs before ranking.
A68: Slovenia | K68: Populate official country context inputs before ranking.
A69: Croatia | K69: Populate official country context inputs before ranking.
A70: Lithuania | K70: Populate official country context inputs before ranking.
A71: Latvia | K71: Populate official country context inputs before ranking.
A72: Georgia | K72: Populate official country context inputs before ranking.
A73: Spain | K73: Populate official country context inputs before ranking.
A74: Germany | K74: Populate official country context inputs before ranking.
A75: Belgium | K75: Populate official country context inputs before ranking.
A76: Ireland | K76: Populate official country context inputs before ranking.
... A87: Vanuatu | K87: Populate official country context inputs before ranking.

Sheet City_Inputs
A1: city_id | B1: display_name | C1: country | D1: cohort | E1: city_type | F1: manifest_status | G1: gross_income | H1: rent | I1: utilities | J1: transit_cost | K1: internet_cost | L1: food_cost | M1: di_ppp_raw | N1: housing_burden_raw | O1: household_debt_burden_raw | P1: household_debt_effective_raw | Q1: working_time_pressure_raw | R1: suicide_mental_strain_raw | S1: personal_safety_raw | T1: transit_access_commute_raw | U1: clean_air_raw | V1: water_sanitation_utility_raw | W1: digital_infrastructure_raw | X1: climate_sunlight_livability_raw | Y1: healthcare_quality_raw | Z1: education_quality_raw | AA1: equal_opportunity_raw | AB1: hospitality_belonging_raw | AC1: tolerance_pluralism_raw | AD1: cultural_public_life_raw | AE1: entrepreneurial_dynamism_raw | AF1: innovation_research_intensity_raw | AG1: investment_signal_raw | AH1: administrative_investment_friction_raw | AI1: visitor_flow_context_raw | AJ1: gdp_per_capita_ppp_context | AK1: gdp_growth_context | AL1: gini_coefficient_context | AM1: ppp_private_consumption_context | AN1: tax_rate_context | AO1: household_debt_proxy_context | AP1: pressure_source_url | AQ1: pressure_source_tier | AR1: pressure_source_date | AS1: pressure_notes | AT1: viability_source_url | AU1: viability_source_tier | AV1: viability_source_date | AW1: viability_notes | AX1: capability_source_url | AY1: capability_source_tier | AZ1: capability_source_date | BA1: capability_notes | BB1: community_source_url | BC1: community_source_tier | BD1: community_source_date | BE1: community_notes | BF1: creative_source_url | BG1: creative_source_tier | BH1: creative_source_date | BI1: creative_notes | BJ1: birth_rate_optimism_raw
A2: th-bangkok | B2: Bangkok | C2: Thailand | D2: Southeast Asia | E2: primary | F2: locked | G2: 1996.67 | H2: 399.33 | I2: 99.83 | J2: 79.87 | K2: 29.95 | L2: 439.27 | N2: 19.9998 | O2: 115.1054 | P2: =IF($O2<>"",$O2,$AO2) | Q2: 42.53 | R2: 16.59 | S2: 2.2 | U2: 25 | V2: 93 | W2: 15.75 | X2: 72 | Y2: 82 | Z2: 49.08 | AA2: 33.5 | AB2: 50.38 | AC2: 42 | AD2: 556.96 | AE2: 1.54 | AF2: 1.16 | AG2: 2.72 | AH2: 2.34 | AJ2: =IFERROR(INDEX(Country_Context!$B$2:$B$87,MATCH($C2,Country_Context!$A$2:$A$87,0)),"") | AK2: =IFERROR(INDEX(Country_Context!$C$2:$C$87,MATCH($C2,Country_Context!$A$2:$A$87,0)),"") | AL2: =IFERROR(INDEX(Country_Context!$D$2:$D$87,MATCH($C2,Country_Context!$A$2:$A$87,0)),"") | AM2: =IFERROR(INDEX(Country_Context!$E$2:$E$87,MATCH($C2,Country_Context!$A$2:$A$87,0)),"") | AN2: =IFERROR(INDEX(Country_Context!$F$2:$F$87,MATCH($C2,Country_Context!$A$2:$A$87,0)),"") | AO2: =IFERROR(INDEX(Country_Context!$G$2:$G$87,MATCH($C2,Country_Context!$A$2:$A$87,0)),"") | AP2: https://api.worldbank.org/v2/country/THA/indicator/NY.GNP.PCAP.PP.CD?format=json&mrv=10 | https://data.worldbank.org/indicator/NY.GNP.PCAP.PP.CD | https://ilostat.ilo.org/data/indicator/?id=HOW_TEMP_SEX_ECO_NB_A&ref_area=THA | +4 more | AQ2: Tier 3, Tier 4 | AR2: 2024-12-31 | AS2: providers=world_bank_col_estimate, derived, ilo_ilostat, who_gho; fields=gross_income, rent, utilities, transit_cost; +9 additional fields | AT2: https://api.worldbank.org/v2/country/THA/indicator/VC.IHR.PSRC.P5?format=json&mrv=10 | https://www.pcd.go.th/ | https://washdata.org | +2 more | AU2: Tier 2, Tier 3 | AV2: 2024-12-31 | AW2: providers=world_bank, thai_gov_pcd_rsc, who_unicef_jmp; fields=personal_safety_raw, clean_air_raw, water_sanitation_utility_raw, digital_infrastructure_raw; +1 additional fields | AX2: https://www.who.int/data/gho/data/indicators/indicator-details/GHO/UHC_INDEX_REPORTED | https://api.worldbank.org/v2/country/THA/indicator/SE.TER.ENRR?format=json&mrv=10 | https://api.worldbank.org/v2/country/THA/indicator/SI.POV.GINI?format=json&mrv=10 | +1 more | AY2: Tier 3 | AZ2: 2025-12-31 | BA2: providers=who_gho, world_bank; fields=healthcare_quality_raw, education_quality_raw, equal_opportunity_raw, gini_coefficient | BB2: https://api.worldbank.org/v2/country/THA/indicator/SM.POP.NETM?format=json&mrv=10 | https://api.worldbank.org/v2/country/THA/indicator/SG.GEN.PARL.ZS?format=json | https://api.worldbank.org/v2/country/THA/indicator/ST.INT.ARVL?format=json&mrv=10 | +1 more | BC2: Tier 3 | BD2: 2025-12-31 | BE2: providers=world_bank; fields=hospitality_belonging_raw, tolerance_pluralism_raw, cultural_public_life_raw, birth_rate_optimism_raw | BF2: https://api.worldbank.org/v2/country/THA/indicator/IC.BUS.NDNS.ZS?format=json&mrv=10 | https://api.worldbank.org/v2/country/THA/indicator/GB.XPD.RSDV.GD.ZS?format=json&mrv=10 | https://api.worldbank.org/v2/country/THA/indicator/BX.KLT.DINV.WD.GD.ZS?format=json&mrv=10 | +3 more | BG2: Tier 3 | BH2: 2024-12-31 | BI2: providers=world_bank; fields=entrepreneurial_dynamism_raw, innovation_research_intensity_raw, investment_signal_raw, administrative_investment_friction_raw; +2 additional fields | BJ2: 1.08
A3: sg-singapore | B3: Singapore | C3: Singapore | D3: Southeast Asia | E3: primary | F3: locked | G3: 10515.83 | H3: 2839.27 | I3: 709.82 | J3: 567.85 | K3: 212.95 | L3: 3123.2 | N3: 27 | O3: 129.1908 | P3: =IF($O3<>"",$O3,$AO3) | Q3: 42.6 | R3: 8.1 | S3: 0.07 | V3: 100 | W3: 27.43 | X3: 62 | Y3: 88 | Z3: 97.29 | AB3: 52.8 | AC3: 29.29 | AD3: 454.21 | AE3: 11.32 | AF3: 2.16 | AG3: 27.76 | AH3: 0.19 | AJ3: =IFERROR(INDEX(Country_Context!$B$2:$B$87,MATCH($C3,Country_Context!$A$2:$A$87,0)),"") | AK3: =IFERROR(INDEX(Country_Context!$C$2:$C$87,MATCH($C3,Country_Context!$A$2:$A$87,0)),"") | AL3: =IFERROR(INDEX(Country_Context!$D$2:$D$87,MATCH($C3,Country_Context!$A$2:$A$87,0)),"") | AM3: =IFERROR(INDEX(Country_Context!$E$2:$E$87,MATCH($C3,Country_Context!$A$2:$A$87,0)),"") | AN3: =IFERROR(INDEX(Country_Context!$F$2:$F$87,MATCH($C3,Country_Context!$A$2:$A$87,0)),"") | AO3: =IFERROR(INDEX(Country_Context!$G$2:$G$87,MATCH($C3,Country_Context!$A$2:$A$87,0)),"") | AP3: https://api.worldbank.org/v2/country/SGP/indicator/NY.GNP.PCAP.PP.CD?format=json&mrv=10 | https://data.worldbank.org/indicator/NY.GNP.PCAP.PP.CD | https://ilostat.ilo.org/data/indicator/?id=HOW_TEMP_SEX_ECO_NB_A&ref_area=SGP | +4 more | AQ3: Tier 3, Tier 4 | AR3: 2024-12-31 | AS3: providers=world_bank_col_estimate, derived, ilo_ilostat, who_gho; fields=gross_income, rent, utilities, transit_cost; +9 additional fields | AT3: https://api.worldbank.org/v2/country/SGP/indicator/VC.IHR.PSRC.P5?format=json&mrv=10 | https://api.worldbank.org/v2/country/SGP/indicator/SH.H2O.SMDW.ZS?format=json&mrv=10 | https://api.worldbank.org/v2/country/SGP/indicator/IT.NET.BBND.P2?format=json&mrv=10 | +1 more | AU3: Tier 3 | AV3: 2024-12-31 | AW3: providers=world_bank, wmo_natl_met; fields=personal_safety_raw, water_sanitation_utility_raw, digital_infrastructure_raw, climate_sunlight_livability_raw | AX3: https://www.who.int/data/gho/data/indicators/indicator-details/GHO/UHC_INDEX_REPORTED | https://api.worldbank.org/v2/country/SGP/indicator/SE.TER.ENRR?format=json&mrv=10 | AY3: Tier 3 | AZ3: 2023-12-31 | BA3: providers=who_gho, world_bank; fields=healthcare_quality_raw, education_quality_raw | BB3: https://api.worldbank.org/v2/country/SGP/indicator/SM.POP.NETM?format=json&mrv=10 | https://api.worldbank.org/v2/country/SGP/indicator/SG.GEN.PARL.ZS?format=json&mrv=10 | https://api.worldbank.org/v2/country/SGP/indicator/ST.INT.ARVL?format=json&mrv=10 | +1 more | BC3: Tier 3 | BD3: 2025-12-31 | BE3: providers=world_bank; fields=hospitality_belonging_raw, tolerance_pluralism_raw, cultural_public_life_raw, birth_rate_optimism_raw | BF3: https://api.worldbank.org/v2/country/SGP/indicator/IC.BUS.NDNS.ZS?format=json&mrv=10 | https://api.worldbank.org/v2/country/SGP/indicator/GB.XPD.RSDV.GD.ZS?format=json&mrv=10 | https://api.worldbank.org/v2/country/SGP/indicator/BX.KLT.DINV.WD.GD.ZS?format=json&mrv=10 | +3 more | BG3: Tier 3 | BH3: 2024-12-31 | BI3: providers=world_bank; fields=entrepreneurial_dynamism_raw, innovation_research_intensity_raw, investment_signal_raw, administrative_investment_friction_raw; +2 additional fields | BJ3: 0.97
A4: my-kuala-lumpur | B4: Kuala Lumpur | C4: Malaysia | D4: Southeast Asia | E4: primary | F4: locked | G4: 3120.83 | H4: 624.17 | I4: 156.04 | J4: 124.83 | K4: 46.81 | L4: 686.58 | N4: 20.0001 | O4: 116.0773 | P4: =IF($O4<>"",$O4,$AO4) | Q4: 44.7 | R4: 5.65 | S4: 0.73 | V4: 94.7 | W4: 13.03 | X4: 56 | Y4: 80 | Z4: 38.5 | AA4: 40.7 | AB4: 54.69 | AC4: 13.51 | AD4: 121.86 | AE4: 2.19 | AF4: 0.95 | AG4: 3.69 | AH4: 1.84 | AJ4: =IFERROR(INDEX(Country_Context!$B$2:$B$87,MATCH($C4,Country_Context!$A$2:$A$87,0)),"") | AK4: =IFERROR(INDEX(Country_Context!$C$2:$C$87,MATCH($C4,Country_Context!$A$2:$A$87,0)),"") | AL4: =IFERROR(INDEX(Country_Context!$D$2:$D$87,MATCH($C4,Country_Context!$A$2:$A$87,0)),"") | AM4: =IFERROR(INDEX(Country_Context!$E$2:$E$87,MATCH($C4,Country_Context!$A$2:$A$87,0)),"") | AN4: =IFERROR(INDEX(Country_Context!$F$2:$F$87,MATCH($C4,Country_Context!$A$2:$A$87,0)),"") | AO4: =IFERROR(INDEX(Country_Context!$G$2:$G$87,MATCH($C4,Country_Context!$A$2:$A$87,0)),"") | AP4: https://api.worldbank.org/v2/country/MYS/indicator/NY.GNP.PCAP.PP.CD?format=json&mrv=10 | https://data.worldbank.org/indicator/NY.GNP.PCAP.PP.CD | https://ilostat.ilo.org/data/indicator/?id=HOW_TEMP_SEX_ECO_NB_A&ref_area=MYS | +4 more | AQ4: Tier 3, Tier 4 | AR4: 2024-12-31 | AS4: providers=world_bank_col_estimate, derived, ilo_ilostat, who_gho; fields=gross_income, rent, utilities, transit_cost; +9 additional fields | AT4: https://api.worldbank.org/v2/country/MYS/indicator/VC.IHR.PSRC.P5?format=json&mrv=10 | https://api.worldbank.org/v2/country/MYS/indicator/SH.H2O.SMDW.ZS?format=json&mrv=10 | https://api.worldbank.org/v2/country/MYS/indicator/IT.NET.BBND.P2?format=json&mrv=10 | +1 more | AU4: Tier 3 | AV4: 2024-12-31 | AW4: providers=world_bank, wmo_natl_met; fields=personal_safety_raw, water_sanitation_utility_raw, digital_infrastructure_raw, climate_sunlight_livability_raw | AX4: https://www.who.int/data/gho/data/indicators/indicator-details/GHO/UHC_INDEX_REPORTED | https://api.worldbank.org/v2/country/MYS/indicator/SE.TER.ENRR?format=json&mrv=10 | https://api.worldbank.org/v2/country/MYS/indicator/SI.POV.GINI?format=json&mrv=10 | +1 more | AY4: Tier 3 | AZ4: 2024-12-31 | BA4: providers=who_gho, world_bank; fields=healthcare_quality_raw, education_quality_raw, equal_opportunity_raw, gini_coefficient | BB4: https://api.worldbank.org/v2/country/MYS/indicator/SM.POP.NETM?format=json&mrv=10 | https://api.worldbank.org/v2/country/MYS/indicator/SG.GEN.PARL.ZS?format=json&mrv=10 | https://api.worldbank.org/v2/country/MYS/indicator/ST.INT.ARVL?format=json&mrv=10 | +1 more | BC4: Tier 3 | BD4: 2025-12-31 | BE4: providers=world_bank; fields=hospitality_belonging_raw, tolerance_pluralism_raw, cultural_public_life_raw, birth_rate_optimism_raw | BF4: https://api.worldbank.org/v2/country/MYS/indicator/IC.BUS.NDNS.ZS?format=json&mrv=10 | https://api.worldbank.org/v2/country/MYS/indicator/GB.XPD.RSDV.GD.ZS?format=json&mrv=10 | https://api.worldbank.org/v2/country/MYS/indicator/BX.KLT.DINV.WD.GD.ZS?format=json&mrv=10 | +3 more | BG4: Tier 3 | BH4: 2024-12-31 | BI4: providers=world_bank; fields=entrepreneurial_dynamism_raw, innovation_research_intensity_raw, investment_signal_raw, administrative_investment_friction_raw; +2 additional fields | BJ4: 1.6
A5: id-jakarta | B5: Jakarta | C5: Indonesia | D5: Southeast Asia | E5: primary | F5: provisional | G5: 1334.17 | H5: 266.83 | I5: 66.71 | J5: 53.37 | K5: 20.01 | L5: 293.52 | N5: 19.9997 | O5: 31.7861 | P5: =IF($O5<>"",$O5,$AO5) | Q5: 38.36 | R5: 1.2 | S5: 0.3 | V5: 30.46 | W5: 4.82 | X5: 54 | Y5: 67 | Z5: 44.88 | AA5: 34.9 | AB5: 49.86 | AC5: 21.03 | AD5: 14.3 | AE5: 0.33 | AF5: 0.28 | AG5: 1.74 | AH5: 2.2 | AJ5: =IFERROR(INDEX(Country_Context!$B$2:$B$87,MATCH($C5,Country_Context!$A$2:$A$87,0)),"") | AK5: =IFERROR(INDEX(Country_Context!$C$2:$C$87,MATCH($C5,Country_Context!$A$2:$A$87,0)),"") | AL5: =IFERROR(INDEX(Country_Context!$D$2:$D$87,MATCH($C5,Country_Context!$A$2:$A$87,0)),"") | AM5: =IFERROR(INDEX(Country_Context!$E$2:$E$87,MATCH($C5,Country_Context!$A$2:$A$87,0)),"") | AN5: =IFERROR(INDEX(Country_Context!$F$2:$F$87,MATCH($C5,Country_Context!$A$2:$A$87,0)),"") | AO5: =IFERROR(INDEX(Country_Context!$G$2:$G$87,MATCH($C5,Country_Context!$A$2:$A$87,0)),"") | AP5: https://api.worldbank.org/v2/country/IDN/indicator/NY.GNP.PCAP.PP.CD?format=json&mrv=10 | https://data.worldbank.org/indicator/NY.GNP.PCAP.PP.CD | https://ilostat.ilo.org/data/indicator/?id=HOW_TEMP_SEX_ECO_NB_A&ref_area=IDN | +4 more | AQ5: Tier 3, Tier 4 | AR5: 2024-12-31 | AS5: providers=world_bank_col_estimate, derived, ilo_ilostat, who_gho; fields=gross_income, rent, utilities, transit_cost; +9 additional fields | AT5: https://api.worldbank.org/v2/country/IDN/indicator/VC.IHR.PSRC.P5?format=json&mrv=10 | https://api.worldbank.org/v2/country/IDN/indicator/SH.H2O.SMDW.ZS?format=json&mrv=10 | https://api.worldbank.org/v2/country/IDN/indicator/IT.NET.BBND.P2?format=json&mrv=10 | +1 more | AU5: Tier 3 | AV5: 2024-12-31 | AW5: providers=world_bank, wmo_natl_met; fields=personal_safety_raw, water_sanitation_utility_raw, digital_infrastructure_raw, climate_sunlight_livability_raw | AX5: https://www.who.int/data/gho/data/indicators/indicator-details/GHO/UHC_INDEX_REPORTED | https://api.worldbank.org/v2/country/IDN/indicator/SE.TER.ENRR?format=json&mrv=10 | https://api.worldbank.org/v2/country/IDN/indicator/SI.POV.GINI?format=json&mrv=10 | +1 more | AY5: Tier 3 | AZ5: 2024-12-31 | BA5: providers=who_gho, world_bank; fields=healthcare_quality_raw, education_quality_raw, equal_opportunity_raw, gini_coefficient | BB5: https://api.worldbank.org/v2/country/IDN/indicator/SM.POP.NETM?format=json&mrv=10 | https://api.worldbank.org/v2/country/IDN/indicator/SG.GEN.PARL.ZS?format=json&mrv=10 | https://api.worldbank.org/v2/country/IDN/indicator/ST.INT.ARVL?format=json&mrv=10 | BC5: Tier 3 | BD5: 2025-12-31 | BE5: providers=world_bank; fields=hospitality_belonging_raw, tolerance_pluralism_raw, cultural_public_life_raw | BF5: https://api.worldbank.org/v2/country/IDN/indicator/IC.BUS.NDNS.ZS?format=json&mrv=10 | https://api.worldbank.org/v2/country/IDN/indicator/GB.XPD.RSDV.GD.ZS?format=json&mrv=10 | https://api.worldbank.org/v2/country/IDN/indicator/BX.KLT.DINV.WD.GD.ZS?format=json&mrv=10 | +3 more | BG5: Tier 3 | BH5: 2024-12-31 | BI5: providers=world_bank; fields=entrepreneurial_dynamism_raw, innovation_research_intensity_raw, investment_signal_raw, administrative_investment_friction_raw; +2 additional fields
A6: ph-makati | B6: Makati | C6: Philippines | D6: Southeast Asia | E6: primary | F6: provisional | G6: 1110.83 | H6: 222.17 | I6: 55.54 | J6: 44.43 | K6: 16.66 | L6: 244.38 | N6: 20.0004 | O6: 49.8137 | P6: =IF($O6<>"",$O6,$AO6) | Q6: 39.99 | R6: 3.49 | S6: 4.35 | V6: 48.48 | W6: 6.54 | Y6: 69 | Z6: 47.41 | AA6: 39.3 | AB6: 48.71 | AC6: 27.33 | AD6: 12.8 | AE6: 0.34 | AF6: 0.32 | AG6: 2.04 | AH6: 2.34 | AJ6: =IFERROR(INDEX(Country_Context!$B$2:$B$87,MATCH($C6,Country_Context!$A$2:$A$87,0)),"") | AK6: =IFERROR(INDEX(Country_Context!$C$2:$C$87,MATCH($C6,Country_Context!$A$2:$A$87,0)),"") | AL6: =IFERROR(INDEX(Country_Context!$D$2:$D$87,MATCH($C6,Country_Context!$A$2:$A$87,0)),"") | AM6: =IFERROR(INDEX(Country_Context!$E$2:$E$87,MATCH($C6,Country_Context!$A$2:$A$87,0)),"") | AN6: =IFERROR(INDEX(Country_Context!$F$2:$F$87,MATCH($C6,Country_Context!$A$2:$A$87,0)),"") | AO6: =IFERROR(INDEX(Country_Context!$G$2:$G$87,MATCH($C6,Country_Context!$A$2:$A$87,0)),"") | AP6: https://api.worldbank.org/v2/country/PHL/indicator/NY.GNP.PCAP.PP.CD?format=json&mrv=10 | https://data.worldbank.org/indicator/NY.GNP.PCAP.PP.CD | https://ilostat.ilo.org/data/indicator/?id=HOW_TEMP_SEX_ECO_NB_A&ref_area=PHL | +4 more | AQ6: Tier 3, Tier 4 | AR6: 2024-12-31 | AS6: providers=world_bank_col_estimate, derived, ilo_ilostat, who_gho; fields=gross_income, rent, utilities, transit_cost; +9 additional fields | AT6: https://api.worldbank.org/v2/country/PHL/indicator/VC.IHR.PSRC.P5?format=json&mrv=10 | https://api.worldbank.org/v2/country/PHL/indicator/SH.H2O.SMDW.ZS?format=json&mrv=10 | https://api.worldbank.org/v2/country/PHL/indicator/IT.NET.BBND.P2?format=json&mrv=10 | AU6: Tier 3 | AV6: 2024-12-31 | AW6: providers=world_bank; fields=personal_safety_raw, water_sanitation_utility_raw, digital_infrastructure_raw | AX6: https://www.who.int/data/gho/data/indicators/indicator-details/GHO/UHC_INDEX_REPORTED | https://api.worldbank.org/v2/country/PHL/indicator/SE.TER.ENRR?format=json&mrv=10 | https://api.worldbank.org/v2/country/PHL/indicator/SI.POV.GINI?format=json&mrv=10 | +1 more | AY6: Tier 3 | AZ6: 2024-12-31 | BA6: providers=who_gho, world_bank; fields=healthcare_quality_raw, education_quality_raw, equal_opportunity_raw, gini_coefficient | BB6: https://api.worldbank.org/v2/country/PHL/indicator/SM.POP.NETM?format=json&mrv=10 | https://api.worldbank.org/v2/country/PHL/indicator/SG.GEN.PARL.ZS?format=json&mrv=10 | https://api.worldbank.org/v2/country/PHL/indicator/ST.INT.ARVL?format=json&mrv=10 | BC6: Tier 3 | BD6: 2025-12-31 | BE6: providers=world_bank; fields=hospitality_belonging_raw, tolerance_pluralism_raw, cultural_public_life_raw | BF6: https://api.worldbank.org/v2/country/PHL/indicator/IC.BUS.NDNS.ZS?format=json&mrv=10 | https://api.worldbank.org/v2/country/PHL/indicator/GB.XPD.RSDV.GD.ZS?format=json&mrv=10 | https://api.worldbank.org/v2/country/PHL/indicator/BX.KLT.DINV.WD.GD.ZS?format=json&mrv=10 | +3 more | BG6: Tier 3 | BH6: 2024-12-31 | BI6: providers=world_bank; fields=entrepreneurial_dynamism_raw, innovation_research_intensity_raw, investment_signal_raw, administrative_investment_friction_raw; +2 additional fields
A7: my-george-town | B7: George Town | C7: Malaysia | D7: Southeast Asia | E7: secondary | F7: locked | G7: 3120.83 | H7: 499.33 | I7: 124.83 | J7: 99.87 | K7: 37.45 | L7: 549.27 | N7: 15.9999 | O7: 116.0773 | P7: =IF($O7<>"",$O7,$AO7) | Q7: 44.7 | R7: 5.65 | S7: 0.73 | V7: 94.7 | W7: 13.03 | Y7: 80 | Z7: 38.5 | AA7: 40.7 | AB7: 54.69 | AC7: 13.51 | AD7: 121.86 | AE7: 2.19 | AF7: 0.95 | AG7: 3.69 | AH7: 1.84 | AJ7: =IFERROR(INDEX(Country_Context!$B$2:$B$87,MATCH($C7,Country_Context!$A$2:$A$87,0)),"") | AK7: =IFERROR(INDEX(Country_Context!$C$2:$C$87,MATCH($C7,Country_Context!$A$2:$A$87,0)),"") | AL7: =IFERROR(INDEX(Country_Context!$D$2:$D$87,MATCH($C7,Country_Context!$A$2:$A$87,0)),"") | AM7: =IFERROR(INDEX(Country_Context!$E$2:$E$87,MATCH($C7,Country_Context!$A$2:$A$87,0)),"") | AN7: =IFERROR(INDEX(Country_Context!$F$2:$F$87,MATCH($C7,Country_Context!$A$2:$A$87,0)),"") | AO7: =IFERROR(INDEX(Country_Context!$G$2:$G$87,MATCH($C7,Country_Context!$A$2:$A$87,0)),"") | AP7: https://api.worldbank.org/v2/country/MYS/indicator/NY.GNP.PCAP.PP.CD?format=json&mrv=10 | https://data.worldbank.org/indicator/NY.GNP.PCAP.PP.CD | https://ilostat.ilo.org/data/indicator/?id=HOW_TEMP_SEX_ECO_NB_A&ref_area=MYS | +4 more | AQ7: Tier 3, Tier 4 | AR7: 2024-12-31 | AS7: providers=world_bank_col_estimate, derived, ilo_ilostat, who_gho; fields=gross_income, rent, utilities, transit_cost; +9 additional fields | AT7: https://api.worldbank.org/v2/country/MYS/indicator/VC.IHR.PSRC.P5?format=json&mrv=10 | https://api.worldbank.org/v2/country/MYS/indicator/SH.H2O.SMDW.ZS?format=json&mrv=10 | https://api.worldbank.org/v2/country/MYS/indicator/IT.NET.BBND.P2?format=json&mrv=10 | AU7: Tier 3 | AV7: 2024-12-31 | AW7: providers=world_bank; fields=personal_safety_raw, water_sanitation_utility_raw, digital_infrastructure_raw | AX7: https://www.who.int/data/gho/data/indicators/indicator-details/GHO/UHC_INDEX_REPORTED | https://api.worldbank.org/v2/country/MYS/indicator/SE.TER.ENRR?format=json&mrv=10 | https://api.worldbank.org/v2/country/MYS/indicator/SI.POV.GINI?format=json&mrv=10 | +1 more | AY7: Tier 3 | AZ7: 2024-12-31 | BA7: providers=who_gho, world_bank; fields=healthcare_quality_raw, education_quality_raw, equal_opportunity_raw, gini_coefficient | BB7: https://api.worldbank.org/v2/country/MYS/indicator/SM.POP.NETM?format=json&mrv=10 | https://api.worldbank.org/v2/country/MYS/indicator/SG.GEN.PARL.ZS?format=json&mrv=10 | https://api.worldbank.org/v2/country/MYS/indicator/ST.INT.ARVL?format=json&mrv=10 | +1 more | BC7: Tier 3 | BD7: 2025-12-31 | BE7: providers=world_bank; fields=hospitality_belonging_raw, tolerance_pluralism_raw, cultural_public_life_raw, birth_rate_optimism_raw | BF7: https://api.worldbank.org/v2/country/MYS/indicator/IC.BUS.NDNS.ZS?format=json&mrv=10 | https://api.worldbank.org/v2/country/MYS/indicator/GB.XPD.RSDV.GD.ZS?format=json&mrv=10 | https://api.worldbank.org/v2/country/MYS/indicator/BX.KLT.DINV.WD.GD.ZS?format=json&mrv=10 | +3 more | BG7: Tier 3 | BH7: 2024-12-31 | BI7: providers=world_bank; fields=entrepreneurial_dynamism_raw, innovation_research_intensity_raw, investment_signal_raw, administrative_investment_friction_raw; +2 additional fields | BJ7: 1.6
A8: th-phuket | B8: Phuket | C8: Thailand | D8: Southeast Asia | E8: secondary | F8: locked | G8: 1996.67 | H8: 359.4 | I8: 89.85 | J8: 71.88 | K8: 26.96 | L8: 395.34 | N8: 18 | O8: 115.1054 | P8: =IF($O8<>"",$O8,$AO8) | Q8: 42.53 | R8: 16.59 | U8: 18 | V8: 90 | W8: 15.75 | X8: 60 | Y8: 82 | Z8: 49.08 | AA8: 33.5 | AB8: 50.38 | AC8: 19.4 | AD8: 556.96 | AE8: 1.54 | AF8: 1.16 | AG8: 2.72 | AH8: 2.34 | AJ8: =IFERROR(INDEX(Country_Context!$B$2:$B$87,MATCH($C8,Country_Context!$A$2:$A$87,0)),"") | AK8: =IFERROR(INDEX(Country_Context!$C$2:$C$87,MATCH($C8,Country_Context!$A$2:$A$87,0)),"") | AL8: =IFERROR(INDEX(Country_Context!$D$2:$D$87,MATCH($C8,Country_Context!$A$2:$A$87,0)),"") | AM8: =IFERROR(INDEX(Country_Context!$E$2:$E$87,MATCH($C8,Country_Context!$A$2:$A$87,0)),"") | AN8: =IFERROR(INDEX(Country_Context!$F$2:$F$87,MATCH($C8,Country_Context!$A$2:$A$87,0)),"") | AO8: =IFERROR(INDEX(Country_Context!$G$2:$G$87,MATCH($C8,Country_Context!$A$2:$A$87,0)),"") | AP8: https://api.worldbank.org/v2/country/THA/indicator/NY.GNP.PCAP.PP.CD?format=json&mrv=10 | https://data.worldbank.org/indicator/NY.GNP.PCAP.PP.CD | https://ilostat.ilo.org/data/indicator/?id=HOW_TEMP_SEX_ECO_NB_A&ref_area=THA | +4 more | AQ8: Tier 3, Tier 4 | AR8: 2024-12-31 | AS8: providers=world_bank_col_estimate, derived, ilo_ilostat, who_gho; fields=gross_income, rent, utilities, transit_cost; +9 additional fields | AT8: https://www.pcd.go.th/ | https://www.pwa.co.th/ | https://api.worldbank.org/v2/country/THA/indicator/IT.NET.BBND.P2?format=json&mrv=10 | +1 more | AU8: Tier 2, Tier 3 | AV8: 2024-12-31 | AW8: providers=thai_gov_pcd_rsc, world_bank, wmo_natl_met; fields=clean_air_raw, water_sanitation_utility_raw, digital_infrastructure_raw, climate_sunlight_livability_raw | AX8: https://www.who.int/data/gho/data/indicators/indicator-details/GHO/UHC_INDEX_REPORTED | https://api.worldbank.org/v2/country/THA/indicator/SE.TER.ENRR?format=json&mrv=10 | https://api.worldbank.org/v2/country/THA/indicator/SI.POV.GINI?format=json&mrv=10 | +1 more | AY8: Tier 3 | AZ8: 2025-12-31 | BA8: providers=who_gho, world_bank; fields=healthcare_quality_raw, education_quality_raw, equal_opportunity_raw, gini_coefficient | BB8: https://api.worldbank.org/v2/country/THA/indicator/SM.POP.NETM?format=json&mrv=10 | https://api.worldbank.org/v2/country/THA/indicator/SG.GEN.PARL.ZS?format=json&mrv=10 | https://api.worldbank.org/v2/country/THA/indicator/ST.INT.ARVL?format=json&mrv=10 | +1 more | BC8: Tier 3 | BD8: 2025-12-31 | BE8: providers=world_bank; fields=hospitality_belonging_raw, tolerance_pluralism_raw, cultural_public_life_raw, birth_rate_optimism_raw | BF8: https://api.worldbank.org/v2/country/THA/indicator/IC.BUS.NDNS.ZS?format=json&mrv=10 | https://api.worldbank.org/v2/country/THA/indicator/GB.XPD.RSDV.GD.ZS?format=json&mrv=10 | https://api.worldbank.org/v2/country/THA/indicator/BX.KLT.DINV.WD.GD.ZS?format=json&mrv=10 | +3 more | BG8: Tier 3 | BH8: 2024-12-31 | BI8: providers=world_bank; fields=entrepreneurial_dynamism_raw, innovation_research_intensity_raw, investment_signal_raw, administrative_investment_friction_raw; +2 additional fields | BJ8: 1.08
A9: th-chiang-mai | B9: Chiang Mai | C9: Thailand | D9: Southeast Asia | E9: secondary | F9: locked | G9: 1996.67 | H9: 259.57 | I9: 64.89 | J9: 51.91 | K9: 19.47 | L9: 285.52 | N9: 13.0001 | O9: 115.1054 | P9: =IF($O9<>"",$O9,$AO9) | Q9: 42.53 | R9: 16.59 | U9: 35 | V9: 95 | W9: 15.75 | X9: 64 | Y9: 82 | Z9: 49.08 | AA9: 33.5 | AB9: 50.38 | AC9: 19.4 | AD9: 556.96 | AE9: 1.54 | AF9: 1.16 | AG9: 2.72 | AH9: 2.34 | AJ9: =IFERROR(INDEX(Country_Context!$B$2:$B$87,MATCH($C9,Country_Context!$A$2:$A$87,0)),"") | AK9: =IFERROR(INDEX(Country_Context!$C$2:$C$87,MATCH($C9,Country_Context!$A$2:$A$87,0)),"") | AL9: =IFERROR(INDEX(Country_Context!$D$2:$D$87,MATCH($C9,Country_Context!$A$2:$A$87,0)),"") | AM9: =IFERROR(INDEX(Country_Context!$E$2:$E$87,MATCH($C9,Country_Context!$A$2:$A$87,0)),"") | AN9: =IFERROR(INDEX(Country_Context!$F$2:$F$87,MATCH($C9,Country_Context!$A$2:$A$87,0)),"") | AO9: =IFERROR(INDEX(Country_Context!$G$2:$G$87,MATCH($C9,Country_Context!$A$2:$A$87,0)),"") | AP9: https://api.worldbank.org/v2/country/THA/indicator/NY.GNP.PCAP.PP.CD?format=json&mrv=10 | https://data.worldbank.org/indicator/NY.GNP.PCAP.PP.CD | https://ilostat.ilo.org/data/indicator/?id=HOW_TEMP_SEX_ECO_NB_A&ref_area=THA | +4 more | AQ9: Tier 3, Tier 4 | AR9: 2024-12-31 | AS9: providers=world_bank_col_estimate, derived, ilo_ilostat, who_gho; fields=gross_income, rent, utilities, transit_cost; +9 additional fields | AT9: https://www.pcd.go.th/ | https://www.pwa.co.th/ | https://api.worldbank.org/v2/country/THA/indicator/IT.NET.BBND.P2?format=json&mrv=10 | +1 more | AU9: Tier 2, Tier 3 | AV9: 2024-12-31 | AW9: providers=thai_gov_pcd_rsc, world_bank, wmo_natl_met; fields=clean_air_raw, water_sanitation_utility_raw, digital_infrastructure_raw, climate_sunlight_livability_raw | AX9: https://www.who.int/data/gho/data/indicators/indicator-details/GHO/UHC_INDEX_REPORTED | https://api.worldbank.org/v2/country/THA/indicator/SE.TER.ENRR?format=json&mrv=10 | https://api.worldbank.org/v2/country/THA/indicator/SI.POV.GINI?format=json&mrv=10 | +1 more | AY9: Tier 3 | AZ9: 2025-12-31 | BA9: providers=who_gho, world_bank; fields=healthcare_quality_raw, education_quality_raw, equal_opportunity_raw, gini_coefficient | BB9: https://api.worldbank.org/v2/country/THA/indicator/SM.POP.NETM?format=json&mrv=10 | https://api.worldbank.org/v2/country/THA/indicator/SG.GEN.PARL.ZS?format=json&mrv=10 | https://api.worldbank.org/v2/country/THA/indicator/ST.INT.ARVL?format=json&mrv=10 | +1 more | BC9: Tier 3 | BD9: 2025-12-31 | BE9: providers=world_bank; fields=hospitality_belonging_raw, tolerance_pluralism_raw, cultural_public_life_raw, birth_rate_optimism_raw | BF9: https://api.worldbank.org/v2/country/THA/indicator/IC.BUS.NDNS.ZS?format=json&mrv=10 | https://api.worldbank.org/v2/country/THA/indicator/GB.XPD.RSDV.GD.ZS?format=json&mrv=10 | https://api.worldbank.org/v2/country/THA/indicator/BX.KLT.DINV.WD.GD.ZS?format=json&mrv=10 | +3 more | BG9: Tier 3 | BH9: 2024-12-31 | BI9: providers=world_bank; fields=entrepreneurial_dynamism_raw, innovation_research_intensity_raw, investment_signal_raw, administrative_investment_friction_raw; +2 additional fields | BJ9: 1.08
A10: my-kuching | B10: Kuching | C10: Malaysia | D10: Southeast Asia | E10: secondary | F10: locked | G10: 3120.83 | H10: 436.92 | I10: 109.23 | J10: 87.38 | K10: 32.77 | L10: 480.61 | N10: 14.0001 | O10: 116.0773 | P10: =IF($O10<>"",$O10,$AO10) | Q10: 44.7 | R10: 5.65 | S10: 0.73 | V10: 94.7 | W10: 13.03 | Y10: 80 | Z10: 38.5 | AA10: 40.7 | AB10: 54.69 | AC10: 13.51 | AD10: 121.86 | AE10: 2.19 | AF10: 0.95 | AG10: 3.69 | AH10: 1.84 | AJ10: =IFERROR(INDEX(Country_Context!$B$2:$B$87,MATCH($C10,Country_Context!$A$2:$A$87,0)),"") | AK10: =IFERROR(INDEX(Country_Context!$C$2:$C$87,MATCH($C10,Country_Context!$A$2:$A$87,0)),"") | AL10: =IFERROR(INDEX(Country_Context!$D$2:$D$87,MATCH($C10,Country_Context!$A$2:$A$87,0)),"") | AM10: =IFERROR(INDEX(Country_Context!$E$2:$E$87,MATCH($C10,Country_Context!$A$2:$A$87,0)),"") | AN10: =IFERROR(INDEX(Country_Context!$F$2:$F$87,MATCH($C10,Country_Context!$A$2:$A$87,0)),"") | AO10: =IFERROR(INDEX(Country_Context!$G$2:$G$87,MATCH($C10,Country_Context!$A$2:$A$87,0)),"") | AP10: https://api.worldbank.org/v2/country/MYS/indicator/NY.GNP.PCAP.PP.CD?format=json&mrv=10 | https://data.worldbank.org/indicator/NY.GNP.PCAP.PP.CD | https://ilostat.ilo.org/data/indicator/?id=HOW_TEMP_SEX_ECO_NB_A&ref_area=MYS | +4 more | AQ10: Tier 3, Tier 4 | AR10: 2024-12-31 | AS10: providers=world_bank_col_estimate, derived, ilo_ilostat, who_gho; fields=gross_income, rent, utilities, transit_cost; +9 additional fields | AT10: https://api.worldbank.org/v2/country/MYS/indicator/VC.IHR.PSRC.P5?format=json&mrv=10 | https://api.worldbank.org/v2/country/MYS/indicator/SH.H2O.SMDW.ZS?format=json&mrv=10 | https://api.worldbank.org/v2/country/MYS/indicator/IT.NET.BBND.P2?format=json&mrv=10 | AU10: Tier 3 | AV10: 2024-12-31 | AW10: providers=world_bank; fields=personal_safety_raw, water_sanitation_utility_raw, digital_infrastructure_raw | AX10: https://www.who.int/data/gho/data/indicators/indicator-details/GHO/UHC_INDEX_REPORTED | https://api.worldbank.org/v2/country/MYS/indicator/SE.TER.ENRR?format=json&mrv=10 | https://api.worldbank.org/v2/country/MYS/indicator/SI.POV.GINI?format=json&mrv=10 | +1 more | AY10: Tier 3 | AZ10: 2024-12-31 | BA10: providers=who_gho, world_bank; fields=healthcare_quality_raw, education_quality_raw, equal_opportunity_raw, gini_coefficient | BB10: https://api.worldbank.org/v2/country/MYS/indicator/SM.POP.NETM?format=json&mrv=10 | https://api.worldbank.org/v2/country/MYS/indicator/SG.GEN.PARL.ZS?format=json&mrv=10 | https://api.worldbank.org/v2/country/MYS/indicator/ST.INT.ARVL?format=json&mrv=10 | +1 more | BC10: Tier 3 | BD10: 2025-12-31 | BE10: providers=world_bank; fields=hospitality_belonging_raw, tolerance_pluralism_raw, cultural_public_life_raw, birth_rate_optimism_raw | BF10: https://api.worldbank.org/v2/country/MYS/indicator/IC.BUS.NDNS.ZS?format=json&mrv=10 | https://api.worldbank.org/v2/country/MYS/indicator/GB.XPD.RSDV.GD.ZS?format=json&mrv=10 | https://api.worldbank.org/v2/country/MYS/indicator/BX.KLT.DINV.WD.GD.ZS?format=json&mrv=10 | +3 more | BG10: Tier 3 | BH10: 2024-12-31 | BI10: providers=world_bank; fields=entrepreneurial_dynamism_raw, innovation_research_intensity_raw, investment_signal_raw, administrative_investment_friction_raw; +2 additional fields | BJ10: 1.6
A11: my-kota-kinabalu | B11: Kota Kinabalu | C11: Malaysia | D11: Southeast Asia | E11: secondary | F11: provisional | G11: 3120.83 | H11: 436.92 | I11: 109.23 | J11: 87.38 | K11: 32.77 | L11: 480.61 | N11: 14.0001 | O11: 116.0773 | P11: =IF($O11<>"",$O11,$AO11) | Q11: 44.7 | R11: 5.65 | S11: 0.73 | U11: 15 | V11: 90 | W11: 13.03 | X11: 60 | Y11: 80 | Z11: 38.5 | AA11: 40.7 | AB11: 54.69 | AC11: 13.51 | AD11: 55 | AE11: 2.19 | AF11: 0.95 | AG11: 3.69 | AH11: 1.84 | AJ11: =IFERROR(INDEX(Country_Context!$B$2:$B$87,MATCH($C11,Country_Context!$A$2:$A$87,0)),"") | AK11: =IFERROR(INDEX(Country_Context!$C$2:$C$87,MATCH($C11,Country_Context!$A$2:$A$87,0)),"") | AL11: =IFERROR(INDEX(Country_Context!$D$2:$D$87,MATCH($C11,Country_Context!$A$2:$A$87,0)),"") | AM11: =IFERROR(INDEX(Country_Context!$E$2:$E$87,MATCH($C11,Country_Context!$A$2:$A$87,0)),"") | AN11: =IFERROR(INDEX(Country_Context!$F$2:$F$87,MATCH($C11,Country_Context!$A$2:$A$87,0)),"") | AO11: =IFERROR(INDEX(Country_Context!$G$2:$G$87,MATCH($C11,Country_Context!$A$2:$A$87,0)),"") | AP11: https://api.worldbank.org/v2/country/MYS/indicator/NY.GNP.PCAP.PP.CD?format=json&mrv=10 | https://data.worldbank.org/indicator/NY.GNP.PCAP.PP.CD | https://ilostat.ilo.org/data/indicator/?id=HOW_TEMP_SEX_ECO_NB_A&ref_area=MYS | +4 more | AQ11: Tier 3, Tier 4 | AR11: 2024-12-31 | AS11: providers=world_bank_col_estimate, derived, ilo_ilostat, who_gho; fields=gross_income, rent, utilities, transit_cost; +9 additional fields | AT11: https://api.worldbank.org/v2/country/MYS/indicator/VC.IHR.PSRC.P5?format=json&mrv=10 | https://worldweather.wmo.int | https://washdata.org | +1 more | AU11: Tier 3 | AV11: 2024-12-31 | AW11: providers=world_bank, wmo_natl_met, who_unicef_jmp; fields=personal_safety_raw, clean_air_raw, water_sanitation_utility_raw, digital_infrastructure_raw; +1 additional fields | AX11: https://www.who.int/data/gho/data/indicators/indicator-details/GHO/UHC_INDEX_REPORTED | https://api.worldbank.org/v2/country/MYS/indicator/SE.TER.ENRR?format=json&mrv=10 | https://api.worldbank.org/v2/country/MYS/indicator/SI.POV.GINI?format=json&mrv=10 | +1 more | AY11: Tier 3 | AZ11: 2024-12-31 | BA11: providers=who_gho, world_bank; fields=healthcare_quality_raw, education_quality_raw, equal_opportunity_raw, gini_coefficient | BB11: https://api.worldbank.org/v2/country/MYS/indicator/SM.POP.NETM?format=json&mrv=10 | https://api.worldbank.org/v2/country/MYS/indicator/SG.GEN.PARL.ZS?format=json&mrv=10 | https://worldweather.wmo.int | +1 more | BC11: Tier 3 | BD11: 2025-12-31 | BE11: providers=world_bank, wmo_natl_met; fields=hospitality_belonging_raw, tolerance_pluralism_raw, cultural_public_life_raw, birth_rate_optimism_raw | BF11: https://api.worldbank.org/v2/country/MYS/indicator/IC.BUS.NDNS.ZS?format=json&mrv=10 | https://api.worldbank.org/v2/country/MYS/indicator/GB.XPD.RSDV.GD.ZS?format=json&mrv=10 | https://api.worldbank.org/v2/country/MYS/indicator/BX.KLT.DINV.WD.GD.ZS?format=json&mrv=10 | +3 more | BG11: Tier 3 | BH11: 2024-12-31 | BI11: providers=world_bank; fields=entrepreneurial_dynamism_raw, innovation_research_intensity_raw, investment_signal_raw, administrative_investment_friction_raw; +2 additional fields | BJ11: 1.6
A12: my-melaka | B12: Melaka | C12: Malaysia | D12: Southeast Asia | E12: secondary | F12: provisional | G12: 3120.83 | H12: 405.71 | I12: 101.43 | J12: 81.14 | K12: 30.43 | L12: 446.28 | N12: 13.0001 | O12: 116.0773 | P12: =IF($O12<>"",$O12,$AO12) | Q12: 44.7 | R12: 5.65 | S12: 0.73 | U12: 18 | V12: 90 | W12: 13.03 | X12: 56 | Y12: 80 | Z12: 38.5 | AA12: 40.7 | AB12: 54.69 | AC12: 13.51 | AD12: 75 | AE12: 2.19 | AF12: 0.95 | AG12: 3.69 | AH12: 1.84 | AJ12: =IFERROR(INDEX(Country_Context!$B$2:$B$87,MATCH($C12,Country_Context!$A$2:$A$87,0)),"") | AK12: =IFERROR(INDEX(Country_Context!$C$2:$C$87,MATCH($C12,Country_Context!$A$2:$A$87,0)),"") | AL12: =IFERROR(INDEX(Country_Context!$D$2:$D$87,MATCH($C12,Country_Context!$A$2:$A$87,0)),"") | AM12: =IFERROR(INDEX(Country_Context!$E$2:$E$87,MATCH($C12,Country_Context!$A$2:$A$87,0)),"") | AN12: =IFERROR(INDEX(Country_Context!$F$2:$F$87,MATCH($C12,Country_Context!$A$2:$A$87,0)),"") | AO12: =IFERROR(INDEX(Country_Context!$G$2:$G$87,MATCH($C12,Country_Context!$A$2:$A$87,0)),"") | AP12: https://api.worldbank.org/v2/country/MYS/indicator/NY.GNP.PCAP.PP.CD?format=json&mrv=10 | https://data.worldbank.org/indicator/NY.GNP.PCAP.PP.CD | https://ilostat.ilo.org/data/indicator/?id=HOW_TEMP_SEX_ECO_NB_A&ref_area=MYS | +4 more | AQ12: Tier 3, Tier 4 | AR12: 2024-12-31 | AS12: providers=world_bank_col_estimate, derived, ilo_ilostat, who_gho; fields=gross_income, rent, utilities, transit_cost; +9 additional fields | AT12: https://api.worldbank.org/v2/country/MYS/indicator/VC.IHR.PSRC.P5?format=json&mrv=10 | https://worldweather.wmo.int | https://washdata.org | +1 more | AU12: Tier 3 | AV12: 2024-12-31 | AW12: providers=world_bank, wmo_natl_met, who_unicef_jmp; fields=personal_safety_raw, clean_air_raw, water_sanitation_utility_raw, digital_infrastructure_raw; +1 additional fields | AX12: https://www.who.int/data/gho/data/indicators/indicator-details/GHO/UHC_INDEX_REPORTED | https://api.worldbank.org/v2/country/MYS/indicator/SE.TER.ENRR?format=json&mrv=10 | https://api.worldbank.org/v2/country/MYS/indicator/SI.POV.GINI?format=json&mrv=10 | +1 more | AY12: Tier 3 | AZ12: 2024-12-31 | BA12: providers=who_gho, world_bank; fields=healthcare_quality_raw, education_quality_raw, equal_opportunity_raw, gini_coefficient | BB12: https://api.worldbank.org/v2/country/MYS/indicator/SM.POP.NETM?format=json&mrv=10 | https://api.worldbank.org/v2/country/MYS/indicator/SG.GEN.PARL.ZS?format=json&mrv=10 | https://worldweather.wmo.int | +1 more | BC12: Tier 3 | BD12: 2025-12-31 | BE12: providers=world_bank, wmo_natl_met; fields=hospitality_belonging_raw, tolerance_pluralism_raw, cultural_public_life_raw, birth_rate_optimism_raw | BF12: https://api.worldbank.org/v2/country/MYS/indicator/IC.BUS.NDNS.ZS?format=json&mrv=10 | https://api.worldbank.org/v2/country/MYS/indicator/GB.XPD.RSDV.GD.ZS?format=json&mrv=10 | https://api.worldbank.org/v2/country/MYS/indicator/BX.KLT.DINV.WD.GD.ZS?format=json&mrv=10 | +3 more | BG12: Tier 3 | BH12: 2024-12-31 | BI12: providers=world_bank; fields=entrepreneurial_dynamism_raw, innovation_research_intensity_raw, investment_signal_raw, administrative_investment_friction_raw; +2 additional fields | BJ12: 1.6
A13: th-hat-yai | B13: Hat Yai | C13: Thailand | D13: Southeast Asia | E13: secondary | F13: provisional | G13: 1996.67 | H13: 239.6 | I13: 59.9 | J13: 47.92 | K13: 17.97 | L13: 263.56 | N13: 12 | O13: 115.1054 | P13: =IF($O13<>"",$O13,$AO13) | Q13: 42.53 | R13: 16.59 | U13: 20 | V13: 92 | W13: 15.75 | X13: 55 | Y13: 82 | Z13: 49.08 | AA13: 33.5 | AB13: 50.38 | AC13: 19.4 | AD13: 556.96 | AE13: 1.54 | AF13: 1.16 | AG13: 2.72 | AH13: 2.34 | AJ13: =IFERROR(INDEX(Country_Context!$B$2:$B$87,MATCH($C13,Country_Context!$A$2:$A$87,0)),"") | AK13: =IFERROR(INDEX(Country_Context!$C$2:$C$87,MATCH($C13,Country_Context!$A$2:$A$87,0)),"") | AL13: =IFERROR(INDEX(Country_Context!$D$2:$D$87,MATCH($C13,Country_Context!$A$2:$A$87,0)),"") | AM13: =IFERROR(INDEX(Country_Context!$E$2:$E$87,MATCH($C13,Country_Context!$A$2:$A$87,0)),"") | AN13: =IFERROR(INDEX(Country_Context!$F$2:$F$87,MATCH($C13,Country_Context!$A$2:$A$87,0)),"") | AO13: =IFERROR(INDEX(Country_Context!$G$2:$G$87,MATCH($C13,Country_Context!$A$2:$A$87,0)),"") | AP13: https://api.worldbank.org/v2/country/THA/indicator/NY.GNP.PCAP.PP.CD?format=json&mrv=10 | https://data.worldbank.org/indicator/NY.GNP.PCAP.PP.CD | https://ilostat.ilo.org/data/indicator/?id=HOW_TEMP_SEX_ECO_NB_A&ref_area=THA | +4 more | AQ13: Tier 3, Tier 4 | AR13: 2024-12-31 | AS13: providers=world_bank_col_estimate, derived, ilo_ilostat, who_gho; fields=gross_income, rent, utilities, transit_cost; +9 additional fields | AT13: https://www.pcd.go.th/ | https://www.pwa.co.th/ | https://api.worldbank.org/v2/country/THA/indicator/IT.NET.BBND.P2?format=json&mrv=10 | +1 more | AU13: Tier 2, Tier 3 | AV13: 2024-12-31 | AW13: providers=thai_gov_pcd_rsc, world_bank, wmo_natl_met; fields=clean_air_raw, water_sanitation_utility_raw, digital_infrastructure_raw, climate_sunlight_livability_raw | AX13: https://www.who.int/data/gho/data/indicators/indicator-details/GHO/UHC_INDEX_REPORTED | https://api.worldbank.org/v2/country/THA/indicator/SE.TER.ENRR?format=json&mrv=10 | https://api.worldbank.org/v2/country/THA/indicator/SI.POV.GINI?format=json&mrv=10 | +1 more | AY13: Tier 3 | AZ13: 2025-12-31 | BA13: providers=who_gho, world_bank; fields=healthcare_quality_raw, education_quality_raw, equal_opportunity_raw, gini_coefficient | BB13: https://api.worldbank.org/v2/country/THA/indicator/SM.POP.NETM?format=json&mrv=10 | https://api.worldbank.org/v2/country/THA/indicator/SG.GEN.PARL.ZS?format=json&mrv=10 | https://api.worldbank.org/v2/country/THA/indicator/ST.INT.ARVL?format=json&mrv=10 | +1 more | BC13: Tier 3 | BD13: 2025-12-31 | BE13: providers=world_bank; fields=hospitality_belonging_raw, tolerance_pluralism_raw, cultural_public_life_raw, birth_rate_optimism_raw | BF13: https://api.worldbank.org/v2/country/THA/indicator/IC.BUS.NDNS.ZS?format=json&mrv=10 | https://api.worldbank.org/v2/country/THA/indicator/GB.XPD.RSDV.GD.ZS?format=json&mrv=10 | https://api.worldbank.org/v2/country/THA/indicator/BX.KLT.DINV.WD.GD.ZS?format=json&mrv=10 | +3 more | BG13: Tier 3 | BH13: 2024-12-31 | BI13: providers=world_bank; fields=entrepreneurial_dynamism_raw, innovation_research_intensity_raw, investment_signal_raw, administrative_investment_friction_raw; +2 additional fields | BJ13: 1.08
A14: tw-taipei | B14: Taipei | C14: Taiwan | D14: East Asia | E14: primary | F14: locked | G14: 5958.33 | H14: 1713.02 | I14: 411.12 | J14: 274.08 | K14: 102.78 | L14: 1370.42 | N14: 28.75 | O14: 86 | P14: =IF($O14<>"",$O14,$AO14) | Q14: 41.5 | R14: 16 | S14: 0.8 | U14: 15 | V14: 99 | W14: 28 | X14: 62 | Y14: 88 | Z14: 95 | AA14: 45 | AC14: 45 | AD14: 60 | AE14: 7.5 | AF14: 3.6 | AG14: 65 | AH14: 9 | AJ14: =IFERROR(INDEX(Country_Context!$B$2:$B$87,MATCH($C14,Country_Context!$A$2:$A$87,0)),"") | AK14: =IFERROR(INDEX(Country_Context!$C$2:$C$87,MATCH($C14,Country_Context!$A$2:$A$87,0)),"") | AL14: =IFERROR(INDEX(Country_Context!$D$2:$D$87,MATCH($C14,Country_Context!$A$2:$A$87,0)),"") | AM14: =IFERROR(INDEX(Country_Context!$E$2:$E$87,MATCH($C14,Country_Context!$A$2:$A$87,0)),"") | AN14: =IFERROR(INDEX(Country_Context!$F$2:$F$87,MATCH($C14,Country_Context!$A$2:$A$87,0)),"") | AO14: =IFERROR(INDEX(Country_Context!$G$2:$G$87,MATCH($C14,Country_Context!$A$2:$A$87,0)),"") | AP14: https://data.worldbank.org/indicator/NY.GNP.PCAP.PP.CD | https://eng.dgbas.gov.tw | https://dep.mohw.gov.tw | AQ14: Tier 1, Tier 4 | AR14: 2024-01-01 | AS14: providers=world_bank_col_estimate, derived, city_official_portal; fields=gross_income, rent, utilities, transit_cost; +6 additional fields | AT14: https://eng.dgbas.gov.tw | https://worldweather.wmo.int | AU14: Tier 1, Tier 3 | AV14: 2024-12-31 | AW14: providers=city_official_portal, wmo_natl_met; fields=personal_safety_raw, clean_air_raw, water_sanitation_utility_raw, digital_infrastructure_raw; +1 additional fields | AX14: https://dep.mohw.gov.tw | https://eng.dgbas.gov.tw | AY14: Tier 1 | AZ14: 2023-12-31 | BA14: providers=city_official_portal; fields=healthcare_quality_raw, education_quality_raw, equal_opportunity_raw | BB14: https://api.worldbank.org/v2/country/TWN | https://eng.dgbas.gov.tw | https://data.worldbank.org/indicator/SP.DYN.TFRT.IN | BC14: Tier 1, Tier 3 | BD14: 2024-12-31 | BE14: providers=world_bank, city_official_portal; fields=tolerance_pluralism_raw, cultural_public_life_raw, birth_rate_optimism_raw | BF14: https://eng.dgbas.gov.tw | BG14: Tier 1 | BH14: 2023-12-31 | BI14: providers=city_official_portal; fields=entrepreneurial_dynamism_raw, innovation_research_intensity_raw, investment_signal_raw, administrative_investment_friction_raw | BJ14: 0.87
A15: kr-busan | B15: Busan | C15: South Korea | D15: East Asia | E15: primary | F15: locked | G15: 4644.75 | H15: 987.01 | I15: 236.88 | J15: 157.92 | K15: 59.22 | L15: 789.61 | N15: 21.25 | O15: 160.3472 | P15: =IF($O15<>"",$O15,$AO15) | Q15: 38.49 | R15: 27.53 | S15: 0.48 | V15: 99.28 | W15: 46.57 | X15: 64 | Y15: 88 | Z15: 106.71 | AA15: 32.9 | AB15: 51.27 | AC15: 20 | AD15: 48.68 | AE15: 3.09 | AF15: 5.21 | AG15: 0.81 | AH15: 1.38 | AJ15: =IFERROR(INDEX(Country_Context!$B$2:$B$87,MATCH($C15,Country_Context!$A$2:$A$87,0)),"") | AK15: =IFERROR(INDEX(Country_Context!$C$2:$C$87,MATCH($C15,Country_Context!$A$2:$A$87,0)),"") | AL15: =IFERROR(INDEX(Country_Context!$D$2:$D$87,MATCH($C15,Country_Context!$A$2:$A$87,0)),"") | AM15: =IFERROR(INDEX(Country_Context!$E$2:$E$87,MATCH($C15,Country_Context!$A$2:$A$87,0)),"") | AN15: =IFERROR(INDEX(Country_Context!$F$2:$F$87,MATCH($C15,Country_Context!$A$2:$A$87,0)),"") | AO15: =IFERROR(INDEX(Country_Context!$G$2:$G$87,MATCH($C15,Country_Context!$A$2:$A$87,0)),"") | AP15: https://api.worldbank.org/v2/country/KOR/indicator/NY.GNP.PCAP.PP.CD?format=json&mrv=10 | https://data.worldbank.org/indicator/NY.GNP.PCAP.PP.CD | https://ilostat.ilo.org/data/indicator/?id=HOW_TEMP_SEX_ECO_NB_A&ref_area=KOR | +4 more | AQ15: Tier 3, Tier 4 | AR15: 2025-12-31 | AS15: providers=world_bank_col_estimate, derived, ilo_ilostat, who_gho; fields=gross_income, rent, utilities, transit_cost; +9 additional fields | AT15: https://api.worldbank.org/v2/country/KOR/indicator/VC.IHR.PSRC.P5?format=json&mrv=10 | https://api.worldbank.org/v2/country/KOR/indicator/SH.H2O.SMDW.ZS?format=json&mrv=10 | https://api.worldbank.org/v2/country/KOR/indicator/IT.NET.BBND.P2?format=json&mrv=10 | +1 more | AU15: Tier 3 | AV15: 2024-12-31 | AW15: providers=world_bank, wmo_natl_met; fields=personal_safety_raw, water_sanitation_utility_raw, digital_infrastructure_raw, climate_sunlight_livability_raw | AX15: https://www.who.int/data/gho/data/indicators/indicator-details/GHO/UHC_INDEX_REPORTED | https://api.worldbank.org/v2/country/KOR/indicator/SE.TER.ENRR?format=json&mrv=10 | https://api.worldbank.org/v2/country/KOR/indicator/SI.POV.GINI?format=json&mrv=10 | +1 more | AY15: Tier 3 | AZ15: 2023-12-31 | BA15: providers=who_gho, world_bank; fields=healthcare_quality_raw, education_quality_raw, equal_opportunity_raw, gini_coefficient | BB15: https://api.worldbank.org/v2/country/KOR/indicator/SM.POP.NETM?format=json&mrv=10 | https://api.worldbank.org/v2/country/KOR/indicator/SG.GEN.PARL.ZS?format=json&mrv=10 | https://api.worldbank.org/v2/country/KOR/indicator/ST.INT.ARVL?format=json&mrv=10 | +1 more | BC15: Tier 3 | BD15: 2025-12-31 | BE15: providers=world_bank; fields=hospitality_belonging_raw, tolerance_pluralism_raw, cultural_public_life_raw, birth_rate_optimism_raw | BF15: https://api.worldbank.org/v2/country/KOR/indicator/IC.BUS.NDNS.ZS?format=json&mrv=10 | https://api.worldbank.org/v2/country/KOR/indicator/GB.XPD.RSDV.GD.ZS?format=json&mrv=10 | https://api.worldbank.org/v2/country/KOR/indicator/BX.KLT.DINV.WD.GD.ZS?format=json&mrv=10 | +3 more | BG15: Tier 3 | BH15: 2024-12-31 | BI15: providers=world_bank; fields=entrepreneurial_dynamism_raw, innovation_research_intensity_raw, investment_signal_raw, administrative_investment_friction_raw; +2 additional fields | BJ15: 0.72
A16: cn-shanghai | B16: Shanghai | C16: China | D16: East Asia | E16: primary | F16: provisional | G16: 3365 | H16: 1093.62 | I16: 262.47 | J16: 174.98 | K16: 65.62 | L16: 874.9 | N16: 32.4999 | O16: 194.166 | P16: =IF($O16<>"",$O16,$AO16) | R16: 8.95 | S16: 0.5 | W16: 44.73 | X16: 58 | Y16: 85 | Z16: 76.88 | AA16: 36 | AB16: 49.81 | AC16: 26.54 | AD16: 21.58 | AE16: 8.58 | AF16: 2.56 | AG16: 0.1 | AH16: 2.86 | AJ16: =IFERROR(INDEX(Country_Context!$B$2:$B$87,MATCH($C16,Country_Context!$A$2:$A$87,0)),"") | AK16: =IFERROR(INDEX(Country_Context!$C$2:$C$87,MATCH($C16,Country_Context!$A$2:$A$87,0)),"") | AL16: =IFERROR(INDEX(Country_Context!$D$2:$D$87,MATCH($C16,Country_Context!$A$2:$A$87,0)),"") | AM16: =IFERROR(INDEX(Country_Context!$E$2:$E$87,MATCH($C16,Country_Context!$A$2:$A$87,0)),"") | AN16: =IFERROR(INDEX(Country_Context!$F$2:$F$87,MATCH($C16,Country_Context!$A$2:$A$87,0)),"") | AO16: =IFERROR(INDEX(Country_Context!$G$2:$G$87,MATCH($C16,Country_Context!$A$2:$A$87,0)),"") | AP16: https://api.worldbank.org/v2/country/CHN/indicator/NY.GNP.PCAP.PP.CD?format=json&mrv=10 | https://data.worldbank.org/indicator/NY.GNP.PCAP.PP.CD | https://www.who.int/data/gho/data/indicators/indicator-details/GHO/SDGSUICIDE | +3 more | AQ16: Tier 3, Tier 4 | AR16: 2024-12-31 | AS16: providers=world_bank_col_estimate, derived, who_gho, world_bank; fields=gross_income, rent, utilities, transit_cost; +8 additional fields | AT16: https://api.worldbank.org/v2/country/CHN/indicator/VC.IHR.PSRC.P5?format=json&mrv=10 | https://api.worldbank.org/v2/country/CHN/indicator/IT.NET.BBND.P2?format=json&mrv=10 | https://worldweather.wmo.int | AU16: Tier 3 | AV16: 2024-12-31 | AW16: providers=world_bank, wmo_natl_met; fields=personal_safety_raw, digital_infrastructure_raw, climate_sunlight_livability_raw | AX16: https://www.who.int/data/gho/data/indicators/indicator-details/GHO/UHC_INDEX_REPORTED | https://api.worldbank.org/v2/country/CHN/indicator/SE.TER.ENRR?format=json&mrv=10 | https://api.worldbank.org/v2/country/CHN/indicator/SI.POV.GINI?format=json&mrv=10 | +1 more | AY16: Tier 3 | AZ16: 2024-12-31 | BA16: providers=who_gho, world_bank; fields=healthcare_quality_raw, education_quality_raw, equal_opportunity_raw, gini_coefficient | BB16: https://api.worldbank.org/v2/country/CHN/indicator/SM.POP.NETM?format=json&mrv=10 | https://api.worldbank.org/v2/country/CHN/indicator/SG.GEN.PARL.ZS?format=json&mrv=10 | https://api.worldbank.org/v2/country/CHN/indicator/ST.INT.ARVL?format=json&mrv=10 | +1 more | BC16: Tier 3 | BD16: 2025-12-31 | BE16: providers=world_bank; fields=hospitality_belonging_raw, tolerance_pluralism_raw, cultural_public_life_raw, birth_rate_optimism_raw | BF16: https://api.worldbank.org/v2/country/CHN/indicator/IC.BUS.NDNS.ZS?format=json&mrv=10 | https://api.worldbank.org/v2/country/CHN/indicator/GB.XPD.RSDV.GD.ZS?format=json&mrv=10 | https://api.worldbank.org/v2/country/CHN/indicator/BX.KLT.DINV.WD.GD.ZS?format=json&mrv=10 | +3 more | BG16: Tier 3 | BH16: 2024-12-31 | BI16: providers=world_bank; fields=entrepreneurial_dynamism_raw, innovation_research_intensity_raw, investment_signal_raw, administrative_investment_friction_raw; +2 additional fields | BJ16: 1
A17: cn-shenzhen | B17: Shenzhen | C17: China | D17: East Asia | E17: primary | F17: provisional | G17: 3140.67 | H17: 942.2 | I17: 226.13 | J17: 150.75 | K17: 56.53 | L17: 753.76 | N17: 30 | O17: 194.166 | P17: =IF($O17<>"",$O17,$AO17) | R17: 8.95 | S17: 0.5 | W17: 44.73 | X17: 66 | Y17: 85 | Z17: 76.88 | AA17: 36 | AB17: 49.81 | AC17: 26.54 | AD17: 21.58 | AE17: 8.58 | AF17: 2.56 | AG17: 0.1 | AH17: 2.86 | AJ17: =IFERROR(INDEX(Country_Context!$B$2:$B$87,MATCH($C17,Country_Context!$A$2:$A$87,0)),"") | AK17: =IFERROR(INDEX(Country_Context!$C$2:$C$87,MATCH($C17,Country_Context!$A$2:$A$87,0)),"") | AL17: =IFERROR(INDEX(Country_Context!$D$2:$D$87,MATCH($C17,Country_Context!$A$2:$A$87,0)),"") | AM17: =IFERROR(INDEX(Country_Context!$E$2:$E$87,MATCH($C17,Country_Context!$A$2:$A$87,0)),"") | AN17: =IFERROR(INDEX(Country_Context!$F$2:$F$87,MATCH($C17,Country_Context!$A$2:$A$87,0)),"") | AO17: =IFERROR(INDEX(Country_Context!$G$2:$G$87,MATCH($C17,Country_Context!$A$2:$A$87,0)),"") | AP17: https://api.worldbank.org/v2/country/CHN/indicator/NY.GNP.PCAP.PP.CD?format=json&mrv=10 | https://data.worldbank.org/indicator/NY.GNP.PCAP.PP.CD | https://www.who.int/data/gho/data/indicators/indicator-details/GHO/SDGSUICIDE | +3 more | AQ17: Tier 3, Tier 4 | AR17: 2024-12-31 | AS17: providers=world_bank_col_estimate, derived, who_gho, world_bank; fields=gross_income, rent, utilities, transit_cost; +8 additional fields | AT17: https://api.worldbank.org/v2/country/CHN/indicator/VC.IHR.PSRC.P5?format=json&mrv=10 | https://api.worldbank.org/v2/country/CHN/indicator/IT.NET.BBND.P2?format=json&mrv=10 | https://worldweather.wmo.int | AU17: Tier 3 | AV17: 2024-12-31 | AW17: providers=world_bank, wmo_natl_met; fields=personal_safety_raw, digital_infrastructure_raw, climate_sunlight_livability_raw | AX17: https://www.who.int/data/gho/data/indicators/indicator-details/GHO/UHC_INDEX_REPORTED | https://api.worldbank.org/v2/country/CHN/indicator/SE.TER.ENRR?format=json&mrv=10 | https://api.worldbank.org/v2/country/CHN/indicator/SI.POV.GINI?format=json&mrv=10 | +1 more | AY17: Tier 3 | AZ17: 2024-12-31 | BA17: providers=who_gho, world_bank; fields=healthcare_quality_raw, education_quality_raw, equal_opportunity_raw, gini_coefficient | BB17: https://api.worldbank.org/v2/country/CHN/indicator/SM.POP.NETM?format=json&mrv=10 | https://api.worldbank.org/v2/country/CHN/indicator/SG.GEN.PARL.ZS?format=json&mrv=10 | https://api.worldbank.org/v2/country/CHN/indicator/ST.INT.ARVL?format=json&mrv=10 | +1 more | BC17: Tier 3 | BD17: 2025-12-31 | BE17: providers=world_bank; fields=hospitality_belonging_raw, tolerance_pluralism_raw, cultural_public_life_raw, birth_rate_optimism_raw | BF17: https://api.worldbank.org/v2/country/CHN/indicator/IC.BUS.NDNS.ZS?format=json&mrv=10 | https://api.worldbank.org/v2/country/CHN/indicator/GB.XPD.RSDV.GD.ZS?format=json&mrv=10 | https://api.worldbank.org/v2/country/CHN/indicator/BX.KLT.DINV.WD.GD.ZS?format=json&mrv=10 | +3 more | BG17: Tier 3 | BH17: 2024-12-31 | BI17: providers=world_bank; fields=entrepreneurial_dynamism_raw, innovation_research_intensity_raw, investment_signal_raw, administrative_investment_friction_raw; +2 additional fields | BJ17: 1
A18: cn-chengdu | B18: Chengdu | C18: China | D18: East Asia | E18: primary | F18: provisional | G18: 2019 | H18: 429.04 | I18: 102.97 | J18: 68.65 | K18: 25.74 | L18: 343.23 | N18: 21.2501 | O18: 194.166 | P18: =IF($O18<>"",$O18,$AO18) | Q18: 46 | R18: 8.95 | S18: 0.5 | U18: 38 | V18: 95 | W18: 44.73 | X18: 42 | Y18: 85 | Z18: 76.88 | AA18: 36 | AB18: 49.81 | AC18: 26.54 | AD18: 68 | AE18: 8.58 | AF18: 2.56 | AG18: 0.1 | AH18: 2.86 | AJ18: =IFERROR(INDEX(Country_Context!$B$2:$B$87,MATCH($C18,Country_Context!$A$2:$A$87,0)),"") | AK18: =IFERROR(INDEX(Country_Context!$C$2:$C$87,MATCH($C18,Country_Context!$A$2:$A$87,0)),"") | AL18: =IFERROR(INDEX(Country_Context!$D$2:$D$87,MATCH($C18,Country_Context!$A$2:$A$87,0)),"") | AM18: =IFERROR(INDEX(Country_Context!$E$2:$E$87,MATCH($C18,Country_Context!$A$2:$A$87,0)),"") | AN18: =IFERROR(INDEX(Country_Context!$F$2:$F$87,MATCH($C18,Country_Context!$A$2:$A$87,0)),"") | AO18: =IFERROR(INDEX(Country_Context!$G$2:$G$87,MATCH($C18,Country_Context!$A$2:$A$87,0)),"") | AP18: https://api.worldbank.org/v2/country/CHN/indicator/NY.GNP.PCAP.PP.CD?format=json&mrv=10 | https://data.worldbank.org/indicator/NY.GNP.PCAP.PP.CD | https://ilostat.ilo.org | +4 more | AQ18: Tier 3, Tier 4 | AR18: 2024-12-31 | AS18: providers=world_bank_col_estimate, derived, ilo_ilostat, who_gho; fields=gross_income, rent, utilities, transit_cost; +9 additional fields | AT18: https://api.worldbank.org/v2/country/CHN/indicator/VC.IHR.PSRC.P5?format=json&mrv=10 | https://worldweather.wmo.int | https://washdata.org | +1 more | AU18: Tier 3 | AV18: 2024-12-31 | AW18: providers=world_bank, wmo_natl_met, who_unicef_jmp; fields=personal_safety_raw, clean_air_raw, water_sanitation_utility_raw, digital_infrastructure_raw; +1 additional fields | AX18: https://www.who.int/data/gho/data/indicators/indicator-details/GHO/UHC_INDEX_REPORTED | https://api.worldbank.org/v2/country/CHN/indicator/SE.TER.ENRR?format=json&mrv=10 | https://api.worldbank.org/v2/country/CHN/indicator/SI.POV.GINI?format=json&mrv=10 | +1 more | AY18: Tier 3 | AZ18: 2024-12-31 | BA18: providers=who_gho, world_bank; fields=healthcare_quality_raw, education_quality_raw, equal_opportunity_raw, gini_coefficient | BB18: https://api.worldbank.org/v2/country/CHN/indicator/SM.POP.NETM?format=json&mrv=10 | https://api.worldbank.org/v2/country/CHN/indicator/SG.GEN.PARL.ZS?format=json&mrv=10 | https://worldweather.wmo.int | +1 more | BC18: Tier 3 | BD18: 2025-12-31 | BE18: providers=world_bank, wmo_natl_met; fields=hospitality_belonging_raw, tolerance_pluralism_raw, cultural_public_life_raw, birth_rate_optimism_raw | BF18: https://api.worldbank.org/v2/country/CHN/indicator/IC.BUS.NDNS.ZS?format=json&mrv=10 | https://api.worldbank.org/v2/country/CHN/indicator/GB.XPD.RSDV.GD.ZS?format=json&mrv=10 | https://api.worldbank.org/v2/country/CHN/indicator/BX.KLT.DINV.WD.GD.ZS?format=json&mrv=10 | +3 more | BG18: Tier 3 | BH18: 2024-12-31 | BI18: providers=world_bank; fields=entrepreneurial_dynamism_raw, innovation_research_intensity_raw, investment_signal_raw, administrative_investment_friction_raw; +2 additional fields | BJ18: 1
A19: cn-chongqing | B19: Chongqing | C19: China | D19: East Asia | E19: primary | F19: provisional | G19: 1906.83 | H19: 381.37 | I19: 91.53 | J19: 61.02 | K19: 22.88 | L19: 305.09 | N19: 20.0002 | O19: 194.166 | P19: =IF($O19<>"",$O19,$AO19) | Q19: 46 | R19: 8.95 | S19: 0.5 | U19: 40 | V19: 95 | W19: 44.73 | X19: 44 | Y19: 85 | Z19: 76.88 | AA19: 36 | AB19: 49.81 | AC19: 26.54 | AD19: 58 | AE19: 8.58 | AF19: 2.56 | AG19: 0.1 | AH19: 2.86 | AJ19: =IFERROR(INDEX(Country_Context!$B$2:$B$87,MATCH($C19,Country_Context!$A$2:$A$87,0)),"") | AK19: =IFERROR(INDEX(Country_Context!$C$2:$C$87,MATCH($C19,Country_Context!$A$2:$A$87,0)),"") | AL19: =IFERROR(INDEX(Country_Context!$D$2:$D$87,MATCH($C19,Country_Context!$A$2:$A$87,0)),"") | AM19: =IFERROR(INDEX(Country_Context!$E$2:$E$87,MATCH($C19,Country_Context!$A$2:$A$87,0)),"") | AN19: =IFERROR(INDEX(Country_Context!$F$2:$F$87,MATCH($C19,Country_Context!$A$2:$A$87,0)),"") | AO19: =IFERROR(INDEX(Country_Context!$G$2:$G$87,MATCH($C19,Country_Context!$A$2:$A$87,0)),"") | AP19: https://api.worldbank.org/v2/country/CHN/indicator/NY.GNP.PCAP.PP.CD?format=json&mrv=10 | https://data.worldbank.org/indicator/NY.GNP.PCAP.PP.CD | https://ilostat.ilo.org | +4 more | AQ19: Tier 3, Tier 4 | AR19: 2024-12-31 | AS19: providers=world_bank_col_estimate, derived, ilo_ilostat, who_gho; fields=gross_income, rent, utilities, transit_cost; +9 additional fields | AT19: https://api.worldbank.org/v2/country/CHN/indicator/VC.IHR.PSRC.P5?format=json&mrv=10 | https://worldweather.wmo.int | https://washdata.org | +1 more | AU19: Tier 3 | AV19: 2024-12-31 | AW19: providers=world_bank, wmo_natl_met, who_unicef_jmp; fields=personal_safety_raw, clean_air_raw, water_sanitation_utility_raw, digital_infrastructure_raw; +1 additional fields | AX19: https://www.who.int/data/gho/data/indicators/indicator-details/GHO/UHC_INDEX_REPORTED | https://api.worldbank.org/v2/country/CHN/indicator/SE.TER.ENRR?format=json&mrv=10 | https://api.worldbank.org/v2/country/CHN/indicator/SI.POV.GINI?format=json&mrv=10 | +1 more | AY19: Tier 3 | AZ19: 2024-12-31 | BA19: providers=who_gho, world_bank; fields=healthcare_quality_raw, education_quality_raw, equal_opportunity_raw, gini_coefficient | BB19: https://api.worldbank.org/v2/country/CHN/indicator/SM.POP.NETM?format=json&mrv=10 | https://api.worldbank.org/v2/country/CHN/indicator/SG.GEN.PARL.ZS?format=json&mrv=10 | https://worldweather.wmo.int | +1 more | BC19: Tier 3 | BD19: 2025-12-31 | BE19: providers=world_bank, wmo_natl_met; fields=hospitality_belonging_raw, tolerance_pluralism_raw, cultural_public_life_raw, birth_rate_optimism_raw | BF19: https://api.worldbank.org/v2/country/CHN/indicator/IC.BUS.NDNS.ZS?format=json&mrv=10 | https://api.worldbank.org/v2/country/CHN/indicator/GB.XPD.RSDV.GD.ZS?format=json&mrv=10 | https://api.worldbank.org/v2/country/CHN/indicator/BX.KLT.DINV.WD.GD.ZS?format=json&mrv=10 | +3 more | BG19: Tier 3 | BH19: 2024-12-31 | BI19: providers=world_bank; fields=entrepreneurial_dynamism_raw, innovation_research_intensity_raw, investment_signal_raw, administrative_investment_friction_raw; +2 additional fields | BJ19: 1
A20: cn-hangzhou | B20: Hangzhou | C20: China | D20: East Asia | E20: primary | F20: provisional | G20: 2692 | H20: 740.3 | I20: 177.67 | J20: 118.45 | K20: 44.42 | L20: 592.24 | N20: 27.5 | O20: 194.166 | P20: =IF($O20<>"",$O20,$AO20) | Q20: 46 | R20: 8.95 | S20: 0.5 | U20: 30 | V20: 95 | W20: 44.73 | X20: 56 | Y20: 85 | Z20: 76.88 | AA20: 36 | AB20: 49.81 | AC20: 26.54 | AD20: 72 | AE20: 8.58 | AF20: 2.56 | AG20: 0.1 | AH20: 2.86 | AJ20: =IFERROR(INDEX(Country_Context!$B$2:$B$87,MATCH($C20,Country_Context!$A$2:$A$87,0)),"") | AK20: =IFERROR(INDEX(Country_Context!$C$2:$C$87,MATCH($C20,Country_Context!$A$2:$A$87,0)),"") | AL20: =IFERROR(INDEX(Country_Context!$D$2:$D$87,MATCH($C20,Country_Context!$A$2:$A$87,0)),"") | AM20: =IFERROR(INDEX(Country_Context!$E$2:$E$87,MATCH($C20,Country_Context!$A$2:$A$87,0)),"") | AN20: =IFERROR(INDEX(Country_Context!$F$2:$F$87,MATCH($C20,Country_Context!$A$2:$A$87,0)),"") | AO20: =IFERROR(INDEX(Country_Context!$G$2:$G$87,MATCH($C20,Country_Context!$A$2:$A$87,0)),"") | AP20: https://api.worldbank.org/v2/country/CHN/indicator/NY.GNP.PCAP.PP.CD?format=json&mrv=10 | https://data.worldbank.org/indicator/NY.GNP.PCAP.PP.CD | https://ilostat.ilo.org | +4 more | AQ20: Tier 3, Tier 4 | AR20: 2024-12-31 | AS20: providers=world_bank_col_estimate, derived, ilo_ilostat, who_gho; fields=gross_income, rent, utilities, transit_cost; +9 additional fields | AT20: https://api.worldbank.org/v2/country/CHN/indicator/VC.IHR.PSRC.P5?format=json&mrv=10 | https://worldweather.wmo.int | https://washdata.org | +1 more | AU20: Tier 3 | AV20: 2024-12-31 | AW20: providers=world_bank, wmo_natl_met, who_unicef_jmp; fields=personal_safety_raw, clean_air_raw, water_sanitation_utility_raw, digital_infrastructure_raw; +1 additional fields | AX20: https://www.who.int/data/gho/data/indicators/indicator-details/GHO/UHC_INDEX_REPORTED | https://api.worldbank.org/v2/country/CHN/indicator/SE.TER.ENRR?format=json&mrv=10 | https://api.worldbank.org/v2/country/CHN/indicator/SI.POV.GINI?format=json&mrv=10 | +1 more | AY20: Tier 3 | AZ20: 2024-12-31 | BA20: providers=who_gho, world_bank; fields=healthcare_quality_raw, education_quality_raw, equal_opportunity_raw, gini_coefficient | BB20: https://api.worldbank.org/v2/country/CHN/indicator/SM.POP.NETM?format=json&mrv=10 | https://api.worldbank.org/v2/country/CHN/indicator/SG.GEN.PARL.ZS?format=json&mrv=10 | https://worldweather.wmo.int | +1 more | BC20: Tier 3 | BD20: 2025-12-31 | BE20: providers=world_bank, wmo_natl_met; fields=hospitality_belonging_raw, tolerance_pluralism_raw, cultural_public_life_raw, birth_rate_optimism_raw | BF20: https://api.worldbank.org/v2/country/CHN/indicator/IC.BUS.NDNS.ZS?format=json&mrv=10 | https://api.worldbank.org/v2/country/CHN/indicator/GB.XPD.RSDV.GD.ZS?format=json&mrv=10 | https://api.worldbank.org/v2/country/CHN/indicator/BX.KLT.DINV.WD.GD.ZS?format=json&mrv=10 | +3 more | BG20: Tier 3 | BH20: 2024-12-31 | BI20: providers=world_bank; fields=entrepreneurial_dynamism_raw, innovation_research_intensity_raw, investment_signal_raw, administrative_investment_friction_raw; +2 additional fields | BJ20: 1
A21: jp-hiroshima | B21: Hiroshima | C21: Japan | D21: East Asia | E21: primary | F21: provisional | G21: 3930.54 | H21: 786.11 | I21: 188.67 | J21: 125.78 | K21: 47.17 | L21: 628.89 | N21: 20.0001 | O21: 123.1289 | P21: =IF($O21<>"",$O21,$AO21) | Q21: 36.6 | R21: 17.43 | S21: 0.23 | V21: 98.73 | W21: 38.63 | Y21: 86 | Z21: 64.89 | AA21: 32.3 | AB21: 51.13 | AC21: 15.7 | AD21: 33.2 | AE21: 0.51 | AF21: 3.41 | AG21: 0.4 | AH21: 1.03 | AJ21: =IFERROR(INDEX(Country_Context!$B$2:$B$87,MATCH($C21,Country_Context!$A$2:$A$87,0)),"") | AK21: =IFERROR(INDEX(Country_Context!$C$2:$C$87,MATCH($C21,Country_Context!$A$2:$A$87,0)),"") | AL21: =IFERROR(INDEX(Country_Context!$D$2:$D$87,MATCH($C21,Country_Context!$A$2:$A$87,0)),"") | AM21: =IFERROR(INDEX(Country_Context!$E$2:$E$87,MATCH($C21,Country_Context!$A$2:$A$87,0)),"") | AN21: =IFERROR(INDEX(Country_Context!$F$2:$F$87,MATCH($C21,Country_Context!$A$2:$A$87,0)),"") | AO21: =IFERROR(INDEX(Country_Context!$G$2:$G$87,MATCH($C21,Country_Context!$A$2:$A$87,0)),"") | AP21: https://api.worldbank.org/v2/country/JPN/indicator/NY.GNP.PCAP.PP.CD?format=json&mrv=10 | https://data.worldbank.org/indicator/NY.GNP.PCAP.PP.CD | https://ilostat.ilo.org/data/indicator/?id=HOW_TEMP_SEX_ECO_NB_A&ref_area=JPN | +3 more | AQ21: Tier 3, Tier 4 | AR21: 2024-12-31 | AS21: providers=world_bank_col_estimate, derived, ilo_ilostat, who_gho; fields=gross_income, rent, utilities, transit_cost; +8 additional fields | AT21: https://api.worldbank.org/v2/country/JPN/indicator/VC.IHR.PSRC.P5?format=json&mrv=10 | https://api.worldbank.org/v2/country/JPN/indicator/SH.H2O.SMDW.ZS?format=json&mrv=10 | https://api.worldbank.org/v2/country/JPN/indicator/IT.NET.BBND.P2?format=json&mrv=10 | AU21: Tier 3 | AV21: 2024-12-31 | AW21: providers=world_bank; fields=personal_safety_raw, water_sanitation_utility_raw, digital_infrastructure_raw | AX21: https://www.who.int/data/gho/data/indicators/indicator-details/GHO/UHC_INDEX_REPORTED | https://api.worldbank.org/v2/country/JPN/indicator/SE.TER.ENRR?format=json&mrv=10 | https://api.worldbank.org/v2/country/JPN/indicator/SI.POV.GINI?format=json&mrv=10 | +1 more | AY21: Tier 3 | AZ21: 2023-12-31 | BA21: providers=who_gho, world_bank; fields=healthcare_quality_raw, education_quality_raw, equal_opportunity_raw, gini_coefficient | BB21: https://api.worldbank.org/v2/country/JPN/indicator/SM.POP.NETM?format=json&mrv=10 | https://api.worldbank.org/v2/country/JPN/indicator/SG.GEN.PARL.ZS?format=json&mrv=10 | https://api.worldbank.org/v2/country/JPN/indicator/ST.INT.ARVL?format=json&mrv=10 | +1 more | BC21: Tier 3 | BD21: 2025-12-31 | BE21: providers=world_bank; fields=hospitality_belonging_raw, tolerance_pluralism_raw, cultural_public_life_raw, birth_rate_optimism_raw | BF21: https://api.worldbank.org/v2/country/JPN/indicator/IC.BUS.NDNS.ZS?format=json&mrv=10 | https://api.worldbank.org/v2/country/JPN/indicator/GB.XPD.RSDV.GD.ZS?format=json&mrv=10 | https://api.worldbank.org/v2/country/JPN/indicator/BX.KLT.DINV.WD.GD.ZS?format=json&mrv=10 | +3 more | BG21: Tier 3 | BH21: 2024-12-31 | BI21: providers=world_bank; fields=entrepreneurial_dynamism_raw, innovation_research_intensity_raw, investment_signal_raw, administrative_investment_friction_raw; +2 additional fields | BJ21: 1.2
A22: kr-suwon | B22: Suwon | C22: South Korea | D22: East Asia | E22: primary | F22: provisional | G22: 5160.83 | H22: 1161.19 | I22: 278.68 | J22: 185.79 | K22: 69.67 | L22: 928.95 | N22: 22.5001 | O22: 160.3472 | P22: =IF($O22<>"",$O22,$AO22) | Q22: 38.49 | R22: 27.53 | S22: 0.48 | U22: 22 | V22: 99 | W22: 46.57 | X22: 60 | Y22: 88 | Z22: 106.71 | AA22: 32.9 | AB22: 51.27 | AC22: 20 | AD22: 65 | AE22: 3.09 | AF22: 5.21 | AG22: 0.81 | AH22: 1.38 | AJ22: =IFERROR(INDEX(Country_Context!$B$2:$B$87,MATCH($C22,Country_Context!$A$2:$A$87,0)),"") | AK22: =IFERROR(INDEX(Country_Context!$C$2:$C$87,MATCH($C22,Country_Context!$A$2:$A$87,0)),"") | AL22: =IFERROR(INDEX(Country_Context!$D$2:$D$87,MATCH($C22,Country_Context!$A$2:$A$87,0)),"") | AM22: =IFERROR(INDEX(Country_Context!$E$2:$E$87,MATCH($C22,Country_Context!$A$2:$A$87,0)),"") | AN22: =IFERROR(INDEX(Country_Context!$F$2:$F$87,MATCH($C22,Country_Context!$A$2:$A$87,0)),"") | AO22: =IFERROR(INDEX(Country_Context!$G$2:$G$87,MATCH($C22,Country_Context!$A$2:$A$87,0)),"") | AP22: https://api.worldbank.org/v2/country/KOR/indicator/NY.GNP.PCAP.PP.CD?format=json&mrv=10 | https://data.worldbank.org/indicator/NY.GNP.PCAP.PP.CD | https://ilostat.ilo.org/data/indicator/?id=HOW_TEMP_SEX_ECO_NB_A&ref_area=KOR | +4 more | AQ22: Tier 3, Tier 4 | AR22: 2025-12-31 | AS22: providers=world_bank_col_estimate, derived, ilo_ilostat, who_gho; fields=gross_income, rent, utilities, transit_cost; +9 additional fields | AT22: https://api.worldbank.org/v2/country/KOR/indicator/VC.IHR.PSRC.P5?format=json&mrv=10 | https://worldweather.wmo.int | https://washdata.org | +1 more | AU22: Tier 3 | AV22: 2024-12-31 | AW22: providers=world_bank, wmo_natl_met, who_unicef_jmp; fields=personal_safety_raw, clean_air_raw, water_sanitation_utility_raw, digital_infrastructure_raw; +1 additional fields | AX22: https://www.who.int/data/gho/data/indicators/indicator-details/GHO/UHC_INDEX_REPORTED | https://api.worldbank.org/v2/country/KOR/indicator/SE.TER.ENRR?format=json&mrv=10 | https://api.worldbank.org/v2/country/KOR/indicator/SI.POV.GINI?format=json&mrv=10 | +1 more | AY22: Tier 3 | AZ22: 2023-12-31 | BA22: providers=who_gho, world_bank; fields=healthcare_quality_raw, education_quality_raw, equal_opportunity_raw, gini_coefficient | BB22: https://api.worldbank.org/v2/country/KOR/indicator/SM.POP.NETM?format=json&mrv=10 | https://api.worldbank.org/v2/country/KOR/indicator/SG.GEN.PARL.ZS?format=json&mrv=10 | https://worldweather.wmo.int | +1 more | BC22: Tier 3 | BD22: 2025-12-31 | BE22: providers=world_bank, wmo_natl_met; fields=hospitality_belonging_raw, tolerance_pluralism_raw, cultural_public_life_raw, birth_rate_optimism_raw | BF22: https://api.worldbank.org/v2/country/KOR/indicator/IC.BUS.NDNS.ZS?format=json&mrv=10 | https://api.worldbank.org/v2/country/KOR/indicator/GB.XPD.RSDV.GD.ZS?format=json&mrv=10 | https://api.worldbank.org/v2/country/KOR/indicator/BX.KLT.DINV.WD.GD.ZS?format=json&mrv=10 | +3 more | BG22: Tier 3 | BH22: 2024-12-31 | BI22: providers=world_bank; fields=entrepreneurial_dynamism_raw, innovation_research_intensity_raw, investment_signal_raw, administrative_investment_friction_raw; +2 additional fields | BJ22: 0.72
A23: kr-jeju-city | B23: Jeju City | C23: South Korea | D23: East Asia | E23: secondary | F23: locked | G23: 5160.83 | H23: 1096.68 | I23: 263.2 | J23: 175.47 | K23: 65.8 | L23: 877.34 | N23: 21.2501 | O23: 160.3472 | P23: =IF($O23<>"",$O23,$AO23) | Q23: 38.49 | R23: 27.53 | S23: 0.48 | V23: 99.28 | W23: 46.57 | X23: 60 | Y23: 88 | Z23: 106.71 | AA23: 32.9 | AB23: 51.27 | AC23: 20 | AD23: 48.68 | AE23: 3.09 | AF23: 5.21 | AG23: 0.81 | AH23: 1.38 | AJ23: =IFERROR(INDEX(Country_Context!$B$2:$B$87,MATCH($C23,Country_Context!$A$2:$A$87,0)),"") | AK23: =IFERROR(INDEX(Country_Context!$C$2:$C$87,MATCH($C23,Country_Context!$A$2:$A$87,0)),"") | AL23: =IFERROR(INDEX(Country_Context!$D$2:$D$87,MATCH($C23,Country_Context!$A$2:$A$87,0)),"") | AM23: =IFERROR(INDEX(Country_Context!$E$2:$E$87,MATCH($C23,Country_Context!$A$2:$A$87,0)),"") | AN23: =IFERROR(INDEX(Country_Context!$F$2:$F$87,MATCH($C23,Country_Context!$A$2:$A$87,0)),"") | AO23: =IFERROR(INDEX(Country_Context!$G$2:$G$87,MATCH($C23,Country_Context!$A$2:$A$87,0)),"") | AP23: https://api.worldbank.org/v2/country/KOR/indicator/NY.GNP.PCAP.PP.CD?format=json&mrv=10 | https://data.worldbank.org/indicator/NY.GNP.PCAP.PP.CD | https://ilostat.ilo.org/data/indicator/?id=HOW_TEMP_SEX_ECO_NB_A&ref_area=KOR | +4 more | AQ23: Tier 3, Tier 4 | AR23: 2025-12-31 | AS23: providers=world_bank_col_estimate, derived, ilo_ilostat, who_gho; fields=gross_income, rent, utilities, transit_cost; +9 additional fields | AT23: https://api.worldbank.org/v2/country/KOR/indicator/VC.IHR.PSRC.P5?format=json&mrv=10 | https://api.worldbank.org/v2/country/KOR/indicator/SH.H2O.SMDW.ZS?format=json&mrv=10 | https://api.worldbank.org/v2/country/KOR/indicator/IT.NET.BBND.P2?format=json&mrv=10 | +1 more | AU23: Tier 3 | AV23: 2024-12-31 | AW23: providers=world_bank, wmo_natl_met; fields=personal_safety_raw, water_sanitation_utility_raw, digital_infrastructure_raw, climate_sunlight_livability_raw | AX23: https://www.who.int/data/gho/data/indicators/indicator-details/GHO/UHC_INDEX_REPORTED | https://api.worldbank.org/v2/country/KOR/indicator/SE.TER.ENRR?format=json&mrv=10 | https://api.worldbank.org/v2/country/KOR/indicator/SI.POV.GINI?format=json&mrv=10 | +1 more | AY23: Tier 3 | AZ23: 2023-12-31 | BA23: providers=who_gho, world_bank; fields=healthcare_quality_raw, education_quality_raw, equal_opportunity_raw, gini_coefficient | BB23: https://api.worldbank.org/v2/country/KOR/indicator/SM.POP.NETM?format=json&mrv=10 | https://api.worldbank.org/v2/country/KOR/indicator/SG.GEN.PARL.ZS?format=json&mrv=10 | https://api.worldbank.org/v2/country/KOR/indicator/ST.INT.ARVL?format=json&mrv=10 | +1 more | BC23: Tier 3 | BD23: 2025-12-31 | BE23: providers=world_bank; fields=hospitality_belonging_raw, tolerance_pluralism_raw, cultural_public_life_raw, birth_rate_optimism_raw | BF23: https://api.worldbank.org/v2/country/KOR/indicator/IC.BUS.NDNS.ZS?format=json&mrv=10 | https://api.worldbank.org/v2/country/KOR/indicator/GB.XPD.RSDV.GD.ZS?format=json&mrv=10 | https://api.worldbank.org/v2/country/KOR/indicator/BX.KLT.DINV.WD.GD.ZS?format=json&mrv=10 | +3 more | BG23: Tier 3 | BH23: 2024-12-31 | BI23: providers=world_bank; fields=entrepreneurial_dynamism_raw, innovation_research_intensity_raw, investment_signal_raw, administrative_investment_friction_raw; +2 additional fields | BJ23: 0.72
A24: jp-fukuoka | B24: Fukuoka | C24: Japan | D24: East Asia | E24: secondary | F24: locked | G24: 3930.54 | H24: 786.11 | I24: 188.67 | J24: 125.78 | K24: 47.17 | L24: 628.89 | N24: 20.0001 | O24: 123.1289 | P24: =IF($O24<>"",$O24,$AO24) | Q24: 36.6 | R24: 17.43 | S24: 0.23 | V24: 98.73 | W24: 38.63 | X24: 67 | Y24: 86 | Z24: 64.89 | AA24: 32.3 | AB24: 51.13 | AC24: 15.7 | AD24: 33.2 | AE24: 0.51 | AF24: 3.41 | AG24: 0.4 | AH24: 1.03 | AJ24: =IFERROR(INDEX(Country_Context!$B$2:$B$87,MATCH($C24,Country_Context!$A$2:$A$87,0)),"") | AK24: =IFERROR(INDEX(Country_Context!$C$2:$C$87,MATCH($C24,Country_Context!$A$2:$A$87,0)),"") | AL24: =IFERROR(INDEX(Country_Context!$D$2:$D$87,MATCH($C24,Country_Context!$A$2:$A$87,0)),"") | AM24: =IFERROR(INDEX(Country_Context!$E$2:$E$87,MATCH($C24,Country_Context!$A$2:$A$87,0)),"") | AN24: =IFERROR(INDEX(Country_Context!$F$2:$F$87,MATCH($C24,Country_Context!$A$2:$A$87,0)),"") | AO24: =IFERROR(INDEX(Country_Context!$G$2:$G$87,MATCH($C24,Country_Context!$A$2:$A$87,0)),"") | AP24: https://api.worldbank.org/v2/country/JPN/indicator/NY.GNP.PCAP.PP.CD?format=json&mrv=10 | https://data.worldbank.org/indicator/NY.GNP.PCAP.PP.CD | https://ilostat.ilo.org/data/indicator/?id=HOW_TEMP_SEX_ECO_NB_A&ref_area=JPN | +3 more | AQ24: Tier 3, Tier 4 | AR24: 2024-12-31 | AS24: providers=world_bank_col_estimate, derived, ilo_ilostat, who_gho; fields=gross_income, rent, utilities, transit_cost; +8 additional fields | AT24: https://api.worldbank.org/v2/country/JPN/indicator/VC.IHR.PSRC.P5?format=json&mrv=10 | https://api.worldbank.org/v2/country/JPN/indicator/SH.H2O.SMDW.ZS?format=json&mrv=10 | https://api.worldbank.org/v2/country/JPN/indicator/IT.NET.BBND.P2?format=json&mrv=10 | +1 more | AU24: Tier 3 | AV24: 2024-12-31 | AW24: providers=world_bank, wmo_natl_met; fields=personal_safety_raw, water_sanitation_utility_raw, digital_infrastructure_raw, climate_sunlight_livability_raw | AX24: https://www.who.int/data/gho/data/indicators/indicator-details/GHO/UHC_INDEX_REPORTED | https://api.worldbank.org/v2/country/JPN/indicator/SE.TER.ENRR?format=json&mrv=10 | https://api.worldbank.org/v2/country/JPN/indicator/SI.POV.GINI?format=json&mrv=10 | +1 more | AY24: Tier 3 | AZ24: 2023-12-31 | BA24: providers=who_gho, world_bank; fields=healthcare_quality_raw, education_quality_raw, equal_opportunity_raw, gini_coefficient | BB24: https://api.worldbank.org/v2/country/JPN/indicator/SM.POP.NETM?format=json&mrv=10 | https://api.worldbank.org/v2/country/JPN/indicator/SG.GEN.PARL.ZS?format=json&mrv=10 | https://api.worldbank.org/v2/country/JPN/indicator/ST.INT.ARVL?format=json&mrv=10 | +1 more | BC24: Tier 3 | BD24: 2025-12-31 | BE24: providers=world_bank; fields=hospitality_belonging_raw, tolerance_pluralism_raw, cultural_public_life_raw, birth_rate_optimism_raw | BF24: https://api.worldbank.org/v2/country/JPN/indicator/IC.BUS.NDNS.ZS?format=json&mrv=10 | https://api.worldbank.org/v2/country/JPN/indicator/GB.XPD.RSDV.GD.ZS?format=json&mrv=10 | https://api.worldbank.org/v2/country/JPN/indicator/BX.KLT.DINV.WD.GD.ZS?format=json&mrv=10 | +3 more | BG24: Tier 3 | BH24: 2024-12-31 | BI24: providers=world_bank; fields=entrepreneurial_dynamism_raw, innovation_research_intensity_raw, investment_signal_raw, administrative_investment_friction_raw; +2 additional fields | BJ24: 1.2
A25: jp-kobe | B25: Kobe | C25: Japan | D25: East Asia | E25: secondary | F25: locked | G25: 4161.75 | H25: 884.37 | I25: 212.25 | J25: 141.5 | K25: 53.06 | L25: 707.5 | N25: 21.25 | O25: 123.1289 | P25: =IF($O25<>"",$O25,$AO25) | Q25: 36.6 | R25: 17.43 | S25: 0.23 | V25: 98.73 | W25: 38.63 | Y25: 86 | Z25: 64.89 | AA25: 32.3 | AB25: 51.13 | AC25: 15.7 | AD25: 33.2 | AE25: 0.51 | AF25: 3.41 | AG25: 0.4 | AH25: 1.03 | AJ25: =IFERROR(INDEX(Country_Context!$B$2:$B$87,MATCH($C25,Country_Context!$A$2:$A$87,0)),"") | AK25: =IFERROR(INDEX(Country_Context!$C$2:$C$87,MATCH($C25,Country_Context!$A$2:$A$87,0)),"") | AL25: =IFERROR(INDEX(Country_Context!$D$2:$D$87,MATCH($C25,Country_Context!$A$2:$A$87,0)),"") | AM25: =IFERROR(INDEX(Country_Context!$E$2:$E$87,MATCH($C25,Country_Context!$A$2:$A$87,0)),"") | AN25: =IFERROR(INDEX(Country_Context!$F$2:$F$87,MATCH($C25,Country_Context!$A$2:$A$87,0)),"") | AO25: =IFERROR(INDEX(Country_Context!$G$2:$G$87,MATCH($C25,Country_Context!$A$2:$A$87,0)),"") | AP25: https://api.worldbank.org/v2/country/JPN/indicator/NY.GNP.PCAP.PP.CD?format=json&mrv=10 | https://data.worldbank.org/indicator/NY.GNP.PCAP.PP.CD | https://ilostat.ilo.org/data/indicator/?id=HOW_TEMP_SEX_ECO_NB_A&ref_area=JPN | +3 more | AQ25: Tier 3, Tier 4 | AR25: 2024-12-31 | AS25: providers=world_bank_col_estimate, derived, ilo_ilostat, who_gho; fields=gross_income, rent, utilities, transit_cost; +8 additional fields | AT25: https://api.worldbank.org/v2/country/JPN/indicator/VC.IHR.PSRC.P5?format=json&mrv=10 | https://api.worldbank.org/v2/country/JPN/indicator/SH.H2O.SMDW.ZS?format=json&mrv=10 | https://api.worldbank.org/v2/country/JPN/indicator/IT.NET.BBND.P2?format=json&mrv=10 | AU25: Tier 3 | AV25: 2024-12-31 | AW25: providers=world_bank; fields=personal_safety_raw, water_sanitation_utility_raw, digital_infrastructure_raw | AX25: https://www.who.int/data/gho/data/indicators/indicator-details/GHO/UHC_INDEX_REPORTED | https://api.worldbank.org/v2/country/JPN/indicator/SE.TER.ENRR?format=json&mrv=10 | https://api.worldbank.org/v2/country/JPN/indicator/SI.POV.GINI?format=json&mrv=10 | +1 more | AY25: Tier 3 | AZ25: 2023-12-31 | BA25: providers=who_gho, world_bank; fields=healthcare_quality_raw, education_quality_raw, equal_opportunity_raw, gini_coefficient | BB25: https://api.worldbank.org/v2/country/JPN/indicator/SM.POP.NETM?format=json&mrv=10 | https://api.worldbank.org/v2/country/JPN/indicator/SG.GEN.PARL.ZS?format=json&mrv=10 | https://api.worldbank.org/v2/country/JPN/indicator/ST.INT.ARVL?format=json&mrv=10 | +1 more | BC25: Tier 3 | BD25: 2025-12-31 | BE25: providers=world_bank; fields=hospitality_belonging_raw, tolerance_pluralism_raw, cultural_public_life_raw, birth_rate_optimism_raw | BF25: https://api.worldbank.org/v2/country/JPN/indicator/IC.BUS.NDNS.ZS?format=json&mrv=10 | https://api.worldbank.org/v2/country/JPN/indicator/GB.XPD.RSDV.GD.ZS?format=json&mrv=10 | https://api.worldbank.org/v2/country/JPN/indicator/BX.KLT.DINV.WD.GD.ZS?format=json&mrv=10 | +3 more | BG25: Tier 3 | BH25: 2024-12-31 | BI25: providers=world_bank; fields=entrepreneurial_dynamism_raw, innovation_research_intensity_raw, investment_signal_raw, administrative_investment_friction_raw; +2 additional fields | BJ25: 1.2
A26: jp-sapporo | B26: Sapporo | C26: Japan | D26: East Asia | E26: secondary | F26: locked | G26: 3930.54 | H26: 786.11 | I26: 188.67 | J26: 125.78 | K26: 47.17 | L26: 628.89 | N26: 20.0001 | O26: 123.1289 | P26: =IF($O26<>"",$O26,$AO26) | Q26: 36.6 | R26: 17.43 | S26: 0.23 | V26: 98.73 | W26: 38.63 | X26: 50 | Y26: 86 | Z26: 64.89 | AA26: 32.3 | AB26: 51.13 | AC26: 15.7 | AD26: 33.2 | AE26: 0.51 | AF26: 3.41 | AG26: 0.4 | AH26: 1.03 | AJ26: =IFERROR(INDEX(Country_Context!$B$2:$B$87,MATCH($C26,Country_Context!$A$2:$A$87,0)),"") | AK26: =IFERROR(INDEX(Country_Context!$C$2:$C$87,MATCH($C26,Country_Context!$A$2:$A$87,0)),"") | AL26: =IFERROR(INDEX(Country_Context!$D$2:$D$87,MATCH($C26,Country_Context!$A$2:$A$87,0)),"") | AM26: =IFERROR(INDEX(Country_Context!$E$2:$E$87,MATCH($C26,Country_Context!$A$2:$A$87,0)),"") | AN26: =IFERROR(INDEX(Country_Context!$F$2:$F$87,MATCH($C26,Country_Context!$A$2:$A$87,0)),"") | AO26: =IFERROR(INDEX(Country_Context!$G$2:$G$87,MATCH($C26,Country_Context!$A$2:$A$87,0)),"") | AP26: https://api.worldbank.org/v2/country/JPN/indicator/NY.GNP.PCAP.PP.CD?format=json&mrv=10 | https://data.worldbank.org/indicator/NY.GNP.PCAP.PP.CD | https://ilostat.ilo.org/data/indicator/?id=HOW_TEMP_SEX_ECO_NB_A&ref_area=JPN | +3 more | AQ26: Tier 3, Tier 4 | AR26: 2024-12-31 | AS26: providers=world_bank_col_estimate, derived, ilo_ilostat, who_gho; fields=gross_income, rent, utilities, transit_cost; +8 additional fields | AT26: https://api.worldbank.org/v2/country/JPN/indicator/VC.IHR.PSRC.P5?format=json&mrv=10 | https://api.worldbank.org/v2/country/JPN/indicator/SH.H2O.SMDW.ZS?format=json&mrv=10 | https://api.worldbank.org/v2/country/JPN/indicator/IT.NET.BBND.P2?format=json&mrv=10 | +1 more | AU26: Tier 3 | AV26: 2024-12-31 | AW26: providers=world_bank, wmo_natl_met; fields=personal_safety_raw, water_sanitation_utility_raw, digital_infrastructure_raw, climate_sunlight_livability_raw | AX26: https://www.who.int/data/gho/data/indicators/indicator-details/GHO/UHC_INDEX_REPORTED | https://api.worldbank.org/v2/country/JPN/indicator/SE.TER.ENRR?format=json&mrv=10 | https://api.worldbank.org/v2/country/JPN/indicator/SI.POV.GINI?format=json&mrv=10 | +1 more | AY26: Tier 3 | AZ26: 2023-12-31 | BA26: providers=who_gho, world_bank; fields=healthcare_quality_raw, education_quality_raw, equal_opportunity_raw, gini_coefficient | BB26: https://api.worldbank.org/v2/country/JPN/indicator/SM.POP.NETM?format=json&mrv=10 | https://api.worldbank.org/v2/country/JPN/indicator/SG.GEN.PARL.ZS?format=json&mrv=10 | https://api.worldbank.org/v2/country/JPN/indicator/ST.INT.ARVL?format=json&mrv=10 | +1 more | BC26: Tier 3 | BD26: 2025-12-31 | BE26: providers=world_bank; fields=hospitality_belonging_raw, tolerance_pluralism_raw, cultural_public_life_raw, birth_rate_optimism_raw | BF26: https://api.worldbank.org/v2/country/JPN/indicator/IC.BUS.NDNS.ZS?format=json&mrv=10 | https://api.worldbank.org/v2/country/JPN/indicator/GB.XPD.RSDV.GD.ZS?format=json&mrv=10 | https://api.worldbank.org/v2/country/JPN/indicator/BX.KLT.DINV.WD.GD.ZS?format=json&mrv=10 | +3 more | BG26: Tier 3 | BH26: 2024-12-31 | BI26: providers=world_bank; fields=entrepreneurial_dynamism_raw, innovation_research_intensity_raw, investment_signal_raw, administrative_investment_friction_raw; +2 additional fields | BJ26: 1.2
A27: cn-tianjin | B27: Tianjin | C27: China | D27: East Asia | E27: secondary | F27: provisional | G27: 2131.17 | H27: 452.87 | I27: 108.69 | J27: 72.46 | K27: 27.17 | L27: 362.3 | N27: 21.2498 | O27: 194.166 | P27: =IF($O27<>"",$O27,$AO27) | R27: 8.95 | S27: 0.5 | W27: 44.73 | X27: 52 | Y27: 85 | Z27: 76.88 | AA27: 36 | AB27: 49.81 | AC27: 26.54 | AD27: 21.58 | AE27: 8.58 | AF27: 2.56 | AG27: 0.1 | AH27: 2.86 | AJ27: =IFERROR(INDEX(Country_Context!$B$2:$B$87,MATCH($C27,Country_Context!$A$2:$A$87,0)),"") | AK27: =IFERROR(INDEX(Country_Context!$C$2:$C$87,MATCH($C27,Country_Context!$A$2:$A$87,0)),"") | AL27: =IFERROR(INDEX(Country_Context!$D$2:$D$87,MATCH($C27,Country_Context!$A$2:$A$87,0)),"") | AM27: =IFERROR(INDEX(Country_Context!$E$2:$E$87,MATCH($C27,Country_Context!$A$2:$A$87,0)),"") | AN27: =IFERROR(INDEX(Country_Context!$F$2:$F$87,MATCH($C27,Country_Context!$A$2:$A$87,0)),"") | AO27: =IFERROR(INDEX(Country_Context!$G$2:$G$87,MATCH($C27,Country_Context!$A$2:$A$87,0)),"") | AP27: https://api.worldbank.org/v2/country/CHN/indicator/NY.GNP.PCAP.PP.CD?format=json&mrv=10 | https://data.worldbank.org/indicator/NY.GNP.PCAP.PP.CD | https://www.who.int/data/gho/data/indicators/indicator-details/GHO/SDGSUICIDE | +3 more | AQ27: Tier 3, Tier 4 | AR27: 2024-12-31 | AS27: providers=world_bank_col_estimate, derived, who_gho, world_bank; fields=gross_income, rent, utilities, transit_cost; +8 additional fields | AT27: https://api.worldbank.org/v2/country/CHN/indicator/VC.IHR.PSRC.P5?format=json&mrv=10 | https://api.worldbank.org/v2/country/CHN/indicator/IT.NET.BBND.P2?format=json&mrv=10 | https://worldweather.wmo.int | AU27: Tier 3 | AV27: 2024-12-31 | AW27: providers=world_bank, wmo_natl_met; fields=personal_safety_raw, digital_infrastructure_raw, climate_sunlight_livability_raw | AX27: https://www.who.int/data/gho/data/indicators/indicator-details/GHO/UHC_INDEX_REPORTED | https://api.worldbank.org/v2/country/CHN/indicator/SE.TER.ENRR?format=json&mrv=10 | https://api.worldbank.org/v2/country/CHN/indicator/SI.POV.GINI?format=json&mrv=10 | +1 more | AY27: Tier 3 | AZ27: 2024-12-31 | BA27: providers=who_gho, world_bank; fields=healthcare_quality_raw, education_quality_raw, equal_opportunity_raw, gini_coefficient | BB27: https://api.worldbank.org/v2/country/CHN/indicator/SM.POP.NETM?format=json&mrv=10 | https://api.worldbank.org/v2/country/CHN/indicator/SG.GEN.PARL.ZS?format=json&mrv=10 | https://api.worldbank.org/v2/country/CHN/indicator/ST.INT.ARVL?format=json&mrv=10 | +1 more | BC27: Tier 3 | BD27: 2025-12-31 | BE27: providers=world_bank; fields=hospitality_belonging_raw, tolerance_pluralism_raw, cultural_public_life_raw, birth_rate_optimism_raw | BF27: https://api.worldbank.org/v2/country/CHN/indicator/IC.BUS.NDNS.ZS?format=json&mrv=10 | https://api.worldbank.org/v2/country/CHN/indicator/GB.XPD.RSDV.GD.ZS?format=json&mrv=10 | https://api.worldbank.org/v2/country/CHN/indicator/BX.KLT.DINV.WD.GD.ZS?format=json&mrv=10 | +3 more | BG27: Tier 3 | BH27: 2024-12-31 | BI27: providers=world_bank; fields=entrepreneurial_dynamism_raw, innovation_research_intensity_raw, investment_signal_raw, administrative_investment_friction_raw; +2 additional fields | BJ27: 1
A28: in-bengaluru | B28: Bengaluru | C28: India | D28: South Asia | E28: primary | F28: locked | G28: 1283.33 | H28: 221.37 | I28: 73.79 | J28: 44.27 | K28: 14.76 | L28: 368.96 | N28: 17.2497 | O28: 50.1422 | P28: =IF($O28<>"",$O28,$AO28) | Q28: 45.72 | R28: 12.56 | S28: 2.82 | V28: 76.44 | W28: 2.75 | Y28: 69 | Z28: 34.42 | AA28: 25.5 | AB28: 49.66 | AC28: 13.65 | AD28: 12.35 | AE28: 0.18 | AF28: 0.65 | AG28: 0.69 | AH28: 2.64 | AJ28: =IFERROR(INDEX(Country_Context!$B$2:$B$87,MATCH($C28,Country_Context!$A$2:$A$87,0)),"") | AK28: =IFERROR(INDEX(Country_Context!$C$2:$C$87,MATCH($C28,Country_Context!$A$2:$A$87,0)),"") | AL28: =IFERROR(INDEX(Country_Context!$D$2:$D$87,MATCH($C28,Country_Context!$A$2:$A$87,0)),"") | AM28: =IFERROR(INDEX(Country_Context!$E$2:$E$87,MATCH($C28,Country_Context!$A$2:$A$87,0)),"") | AN28: =IFERROR(INDEX(Country_Context!$F$2:$F$87,MATCH($C28,Country_Context!$A$2:$A$87,0)),"") | AO28: =IFERROR(INDEX(Country_Context!$G$2:$G$87,MATCH($C28,Country_Context!$A$2:$A$87,0)),"") | AP28: https://api.worldbank.org/v2/country/IND/indicator/NY.GNP.PCAP.PP.CD?format=json&mrv=10 | https://data.worldbank.org/indicator/NY.GNP.PCAP.PP.CD | https://ilostat.ilo.org/data/indicator/?id=HOW_TEMP_SEX_ECO_NB_A&ref_area=IND | +4 more | AQ28: Tier 3, Tier 4 | AR28: 2024-12-31 | AS28: providers=world_bank_col_estimate, derived, ilo_ilostat, who_gho; fields=gross_income, rent, utilities, transit_cost; +9 additional fields | AT28: https://api.worldbank.org/v2/country/IND/indicator/VC.IHR.PSRC.P5?format=json&mrv=10 | https://api.worldbank.org/v2/country/IND/indicator/SH.H2O.SMDW.ZS?format=json&mrv=10 | https://api.worldbank.org/v2/country/IND/indicator/IT.NET.BBND.P2?format=json&mrv=10 | AU28: Tier 3 | AV28: 2024-12-31 | AW28: providers=world_bank; fields=personal_safety_raw, water_sanitation_utility_raw, digital_infrastructure_raw | AX28: https://www.who.int/data/gho/data/indicators/indicator-details/GHO/UHC_INDEX_REPORTED | https://api.worldbank.org/v2/country/IND/indicator/SE.TER.ENRR?format=json&mrv=10 | https://api.worldbank.org/v2/country/IND/indicator/SI.POV.GINI?format=json&mrv=10 | +1 more | AY28: Tier 3 | AZ28: 2024-12-31 | BA28: providers=who_gho, world_bank; fields=healthcare_quality_raw, education_quality_raw, equal_opportunity_raw, gini_coefficient | BB28: https://api.worldbank.org/v2/country/IND/indicator/SM.POP.NETM?format=json&mrv=10 | https://api.worldbank.org/v2/country/IND/indicator/SG.GEN.PARL.ZS?format=json&mrv=10 | https://api.worldbank.org/v2/country/IND/indicator/ST.INT.ARVL?format=json&mrv=10 | +1 more | BC28: Tier 3 | BD28: 2025-12-31 | BE28: providers=world_bank; fields=hospitality_belonging_raw, tolerance_pluralism_raw, cultural_public_life_raw, birth_rate_optimism_raw | BF28: https://api.worldbank.org/v2/country/IND/indicator/IC.BUS.NDNS.ZS?format=json&mrv=10 | https://api.worldbank.org/v2/country/IND/indicator/GB.XPD.RSDV.GD.ZS?format=json&mrv=10 | https://api.worldbank.org/v2/country/IND/indicator/BX.KLT.DINV.WD.GD.ZS?format=json&mrv=10 | +3 more | BG28: Tier 3 | BH28: 2024-12-31 | BI28: providers=world_bank; fields=entrepreneurial_dynamism_raw, innovation_research_intensity_raw, investment_signal_raw, administrative_investment_friction_raw; +2 additional fields | BJ28: 2
A29: in-hyderabad | B29: Hyderabad | C29: India | D29: South Asia | E29: primary | F29: locked | G29: 1145.83 | H29: 180.47 | I29: 60.16 | J29: 36.09 | K29: 12.03 | L29: 300.78 | N29: 15.7502 | O29: 50.1422 | P29: =IF($O29<>"",$O29,$AO29) | Q29: 45.72 | R29: 12.56 | S29: 2.82 | V29: 76.44 | W29: 2.75 | X29: 64 | Y29: 69 | Z29: 34.42 | AA29: 25.5 | AB29: 49.66 | AC29: 13.65 | AD29: 12.35 | AE29: 0.18 | AF29: 0.65 | AG29: 0.69 | AH29: 2.64 | AJ29: =IFERROR(INDEX(Country_Context!$B$2:$B$87,MATCH($C29,Country_Context!$A$2:$A$87,0)),"") | AK29: =IFERROR(INDEX(Country_Context!$C$2:$C$87,MATCH($C29,Country_Context!$A$2:$A$87,0)),"") | AL29: =IFERROR(INDEX(Country_Context!$D$2:$D$87,MATCH($C29,Country_Context!$A$2:$A$87,0)),"") | AM29: =IFERROR(INDEX(Country_Context!$E$2:$E$87,MATCH($C29,Country_Context!$A$2:$A$87,0)),"") | AN29: =IFERROR(INDEX(Country_Context!$F$2:$F$87,MATCH($C29,Country_Context!$A$2:$A$87,0)),"") | AO29: =IFERROR(INDEX(Country_Context!$G$2:$G$87,MATCH($C29,Country_Context!$A$2:$A$87,0)),"") | AP29: https://api.worldbank.org/v2/country/IND/indicator/NY.GNP.PCAP.PP.CD?format=json&mrv=10 | https://data.worldbank.org/indicator/NY.GNP.PCAP.PP.CD | https://ilostat.ilo.org/data/indicator/?id=HOW_TEMP_SEX_ECO_NB_A&ref_area=IND | +4 more | AQ29: Tier 3, Tier 4 | AR29: 2024-12-31 | AS29: providers=world_bank_col_estimate, derived, ilo_ilostat, who_gho; fields=gross_income, rent, utilities, transit_cost; +9 additional fields | AT29: https://api.worldbank.org/v2/country/IND/indicator/VC.IHR.PSRC.P5?format=json&mrv=10 | https://api.worldbank.org/v2/country/IND/indicator/SH.H2O.SMDW.ZS?format=json&mrv=10 | https://api.worldbank.org/v2/country/IND/indicator/IT.NET.BBND.P2?format=json&mrv=10 | +1 more | AU29: Tier 3 | AV29: 2024-12-31 | AW29: providers=world_bank, wmo_natl_met; fields=personal_safety_raw, water_sanitation_utility_raw, digital_infrastructure_raw, climate_sunlight_livability_raw | AX29: https://www.who.int/data/gho/data/indicators/indicator-details/GHO/UHC_INDEX_REPORTED | https://api.worldbank.org/v2/country/IND/indicator/SE.TER.ENRR?format=json&mrv=10 | https://api.worldbank.org/v2/country/IND/indicator/SI.POV.GINI?format=json&mrv=10 | +1 more | AY29: Tier 3 | AZ29: 2024-12-31 | BA29: providers=who_gho, world_bank; fields=healthcare_quality_raw, education_quality_raw, equal_opportunity_raw, gini_coefficient | BB29: https://api.worldbank.org/v2/country/IND/indicator/SM.POP.NETM?format=json&mrv=10 | https://api.worldbank.org/v2/country/IND/indicator/SG.GEN.PARL.ZS?format=json&mrv=10 | https://api.worldbank.org/v2/country/IND/indicator/ST.INT.ARVL?format=json&mrv=10 | +1 more | BC29: Tier 3 | BD29: 2025-12-31 | BE29: providers=world_bank; fields=hospitality_belonging_raw, tolerance_pluralism_raw, cultural_public_life_raw, birth_rate_optimism_raw | BF29: https://api.worldbank.org/v2/country/IND/indicator/IC.BUS.NDNS.ZS?format=json&mrv=10 | https://api.worldbank.org/v2/country/IND/indicator/GB.XPD.RSDV.GD.ZS?format=json&mrv=10 | https://api.worldbank.org/v2/country/IND/indicator/BX.KLT.DINV.WD.GD.ZS?format=json&mrv=10 | +3 more | BG29: Tier 3 | BH29: 2024-12-31 | BI29: providers=world_bank; fields=entrepreneurial_dynamism_raw, innovation_research_intensity_raw, investment_signal_raw, administrative_investment_friction_raw; +2 additional fields | BJ29: 2
A30: in-chandigarh | B30: Chandigarh | C30: India | D30: South Asia | E30: primary | F30: provisional | G30: 916.67 | H30: 137.5 | I30: 45.83 | J30: 27.5 | K30: 9.17 | L30: 229.17 | N30: 14.9999 | O30: 50.1422 | P30: =IF($O30<>"",$O30,$AO30) | Q30: 45.72 | R30: 12.56 | S30: 2.82 | U30: 45 | V30: 85 | W30: 2.75 | X30: 55 | Y30: 69 | Z30: 34.42 | AA30: 25.5 | AB30: 49.66 | AC30: 13.65 | AD30: 50 | AE30: 0.18 | AF30: 0.65 | AG30: 0.69 | AH30: 2.64 | AJ30: =IFERROR(INDEX(Country_Context!$B$2:$B$87,MATCH($C30,Country_Context!$A$2:$A$87,0)),"") | AK30: =IFERROR(INDEX(Country_Context!$C$2:$C$87,MATCH($C30,Country_Context!$A$2:$A$87,0)),"") | AL30: =IFERROR(INDEX(Country_Context!$D$2:$D$87,MATCH($C30,Country_Context!$A$2:$A$87,0)),"") | AM30: =IFERROR(INDEX(Country_Context!$E$2:$E$87,MATCH($C30,Country_Context!$A$2:$A$87,0)),"") | AN30: =IFERROR(INDEX(Country_Context!$F$2:$F$87,MATCH($C30,Country_Context!$A$2:$A$87,0)),"") | AO30: =IFERROR(INDEX(Country_Context!$G$2:$G$87,MATCH($C30,Country_Context!$A$2:$A$87,0)),"") | AP30: https://api.worldbank.org/v2/country/IND/indicator/NY.GNP.PCAP.PP.CD?format=json&mrv=10 | https://data.worldbank.org/indicator/NY.GNP.PCAP.PP.CD | https://ilostat.ilo.org/data/indicator/?id=HOW_TEMP_SEX_ECO_NB_A&ref_area=IND | +4 more | AQ30: Tier 3, Tier 4 | AR30: 2024-12-31 | AS30: providers=world_bank_col_estimate, derived, ilo_ilostat, who_gho; fields=gross_income, rent, utilities, transit_cost; +9 additional fields | AT30: https://api.worldbank.org/v2/country/IND/indicator/VC.IHR.PSRC.P5?format=json&mrv=10 | https://worldweather.wmo.int | https://washdata.org | +1 more | AU30: Tier 3 | AV30: 2024-12-31 | AW30: providers=world_bank, wmo_natl_met, who_unicef_jmp; fields=personal_safety_raw, clean_air_raw, water_sanitation_utility_raw, digital_infrastructure_raw; +1 additional fields | AX30: https://www.who.int/data/gho/data/indicators/indicator-details/GHO/UHC_INDEX_REPORTED | https://api.worldbank.org/v2/country/IND/indicator/SE.TER.ENRR?format=json&mrv=10 | https://api.worldbank.org/v2/country/IND/indicator/SI.POV.GINI?format=json&mrv=10 | +1 more | AY30: Tier 3 | AZ30: 2024-12-31 | BA30: providers=who_gho, world_bank; fields=healthcare_quality_raw, education_quality_raw, equal_opportunity_raw, gini_coefficient | BB30: https://api.worldbank.org/v2/country/IND/indicator/SM.POP.NETM?format=json&mrv=10 | https://api.worldbank.org/v2/country/IND/indicator/SG.GEN.PARL.ZS?format=json&mrv=10 | https://worldweather.wmo.int | +1 more | BC30: Tier 3 | BD30: 2025-12-31 | BE30: providers=world_bank, wmo_natl_met; fields=hospitality_belonging_raw, tolerance_pluralism_raw, cultural_public_life_raw, birth_rate_optimism_raw | BF30: https://api.worldbank.org/v2/country/IND/indicator/IC.BUS.NDNS.ZS?format=json&mrv=10 | https://api.worldbank.org/v2/country/IND/indicator/GB.XPD.RSDV.GD.ZS?format=json&mrv=10 | https://api.worldbank.org/v2/country/IND/indicator/BX.KLT.DINV.WD.GD.ZS?format=json&mrv=10 | +3 more | BG30: Tier 3 | BH30: 2024-12-31 | BI30: providers=world_bank; fields=entrepreneurial_dynamism_raw, innovation_research_intensity_raw, investment_signal_raw, administrative_investment_friction_raw; +2 additional fields | BJ30: 2
A31: lk-colombo | B31: Colombo | C31: Sri Lanka | D31: South Asia | E31: primary | F31: locked | G31: 1270 | H31: 190.5 | I31: 63.5 | J31: 38.1 | K31: 12.7 | L31: 317.5 | N31: 15 | O31: 46.8716 | P31: =IF($O31<>"",$O31,$AO31) | Q31: 41.72 | R31: 14.74 | S31: 3.31 | V31: 46.93 | W31: 8.77 | Y31: 72 | Z31: 20.74 | AA31: 37.7 | AB31: 48.6 | AC31: 10 | AD31: 24.64 | AE31: 1.2 | AF31: 0.11 | AG31: 0.77 | AH31: 3.01 | AJ31: =IFERROR(INDEX(Country_Context!$B$2:$B$87,MATCH($C31,Country_Context!$A$2:$A$87,0)),"") | AK31: =IFERROR(INDEX(Country_Context!$C$2:$C$87,MATCH($C31,Country_Context!$A$2:$A$87,0)),"") | AL31: =IFERROR(INDEX(Country_Context!$D$2:$D$87,MATCH($C31,Country_Context!$A$2:$A$87,0)),"") | AM31: =IFERROR(INDEX(Country_Context!$E$2:$E$87,MATCH($C31,Country_Context!$A$2:$A$87,0)),"") | AN31: =IFERROR(INDEX(Country_Context!$F$2:$F$87,MATCH($C31,Country_Context!$A$2:$A$87,0)),"") | AO31: =IFERROR(INDEX(Country_Context!$G$2:$G$87,MATCH($C31,Country_Context!$A$2:$A$87,0)),"") | AP31: https://api.worldbank.org/v2/country/LKA/indicator/NY.GNP.PCAP.PP.CD?format=json&mrv=10 | https://data.worldbank.org/indicator/NY.GNP.PCAP.PP.CD | https://ilostat.ilo.org/data/indicator/?id=HOW_TEMP_SEX_ECO_NB_A&ref_area=LKA | +4 more | AQ31: Tier 3, Tier 4 | AR31: 2024-12-31 | AS31: providers=world_bank_col_estimate, derived, ilo_ilostat, who_gho; fields=gross_income, rent, utilities, transit_cost; +9 additional fields | AT31: https://api.worldbank.org/v2/country/LKA/indicator/VC.IHR.PSRC.P5?format=json&mrv=10 | https://api.worldbank.org/v2/country/LKA/indicator/SH.H2O.SMDW.ZS?format=json&mrv=10 | https://api.worldbank.org/v2/country/LKA/indicator/IT.NET.BBND.P2?format=json&mrv=10 | AU31: Tier 3 | AV31: 2024-12-31 | AW31: providers=world_bank; fields=personal_safety_raw, water_sanitation_utility_raw, digital_infrastructure_raw | AX31: https://www.who.int/data/gho/data/indicators/indicator-details/GHO/UHC_INDEX_REPORTED | https://api.worldbank.org/v2/country/LKA/indicator/SE.TER.ENRR?format=json&mrv=10 | https://api.worldbank.org/v2/country/LKA/indicator/SI.POV.GINI?format=json&mrv=10 | +1 more | AY31: Tier 3 | AZ31: 2023-12-31 | BA31: providers=who_gho, world_bank; fields=healthcare_quality_raw, education_quality_raw, equal_opportunity_raw, gini_coefficient | BB31: https://api.worldbank.org/v2/country/LKA/indicator/SM.POP.NETM?format=json&mrv=10 | https://api.worldbank.org/v2/country/LKA/indicator/SG.GEN.PARL.ZS?format=json&mrv=10 | https://api.worldbank.org/v2/country/LKA/indicator/ST.INT.ARVL?format=json&mrv=10 | +1 more | BC31: Tier 3 | BD31: 2025-12-31 | BE31: providers=world_bank; fields=hospitality_belonging_raw, tolerance_pluralism_raw, cultural_public_life_raw, birth_rate_optimism_raw | BF31: https://api.worldbank.org/v2/country/LKA/indicator/IC.BUS.NDNS.ZS?format=json&mrv=10 | https://api.worldbank.org/v2/country/LKA/indicator/GB.XPD.RSDV.GD.ZS?format=json&mrv=10 | https://api.worldbank.org/v2/country/LKA/indicator/BX.KLT.DINV.WD.GD.ZS?format=json&mrv=10 | +3 more | BG31: Tier 3 | BH31: 2024-12-31 | BI31: providers=world_bank; fields=entrepreneurial_dynamism_raw, innovation_research_intensity_raw, investment_signal_raw, administrative_investment_friction_raw; +2 additional fields | BJ31: 1.99
A32: bd-dhaka | B32: Dhaka | C32: Bangladesh | D32: South Asia | E32: primary | F32: provisional | G32: 838.33 | H32: 125.75 | I32: 41.92 | J32: 25.15 | K32: 8.38 | L32: 209.58 | N32: 15.0001 | O32: 35.7061 | P32: =IF($O32<>"",$O32,$AO32) | Q32: 46.73 | R32: 2.81 | S32: 2.34 | V32: 59.13 | W32: 7.89 | Y32: 54 | Z32: 23.73 | AA32: 30.9 | AB32: 47.68 | AC32: 20.86 | AD32: 1.86 | AE32: 0.04 | AF32: 2.58 | AG32: 0.29 | AH32: 3.41 | AJ32: =IFERROR(INDEX(Country_Context!$B$2:$B$87,MATCH($C32,Country_Context!$A$2:$A$87,0)),"") | AK32: =IFERROR(INDEX(Country_Context!$C$2:$C$87,MATCH($C32,Country_Context!$A$2:$A$87,0)),"") | AL32: =IFERROR(INDEX(Country_Context!$D$2:$D$87,MATCH($C32,Country_Context!$A$2:$A$87,0)),"") | AM32: =IFERROR(INDEX(Country_Context!$E$2:$E$87,MATCH($C32,Country_Context!$A$2:$A$87,0)),"") | AN32: =IFERROR(INDEX(Country_Context!$F$2:$F$87,MATCH($C32,Country_Context!$A$2:$A$87,0)),"") | AO32: =IFERROR(INDEX(Country_Context!$G$2:$G$87,MATCH($C32,Country_Context!$A$2:$A$87,0)),"") | AP32: https://api.worldbank.org/v2/country/BGD/indicator/NY.GNP.PCAP.PP.CD?format=json&mrv=10 | https://data.worldbank.org/indicator/NY.GNP.PCAP.PP.CD | https://ilostat.ilo.org/data/indicator/?id=HOW_TEMP_SEX_ECO_NB_A&ref_area=BGD | +4 more | AQ32: Tier 3, Tier 4 | AR32: 2024-12-31 | AS32: providers=world_bank_col_estimate, derived, ilo_ilostat, who_gho; fields=gross_income, rent, utilities, transit_cost; +9 additional fields | AT32: https://api.worldbank.org/v2/country/BGD/indicator/VC.IHR.PSRC.P5?format=json&mrv=10 | https://api.worldbank.org/v2/country/BGD/indicator/SH.H2O.SMDW.ZS?format=json&mrv=10 | https://api.worldbank.org/v2/country/BGD/indicator/IT.NET.BBND.P2?format=json&mrv=10 | AU32: Tier 3 | AV32: 2024-12-31 | AW32: providers=world_bank; fields=personal_safety_raw, water_sanitation_utility_raw, digital_infrastructure_raw | AX32: https://www.who.int/data/gho/data/indicators/indicator-details/GHO/UHC_INDEX_REPORTED | https://api.worldbank.org/v2/country/BGD/indicator/SE.TER.ENRR?format=json&mrv=10 | https://api.worldbank.org/v2/country/BGD/indicator/SI.POV.GINI?format=json&mrv=10 | +1 more | AY32: Tier 3 | AZ32: 2024-12-31 | BA32: providers=who_gho, world_bank; fields=healthcare_quality_raw, education_quality_raw, equal_opportunity_raw, gini_coefficient | BB32: https://api.worldbank.org/v2/country/BGD/indicator/SM.POP.NETM?format=json&mrv=10 | https://api.worldbank.org/v2/country/BGD/indicator/SG.GEN.PARL.ZS?format=json&mrv=10 | https://api.worldbank.org/v2/country/BGD/indicator/ST.INT.ARVL?format=json&mrv=10 | +1 more | BC32: Tier 3 | BD32: 2025-12-31 | BE32: providers=world_bank; fields=hospitality_belonging_raw, tolerance_pluralism_raw, cultural_public_life_raw, birth_rate_optimism_raw | BF32: https://api.worldbank.org/v2/country/BGD/indicator/IC.BUS.NDNS.ZS?format=json&mrv=10 | https://api.worldbank.org/v2/country/BGD/indicator/IP.PAT.RESD?format=json&mrv=10 | https://api.worldbank.org/v2/country/BGD/indicator/BX.KLT.DINV.WD.GD.ZS?format=json&mrv=10 | +3 more | BG32: Tier 3 | BH32: 2024-12-31 | BI32: providers=world_bank; fields=entrepreneurial_dynamism_raw, innovation_research_intensity_raw, investment_signal_raw, administrative_investment_friction_raw; +2 additional fields | BJ32: 1.95
A33: pk-karachi | B33: Karachi | C33: Pakistan | D33: South Asia | E33: primary | F33: provisional | G33: 508.33 | H33: 68.62 | I33: 22.87 | J33: 13.72 | K33: 4.57 | L33: 114.37 | N33: 13.4991 | O33: 11.3901 | P33: =IF($O33<>"",$O33,$AO33) | Q33: 46.77 | R33: 5.64 | S33: 4.33 | V33: 44.97 | W33: 1.36 | Y33: 56 | Z33: 10.86 | AA33: 29.6 | AB33: 45.08 | AC33: 17.04 | AD33: 30.61 | AE33: 0.19 | AF33: 0.16 | AG33: 0.72 | AH33: 3.4 | AJ33: =IFERROR(INDEX(Country_Context!$B$2:$B$87,MATCH($C33,Country_Context!$A$2:$A$87,0)),"") | AK33: =IFERROR(INDEX(Country_Context!$C$2:$C$87,MATCH($C33,Country_Context!$A$2:$A$87,0)),"") | AL33: =IFERROR(INDEX(Country_Context!$D$2:$D$87,MATCH($C33,Country_Context!$A$2:$A$87,0)),"") | AM33: =IFERROR(INDEX(Country_Context!$E$2:$E$87,MATCH($C33,Country_Context!$A$2:$A$87,0)),"") | AN33: =IFERROR(INDEX(Country_Context!$F$2:$F$87,MATCH($C33,Country_Context!$A$2:$A$87,0)),"") | AO33: =IFERROR(INDEX(Country_Context!$G$2:$G$87,MATCH($C33,Country_Context!$A$2:$A$87,0)),"") | AP33: https://api.worldbank.org/v2/country/PAK/indicator/NY.GNP.PCAP.PP.CD?format=json&mrv=10 | https://data.worldbank.org/indicator/NY.GNP.PCAP.PP.CD | https://ilostat.ilo.org/data/indicator/?id=HOW_TEMP_SEX_ECO_NB_A&ref_area=PAK | +3 more | AQ33: Tier 3, Tier 4 | AR33: 2025-12-31 | AS33: providers=world_bank_col_estimate, derived, ilo_ilostat, who_gho; fields=gross_income, rent, utilities, transit_cost; +8 additional fields | AT33: https://api.worldbank.org/v2/country/PAK/indicator/VC.IHR.PSRC.P5?format=json&mrv=10 | https://api.worldbank.org/v2/country/PAK/indicator/SH.H2O.SMDW.ZS?format=json&mrv=10 | https://api.worldbank.org/v2/country/PAK/indicator/IT.NET.BBND.P2?format=json&mrv=10 | AU33: Tier 3 | AV33: 2024-12-31 | AW33: providers=world_bank; fields=personal_safety_raw, water_sanitation_utility_raw, digital_infrastructure_raw | AX33: https://www.who.int/data/gho/data/indicators/indicator-details/GHO/UHC_INDEX_REPORTED | https://api.worldbank.org/v2/country/PAK/indicator/SE.TER.ENRR?format=json&mrv=10 | https://api.worldbank.org/v2/country/PAK/indicator/SI.POV.GINI?format=json&mrv=10 | +1 more | AY33: Tier 3 | AZ33: 2024-12-31 | BA33: providers=who_gho, world_bank; fields=healthcare_quality_raw, education_quality_raw, equal_opportunity_raw, gini_coefficient | BB33: https://api.worldbank.org/v2/country/PAK/indicator/SM.POP.NETM?format=json&mrv=10 | https://api.worldbank.org/v2/country/PAK/indicator/SG.GEN.PARL.ZS?format=json&mrv=10 | https://api.worldbank.org/v2/country/PAK/indicator/SP.POP.DPND?format=json&mrv=10 | +1 more | BC33: Tier 3 | BD33: 2025-12-31 | BE33: providers=world_bank; fields=hospitality_belonging_raw, tolerance_pluralism_raw, cultural_public_life_raw, birth_rate_optimism_raw | BF33: https://api.worldbank.org/v2/country/PAK/indicator/IC.BUS.NDNS.ZS?format=json&mrv=10 | https://api.worldbank.org/v2/country/PAK/indicator/GB.XPD.RSDV.GD.ZS?format=json&mrv=10 | https://api.worldbank.org/v2/country/PAK/indicator/BX.KLT.DINV.WD.GD.ZS?format=json&mrv=10 | +3 more | BG33: Tier 3 | BH33: 2024-12-31 | BI33: providers=world_bank; fields=entrepreneurial_dynamism_raw, innovation_research_intensity_raw, investment_signal_raw, administrative_investment_friction_raw; +2 additional fields | BJ33: 3.36
A34: pk-lahore | B34: Lahore | C34: Pakistan | D34: South Asia | E34: secondary | F34: locked | G34: 508.33 | H34: 64.81 | I34: 21.6 | J34: 12.96 | K34: 4.32 | L34: 108.02 | N34: 12.7496 | O34: 11.3901 | P34: =IF($O34<>"",$O34,$AO34) | Q34: 46.77 | R34: 5.64 | S34: 4.33 | V34: 44.97 | W34: 1.36 | Y34: 56 | Z34: 10.86 | AA34: 29.6 | AB34: 45.08 | AC34: 17.04 | AD34: 30.61 | AE34: 0.19 | AF34: 0.16 | AG34: 0.72 | AH34: 3.4 | AJ34: =IFERROR(INDEX(Country_Context!$B$2:$B$87,MATCH($C34,Country_Context!$A$2:$A$87,0)),"") | AK34: =IFERROR(INDEX(Country_Context!$C$2:$C$87,MATCH($C34,Country_Context!$A$2:$A$87,0)),"") | AL34: =IFERROR(INDEX(Country_Context!$D$2:$D$87,MATCH($C34,Country_Context!$A$2:$A$87,0)),"") | AM34: =IFERROR(INDEX(Country_Context!$E$2:$E$87,MATCH($C34,Country_Context!$A$2:$A$87,0)),"") | AN34: =IFERROR(INDEX(Country_Context!$F$2:$F$87,MATCH($C34,Country_Context!$A$2:$A$87,0)),"") | AO34: =IFERROR(INDEX(Country_Context!$G$2:$G$87,MATCH($C34,Country_Context!$A$2:$A$87,0)),"") | AP34: https://api.worldbank.org/v2/country/PAK/indicator/NY.GNP.PCAP.PP.CD?format=json&mrv=10 | https://data.worldbank.org/indicator/NY.GNP.PCAP.PP.CD | https://ilostat.ilo.org/data/indicator/?id=HOW_TEMP_SEX_ECO_NB_A&ref_area=PAK | +3 more | AQ34: Tier 3, Tier 4 | AR34: 2025-12-31 | AS34: providers=world_bank_col_estimate, derived, ilo_ilostat, who_gho; fields=gross_income, rent, utilities, transit_cost; +8 additional fields | AT34: https://api.worldbank.org/v2/country/PAK/indicator/VC.IHR.PSRC.P5?format=json&mrv=10 | https://api.worldbank.org/v2/country/PAK/indicator/SH.H2O.SMDW.ZS?format=json&mrv=10 | https://api.worldbank.org/v2/country/PAK/indicator/IT.NET.BBND.P2?format=json&mrv=10 | AU34: Tier 3 | AV34: 2024-12-31 | AW34: providers=world_bank; fields=personal_safety_raw, water_sanitation_utility_raw, digital_infrastructure_raw | AX34: https://www.who.int/data/gho/data/indicators/indicator-details/GHO/UHC_INDEX_REPORTED | https://api.worldbank.org/v2/country/PAK/indicator/SE.TER.ENRR?format=json&mrv=10 | https://api.worldbank.org/v2/country/PAK/indicator/SI.POV.GINI?format=json&mrv=10 | +1 more | AY34: Tier 3 | AZ34: 2024-12-31 | BA34: providers=who_gho, world_bank; fields=healthcare_quality_raw, education_quality_raw, equal_opportunity_raw, gini_coefficient | BB34: https://api.worldbank.org/v2/country/PAK/indicator/SM.POP.NETM?format=json&mrv=10 | https://api.worldbank.org/v2/country/PAK/indicator/SG.GEN.PARL.ZS?format=json&mrv=10 | https://api.worldbank.org/v2/country/PAK/indicator/SP.POP.DPND?format=json&mrv=10 | +1 more | BC34: Tier 3 | BD34: 2025-12-31 | BE34: providers=world_bank; fields=hospitality_belonging_raw, tolerance_pluralism_raw, cultural_public_life_raw, birth_rate_optimism_raw | BF34: https://api.worldbank.org/v2/country/PAK/indicator/IC.BUS.NDNS.ZS?format=json&mrv=10 | https://api.worldbank.org/v2/country/PAK/indicator/GB.XPD.RSDV.GD.ZS?format=json&mrv=10 | https://api.worldbank.org/v2/country/PAK/indicator/BX.KLT.DINV.WD.GD.ZS?format=json&mrv=10 | +3 more | BG34: Tier 3 | BH34: 2024-12-31 | BI34: providers=world_bank; fields=entrepreneurial_dynamism_raw, innovation_research_intensity_raw, investment_signal_raw, administrative_investment_friction_raw; +2 additional fields | BJ34: 3.36
A35: bd-chattogram | B35: Chattogram | C35: Bangladesh | D35: South Asia | E35: secondary | F35: locked | G35: 838.33 | H35: 100.6 | I35: 33.53 | J35: 20.12 | K35: 6.71 | L35: 167.67 | N35: 12 | O35: 35.7061 | P35: =IF($O35<>"",$O35,$AO35) | Q35: 46.73 | R35: 2.81 | S35: 2.34 | V35: 59.13 | W35: 7.89 | Y35: 54 | Z35: 23.73 | AA35: 30.9 | AB35: 47.68 | AC35: 20.86 | AD35: 1.86 | AE35: 0.04 | AF35: 2.58 | AG35: 0.29 | AH35: 3.41 | AJ35: =IFERROR(INDEX(Country_Context!$B$2:$B$87,MATCH($C35,Country_Context!$A$2:$A$87,0)),"") | AK35: =IFERROR(INDEX(Country_Context!$C$2:$C$87,MATCH($C35,Country_Context!$A$2:$A$87,0)),"") | AL35: =IFERROR(INDEX(Country_Context!$D$2:$D$87,MATCH($C35,Country_Context!$A$2:$A$87,0)),"") | AM35: =IFERROR(INDEX(Country_Context!$E$2:$E$87,MATCH($C35,Country_Context!$A$2:$A$87,0)),"") | AN35: =IFERROR(INDEX(Country_Context!$F$2:$F$87,MATCH($C35,Country_Context!$A$2:$A$87,0)),"") | AO35: =IFERROR(INDEX(Country_Context!$G$2:$G$87,MATCH($C35,Country_Context!$A$2:$A$87,0)),"") | AP35: https://api.worldbank.org/v2/country/BGD/indicator/NY.GNP.PCAP.PP.CD?format=json&mrv=10 | https://data.worldbank.org/indicator/NY.GNP.PCAP.PP.CD | https://ilostat.ilo.org/data/indicator/?id=HOW_TEMP_SEX_ECO_NB_A&ref_area=BGD | +4 more | AQ35: Tier 3, Tier 4 | AR35: 2024-12-31 | AS35: providers=world_bank_col_estimate, derived, ilo_ilostat, who_gho; fields=gross_income, rent, utilities, transit_cost; +9 additional fields | AT35: https://api.worldbank.org/v2/country/BGD/indicator/VC.IHR.PSRC.P5?format=json&mrv=10 | https://api.worldbank.org/v2/country/BGD/indicator/SH.H2O.SMDW.ZS?format=json&mrv=10 | https://api.worldbank.org/v2/country/BGD/indicator/IT.NET.BBND.P2?format=json&mrv=10 | AU35: Tier 3 | AV35: 2024-12-31 | AW35: providers=world_bank; fields=personal_safety_raw, water_sanitation_utility_raw, digital_infrastructure_raw | AX35: https://www.who.int/data/gho/data/indicators/indicator-details/GHO/UHC_INDEX_REPORTED | https://api.worldbank.org/v2/country/BGD/indicator/SE.TER.ENRR?format=json&mrv=10 | https://api.worldbank.org/v2/country/BGD/indicator/SI.POV.GINI?format=json&mrv=10 | +1 more | AY35: Tier 3 | AZ35: 2024-12-31 | BA35: providers=who_gho, world_bank; fields=healthcare_quality_raw, education_quality_raw, equal_opportunity_raw, gini_coefficient | BB35: https://api.worldbank.org/v2/country/BGD/indicator/SM.POP.NETM?format=json&mrv=10 | https://api.worldbank.org/v2/country/BGD/indicator/SG.GEN.PARL.ZS?format=json&mrv=10 | https://api.worldbank.org/v2/country/BGD/indicator/ST.INT.ARVL?format=json&mrv=10 | +1 more | BC35: Tier 3 | BD35: 2025-12-31 | BE35: providers=world_bank; fields=hospitality_belonging_raw, tolerance_pluralism_raw, cultural_public_life_raw, birth_rate_optimism_raw | BF35: https://api.worldbank.org/v2/country/BGD/indicator/IC.BUS.NDNS.ZS?format=json&mrv=10 | https://api.worldbank.org/v2/country/BGD/indicator/IP.PAT.RESD?format=json&mrv=10 | https://api.worldbank.org/v2/country/BGD/indicator/BX.KLT.DINV.WD.GD.ZS?format=json&mrv=10 | +3 more | BG35: Tier 3 | BH35: 2024-12-31 | BI35: providers=world_bank; fields=entrepreneurial_dynamism_raw, innovation_research_intensity_raw, investment_signal_raw, administrative_investment_friction_raw; +2 additional fields | BJ35: 1.95
A36: np-kathmandu | B36: Kathmandu | C36: Nepal | D36: South Asia | E36: secondary | F36: provisional | G36: 485.83 | H36: 72.87 | I36: 24.29 | J36: 14.57 | K36: 4.86 | L36: 121.46 | N36: 14.9991 | O36: 91.9385 | P36: =IF($O36<>"",$O36,$AO36) | R36: 10.14 | S36: 2.13 | V36: 16.49 | W36: 4.83 | Y36: 58 | Z36: 21.29 | AA36: 30 | AB36: 37.7 | AC36: 33.09 | AD36: 7.76 | AE36: 1.38 | AF36: 2.12 | AG36: 0.13 | AH36: 3.16 | AJ36: =IFERROR(INDEX(Country_Context!$B$2:$B$87,MATCH($C36,Country_Context!$A$2:$A$87,0)),"") | AK36: =IFERROR(INDEX(Country_Context!$C$2:$C$87,MATCH($C36,Country_Context!$A$2:$A$87,0)),"") | AL36: =IFERROR(INDEX(Country_Context!$D$2:$D$87,MATCH($C36,Country_Context!$A$2:$A$87,0)),"") | AM36: =IFERROR(INDEX(Country_Context!$E$2:$E$87,MATCH($C36,Country_Context!$A$2:$A$87,0)),"") | AN36: =IFERROR(INDEX(Country_Context!$F$2:$F$87,MATCH($C36,Country_Context!$A$2:$A$87,0)),"") | AO36: =IFERROR(INDEX(Country_Context!$G$2:$G$87,MATCH($C36,Country_Context!$A$2:$A$87,0)),"") | AP36: https://api.worldbank.org/v2/country/NPL/indicator/NY.GNP.PCAP.PP.CD?format=json&mrv=10 | https://data.worldbank.org/indicator/NY.GNP.PCAP.PP.CD | https://www.who.int/data/gho/data/indicators/indicator-details/GHO/SDGSUICIDE | +3 more | AQ36: Tier 3, Tier 4 | AR36: 2024-12-31 | AS36: providers=world_bank_col_estimate, derived, who_gho, world_bank; fields=gross_income, rent, utilities, transit_cost; +8 additional fields | AT36: https://api.worldbank.org/v2/country/NPL/indicator/VC.IHR.PSRC.P5?format=json&mrv=10 | https://api.worldbank.org/v2/country/NPL/indicator/SH.H2O.SMDW.ZS?format=json&mrv=10 | https://api.worldbank.org/v2/country/NPL/indicator/IT.NET.BBND.P2?format=json&mrv=10 | AU36: Tier 3 | AV36: 2024-12-31 | AW36: providers=world_bank; fields=personal_safety_raw, water_sanitation_utility_raw, digital_infrastructure_raw | AX36: https://www.who.int/data/gho/data/indicators/indicator-details/GHO/UHC_INDEX_REPORTED | https://api.worldbank.org/v2/country/NPL/indicator/SE.TER.ENRR?format=json&mrv=10 | https://api.worldbank.org/v2/country/NPL/indicator/SI.POV.GINI?format=json&mrv=10 | +1 more | AY36: Tier 3 | AZ36: 2024-12-31 | BA36: providers=who_gho, world_bank; fields=healthcare_quality_raw, education_quality_raw, equal_opportunity_raw, gini_coefficient | BB36: https://api.worldbank.org/v2/country/NPL/indicator/SM.POP.NETM?format=json&mrv=10 | https://api.worldbank.org/v2/country/NPL/indicator/SG.GEN.PARL.ZS?format=json&mrv=10 | https://api.worldbank.org/v2/country/NPL/indicator/ST.INT.ARVL?format=json&mrv=10 | BC36: Tier 3 | BD36: 2025-12-31 | BE36: providers=world_bank; fields=hospitality_belonging_raw, tolerance_pluralism_raw, cultural_public_life_raw | BF36: https://api.worldbank.org/v2/country/NPL/indicator/IC.BUS.NDNS.ZS?format=json&mrv=10 | https://api.worldbank.org/v2/country/NPL/indicator/IP.PAT.RESD?format=json&mrv=10 | https://api.worldbank.org/v2/country/NPL/indicator/BX.KLT.DINV.WD.GD.ZS?format=json&mrv=10 | +3 more | BG36: Tier 3 | BH36: 2024-12-31 | BI36: providers=world_bank; fields=entrepreneurial_dynamism_raw, innovation_research_intensity_raw, investment_signal_raw, administrative_investment_friction_raw; +2 additional fields
A37: bt-thimphu | B37: Thimphu | C37: Bhutan | D37: South Asia | E37: secondary | F37: locked | G37: 1276.67 | H37: 191.5 | I37: 63.83 | J37: 38.3 | K37: 12.77 | L37: 319.17 | N37: 15 | O37: 51.8935 | P37: =IF($O37<>"",$O37,$AO37) | Q37: 54.42 | R37: 4.9 | S37: 2.47 | V37: 65.59 | W37: 1.32 | Y37: 69 | Z37: 13.01 | AA37: 28.5 | AB37: 50.57 | AC37: 4.26 | AD37: 37.65 | AE37: 0.07 | AF37: 10.11 | AG37: 0.34 | AH37: 2.9 | AJ37: =IFERROR(INDEX(Country_Context!$B$2:$B$87,MATCH($C37,Country_Context!$A$2:$A$87,0)),"") | AK37: =IFERROR(INDEX(Country_Context!$C$2:$C$87,MATCH($C37,Country_Context!$A$2:$A$87,0)),"") | AL37: =IFERROR(INDEX(Country_Context!$D$2:$D$87,MATCH($C37,Country_Context!$A$2:$A$87,0)),"") | AM37: =IFERROR(INDEX(Country_Context!$E$2:$E$87,MATCH($C37,Country_Context!$A$2:$A$87,0)),"") | AN37: =IFERROR(INDEX(Country_Context!$F$2:$F$87,MATCH($C37,Country_Context!$A$2:$A$87,0)),"") | AO37: =IFERROR(INDEX(Country_Context!$G$2:$G$87,MATCH($C37,Country_Context!$A$2:$A$87,0)),"") | AP37: https://api.worldbank.org/v2/country/BTN/indicator/NY.GNP.PCAP.PP.CD?format=json&mrv=10 | https://data.worldbank.org/indicator/NY.GNP.PCAP.PP.CD | https://ilostat.ilo.org/data/indicator/?id=HOW_TEMP_SEX_ECO_NB_A&ref_area=BTN | +4 more | AQ37: Tier 3, Tier 4 | AR37: 2024-12-31 | AS37: providers=world_bank_col_estimate, derived, ilo_ilostat, who_gho; fields=gross_income, rent, utilities, transit_cost; +9 additional fields | AT37: https://api.worldbank.org/v2/country/BTN/indicator/VC.IHR.PSRC.P5?format=json&mrv=10 | https://api.worldbank.org/v2/country/BTN/indicator/SH.H2O.SMDW.ZS?format=json&mrv=10 | https://api.worldbank.org/v2/country/BTN/indicator/IT.NET.BBND.P2?format=json&mrv=10 | AU37: Tier 3 | AV37: 2024-12-31 | AW37: providers=world_bank; fields=personal_safety_raw, water_sanitation_utility_raw, digital_infrastructure_raw | AX37: https://www.who.int/data/gho/data/indicators/indicator-details/GHO/UHC_INDEX_REPORTED | https://api.worldbank.org/v2/country/BTN/indicator/SE.TER.ENRR?format=json&mrv=10 | https://api.worldbank.org/v2/country/BTN/indicator/SI.POV.GINI?format=json&mrv=10 | +1 more | AY37: Tier 3 | AZ37: 2024-12-31 | BA37: providers=who_gho, world_bank; fields=healthcare_quality_raw, education_quality_raw, equal_opportunity_raw, gini_coefficient | BB37: https://api.worldbank.org/v2/country/BTN/indicator/SM.POP.NETM?format=json&mrv=10 | https://api.worldbank.org/v2/country/BTN/indicator/SG.GEN.PARL.ZS?format=json&mrv=10 | https://api.worldbank.org/v2/country/BTN/indicator/ST.INT.ARVL?format=json&mrv=10 | BC37: Tier 3 | BD37: 2025-12-31 | BE37: providers=world_bank; fields=hospitality_belonging_raw, tolerance_pluralism_raw, cultural_public_life_raw | BF37: https://api.worldbank.org/v2/country/BTN/indicator/IC.BUS.NDNS.ZS?format=json&mrv=10 | https://api.worldbank.org/v2/country/BTN/indicator/IP.PAT.RESD?format=json&mrv=10 | https://api.worldbank.org/v2/country/BTN/indicator/BX.KLT.DINV.WD.GD.ZS?format=json&mrv=10 | +3 more | BG37: Tier 3 | BH37: 2023-12-31 | BI37: providers=world_bank; fields=entrepreneurial_dynamism_raw, innovation_research_intensity_raw, investment_signal_raw, administrative_investment_friction_raw; +2 additional fields
A38: mv-male | B38: Male | C38: Maldives | D38: South Asia | E38: secondary | F38: locked | G38: 1950 | H38: 292.5 | I38: 97.5 | J38: 58.5 | K38: 19.5 | L38: 487.5 | N38: 15 | O38: 31.5415 | P38: =IF($O38<>"",$O38,$AO38) | Q38: 46.48 | R38: 1.47 | S38: 0.62 | W38: 18.73 | Y38: 71 | Z38: 48.5 | AA38: 29.3 | AB38: 45.67 | AC38: 3.23 | AD38: 1051.54 | AE38: 4.22 | AG38: 11.42 | AH38: 3.17 | AJ38: =IFERROR(INDEX(Country_Context!$B$2:$B$87,MATCH($C38,Country_Context!$A$2:$A$87,0)),"") | AK38: =IFERROR(INDEX(Country_Context!$C$2:$C$87,MATCH($C38,Country_Context!$A$2:$A$87,0)),"") | AL38: =IFERROR(INDEX(Country_Context!$D$2:$D$87,MATCH($C38,Country_Context!$A$2:$A$87,0)),"") | AM38: =IFERROR(INDEX(Country_Context!$E$2:$E$87,MATCH($C38,Country_Context!$A$2:$A$87,0)),"") | AN38: =IFERROR(INDEX(Country_Context!$F$2:$F$87,MATCH($C38,Country_Context!$A$2:$A$87,0)),"") | AO38: =IFERROR(INDEX(Country_Context!$G$2:$G$87,MATCH($C38,Country_Context!$A$2:$A$87,0)),"") | AP38: https://api.worldbank.org/v2/country/MDV/indicator/NY.GNP.PCAP.PP.CD?format=json&mrv=10 | https://data.worldbank.org/indicator/NY.GNP.PCAP.PP.CD | https://ilostat.ilo.org/data/indicator/?id=HOW_TEMP_SEX_ECO_NB_A&ref_area=MDV | +4 more | AQ38: Tier 3, Tier 4 | AR38: 2024-12-31 | AS38: providers=world_bank_col_estimate, derived, ilo_ilostat, who_gho; fields=gross_income, rent, utilities, transit_cost; +9 additional fields | AT38: https://api.worldbank.org/v2/country/MDV/indicator/VC.IHR.PSRC.P5?format=json&mrv=10 | https://api.worldbank.org/v2/country/MDV/indicator/IT.NET.BBND.P2?format=json&mrv=10 | AU38: Tier 3 | AV38: 2023-12-31 | AW38: providers=world_bank; fields=personal_safety_raw, digital_infrastructure_raw | AX38: https://www.who.int/data/gho/data/indicators/indicator-details/GHO/UHC_INDEX_REPORTED | https://api.worldbank.org/v2/country/MDV/indicator/SE.TER.ENRR?format=json&mrv=10 | https://api.worldbank.org/v2/country/MDV/indicator/SI.POV.GINI?format=json&mrv=10 | +1 more | AY38: Tier 3 | AZ38: 2023-12-31 | BA38: providers=who_gho, world_bank; fields=healthcare_quality_raw, education_quality_raw, equal_opportunity_raw, gini_coefficient | BB38: https://api.worldbank.org/v2/country/MDV/indicator/SM.POP.NETM?format=json&mrv=10 | https://api.worldbank.org/v2/country/MDV/indicator/SG.GEN.PARL.ZS?format=json&mrv=10 | https://api.worldbank.org/v2/country/MDV/indicator/ST.INT.ARVL?format=json&mrv=10 | BC38: Tier 3 | BD38: 2025-12-31 | BE38: providers=world_bank; fields=hospitality_belonging_raw, tolerance_pluralism_raw, cultural_public_life_raw | BF38: https://api.worldbank.org/v2/country/MDV/indicator/IC.BUS.NDNS.ZS?format=json&mrv=10 | https://api.worldbank.org/v2/country/MDV/indicator/BX.KLT.DINV.WD.GD.ZS?format=json&mrv=10 | https://api.worldbank.org/v2/country/MDV/indicator/RQ.EST?format=json&mrv=10 | +2 more | BG38: Tier 3 | BH38: 2024-12-31 | BI38: providers=world_bank; fields=entrepreneurial_dynamism_raw, investment_signal_raw, administrative_investment_friction_raw, gdp_per_capita_ppp; +1 additional fields
A39: fr-paris | B39: Paris | C39: France | D39: Western, Northern, and Southern Europe | E39: primary | F39: locked | G39: 6121.83 | H39: 2785.43 | I39: 557.09 | J39: 397.92 | K39: 119.38 | L39: 1193.76 | N39: 45.5 | O39: 103.9081 | P39: =IF($O39<>"",$O39,$AO39) | Q39: 35.49 | R39: 16.58 | S39: 1.34 | V39: 99.71 | W39: 48.67 | X39: 50 | Y39: 82 | Z39: 70.45 | AA39: 31.8 | AB39: 51.34 | AC39: 36.05 | AD39: 1708.33 | AE39: 6.71 | AF39: 2.23 | AG39: 1.65 | AH39: 1.35 | AJ39: =IFERROR(INDEX(Country_Context!$B$2:$B$87,MATCH($C39,Country_Context!$A$2:$A$87,0)),"") | AK39: =IFERROR(INDEX(Country_Context!$C$2:$C$87,MATCH($C39,Country_Context!$A$2:$A$87,0)),"") | AL39: =IFERROR(INDEX(Country_Context!$D$2:$D$87,MATCH($C39,Country_Context!$A$2:$A$87,0)),"") | AM39: =IFERROR(INDEX(Country_Context!$E$2:$E$87,MATCH($C39,Country_Context!$A$2:$A$87,0)),"") | AN39: =IFERROR(INDEX(Country_Context!$F$2:$F$87,MATCH($C39,Country_Context!$A$2:$A$87,0)),"") | AO39: =IFERROR(INDEX(Country_Context!$G$2:$G$87,MATCH($C39,Country_Context!$A$2:$A$87,0)),"") | AP39: https://api.worldbank.org/v2/country/FRA/indicator/NY.GNP.PCAP.PP.CD?format=json&mrv=10 | https://data.worldbank.org/indicator/NY.GNP.PCAP.PP.CD | https://ilostat.ilo.org/data/indicator/?id=HOW_TEMP_SEX_ECO_NB_A&ref_area=FRA | +4 more | AQ39: Tier 3, Tier 4 | AR39: 2024-12-31 | AS39: providers=world_bank_col_estimate, derived, ilo_ilostat, who_gho; fields=gross_income, rent, utilities, transit_cost; +9 additional fields | AT39: https://api.worldbank.org/v2/country/FRA/indicator/VC.IHR.PSRC.P5?format=json&mrv=10 | https://api.worldbank.org/v2/country/FRA/indicator/SH.H2O.SMDW.ZS?format=json&mrv=10 | https://api.worldbank.org/v2/country/FRA/indicator/IT.NET.BBND.P2?format=json&mrv=10 | +1 more | AU39: Tier 3 | AV39: 2024-12-31 | AW39: providers=world_bank, wmo_natl_met; fields=personal_safety_raw, water_sanitation_utility_raw, digital_infrastructure_raw, climate_sunlight_livability_raw | AX39: https://www.who.int/data/gho/data/indicators/indicator-details/GHO/UHC_INDEX_REPORTED | https://api.worldbank.org/v2/country/FRA/indicator/SE.TER.ENRR?format=json&mrv=10 | https://api.worldbank.org/v2/country/FRA/indicator/SI.POV.GINI?format=json&mrv=10 | +1 more | AY39: Tier 3 | AZ39: 2023-12-31 | BA39: providers=who_gho, world_bank; fields=healthcare_quality_raw, education_quality_raw, equal_opportunity_raw, gini_coefficient | BB39: https://api.worldbank.org/v2/country/FRA/indicator/SM.POP.NETM?format=json&mrv=10 | https://api.worldbank.org/v2/country/FRA/indicator/SG.GEN.PARL.ZS?format=json&mrv=10 | https://api.worldbank.org/v2/country/FRA/indicator/ST.INT.ARVL?format=json&mrv=10 | +1 more | BC39: Tier 3 | BD39: 2025-12-31 | BE39: providers=world_bank; fields=hospitality_belonging_raw, tolerance_pluralism_raw, cultural_public_life_raw, birth_rate_optimism_raw | BF39: https://api.worldbank.org/v2/country/FRA/indicator/IC.BUS.NDNS.ZS?format=json&mrv=10 | https://api.worldbank.org/v2/country/FRA/indicator/GB.XPD.RSDV.GD.ZS?format=json&mrv=10 | https://api.worldbank.org/v2/country/FRA/indicator/BX.KLT.DINV.WD.GD.ZS?format=json&mrv=10 | +3 more | BG39: Tier 3 | BH39: 2024-12-31 | BI39: providers=world_bank; fields=entrepreneurial_dynamism_raw, innovation_research_intensity_raw, investment_signal_raw, administrative_investment_friction_raw; +2 additional fields | BJ39: 1.68
A40: at-vienna | B40: Vienna | C40: Austria | D40: Western, Northern, and Southern Europe | E40: primary | F40: locked | G40: 6180 | H40: 2163 | I40: 432.6 | J40: 309 | K40: 92.7 | L40: 927 | N40: 35 | O40: 81.4953 | P40: =IF($O40<>"",$O40,$AO40) | Q40: 33.41 | R40: 14.51 | S40: 0.88 | V40: 98.89 | W40: 29.37 | X40: 52 | Y40: 84 | Z40: 91.68 | AA40: 31.2 | AB40: 51.23 | AC40: 36.07 | AD40: 1644.26 | AE40: 0.95 | AF40: 3.2 | AG40: 2.55 | AH40: 1.14 | AJ40: =IFERROR(INDEX(Country_Context!$B$2:$B$87,MATCH($C40,Country_Context!$A$2:$A$87,0)),"") | AK40: =IFERROR(INDEX(Country_Context!$C$2:$C$87,MATCH($C40,Country_Context!$A$2:$A$87,0)),"") | AL40: =IFERROR(INDEX(Country_Context!$D$2:$D$87,MATCH($C40,Country_Context!$A$2:$A$87,0)),"") | AM40: =IFERROR(INDEX(Country_Context!$E$2:$E$87,MATCH($C40,Country_Context!$A$2:$A$87,0)),"") | AN40: =IFERROR(INDEX(Country_Context!$F$2:$F$87,MATCH($C40,Country_Context!$A$2:$A$87,0)),"") | AO40: =IFERROR(INDEX(Country_Context!$G$2:$G$87,MATCH($C40,Country_Context!$A$2:$A$87,0)),"") | AP40: https://api.worldbank.org/v2/country/AUT/indicator/NY.GNP.PCAP.PP.CD?format=json&mrv=10 | https://data.worldbank.org/indicator/NY.GNP.PCAP.PP.CD | https://ilostat.ilo.org/data/indicator/?id=HOW_TEMP_SEX_ECO_NB_A&ref_area=AUT | +4 more | AQ40: Tier 3, Tier 4 | AR40: 2024-12-31 | AS40: providers=world_bank_col_estimate, derived, ilo_ilostat, who_gho; fields=gross_income, rent, utilities, transit_cost; +9 additional fields | AT40: https://api.worldbank.org/v2/country/AUT/indicator/VC.IHR.PSRC.P5?format=json&mrv=10 | https://api.worldbank.org/v2/country/AUT/indicator/SH.H2O.SMDW.ZS?format=json&mrv=10 | https://api.worldbank.org/v2/country/AUT/indicator/IT.NET.BBND.P2?format=json&mrv=10 | +1 more | AU40: Tier 3 | AV40: 2024-12-31 | AW40: providers=world_bank, wmo_natl_met; fields=personal_safety_raw, water_sanitation_utility_raw, digital_infrastructure_raw, climate_sunlight_livability_raw | AX40: https://www.who.int/data/gho/data/indicators/indicator-details/GHO/UHC_INDEX_REPORTED | https://api.worldbank.org/v2/country/AUT/indicator/SE.TER.ENRR?format=json&mrv=10 | https://api.worldbank.org/v2/country/AUT/indicator/SI.POV.GINI?format=json&mrv=10 | +1 more | AY40: Tier 3 | AZ40: 2023-12-31 | BA40: providers=who_gho, world_bank; fields=healthcare_quality_raw, education_quality_raw, equal_opportunity_raw, gini_coefficient | BB40: https://api.worldbank.org/v2/country/AUT/indicator/SM.POP.NETM?format=json&mrv=10 | https://api.worldbank.org/v2/country/AUT/indicator/SG.GEN.PARL.ZS?format=json&mrv=10 | https://api.worldbank.org/v2/country/AUT/indicator/ST.INT.ARVL?format=json&mrv=10 | +1 more | BC40: Tier 3 | BD40: 2025-12-31 | BE40: providers=world_bank; fields=hospitality_belonging_raw, tolerance_pluralism_raw, cultural_public_life_raw, birth_rate_optimism_raw | BF40: https://api.worldbank.org/v2/country/AUT/indicator/IC.BUS.NDNS.ZS?format=json&mrv=10 | https://api.worldbank.org/v2/country/AUT/indicator/GB.XPD.RSDV.GD.ZS?format=json&mrv=10 | https://api.worldbank.org/v2/country/AUT/indicator/BX.KLT.DINV.WD.GD.ZS?format=json&mrv=10 | +3 more | BG40: Tier 3 | BH40: 2024-12-31 | BI40: providers=world_bank; fields=entrepreneurial_dynamism_raw, innovation_research_intensity_raw, investment_signal_raw, administrative_investment_friction_raw; +2 additional fields | BJ40: 1.41
A41: ch-zurich | B41: Zurich | C41: Switzerland | D41: Western, Northern, and Southern Europe | E41: primary | F41: locked | G41: 9342 | H41: 4087.12 | I41: 817.43 | J41: 583.88 | K41: 175.16 | L41: 1751.62 | N41: 43.7499 | O41: 170.3782 | P41: =IF($O41<>"",$O41,$AO41) | Q41: 35.21 | R41: 14.02 | S41: 0.6 | V41: 96.7 | W41: 47.7 | X41: 50 | Y41: 87 | Z41: 74.01 | AA41: 33.8 | AB41: 54.14 | AC41: 38.5 | AD41: 1312.3 | AE41: 4.63 | AF41: 3.31 | AG41: -11.57 | AH41: 0.77 | AJ41: =IFERROR(INDEX(Country_Context!$B$2:$B$87,MATCH($C41,Country_Context!$A$2:$A$87,0)),"") | AK41: =IFERROR(INDEX(Country_Context!$C$2:$C$87,MATCH($C41,Country_Context!$A$2:$A$87,0)),"") | AL41: =IFERROR(INDEX(Country_Context!$D$2:$D$87,MATCH($C41,Country_Context!$A$2:$A$87,0)),"") | AM41: =IFERROR(INDEX(Country_Context!$E$2:$E$87,MATCH($C41,Country_Context!$A$2:$A$87,0)),"") | AN41: =IFERROR(INDEX(Country_Context!$F$2:$F$87,MATCH($C41,Country_Context!$A$2:$A$87,0)),"") | AO41: =IFERROR(INDEX(Country_Context!$G$2:$G$87,MATCH($C41,Country_Context!$A$2:$A$87,0)),"") | AP41: https://api.worldbank.org/v2/country/CHE/indicator/NY.GNP.PCAP.PP.CD?format=json&mrv=10 | https://data.worldbank.org/indicator/NY.GNP.PCAP.PP.CD | https://ilostat.ilo.org/data/indicator/?id=HOW_TEMP_SEX_ECO_NB_A&ref_area=CHE | +4 more | AQ41: Tier 3, Tier 4 | AR41: 2024-12-31 | AS41: providers=world_bank_col_estimate, derived, ilo_ilostat, who_gho; fields=gross_income, rent, utilities, transit_cost; +9 additional fields | AT41: https://api.worldbank.org/v2/country/CHE/indicator/VC.IHR.PSRC.P5?format=json&mrv=10 | https://api.worldbank.org/v2/country/CHE/indicator/SH.H2O.SMDW.ZS?format=json&mrv=10 | https://api.worldbank.org/v2/country/CHE/indicator/IT.NET.BBND.P2?format=json&mrv=10 | +1 more | AU41: Tier 3 | AV41: 2024-12-31 | AW41: providers=world_bank, wmo_natl_met; fields=personal_safety_raw, water_sanitation_utility_raw, digital_infrastructure_raw, climate_sunlight_livability_raw | AX41: https://www.who.int/data/gho/data/indicators/indicator-details/GHO/UHC_INDEX_REPORTED | https://api.worldbank.org/v2/country/CHE/indicator/SE.TER.ENRR?format=json&mrv=10 | https://api.worldbank.org/v2/country/CHE/indicator/SI.POV.GINI?format=json&mrv=10 | +1 more | AY41: Tier 3 | AZ41: 2023-12-31 | BA41: providers=who_gho, world_bank; fields=healthcare_quality_raw, education_quality_raw, equal_opportunity_raw, gini_coefficient | BB41: https://api.worldbank.org/v2/country/CHE/indicator/SM.POP.NETM?format=json&mrv=10 | https://api.worldbank.org/v2/country/CHE/indicator/SG.GEN.PARL.ZS?format=json&mrv=10 | https://api.worldbank.org/v2/country/CHE/indicator/ST.INT.ARVL?format=json&mrv=10 | +1 more | BC41: Tier 3 | BD41: 2025-12-31 | BE41: providers=world_bank; fields=hospitality_belonging_raw, tolerance_pluralism_raw, cultural_public_life_raw, birth_rate_optimism_raw | BF41: https://api.worldbank.org/v2/country/CHE/indicator/IC.BUS.NDNS.ZS?format=json&mrv=10 | https://api.worldbank.org/v2/country/CHE/indicator/GB.XPD.RSDV.GD.ZS?format=json&mrv=10 | https://api.worldbank.org/v2/country/CHE/indicator/BX.KLT.DINV.WD.GD.ZS?format=json&mrv=10 | +3 more | BG41: Tier 3 | BH41: 2024-12-31 | BI41: providers=world_bank; fields=entrepreneurial_dynamism_raw, innovation_research_intensity_raw, investment_signal_raw, administrative_investment_friction_raw; +2 additional fields | BJ41: 1.46
A42: nl-amsterdam | B42: Amsterdam | C42: Netherlands | D42: Western, Northern, and Southern Europe | E42: primary | F42: provisional | G42: 7788.92 | H42: 3271.35 | I42: 654.27 | J42: 467.34 | K42: 140.2 | L42: 1402.01 | N42: 42 | O42: 82.3297 | P42: =IF($O42<>"",$O42,$AO42) | Q42: 30.24 | R42: 11.5 | S42: 0.69 | V42: 99.96 | W42: 43.26 | X42: 46 | Y42: 85 | Z42: 86.59 | AA42: 25.7 | AB42: 55.82 | AC42: 38.67 | AD42: 403.76 | AE42: 3.43 | AF42: 2.26 | AG42: -1.4 | AH42: 0.71 | AJ42: =IFERROR(INDEX(Country_Context!$B$2:$B$87,MATCH($C42,Country_Context!$A$2:$A$87,0)),"") | AK42: =IFERROR(INDEX(Country_Context!$C$2:$C$87,MATCH($C42,Country_Context!$A$2:$A$87,0)),"") | AL42: =IFERROR(INDEX(Country_Context!$D$2:$D$87,MATCH($C42,Country_Context!$A$2:$A$87,0)),"") | AM42: =IFERROR(INDEX(Country_Context!$E$2:$E$87,MATCH($C42,Country_Context!$A$2:$A$87,0)),"") | AN42: =IFERROR(INDEX(Country_Context!$F$2:$F$87,MATCH($C42,Country_Context!$A$2:$A$87,0)),"") | AO42: =IFERROR(INDEX(Country_Context!$G$2:$G$87,MATCH($C42,Country_Context!$A$2:$A$87,0)),"") | AP42: https://api.worldbank.org/v2/country/NLD/indicator/NY.GNP.PCAP.PP.CD?format=json&mrv=10 | https://data.worldbank.org/indicator/NY.GNP.PCAP.PP.CD | https://ilostat.ilo.org/data/indicator/?id=HOW_TEMP_SEX_ECO_NB_A&ref_area=NLD | +4 more | AQ42: Tier 3, Tier 4 | AR42: 2024-12-31 | AS42: providers=world_bank_col_estimate, derived, ilo_ilostat, who_gho; fields=gross_income, rent, utilities, transit_cost; +9 additional fields | AT42: https://api.worldbank.org/v2/country/NLD/indicator/VC.IHR.PSRC.P5?format=json&mrv=10 | https://api.worldbank.org/v2/country/NLD/indicator/SH.H2O.SMDW.ZS?format=json&mrv=10 | https://api.worldbank.org/v2/country/NLD/indicator/IT.NET.BBND.P2?format=json&mrv=10 | +1 more | AU42: Tier 3 | AV42: 2024-12-31 | AW42: providers=world_bank, wmo_natl_met; fields=personal_safety_raw, water_sanitation_utility_raw, digital_infrastructure_raw, climate_sunlight_livability_raw | AX42: https://www.who.int/data/gho/data/indicators/indicator-details/GHO/UHC_INDEX_REPORTED | https://api.worldbank.org/v2/country/NLD/indicator/SE.TER.ENRR?format=json&mrv=10 | https://api.worldbank.org/v2/country/NLD/indicator/SI.POV.GINI?format=json&mrv=10 | +1 more | AY42: Tier 3 | AZ42: 2023-12-31 | BA42: providers=who_gho, world_bank; fields=healthcare_quality_raw, education_quality_raw, equal_opportunity_raw, gini_coefficient | BB42: https://api.worldbank.org/v2/country/NLD/indicator/SM.POP.NETM?format=json&mrv=10 | https://api.worldbank.org/v2/country/NLD/indicator/SG.GEN.PARL.ZS?format=json&mrv=10 | https://api.worldbank.org/v2/country/NLD/indicator/ST.INT.ARVL?format=json&mrv=10 | +1 more | BC42: Tier 3 | BD42: 2025-12-31 | BE42: providers=world_bank; fields=hospitality_belonging_raw, tolerance_pluralism_raw, cultural_public_life_raw, birth_rate_optimism_raw | BF42: https://api.worldbank.org/v2/country/NLD/indicator/IC.BUS.NDNS.ZS?format=json&mrv=10 | https://api.worldbank.org/v2/country/NLD/indicator/GB.XPD.RSDV.GD.ZS?format=json&mrv=10 | https://api.worldbank.org/v2/country/NLD/indicator/BX.KLT.DINV.WD.GD.ZS?format=json&mrv=10 | +3 more | BG42: Tier 3 | BH42: 2024-12-31 | BI42: providers=world_bank; fields=entrepreneurial_dynamism_raw, innovation_research_intensity_raw, investment_signal_raw, administrative_investment_friction_raw; +2 additional fields | BJ42: 1.49
A43: dk-copenhagen | B43: Copenhagen | C43: Denmark | D43: Western, Northern, and Southern Europe | E43: primary | F43: provisional | G43: 7409.5 | H43: 2982.32 | I43: 596.46 | J43: 426.05 | K43: 127.81 | L43: 1278.14 | N43: 40.2499 | O43: 144.0931 | P43: =IF($O43<>"",$O43,$AO43) | Q43: 32.39 | R43: 10.46 | S43: 0.84 | V43: 99.92 | W43: 44.03 | X43: 40 | Y43: 85 | Z43: 81.23 | AA43: 29.9 | AB43: 53.7 | AC43: 45.25 | AD43: 2609.17 | AE43: 7.3 | AF43: 2.89 | AG43: 4.37 | AH43: 0.66 | AJ43: =IFERROR(INDEX(Country_Context!$B$2:$B$87,MATCH($C43,Country_Context!$A$2:$A$87,0)),"") | AK43: =IFERROR(INDEX(Country_Context!$C$2:$C$87,MATCH($C43,Country_Context!$A$2:$A$87,0)),"") | AL43: =IFERROR(INDEX(Country_Context!$D$2:$D$87,MATCH($C43,Country_Context!$A$2:$A$87,0)),"") | AM43: =IFERROR(INDEX(Country_Context!$E$2:$E$87,MATCH($C43,Country_Context!$A$2:$A$87,0)),"") | AN43: =IFERROR(INDEX(Country_Context!$F$2:$F$87,MATCH($C43,Country_Context!$A$2:$A$87,0)),"") | AO43: =IFERROR(INDEX(Country_Context!$G$2:$G$87,MATCH($C43,Country_Context!$A$2:$A$87,0)),"") | AP43: https://api.worldbank.org/v2/country/DNK/indicator/NY.GNP.PCAP.PP.CD?format=json&mrv=10 | https://data.worldbank.org/indicator/NY.GNP.PCAP.PP.CD | https://ilostat.ilo.org/data/indicator/?id=HOW_TEMP_SEX_ECO_NB_A&ref_area=DNK | +4 more | AQ43: Tier 3, Tier 4 | AR43: 2024-12-31 | AS43: providers=world_bank_col_estimate, derived, ilo_ilostat, who_gho; fields=gross_income, rent, utilities, transit_cost; +9 additional fields | AT43: https://api.worldbank.org/v2/country/DNK/indicator/VC.IHR.PSRC.P5?format=json&mrv=10 | https://api.worldbank.org/v2/country/DNK/indicator/SH.H2O.SMDW.ZS?format=json&mrv=10 | https://api.worldbank.org/v2/country/DNK/indicator/IT.NET.BBND.P2?format=json&mrv=10 | +1 more | AU43: Tier 3 | AV43: 2024-12-31 | AW43: providers=world_bank, wmo_natl_met; fields=personal_safety_raw, water_sanitation_utility_raw, digital_infrastructure_raw, climate_sunlight_livability_raw | AX43: https://www.who.int/data/gho/data/indicators/indicator-details/GHO/UHC_INDEX_REPORTED | https://api.worldbank.org/v2/country/DNK/indicator/SE.TER.ENRR?format=json&mrv=10 | https://api.worldbank.org/v2/country/DNK/indicator/SI.POV.GINI?format=json&mrv=10 | +1 more | AY43: Tier 3 | AZ43: 2023-12-31 | BA43: providers=who_gho, world_bank; fields=healthcare_quality_raw, education_quality_raw, equal_opportunity_raw, gini_coefficient | BB43: https://api.worldbank.org/v2/country/DNK/indicator/SM.POP.NETM?format=json&mrv=10 | https://api.worldbank.org/v2/country/DNK/indicator/SG.GEN.PARL.ZS?format=json&mrv=10 | https://api.worldbank.org/v2/country/DNK/indicator/ST.INT.ARVL?format=json&mrv=10 | +1 more | BC43: Tier 3 | BD43: 2025-12-31 | BE43: providers=world_bank; fields=hospitality_belonging_raw, tolerance_pluralism_raw, cultural_public_life_raw, birth_rate_optimism_raw | BF43: https://api.worldbank.org/v2/country/DNK/indicator/IC.BUS.NDNS.ZS?format=json&mrv=10 | https://api.worldbank.org/v2/country/DNK/indicator/GB.XPD.RSDV.GD.ZS?format=json&mrv=10 | https://api.worldbank.org/v2/country/DNK/indicator/BX.KLT.DINV.WD.GD.ZS?format=json&mrv=10 | +3 more | BG43: Tier 3 | BH43: 2024-12-31 | BI43: providers=world_bank; fields=entrepreneurial_dynamism_raw, innovation_research_intensity_raw, investment_signal_raw, administrative_investment_friction_raw; +2 additional fields | BJ43: 1.55
A44: it-milan | B44: Milan | C44: Italy | D44: Western, Northern, and Southern Europe | E44: primary | F44: provisional | G44: 39023.18 | H44: 2480.2 | I44: 496.04 | J44: 330 | K44: 106.29 | L44: 1062.94 | N44: 6.3557 | O44: 59.3116 | P44: =IF($O44<>"",$O44,$AO44) | Q44: 35.96 | R44: 6.99 | S44: 0.5 | T44: 75.43 | U44: 21 | V44: 96.76 | W44: 31.84 | X44: 54 | Y44: 82 | Z44: 75.95 | AA44: 34.3 | AB44: 51.28 | AC44: 32.25 | AD44: 651.69 | AE44: 2.85 | AF44: 1.39 | AG44: 1.13 | AH44: 1.86 | AI44: 8.5 | AJ44: =IFERROR(INDEX(Country_Context!$B$2:$B$87,MATCH($C44,Country_Context!$A$2:$A$87,0)),"") | AK44: =IFERROR(INDEX(Country_Context!$C$2:$C$87,MATCH($C44,Country_Context!$A$2:$A$87,0)),"") | AL44: =IFERROR(INDEX(Country_Context!$D$2:$D$87,MATCH($C44,Country_Context!$A$2:$A$87,0)),"") | AM44: =IFERROR(INDEX(Country_Context!$E$2:$E$87,MATCH($C44,Country_Context!$A$2:$A$87,0)),"") | AN44: =IFERROR(INDEX(Country_Context!$F$2:$F$87,MATCH($C44,Country_Context!$A$2:$A$87,0)),"") | AO44: =IFERROR(INDEX(Country_Context!$G$2:$G$87,MATCH($C44,Country_Context!$A$2:$A$87,0)),"") | AP44: https://dati.comune.milano.it/dataset/edfe847d-05f1-4d25-ba44-283d22b1ec73/resource/76b54f5a-24a6-4f7f-a3a9-a6152d8da601/download/redditi_e_principali_variabili_irpef_su_base_comunale_csv_2023.csv | https://api.worldbank.org/v2/country/ITA/indicator/NY.GNP.PCAP.PP.CD?format=json&mrv=10 | https://www.atm.it/en/ViaggiaConNoi/Abbonamenti/Pages/Tipologie.aspx | +6 more | AQ44: Tier 1, Tier 3, Tier 4 | AR44: 2026-03-12 | AS44: providers=comune_milano_open_data, world_bank_col_estimate, atm_milano, derived; fields=gross_income, rent, utilities, transit_cost; +9 additional fields | AT44: https://dati.comune.milano.it/dataset/34e2d2af-5c3b-4768-918b-ab7e5c0d15da/resource/8b03b9f2-f2d7-4408-b439-bc6efc093cff/download/ds564_reati_denunciati_2004_2023.csv | https://dati.comune.milano.it/dataset/0ac0f655-1858-410a-9873-70fd057ef65d/resource/39d6ef17-8882-49b6-b2de-dd4a8486d923/download/ds393_popolazione_pendolari_movimenti_interni_mezzo_tempo_orario_uscita_genere__2011c.csv | https://www.arpalombardia.it/agenda/notizie/2026/qualita-dell-aria-prosegue-il-miglioramento-anche-nell-anno-2025/ | +3 more | AU44: Tier 1, Tier 2, Tier 3 | AV44: 2026-03-12 | AW44: providers=comune_milano_open_data, arpa_lombardia, world_bank, wmo_natl_met; fields=personal_safety_raw, transit_access_commute_raw, clean_air_raw, water_sanitation_utility_raw; +2 additional fields | AX44: https://www.who.int/data/gho/data/indicators/indicator-details/GHO/UHC_INDEX_REPORTED | https://api.worldbank.org/v2/country/ITA/indicator/SE.TER.ENRR?format=json&mrv=10 | https://api.worldbank.org/v2/country/ITA/indicator/SI.POV.GINI?format=json&mrv=10 | +1 more | AY44: Tier 3 | AZ44: 2023-12-31 | BA44: providers=who_gho, world_bank; fields=healthcare_quality_raw, education_quality_raw, equal_opportunity_raw, gini_coefficient | BB44: https://api.worldbank.org/v2/country/ITA/indicator/SM.POP.NETM?format=json&mrv=10 | https://api.worldbank.org/v2/country/ITA/indicator/SG.GEN.PARL.ZS?format=json&mrv=10 | https://api.worldbank.org/v2/country/ITA/indicator/ST.INT.ARVL?format=json&mrv=10 | +1 more | BC44: Tier 3 | BD44: 2025-12-31 | BE44: providers=world_bank; fields=hospitality_belonging_raw, tolerance_pluralism_raw, cultural_public_life_raw, birth_rate_optimism_raw | BF44: https://api.worldbank.org/v2/country/ITA/indicator/IC.BUS.NDNS.ZS?format=json&mrv=10 | https://api.worldbank.org/v2/country/ITA/indicator/GB.XPD.RSDV.GD.ZS?format=json&mrv=10 | https://api.worldbank.org/v2/country/ITA/indicator/BX.KLT.DINV.WD.GD.ZS?format=json&mrv=10 | +4 more | BG44: Tier 1, Tier 3 | BH44: 2026-03-12 | BI44: providers=world_bank, comune_milano_open_data; fields=entrepreneurial_dynamism_raw, innovation_research_intensity_raw, investment_signal_raw, administrative_investment_friction_raw; +3 additional fields | BJ44: 1.24
A45: at-graz | B45: Graz | C45: Austria | D45: Western, Northern, and Southern Europe | E45: secondary | F45: locked | G45: 6180 | H45: 1730.4 | I45: 346.08 | J45: 247.2 | K45: 74.16 | L45: 741.6 | N45: 28 | O45: 81.4953 | P45: =IF($O45<>"",$O45,$AO45) | Q45: 33.41 | R45: 14.51 | S45: 0.88 | V45: 98.89 | W45: 29.37 | X45: 50 | Y45: 84 | Z45: 91.68 | AA45: 31.2 | AB45: 51.23 | AC45: 36.07 | AD45: 1644.26 | AE45: 0.95 | AF45: 3.2 | AG45: 2.55 | AH45: 1.14 | AJ45: =IFERROR(INDEX(Country_Context!$B$2:$B$87,MATCH($C45,Country_Context!$A$2:$A$87,0)),"") | AK45: =IFERROR(INDEX(Country_Context!$C$2:$C$87,MATCH($C45,Country_Context!$A$2:$A$87,0)),"") | AL45: =IFERROR(INDEX(Country_Context!$D$2:$D$87,MATCH($C45,Country_Context!$A$2:$A$87,0)),"") | AM45: =IFERROR(INDEX(Country_Context!$E$2:$E$87,MATCH($C45,Country_Context!$A$2:$A$87,0)),"") | AN45: =IFERROR(INDEX(Country_Context!$F$2:$F$87,MATCH($C45,Country_Context!$A$2:$A$87,0)),"") | AO45: =IFERROR(INDEX(Country_Context!$G$2:$G$87,MATCH($C45,Country_Context!$A$2:$A$87,0)),"") | AP45: https://api.worldbank.org/v2/country/AUT/indicator/NY.GNP.PCAP.PP.CD?format=json&mrv=10 | https://data.worldbank.org/indicator/NY.GNP.PCAP.PP.CD | https://ilostat.ilo.org/data/indicator/?id=HOW_TEMP_SEX_ECO_NB_A&ref_area=AUT | +4 more | AQ45: Tier 3, Tier 4 | AR45: 2024-12-31 | AS45: providers=world_bank_col_estimate, derived, ilo_ilostat, who_gho; fields=gross_income, rent, utilities, transit_cost; +9 additional fields | AT45: https://api.worldbank.org/v2/country/AUT/indicator/VC.IHR.PSRC.P5?format=json&mrv=10 | https://api.worldbank.org/v2/country/AUT/indicator/SH.H2O.SMDW.ZS?format=json&mrv=10 | https://api.worldbank.org/v2/country/AUT/indicator/IT.NET.BBND.P2?format=json&mrv=10 | +1 more | AU45: Tier 3 | AV45: 2024-12-31 | AW45: providers=world_bank, wmo_natl_met; fields=personal_safety_raw, water_sanitation_utility_raw, digital_infrastructure_raw, climate_sunlight_livability_raw | AX45: https://www.who.int/data/gho/data/indicators/indicator-details/GHO/UHC_INDEX_REPORTED | https://api.worldbank.org/v2/country/AUT/indicator/SE.TER.ENRR?format=json&mrv=10 | https://api.worldbank.org/v2/country/AUT/indicator/SI.POV.GINI?format=json&mrv=10 | +1 more | AY45: Tier 3 | AZ45: 2023-12-31 | BA45: providers=who_gho, world_bank; fields=healthcare_quality_raw, education_quality_raw, equal_opportunity_raw, gini_coefficient | BB45: https://api.worldbank.org/v2/country/AUT/indicator/SM.POP.NETM?format=json&mrv=10 | https://api.worldbank.org/v2/country/AUT/indicator/SG.GEN.PARL.ZS?format=json&mrv=10 | https://api.worldbank.org/v2/country/AUT/indicator/ST.INT.ARVL?format=json&mrv=10 | +1 more | BC45: Tier 3 | BD45: 2025-12-31 | BE45: providers=world_bank; fields=hospitality_belonging_raw, tolerance_pluralism_raw, cultural_public_life_raw, birth_rate_optimism_raw | BF45: https://api.worldbank.org/v2/country/AUT/indicator/IC.BUS.NDNS.ZS?format=json&mrv=10 | https://api.worldbank.org/v2/country/AUT/indicator/GB.XPD.RSDV.GD.ZS?format=json&mrv=10 | https://api.worldbank.org/v2/country/AUT/indicator/BX.KLT.DINV.WD.GD.ZS?format=json&mrv=10 | +3 more | BG45: Tier 3 | BH45: 2024-12-31 | BI45: providers=world_bank; fields=entrepreneurial_dynamism_raw, innovation_research_intensity_raw, investment_signal_raw, administrative_investment_friction_raw; +2 additional fields | BJ45: 1.41
A46: pt-porto | B46: Porto | C46: Portugal | D46: Western, Northern, and Southern Europe | E46: secondary | F46: locked | G46: 4227.5 | H46: 1257.68 | I46: 251.54 | J46: 179.67 | K46: 53.9 | L46: 539.01 | N46: 29.75 | O46: 77.1375 | P46: =IF($O46<>"",$O46,$AO46) | Q46: 37.27 | R46: 11.52 | S46: 0.72 | V46: 95.22 | W46: 44.11 | X46: 62 | Y46: 83 | Z46: 77.68 | AA46: 33.9 | AB46: 51.54 | AC46: 32.61 | AD46: 393.47 | AE46: 6.95 | AF46: 1.7 | AG46: 4.31 | AH46: 1.74 | AJ46: =IFERROR(INDEX(Country_Context!$B$2:$B$87,MATCH($C46,Country_Context!$A$2:$A$87,0)),"") | AK46: =IFERROR(INDEX(Country_Context!$C$2:$C$87,MATCH($C46,Country_Context!$A$2:$A$87,0)),"") | AL46: =IFERROR(INDEX(Country_Context!$D$2:$D$87,MATCH($C46,Country_Context!$A$2:$A$87,0)),"") | AM46: =IFERROR(INDEX(Country_Context!$E$2:$E$87,MATCH($C46,Country_Context!$A$2:$A$87,0)),"") | AN46: =IFERROR(INDEX(Country_Context!$F$2:$F$87,MATCH($C46,Country_Context!$A$2:$A$87,0)),"") | AO46: =IFERROR(INDEX(Country_Context!$G$2:$G$87,MATCH($C46,Country_Context!$A$2:$A$87,0)),"") | AP46: https://api.worldbank.org/v2/country/PRT/indicator/NY.GNP.PCAP.PP.CD?format=json&mrv=10 | https://data.worldbank.org/indicator/NY.GNP.PCAP.PP.CD | https://ilostat.ilo.org/data/indicator/?id=HOW_TEMP_SEX_ECO_NB_A&ref_area=PRT | +4 more | AQ46: Tier 3, Tier 4 | AR46: 2025-12-31 | AS46: providers=world_bank_col_estimate, derived, ilo_ilostat, who_gho; fields=gross_income, rent, utilities, transit_cost; +9 additional fields | AT46: https://api.worldbank.org/v2/country/PRT/indicator/VC.IHR.PSRC.P5?format=json&mrv=10 | https://api.worldbank.org/v2/country/PRT/indicator/SH.H2O.SMDW.ZS?format=json&mrv=10 | https://api.worldbank.org/v2/country/PRT/indicator/IT.NET.BBND.P2?format=json&mrv=10 | +1 more | AU46: Tier 3 | AV46: 2024-12-31 | AW46: providers=world_bank, wmo_natl_met; fields=personal_safety_raw, water_sanitation_utility_raw, digital_infrastructure_raw, climate_sunlight_livability_raw | AX46: https://www.who.int/data/gho/data/indicators/indicator-details/GHO/UHC_INDEX_REPORTED | https://api.worldbank.org/v2/country/PRT/indicator/SE.TER.ENRR?format=json&mrv=10 | https://api.worldbank.org/v2/country/PRT/indicator/SI.POV.GINI?format=json&mrv=10 | +1 more | AY46: Tier 3 | AZ46: 2023-12-31 | BA46: providers=who_gho, world_bank; fields=healthcare_quality_raw, education_quality_raw, equal_opportunity_raw, gini_coefficient | BB46: https://api.worldbank.org/v2/country/PRT/indicator/SM.POP.NETM?format=json&mrv=10 | https://api.worldbank.org/v2/country/PRT/indicator/SG.GEN.PARL.ZS?format=json&mrv=10 | https://api.worldbank.org/v2/country/PRT/indicator/ST.INT.ARVL?format=json&mrv=10 | +1 more | BC46: Tier 3 | BD46: 2025-12-31 | BE46: providers=world_bank; fields=hospitality_belonging_raw, tolerance_pluralism_raw, cultural_public_life_raw, birth_rate_optimism_raw | BF46: https://api.worldbank.org/v2/country/PRT/indicator/IC.BUS.NDNS.ZS?format=json&mrv=10 | https://api.worldbank.org/v2/country/PRT/indicator/GB.XPD.RSDV.GD.ZS?format=json&mrv=10 | https://api.worldbank.org/v2/country/PRT/indicator/BX.KLT.DINV.WD.GD.ZS?format=json&mrv=10 | +3 more | BG46: Tier 3 | BH46: 2024-12-31 | BI46: providers=world_bank; fields=entrepreneurial_dynamism_raw, innovation_research_intensity_raw, investment_signal_raw, administrative_investment_friction_raw; +2 additional fields | BJ46: 1.43
A47: pt-braga | B47: Braga | C47: Portugal | D47: Western, Northern, and Southern Europe | E47: secondary | F47: locked | G47: 4227.5 | H47: 1109.72 | I47: 221.94 | J47: 158.53 | K47: 47.56 | L47: 475.59 | N47: 26.25 | O47: 77.1375 | P47: =IF($O47<>"",$O47,$AO47) | Q47: 37.27 | R47: 11.52 | S47: 0.72 | V47: 95.22 | W47: 44.11 | X47: 58 | Y47: 83 | Z47: 77.68 | AA47: 33.9 | AB47: 51.54 | AC47: 32.61 | AD47: 393.47 | AE47: 6.95 | AF47: 1.7 | AG47: 4.31 | AH47: 1.74 | AJ47: =IFERROR(INDEX(Country_Context!$B$2:$B$87,MATCH($C47,Country_Context!$A$2:$A$87,0)),"") | AK47: =IFERROR(INDEX(Country_Context!$C$2:$C$87,MATCH($C47,Country_Context!$A$2:$A$87,0)),"") | AL47: =IFERROR(INDEX(Country_Context!$D$2:$D$87,MATCH($C47,Country_Context!$A$2:$A$87,0)),"") | AM47: =IFERROR(INDEX(Country_Context!$E$2:$E$87,MATCH($C47,Country_Context!$A$2:$A$87,0)),"") | AN47: =IFERROR(INDEX(Country_Context!$F$2:$F$87,MATCH($C47,Country_Context!$A$2:$A$87,0)),"") | AO47: =IFERROR(INDEX(Country_Context!$G$2:$G$87,MATCH($C47,Country_Context!$A$2:$A$87,0)),"") | AP47: https://api.worldbank.org/v2/country/PRT/indicator/NY.GNP.PCAP.PP.CD?format=json&mrv=10 | https://data.worldbank.org/indicator/NY.GNP.PCAP.PP.CD | https://ilostat.ilo.org/data/indicator/?id=HOW_TEMP_SEX_ECO_NB_A&ref_area=PRT | +4 more | AQ47: Tier 3, Tier 4 | AR47: 2025-12-31 | AS47: providers=world_bank_col_estimate, derived, ilo_ilostat, who_gho; fields=gross_income, rent, utilities, transit_cost; +9 additional fields | AT47: https://api.worldbank.org/v2/country/PRT/indicator/VC.IHR.PSRC.P5?format=json&mrv=10 | https://api.worldbank.org/v2/country/PRT/indicator/SH.H2O.SMDW.ZS?format=json&mrv=10 | https://api.worldbank.org/v2/country/PRT/indicator/IT.NET.BBND.P2?format=json&mrv=10 | +1 more | AU47: Tier 3 | AV47: 2024-12-31 | AW47: providers=world_bank, wmo_natl_met; fields=personal_safety_raw, water_sanitation_utility_raw, digital_infrastructure_raw, climate_sunlight_livability_raw | AX47: https://www.who.int/data/gho/data/indicators/indicator-details/GHO/UHC_INDEX_REPORTED | https://api.worldbank.org/v2/country/PRT/indicator/SE.TER.ENRR?format=json&mrv=10 | https://api.worldbank.org/v2/country/PRT/indicator/SI.POV.GINI?format=json&mrv=10 | +1 more | AY47: Tier 3 | AZ47: 2023-12-31 | BA47: providers=who_gho, world_bank; fields=healthcare_quality_raw, education_quality_raw, equal_opportunity_raw, gini_coefficient | BB47: https://api.worldbank.org/v2/country/PRT/indicator/SM.POP.NETM?format=json&mrv=10 | https://api.worldbank.org/v2/country/PRT/indicator/SG.GEN.PARL.ZS?format=json&mrv=10 | https://api.worldbank.org/v2/country/PRT/indicator/ST.INT.ARVL?format=json&mrv=10 | +1 more | BC47: Tier 3 | BD47: 2025-12-31 | BE47: providers=world_bank; fields=hospitality_belonging_raw, tolerance_pluralism_raw, cultural_public_life_raw, birth_rate_optimism_raw | BF47: https://api.worldbank.org/v2/country/PRT/indicator/IC.BUS.NDNS.ZS?format=json&mrv=10 | https://api.worldbank.org/v2/country/PRT/indicator/GB.XPD.RSDV.GD.ZS?format=json&mrv=10 | https://api.worldbank.org/v2/country/PRT/indicator/BX.KLT.DINV.WD.GD.ZS?format=json&mrv=10 | +3 more | BG47: Tier 3 | BH47: 2024-12-31 | BI47: providers=world_bank; fields=entrepreneurial_dynamism_raw, innovation_research_intensity_raw, investment_signal_raw, administrative_investment_friction_raw; +2 additional fields | BJ47: 1.43
A48: ee-tallinn | B48: Tallinn | C48: Estonia | D48: Western, Northern, and Southern Europe | E48: secondary | F48: locked | G48: 4073.33 | H48: 1283.1 | I48: 256.62 | J48: 183.3 | K48: 54.99 | L48: 549.9 | N48: 31.5 | O48: 60.5329 | P48: =IF($O48<>"",$O48,$AO48) | Q48: 35.8 | R48: 14.94 | S48: 1.54 | V48: 98.94 | W48: 35.25 | X48: 34 | Y48: 79 | Z48: 67.62 | AA48: 30.7 | AB48: 40.27 | AC48: 29.7 | AD48: 1235.12 | AE48: 24.32 | AF48: 1.78 | AG48: -7.97 | AH48: 1.07 | AJ48: =IFERROR(INDEX(Country_Context!$B$2:$B$87,MATCH($C48,Country_Context!$A$2:$A$87,0)),"") | AK48: =IFERROR(INDEX(Country_Context!$C$2:$C$87,MATCH($C48,Country_Context!$A$2:$A$87,0)),"") | AL48: =IFERROR(INDEX(Country_Context!$D$2:$D$87,MATCH($C48,Country_Context!$A$2:$A$87,0)),"") | AM48: =IFERROR(INDEX(Country_Context!$E$2:$E$87,MATCH($C48,Country_Context!$A$2:$A$87,0)),"") | AN48: =IFERROR(INDEX(Country_Context!$F$2:$F$87,MATCH($C48,Country_Context!$A$2:$A$87,0)),"") | AO48: =IFERROR(INDEX(Country_Context!$G$2:$G$87,MATCH($C48,Country_Context!$A$2:$A$87,0)),"") | AP48: https://api.worldbank.org/v2/country/EST/indicator/NY.GNP.PCAP.PP.CD?format=json&mrv=10 | https://data.worldbank.org/indicator/NY.GNP.PCAP.PP.CD | https://ilostat.ilo.org/data/indicator/?id=HOW_TEMP_SEX_ECO_NB_A&ref_area=EST | +4 more | AQ48: Tier 3, Tier 4 | AR48: 2024-12-31 | AS48: providers=world_bank_col_estimate, derived, ilo_ilostat, who_gho; fields=gross_income, rent, utilities, transit_cost; +9 additional fields | AT48: https://api.worldbank.org/v2/country/EST/indicator/VC.IHR.PSRC.P5?format=json&mrv=10 | https://api.worldbank.org/v2/country/EST/indicator/SH.H2O.SMDW.ZS?format=json&mrv=10 | https://api.worldbank.org/v2/country/EST/indicator/IT.NET.BBND.P2?format=json&mrv=10 | +1 more | AU48: Tier 3 | AV48: 2024-12-31 | AW48: providers=world_bank, wmo_natl_met; fields=personal_safety_raw, water_sanitation_utility_raw, digital_infrastructure_raw, climate_sunlight_livability_raw | AX48: https://www.who.int/data/gho/data/indicators/indicator-details/GHO/UHC_INDEX_REPORTED | https://api.worldbank.org/v2/country/EST/indicator/SE.TER.ENRR?format=json&mrv=10 | https://api.worldbank.org/v2/country/EST/indicator/SI.POV.GINI?format=json&mrv=10 | +1 more | AY48: Tier 3 | AZ48: 2023-12-31 | BA48: providers=who_gho, world_bank; fields=healthcare_quality_raw, education_quality_raw, equal_opportunity_raw, gini_coefficient | BB48: https://api.worldbank.org/v2/country/EST/indicator/SM.POP.NETM?format=json&mrv=10 | https://api.worldbank.org/v2/country/EST/indicator/SG.GEN.PARL.ZS?format=json&mrv=10 | https://api.worldbank.org/v2/country/EST/indicator/ST.INT.ARVL?format=json&mrv=10 | BC48: Tier 3 | BD48: 2025-12-31 | BE48: providers=world_bank; fields=hospitality_belonging_raw, tolerance_pluralism_raw, cultural_public_life_raw | BF48: https://api.worldbank.org/v2/country/EST/indicator/IC.BUS.NDNS.ZS?format=json&mrv=10 | https://api.worldbank.org/v2/country/EST/indicator/GB.XPD.RSDV.GD.ZS?format=json&mrv=10 | https://api.worldbank.org/v2/country/EST/indicator/BX.KLT.DINV.WD.GD.ZS?format=json&mrv=10 | +3 more | BG48: Tier 3 | BH48: 2024-12-31 | BI48: providers=world_bank; fields=entrepreneurial_dynamism_raw, innovation_research_intensity_raw, investment_signal_raw, administrative_investment_friction_raw; +2 additional fields
A49: fi-helsinki | B49: Helsinki | C49: Finland | D49: Western, Northern, and Southern Europe | E49: secondary | F49: provisional | G49: 5470 | H49: 2010.22 | I49: 402.05 | J49: 287.18 | K49: 86.15 | L49: 861.53 | N49: 36.7499 | O49: 90.8647 | P49: =IF($O49<>"",$O49,$AO49) | Q49: 33.83 | R49: 14.57 | S49: 0.98 | V49: 99.65 | W49: 35.33 | X49: 32 | Y49: 86 | Z49: 108.13 | AA49: 27.4 | AB49: 53.25 | AC49: 46 | AD49: 159.43 | AE49: 6.11 | AF49: 2.96 | AG49: 2.93 | AH49: 0.73 | AJ49: =IFERROR(INDEX(Country_Context!$B$2:$B$87,MATCH($C49,Country_Context!$A$2:$A$87,0)),"") | AK49: =IFERROR(INDEX(Country_Context!$C$2:$C$87,MATCH($C49,Country_Context!$A$2:$A$87,0)),"") | AL49: =IFERROR(INDEX(Country_Context!$D$2:$D$87,MATCH($C49,Country_Context!$A$2:$A$87,0)),"") | AM49: =IFERROR(INDEX(Country_Context!$E$2:$E$87,MATCH($C49,Country_Context!$A$2:$A$87,0)),"") | AN49: =IFERROR(INDEX(Country_Context!$F$2:$F$87,MATCH($C49,Country_Context!$A$2:$A$87,0)),"") | AO49: =IFERROR(INDEX(Country_Context!$G$2:$G$87,MATCH($C49,Country_Context!$A$2:$A$87,0)),"") | AP49: https://api.worldbank.org/v2/country/FIN/indicator/NY.GNP.PCAP.PP.CD?format=json&mrv=10 | https://data.worldbank.org/indicator/NY.GNP.PCAP.PP.CD | https://ilostat.ilo.org/data/indicator/?id=HOW_TEMP_SEX_ECO_NB_A&ref_area=FIN | +4 more | AQ49: Tier 3, Tier 4 | AR49: 2024-12-31 | AS49: providers=world_bank_col_estimate, derived, ilo_ilostat, who_gho; fields=gross_income, rent, utilities, transit_cost; +9 additional fields | AT49: https://api.worldbank.org/v2/country/FIN/indicator/VC.IHR.PSRC.P5?format=json&mrv=10 | https://api.worldbank.org/v2/country/FIN/indicator/SH.H2O.SMDW.ZS?format=json&mrv=10 | https://api.worldbank.org/v2/country/FIN/indicator/IT.NET.BBND.P2?format=json&mrv=10 | +1 more | AU49: Tier 3 | AV49: 2024-12-31 | AW49: providers=world_bank, wmo_natl_met; fields=personal_safety_raw, water_sanitation_utility_raw, digital_infrastructure_raw, climate_sunlight_livability_raw | AX49: https://www.who.int/data/gho/data/indicators/indicator-details/GHO/UHC_INDEX_REPORTED | https://api.worldbank.org/v2/country/FIN/indicator/SE.TER.ENRR?format=json&mrv=10 | https://api.worldbank.org/v2/country/FIN/indicator/SI.POV.GINI?format=json&mrv=10 | +1 more | AY49: Tier 3 | AZ49: 2023-12-31 | BA49: providers=who_gho, world_bank; fields=healthcare_quality_raw, education_quality_raw, equal_opportunity_raw, gini_coefficient | BB49: https://api.worldbank.org/v2/country/FIN/indicator/SM.POP.NETM?format=json&mrv=10 | https://api.worldbank.org/v2/country/FIN/indicator/SG.GEN.PARL.ZS?format=json&mrv=10 | https://api.worldbank.org/v2/country/FIN/indicator/ST.INT.ARVL?format=json&mrv=10 | +1 more | BC49: Tier 3 | BD49: 2025-12-31 | BE49: providers=world_bank; fields=hospitality_belonging_raw, tolerance_pluralism_raw, cultural_public_life_raw, birth_rate_optimism_raw | BF49: https://api.worldbank.org/v2/country/FIN/indicator/IC.BUS.NDNS.ZS?format=json&mrv=10 | https://api.worldbank.org/v2/country/FIN/indicator/GB.XPD.RSDV.GD.ZS?format=json&mrv=10 | https://api.worldbank.org/v2/country/FIN/indicator/BX.KLT.DINV.WD.GD.ZS?format=json&mrv=10 | +3 more | BG49: Tier 3 | BH49: 2024-12-31 | BI49: providers=world_bank; fields=entrepreneurial_dynamism_raw, innovation_research_intensity_raw, investment_signal_raw, administrative_investment_friction_raw; +2 additional fields | BJ49: 1.32
