Workbook

Sheet Google_Sheets_Guide
A1: SLIC Google Sheets Template
A2: Import this workbook into Google Sheets to collect trusted source inputs, inspect formulas, and rerank transparently.
A3: Current verified-source completion | B3: country values=359/378, city values=8/2652
A4: What to edit | B4: Country_Context and City_Inputs
A5: What not to overwrite | B5: Keep formulas intact in Norm_Stats, Scores, and Leaderboard so the board recalculates correctly.
A6: Trusted source policy | B6: Every filled value should keep a visible source URL, source tier, source date, and note trail.
A7: Provider registry | B7: Use Providers_Registry as the starter reference for approved source families and tiers.
A8: Raw audit tabs | B8: Country_Source_Rows and City_Source_Rows mirror the verified-source CSV pack so the collection workflow stays auditable.
A9: Source guide tabs | B9: Field_Source_Guide sets the preferred evidence for each city metric, and City_Source_Playbook adds curated city-specific starting points such as Milan and Bologna.
A10: Publishing rule | B10: Only publish rankings after the verified source pack yields ranked rows and the audit passes.
A12: Current validation issues
A13: No source-pack validation issues currently detected.
A15: Suggested workflow
A16: 1. Fill country context rows first from official sources.
A17: 2. Use Field_Source_Guide and City_Source_Playbook before touching City_Source_Rows.
A18: 3. Fill city inputs with source URLs and dates attached to each pillar trail.
A19: 4. Re-import or keep editing in Google Sheets until the Leaderboard starts producing ranked rows.
A20: 5. Sync the same values back into the verified-source CSV pack for build-time publication.
A22: Internal reference layer
A23: Economist_Reference | B23: Auto-extracted from The World in Numbers PDF for analyst speed only. Do not treat these values as publishable scoring inputs.
A24: Economist_Match_Review | B24: One review row per SLIC country. Promote nothing automatically into Country_Context; every value still needs a trusted non-reference source.
A25: Reference-only provider rule | B25: economist_world_in_numbers is Tier 4 and reference_only=true, so it cannot make the public ranking publishable on its own.

Sheet Source_Coverage
A1: Source Coverage Dashboard
A3: Overall
A4: Metric | B4: Filled | C4: Total | D4: Completion
A5: Country_Context completion | B5: 359 | C5: 378 | D5: 95.0%
A6: City_Inputs completion | B6: 8 | C6: 2652 | D6: 0.3%
A7: Curated city playbook rows | B7: 52 | C7: 52 | D7: 100.0%
A8: Current city universe | B8: 102 | C8: 102 | D8: 100.0%
A11: Country Field Coverage
A12: Field | B12: Filled | C12: Total | D12: Completion
A13: GDP per capita (PPP) | B13: 62 | C13: 63 | D13: 98.4%
A14: GDP growth | B14: 62 | C14: 63 | D14: 98.4%
A15: Gini coefficient | B15: 55 | C15: 63 | D15: 87.3%
A16: PPP private consumption factor | B16: 62 | C16: 63 | D16: 98.4%
A17: Tax rate assumption | B17: 57 | C17: 63 | D17: 90.5%
A18: Household debt proxy | B18: 61 | C18: 63 | D18: 96.8%
A20: Italy Spotlight
A21: Target | B21: Filled | C21: Total | D21: Completion
A22: Italy Country_Context | B22: 6 | C22: 6 | D22: 100.0%
A23: Milan City_Inputs | B23: 8 | C23: 26 | D23: 30.8%
A24: Bologna City_Inputs | B24: 0 | C24: 26 | D24: 0.0%
A26: City Field Coverage
A27: Field | B27: Filled | C27: Total | D27: Completion
A28: Gross income | B28: 1 | C28: 102 | D28: 1.0%
A29: Rent | B29: 0 | C29: 102 | D29: 0.0%
A30: Utilities | B30: 0 | C30: 102 | D30: 0.0%
A31: Transit cost | B31: 1 | C31: 102 | D31: 1.0%
A32: Internet cost | B32: 0 | C32: 102 | D32: 0.0%
A33: Food cost | B33: 0 | C33: 102 | D33: 0.0%
A34: Housing burden raw | B34: 0 | C34: 102 | D34: 0.0%
A35: Household debt burden raw | B35: 0 | C35: 102 | D35: 0.0%
A36: Working time pressure raw | B36: 0 | C36: 102 | D36: 0.0%
A37: Suicide or mental strain raw | B37: 0 | C37: 102 | D37: 0.0%
A38: Personal safety raw | B38: 1 | C38: 102 | D38: 1.0%
A39: Transit access and commute raw | B39: 1 | C39: 102 | D39: 1.0%
... A53: Visitor flow context raw | B53: 1 | C53: 102 | D53: 1.0%

Sheet README
A1: SLIC Scoring Workbook
A3: Purpose | B3: This workbook is the operational source of truth for the global SLIC city ranking. Enter or import data into Country_Context and City_Inputs, then review Scores, Leaderboard, Region_Comparison, and the Thai-specific scaffold.
A4: Official formula | B4: SLIC(c) = 0.25 Pressure + 0.22 DailyViability + 0.18 HumanCapability + 0.15 Community + 0.20 CreativeVitality
A5: Disposable income term | B5: DI_ppp = ((gross_income x (1 - tax_rate)) - rent - utilities - transit - internet - food) / ppp_private_consumption
A6: Normalization | B6: Each scored input is winsorized at the 5th and 95th percentiles, then converted to a 0-100 score. Harmful variables such as crime, debt, suicide, PM2.5, and administrative friction are reverse-scored.
A7: Coverage rules | B7: A city is Ranked only when overall weighted coverage is at least 50% and every pillar clears the 35% minimum. Coverage grades: A >= 75%, B = 50-74%, C = 35-49%, below 35% = Watchlist.
A8: Source hierarchy | B8: Tier 1 city/metro official data > Tier 2 subnational official data > Tier 3 national and international official data > Tier 4 audited secondary and experimental layers.
A9: Doctrinal rule: safety | B9: Safety is scored by harm and victimization outcomes, never by camera count or visible control hardware.
A10: Doctrinal rule: tolerance | B10: Tolerance is scored through low-friction coexistence and real personal freedom, not symbolic branding proxies.
A11: Doctrinal rule: visitor flows | B11: Visitor flow is contextual only. It should be reviewed against crime, civic strain, and public-life quality rather than treated as an automatic positive.
A12: Country context | B12: GDP per capita PPP, GDP growth, Gini coefficient, PPP private consumption, and user-supplied tax rate are visible in Country_Context. GDP terms are capped context inputs, not headline determinants.
A13: How tax works | B13: Populate tax_rate_assumption in Country_Context as a decimal such as 0.18. City_Inputs pulls that value automatically into tax_rate_context and recomputes di_ppp_raw.
A14: Region comparison | B14: Region_Comparison summarizes ranked city counts and average scores by cohort so Europe, Asia, the Americas, Africa, the Middle East, and Oceania can be compared cleanly.
A15: Thai companion | B15: Thai_Ranking_Scaffold is a separate sheet for a Thailand-only ranking. It emphasizes province GDP per capita, pollution, hospitals, schools, infrastructure, income, longevity, and competitiveness.
A18: Coverage thresholds
A19: ranked_min_overall | B19: 0.5
A20: ranked_min_pillar | B20: 0.35
A21: grade_a_min | B21: 0.75
A22: grade_b_min | B22: 0.5
A23: grade_c_min | B23: 0.35
A26: Source tiers
A27: Tier 1 | B27: City and metro official data | C27: Open-data portals, utility regulators, transit feeds, hospital quality releases, and city statistical offices.
A28: Tier 2 | B28: State, province, and subnational official data | C28: Regional statistical offices, metropolitan observatories, and subnational administrative datasets.
A29: Tier 3 | B29: National and international official datasets | C29: World Bank, WHO, ILO, UNESCO UIS, OECD, WIPO, and WHO/UNICEF JMP.
A30: Tier 4 | B30: Audited secondary and experimental layers | C30: OpenAQ, M-Lab, social listening, crowdsourced cost layers, and city testimony with visible caveats.

Sheet Metric_Catalog
A1: metric_id | B1: metric_name | C1: pillar_id | D1: pillar_name | E1: pillar_weight | F1: metric_weight | G1: directionality | H1: scoring_role | I1: requiredness | J1: data_level | K1: source_priority | L1: workbook_input | M1: notes
A2: disposable_income_ppp | B2: Tax-adjusted PPP disposable income | C2: pressure | D2: Pressure, Affordability, and Room to Live | E2: 25 | F2: 9 | G2: positive | H2: scored | I2: core | J2: city_or_metro_with_country_context | K2: Tier 1 city/metro > Tier 2 subnational > Tier 3 national/international > Tier 4 audited secondary | L2: di_ppp_raw | M2: Derived from gross income, tax, rent, utilities, transit, internet, food, and PPP private consumption.
A3: housing_burden | B3: Housing burden | C3: pressure | D3: Pressure, Affordability, and Room to Live | E3: 25 | F3: 5 | G3: negative | H3: scored | I3: core | J3: city_or_metro | K3: Tier 1 city/metro > Tier 2 subnational > Tier 3 national/international > Tier 4 audited secondary | L3: housing_burden_raw | M3: Higher rent or housing cost share scores worse.
A4: household_debt_burden | B4: Household debt burden | C4: pressure | D4: Pressure, Affordability, and Room to Live | E4: 25 | F4: 4 | G4: negative | H4: scored | I4: core | J4: city_with_country_proxy_fallback | K4: Tier 1 city/metro > Tier 2 subnational > Tier 3 country debt proxy > Tier 4 audited secondary | L4: household_debt_effective_raw | M4: Uses country proxy when city debt burden is unavailable.
A5: working_time_pressure | B5: Working time pressure | C5: pressure | D5: Pressure, Affordability, and Room to Live | E5: 25 | F5: 4 | G5: negative | H5: scored | I5: core | J5: city_or_metro_with_subnational_fallback | K5: Tier 1 city/metro > Tier 2 subnational > Tier 3 ILO/national > Tier 4 audited secondary | L5: working_time_pressure_raw | M5: Higher weekly-hours and overwork prevalence score worse.
A6: suicide_mental_strain | B6: Suicide and severe mental strain | C6: pressure | D6: Pressure, Affordability, and Room to Live | E6: 25 | F6: 3 | G6: negative | H6: scored | I6: core | J6: city_or_metro_with_subnational_fallback | K6: Tier 1 city/metro > Tier 2 subnational > Tier 3 WHO/national > Tier 4 audited secondary | L6: suicide_mental_strain_raw | M6: Lower suicide or equivalent severe-strain rates score better.
A7: personal_safety | B7: Personal safety | C7: viability | D7: Daily Viability and Convenience | E7: 22 | F7: 5 | G7: negative | H7: scored | I7: core | J7: city_or_metro | K7: Tier 1 city/metro > Tier 2 subnational > Tier 3 national/international > Tier 4 audited secondary | L7: personal_safety_raw | M7: Enter a harm-and-victimization index or rate. Camera counts do not score.
A8: transit_access_commute | B8: Transit access and commute burden | C8: viability | D8: Daily Viability and Convenience | E8: 22 | F8: 5 | G8: positive | H8: scored | I8: core | J8: city_or_metro | K8: Tier 1 city/metro > Tier 2 GTFS/subnational > Tier 3 national/international > Tier 4 audited secondary | L8: transit_access_commute_raw | M8: Enter a composite where better access and lower burden push the value upward.
A9: clean_air | B9: Clean air | C9: viability | D9: Daily Viability and Convenience | E9: 22 | F9: 4 | G9: negative | H9: scored | I9: core | J9: city_or_metro | K9: Tier 1 city/metro > Tier 3 WHO/OpenAQ/national > Tier 4 audited secondary | L9: clean_air_raw | M9: Lower PM2.5 or pollution exposure scores better.
A10: water_sanitation_utility | B10: Water, sanitation, and utility reliability | C10: viability | D10: Daily Viability and Convenience | E10: 22 | F10: 4 | G10: positive | H10: scored | I10: core | J10: city_or_metro_with_country_fallback | K10: Tier 1 city/metro > Tier 2 subnational > Tier 3 JMP/national > Tier 4 audited secondary | L10: water_sanitation_utility_raw | M10: Enter a composite where safer access and higher reliability score better.
A11: digital_infrastructure | B11: Digital infrastructure | C11: viability | D11: Daily Viability and Convenience | E11: 22 | F11: 4 | G11: positive | H11: scored | I11: core | J11: city_or_metro_with_country_fallback | K11: Tier 1 city/metro > Tier 2 subnational > Tier 3 OECD/World Bank/M-Lab > Tier 4 audited secondary | L11: digital_infrastructure_raw | M11: Higher broadband quality, affordability, and fibre readiness score better.
A12: healthcare_quality | B12: Healthcare quality | C12: capability | D12: Human Capability | E12: 18 | F12: 8 | G12: positive | H12: scored | I12: core | J12: city_or_metro_with_country_context | K12: Tier 1 city/metro > Tier 2 subnational > Tier 3 WHO/OECD/national > Tier 4 audited secondary | L12: healthcare_quality_raw | M12: Higher effective-care access and outcome quality score better.
A13: education_quality | B13: Education quality | C13: capability | D13: Human Capability | E13: 18 | F13: 6 | G13: positive | H13: scored | I13: core | J13: city_or_metro_with_country_context | K13: Tier 1 city/metro > Tier 2 subnational > Tier 3 UNESCO/OECD/World Bank > Tier 4 audited secondary | L13: education_quality_raw | M13: Higher learning quality and skills formation score better.
... A25: visitor_flow_context | B25: Visitor flow context | C25: community | D25: Community and Openness | E25: 15 | F25: 0 | G25: contextual | H25: context_only | I25: supporting | J25: city_or_metro | K25: Tier 1 tourism/open mobility > Tier 4 audited secondary | L25: visitor_flow_context_raw | M25: Visible on the workbook and leaderboard context layer but not scored directly.

Sheet City_Universe
A1: city_id | B1: display_name | C1: fua_name | D1: country | E1: cohort | F1: city_type | G1: manifest_status | H1: inclusion_rationale
A2: th-bangkok | B2: Bangkok | C2: Bangkok Metropolitan Region | D2: Thailand | E2: Southeast Asia | F2: primary | G2: locked | H2: User anchor and regional benchmark for hospitality, economic dynamism, and affordability-pressure tradeoffs.
A3: sg-singapore | B3: Singapore | C3: Singapore | D3: Singapore | E3: Southeast Asia | F3: primary | G3: locked | H3: Global convenience benchmark included to test how systems quality interacts with pressure, cost, and meaning.
A4: my-kuala-lumpur | B4: Kuala Lumpur | C4: Klang Valley | D4: Malaysia | E4: Southeast Asia | F4: primary | G4: locked | H4: User anchor and regional economic core with strong competitiveness, connectivity, and mixed affordability.
A5: id-jakarta | B5: Jakarta | C5: Jakarta Metropolitan Area | D5: Indonesia | E5: Southeast Asia | F5: primary | G5: provisional | H5: Necessary Southeast Asian benchmark for scale, competitiveness, and infrastructure-pressure tradeoffs.
A6: ph-makati | B6: Makati | C6: Metro Manila Core Business District | D6: Philippines | E6: Southeast Asia | F6: primary | G6: provisional | H6: Metro-core Philippine test case included for business density, services, and lived-affordability stress.
A7: my-george-town | B7: George Town | C7: Penang Conurbation | D7: Malaysia | E7: Southeast Asia | F7: secondary | G7: locked | H7: User anchor for semiconductor economy, cultural texture, and secondary-city livability.
A8: th-phuket | B8: Phuket | C8: Phuket Island Urban Area | D8: Thailand | E8: Southeast Asia | F8: secondary | G8: locked | H8: User anchor and tourism-livability stress test for cost, safety, and service quality.
A9: th-chiang-mai | B9: Chiang Mai | C9: Chiang Mai Metropolitan Area | D9: Thailand | E9: Southeast Asia | F9: secondary | G9: locked | H9: User anchor for creativity, secondary-city ambition, and lifestyle viability.
A10: my-kuching | B10: Kuching | C10: Greater Kuching | D10: Malaysia | E10: Southeast Asia | F10: secondary | G10: locked | H10: User anchor included as a calmer secondary-city comparator with strong everyday livability appeal.
A11: th-hat-yai | B11: Hat Yai | C11: Hat Yai-Songkhla Urban Area | D11: Thailand | E11: Southeast Asia | F11: secondary | G11: provisional | H11: Southern Thai trade and services challenger included to test regional depth beyond capital-city bias.
A12: tw-taipei | B12: Taipei | C12: Taipei-Keelung-Taoyuan Metropolitan Area | D12: Taiwan | E12: East Asia | F12: primary | G12: locked | H12: High-systems, high-street-life benchmark aligned with earlier SLIC discussion.
... A103: fj-suva | B103: Suva | C103: Greater Suva | D103: Fiji | E103: Oceania | F103: secondary | G103: locked | H103: Pacific regional challenger included so Oceania is not reduced to Australia and New Zealand alone.

Sheet Country_Context
A1: country | B1: gdp_per_capita_ppp | C1: gdp_growth | D1: gini_coefficient | E1: ppp_private_consumption | F1: tax_rate_assumption | G1: household_debt_proxy | H1: source_url | I1: source_tier | J1: update_date | K1: notes
A2: Thailand | B2: 24712.07 | C2: 2.5418 | D2: 33.5 | E2: 10.945576 | F2: 0.152577 | G2: 115.1054 | H2: https://api.worldbank.org/v2/country/THA/indicator/NY.GDP.PCAP.PP.CD?format=json&mrv=30 | https://api.worldbank.org/v2/country/THA/indicator/NY.GDP.MKTP.KD.ZG?format=json&mrv=30 | https://api.worldbank.org/v2/country/THA/indicator/SI.POV.GINI?format=json&mrv=30 | +3 more | I2: Tier 3 | J2: 2024-12-31 | K2: providers=world_bank; fields=gdp_per_capita_ppp, gdp_growth, gini_coefficient, ppp_private_consumption; +2 additional fields
A3: Singapore | B3: 150689.3 | C3: 4.388 | E3: 1.04203 | F3: 0.141917 | G3: 129.1908 | H3: https://api.worldbank.org/v2/country/SGP/indicator/NY.GDP.PCAP.PP.CD?format=json&mrv=30 | https://api.worldbank.org/v2/country/SGP/indicator/NY.GDP.MKTP.KD.ZG?format=json&mrv=30 | https://api.worldbank.org/v2/country/SGP/indicator/PA.NUS.PRVT.PP?format=json&mrv=30 | +2 more | I3: Tier 3 | J3: 2024-12-31 | K3: providers=world_bank; fields=gdp_per_capita_ppp, gdp_growth, ppp_private_consumption, tax_rate_assumption; +1 additional fields
A4: Malaysia | B4: 38779.28 | C4: 5.1055 | D4: 40.7 | E4: 1.449227 | F4: 0.125648 | G4: 116.0773 | H4: https://api.worldbank.org/v2/country/MYS/indicator/NY.GDP.PCAP.PP.CD?format=json&mrv=30 | https://api.worldbank.org/v2/country/MYS/indicator/NY.GDP.MKTP.KD.ZG?format=json&mrv=30 | https://api.worldbank.org/v2/country/MYS/indicator/SI.POV.GINI?format=json&mrv=30 | +3 more | I4: Tier 3 | J4: 2024-12-31 | K4: providers=world_bank; fields=gdp_per_capita_ppp, gdp_growth, gini_coefficient, ppp_private_consumption; +2 additional fields
A5: Indonesia | B5: 16448.28 | C5: 5.0303 | D5: 34.9 | E5: 5104.9843 | F5: 0.110578 | G5: 31.7861 | H5: https://api.worldbank.org/v2/country/IDN/indicator/NY.GDP.PCAP.PP.CD?format=json&mrv=30 | https://api.worldbank.org/v2/country/IDN/indicator/NY.GDP.MKTP.KD.ZG?format=json&mrv=30 | https://api.worldbank.org/v2/country/IDN/indicator/SI.POV.GINI?format=json&mrv=30 | +3 more | I5: Tier 3 | J5: 2024-12-31 | K5: providers=world_bank; fields=gdp_per_capita_ppp, gdp_growth, gini_coefficient, ppp_private_consumption; +2 additional fields
A6: Philippines | B6: 11794.14 | C6: 5.692 | D6: 39.3 | E6: 20.743506 | F6: 0.141044 | G6: 49.8137 | H6: https://api.worldbank.org/v2/country/PHL/indicator/NY.GDP.PCAP.PP.CD?format=json&mrv=30 | https://api.worldbank.org/v2/country/PHL/indicator/NY.GDP.MKTP.KD.ZG?format=json&mrv=30 | https://api.worldbank.org/v2/country/PHL/indicator/SI.POV.GINI?format=json&mrv=30 | +3 more | I6: Tier 3 | J6: 2024-12-31 | K6: providers=world_bank; fields=gdp_per_capita_ppp, gdp_growth, gini_coefficient, ppp_private_consumption; +2 additional fields
A7: Taiwan | K7: Populate official country context inputs before ranking.
A8: South Korea | B8: 61051.35 | C8: 2.0036 | D8: 32.9 | E8: 872.46874 | F8: 0.145991 | G8: 160.3472 | H8: https://api.worldbank.org/v2/country/KOR/indicator/NY.GDP.PCAP.PP.CD?format=json&mrv=30 | https://api.worldbank.org/v2/country/KOR/indicator/NY.GDP.MKTP.KD.ZG?format=json&mrv=30 | https://api.worldbank.org/v2/country/KOR/indicator/SI.POV.GINI?format=json&mrv=30 | +3 more | I8: Tier 3 | J8: 2024-12-31 | K8: providers=world_bank; fields=gdp_per_capita_ppp, gdp_growth, gini_coefficient, ppp_private_consumption; +2 additional fields
A9: China | B9: 27104.87 | C9: 4.9774 | D9: 36 | E9: 3.550789 | F9: 0.076382 | G9: 194.166 | H9: https://api.worldbank.org/v2/country/CHN/indicator/NY.GDP.PCAP.PP.CD?format=json&mrv=30 | https://api.worldbank.org/v2/country/CHN/indicator/NY.GDP.MKTP.KD.ZG?format=json&mrv=30 | https://api.worldbank.org/v2/country/CHN/indicator/SI.POV.GINI?format=json&mrv=30 | +3 more | I9: Tier 3 | J9: 2024-12-31 | K9: providers=world_bank; fields=gdp_per_capita_ppp, gdp_growth, gini_coefficient, ppp_private_consumption; +2 additional fields
A10: Japan | B10: 52039.17 | C10: 0.1043 | D10: 32.3 | E10: 99.384798 | G10: 123.1289 | H10: https://api.worldbank.org/v2/country/JPN/indicator/NY.GDP.PCAP.PP.CD?format=json&mrv=30 | https://api.worldbank.org/v2/country/JPN/indicator/NY.GDP.MKTP.KD.ZG?format=json&mrv=30 | https://api.worldbank.org/v2/country/JPN/indicator/SI.POV.GINI?format=json&mrv=30 | +2 more | I10: Tier 3 | J10: 2024-12-31 | K10: providers=world_bank; fields=gdp_per_capita_ppp, gdp_growth, gini_coefficient, ppp_private_consumption; +1 additional fields
A11: India | B11: 11159.99 | C11: 6.4948 | D11: 25.5 | E11: 19.896916 | F11: 0.067344 | G11: 50.1422 | H11: https://api.worldbank.org/v2/country/IND/indicator/NY.GDP.PCAP.PP.CD?format=json&mrv=30 | https://api.worldbank.org/v2/country/IND/indicator/NY.GDP.MKTP.KD.ZG?format=json&mrv=30 | https://api.worldbank.org/v2/country/IND/indicator/SI.POV.GINI?format=json&mrv=30 | +3 more | I11: Tier 3 | J11: 2024-12-31 | K11: providers=world_bank; fields=gdp_per_capita_ppp, gdp_growth, gini_coefficient, ppp_private_consumption; +2 additional fields
A12: Sri Lanka | B12: 15632.59 | C12: 5.0087 | D12: 37.7 | E12: 87.489315 | F12: 0.099219 | G12: 46.8716 | H12: https://api.worldbank.org/v2/country/LKA/indicator/NY.GDP.PCAP.PP.CD?format=json&mrv=30 | https://api.worldbank.org/v2/country/LKA/indicator/NY.GDP.MKTP.KD.ZG?format=json&mrv=30 | https://api.worldbank.org/v2/country/LKA/indicator/SI.POV.GINI?format=json&mrv=30 | +3 more | I12: Tier 3 | J12: 2024-12-31 | K12: providers=world_bank; fields=gdp_per_capita_ppp, gdp_growth, gini_coefficient, ppp_private_consumption; +2 additional fields
A13: Bangladesh | B13: 9646.77 | C13: 4.2233 | D13: 30.9 | E13: 32.990539 | F13: 0.076424 | G13: 35.7061 | H13: https://api.worldbank.org/v2/country/BGD/indicator/NY.GDP.PCAP.PP.CD?format=json&mrv=30 | https://api.worldbank.org/v2/country/BGD/indicator/NY.GDP.MKTP.KD.ZG?format=json&mrv=30 | https://api.worldbank.org/v2/country/BGD/indicator/SI.POV.GINI?format=json&mrv=30 | +3 more | I13: Tier 3 | J13: 2024-12-31 | K13: providers=world_bank; fields=gdp_per_capita_ppp, gdp_growth, gini_coefficient, ppp_private_consumption; +2 additional fields
A14: Pakistan | B14: 6252.12 | C14: 3.049 | D14: 29.6 | E14: 64.860994 | G14: 11.3901 | H14: https://api.worldbank.org/v2/country/PAK/indicator/NY.GDP.PCAP.PP.CD?format=json&mrv=30 | https://api.worldbank.org/v2/country/PAK/indicator/NY.GDP.MKTP.KD.ZG?format=json&mrv=30 | https://api.worldbank.org/v2/country/PAK/indicator/SI.POV.GINI?format=json&mrv=30 | +2 more | I14: Tier 3 | J14: 2024-12-31 | K14: providers=world_bank; fields=gdp_per_capita_ppp, gdp_growth, gini_coefficient, ppp_private_consumption; +1 additional fields
A15: Nepal | B15: 5736.62 | C15: 3.6654 | D15: 30 | E15: 35.285741 | F15: 0.139449 | G15: 91.9385 | H15: https://api.worldbank.org/v2/country/NPL/indicator/NY.GDP.PCAP.PP.CD?format=json&mrv=30 | https://api.worldbank.org/v2/country/NPL/indicator/NY.GDP.MKTP.KD.ZG?format=json&mrv=30 | https://api.worldbank.org/v2/country/NPL/indicator/SI.POV.GINI?format=json&mrv=30 | +3 more | I15: Tier 3 | J15: 2024-12-31 | K15: providers=world_bank; fields=gdp_per_capita_ppp, gdp_growth, gini_coefficient, ppp_private_consumption; +2 additional fields
A16: Bhutan | B16: 16215.15 | C16: 4.6322 | D16: 28.5 | E16: 20.878112 | F16: 0.122846 | G16: 51.8935 | H16: https://api.worldbank.org/v2/country/BTN/indicator/NY.GDP.PCAP.PP.CD?format=json&mrv=30 | https://api.worldbank.org/v2/country/BTN/indicator/NY.GDP.MKTP.KD.ZG?format=json&mrv=30 | https://api.worldbank.org/v2/country/BTN/indicator/SI.POV.GINI?format=json&mrv=30 | +3 more | I16: Tier 3 | J16: 2024-12-31 | K16: providers=world_bank; fields=gdp_per_capita_ppp, gdp_growth, gini_coefficient, ppp_private_consumption; +2 additional fields
A17: Maldives | B17: 26182.78 | C17: 3.4944 | D17: 29.3 | E17: 9.455282 | F17: 0.194532 | G17: 31.5415 | H17: https://api.worldbank.org/v2/country/MDV/indicator/NY.GDP.PCAP.PP.CD?format=json&mrv=30 | https://api.worldbank.org/v2/country/MDV/indicator/NY.GDP.MKTP.KD.ZG?format=json&mrv=30 | https://api.worldbank.org/v2/country/MDV/indicator/SI.POV.GINI?format=json&mrv=30 | +3 more | I17: Tier 3 | J17: 2024-12-31 | K17: providers=world_bank; fields=gdp_per_capita_ppp, gdp_growth, gini_coefficient, ppp_private_consumption; +2 additional fields
A18: France | B18: 62556.92 | C18: 1.1905 | D18: 31.8 | E18: 0.716934 | F18: 0.23077 | G18: 103.9081 | H18: https://api.worldbank.org/v2/country/FRA/indicator/NY.GDP.PCAP.PP.CD?format=json&mrv=30 | https://api.worldbank.org/v2/country/FRA/indicator/NY.GDP.MKTP.KD.ZG?format=json&mrv=30 | https://api.worldbank.org/v2/country/FRA/indicator/SI.POV.GINI?format=json&mrv=30 | +3 more | I18: Tier 3 | J18: 2024-12-31 | K18: providers=world_bank; fields=gdp_per_capita_ppp, gdp_growth, gini_coefficient, ppp_private_consumption; +2 additional fields
A19: Austria | B19: 73911.44 | C19: -0.6591 | D19: 31.2 | E19: 0.720487 | F19: 0.256407 | G19: 81.4953 | H19: https://api.worldbank.org/v2/country/AUT/indicator/NY.GDP.PCAP.PP.CD?format=json&mrv=30 | https://api.worldbank.org/v2/country/AUT/indicator/NY.GDP.MKTP.KD.ZG?format=json&mrv=30 | https://api.worldbank.org/v2/country/AUT/indicator/SI.POV.GINI?format=json&mrv=30 | +3 more | I19: Tier 3 | J19: 2024-12-31 | K19: providers=world_bank; fields=gdp_per_capita_ppp, gdp_growth, gini_coefficient, ppp_private_consumption; +2 additional fields
A20: Switzerland | B20: 96497.69 | C20: 1.3023 | D20: 33.8 | E20: 1.062369 | F20: 0.090036 | G20: 170.3782 | H20: https://api.worldbank.org/v2/country/CHE/indicator/NY.GDP.PCAP.PP.CD?format=json&mrv=30 | https://api.worldbank.org/v2/country/CHE/indicator/NY.GDP.MKTP.KD.ZG?format=json&mrv=30 | https://api.worldbank.org/v2/country/CHE/indicator/SI.POV.GINI?format=json&mrv=30 | +3 more | I20: Tier 3 | J20: 2024-12-31 | K20: providers=world_bank; fields=gdp_per_capita_ppp, gdp_growth, gini_coefficient, ppp_private_consumption; +2 additional fields
A21: Netherlands | B21: 86173.63 | C21: 1.081 | D21: 25.7 | E21: 0.74195 | F21: 0.25254 | G21: 82.3297 | H21: https://api.worldbank.org/v2/country/NLD/indicator/NY.GDP.PCAP.PP.CD?format=json&mrv=30 | https://api.worldbank.org/v2/country/NLD/indicator/NY.GDP.MKTP.KD.ZG?format=json&mrv=30 | https://api.worldbank.org/v2/country/NLD/indicator/SI.POV.GINI?format=json&mrv=30 | +3 more | I21: Tier 3 | J21: 2024-12-31 | K21: providers=world_bank; fields=gdp_per_capita_ppp, gdp_growth, gini_coefficient, ppp_private_consumption; +2 additional fields
A22: Denmark | B22: 81878.23 | C22: 3.4778 | D22: 29.9 | E22: 6.764411 | F22: 0.315935 | G22: 144.0931 | H22: https://api.worldbank.org/v2/country/DNK/indicator/NY.GDP.PCAP.PP.CD?format=json&mrv=30 | https://api.worldbank.org/v2/country/DNK/indicator/NY.GDP.MKTP.KD.ZG?format=json&mrv=30 | https://api.worldbank.org/v2/country/DNK/indicator/SI.POV.GINI?format=json&mrv=30 | +3 more | I22: Tier 3 | J22: 2024-12-31 | K22: providers=world_bank; fields=gdp_per_capita_ppp, gdp_growth, gini_coefficient, ppp_private_consumption; +2 additional fields
A23: Italy | B23: 62014.27 | C23: 0.6927 | D23: 34.3 | E23: 0.625157 | F23: 0.24708 | G23: 59.3116 | H23: https://api.worldbank.org/v2/country/ITA/indicator/NY.GDP.PCAP.PP.CD?format=json&mrv=30 | https://api.worldbank.org/v2/country/ITA/indicator/NY.GDP.MKTP.KD.ZG?format=json&mrv=30 | https://api.worldbank.org/v2/country/ITA/indicator/SI.POV.GINI?format=json&mrv=30 | +3 more | I23: Tier 3 | J23: 2024-12-31 | K23: providers=world_bank; fields=gdp_per_capita_ppp, gdp_growth, gini_coefficient, ppp_private_consumption; +2 additional fields
A24: Portugal | B24: 51679.89 | C24: 2.1397 | D24: 33.9 | E24: 0.558749 | F24: 0.226188 | G24: 77.1375 | H24: https://api.worldbank.org/v2/country/PRT/indicator/NY.GDP.PCAP.PP.CD?format=json&mrv=30 | https://api.worldbank.org/v2/country/PRT/indicator/NY.GDP.MKTP.KD.ZG?format=json&mrv=30 | https://api.worldbank.org/v2/country/PRT/indicator/SI.POV.GINI?format=json&mrv=30 | +3 more | I24: Tier 3 | J24: 2024-12-31 | K24: providers=world_bank; fields=gdp_per_capita_ppp, gdp_growth, gini_coefficient, ppp_private_consumption; +2 additional fields
A25: Estonia | B25: 49968.71 | C25: -0.09 | D25: 30.7 | E25: 0.646078 | F25: 0.21329 | G25: 60.5329 | H25: https://api.worldbank.org/v2/country/EST/indicator/NY.GDP.PCAP.PP.CD?format=json&mrv=30 | https://api.worldbank.org/v2/country/EST/indicator/NY.GDP.MKTP.KD.ZG?format=json&mrv=30 | https://api.worldbank.org/v2/country/EST/indicator/SI.POV.GINI?format=json&mrv=30 | +3 more | I25: Tier 3 | J25: 2024-12-31 | K25: providers=world_bank; fields=gdp_per_capita_ppp, gdp_growth, gini_coefficient, ppp_private_consumption; +2 additional fields
A26: Finland | B26: 65378.38 | C26: 0.4162 | D26: 27.4 | E26: 0.788236 | F26: 0.253757 | G26: 90.8647 | H26: https://api.worldbank.org/v2/country/FIN/indicator/NY.GDP.PCAP.PP.CD?format=json&mrv=30 | https://api.worldbank.org/v2/country/FIN/indicator/NY.GDP.MKTP.KD.ZG?format=json&mrv=30 | https://api.worldbank.org/v2/country/FIN/indicator/SI.POV.GINI?format=json&mrv=30 | +3 more | I26: Tier 3 | J26: 2024-12-31 | K26: providers=world_bank; fields=gdp_per_capita_ppp, gdp_growth, gini_coefficient, ppp_private_consumption; +2 additional fields
... A37: Costa Rica | B37: 31106.76 | C37: 4.3212 | D37: 45.8 | E37: 328.04659 | F37: 0.139115 | G37: 50.9742 | H37: https://api.worldbank.org/v2/country/CRI/indicator/NY.GDP.PCAP.PP.CD?format=json&mrv=30 | https://api.worldbank.org/v2/country/CRI/indicator/NY.GDP.MKTP.KD.ZG?format=json&mrv=30 | https://api.worldbank.org/v2/country/CRI/indicator/SI.POV.GINI?format=json&mrv=30 | +3 more | I37: Tier 3 | J37: 2024-12-31 | K37: providers=world_bank; fields=gdp_per_capita_ppp, gdp_growth, gini_coefficient, ppp_private_consumption; +2 additional fields
A38: Puerto Rico | B38: 50247.85 | C38: 3.1771 | E38: 0.896932 | H38: https://api.worldbank.org/v2/country/PRI/indicator/NY.GDP.PCAP.PP.CD?format=json&mrv=30 | https://api.worldbank.org/v2/country/PRI/indicator/NY.GDP.MKTP.KD.ZG?format=json&mrv=30 | https://api.worldbank.org/v2/country/PRI/indicator/PA.NUS.PRVT.PP?format=json&mrv=30 | I38: Tier 3 | J38: 2024-12-31 | K38: providers=world_bank; fields=gdp_per_capita_ppp, gdp_growth, ppp_private_consumption
A39: Brazil | B39: 22338.48 | C39: 3.4193 | D39: 51.6 | E39: 2.524497 | F39: 0.154102 | G39: 75.6164 | H39: https://api.worldbank.org/v2/country/BRA/indicator/NY.GDP.PCAP.PP.CD?format=json&mrv=30 | https://api.worldbank.org/v2/country/BRA/indicator/NY.GDP.MKTP.KD.ZG?format=json&mrv=30 | https://api.worldbank.org/v2/country/BRA/indicator/SI.POV.GINI?format=json&mrv=30 | +3 more | I39: Tier 3 | J39: 2024-12-31 | K39: providers=world_bank; fields=gdp_per_capita_ppp, gdp_growth, gini_coefficient, ppp_private_consumption; +2 additional fields
A40: Argentina | B40: 30431.19 | C40: -1.3429 | D40: 42.4 | E40: 42.98624 | F40: 0.099289 | G40: 13.0788 | H40: https://api.worldbank.org/v2/country/ARG/indicator/NY.GDP.PCAP.PP.CD?format=json&mrv=30 | https://api.worldbank.org/v2/country/ARG/indicator/NY.GDP.MKTP.KD.ZG?format=json&mrv=30 | https://api.worldbank.org/v2/country/ARG/indicator/SI.POV.GINI?format=json&mrv=30 | +3 more | I40: Tier 3 | J40: 2024-12-31 | K40: providers=world_bank; fields=gdp_per_capita_ppp, gdp_growth, gini_coefficient, ppp_private_consumption; +2 additional fields
A41: Chile | B41: 36181.16 | C41: 2.6443 | D41: 43 | E41: 464.87603 | F41: 0.177194 | G41: 74.9355 | H41: https://api.worldbank.org/v2/country/CHL/indicator/NY.GDP.PCAP.PP.CD?format=json&mrv=30 | https://api.worldbank.org/v2/country/CHL/indicator/NY.GDP.MKTP.KD.ZG?format=json&mrv=30 | https://api.worldbank.org/v2/country/CHL/indicator/SI.POV.GINI?format=json&mrv=30 | +3 more | I41: Tier 3 | J41: 2024-12-31 | K41: providers=world_bank; fields=gdp_per_capita_ppp, gdp_growth, gini_coefficient, ppp_private_consumption; +2 additional fields
A42: Colombia | B42: 22349.44 | C42: 1.5983 | D42: 53.9 | E42: 1542.1938 | F42: 0.152812 | G42: 39.5117 | H42: https://api.worldbank.org/v2/country/COL/indicator/NY.GDP.PCAP.PP.CD?format=json&mrv=30 | https://api.worldbank.org/v2/country/COL/indicator/NY.GDP.MKTP.KD.ZG?format=json&mrv=30 | https://api.worldbank.org/v2/country/COL/indicator/SI.POV.GINI?format=json&mrv=30 | +3 more | I42: Tier 3 | J42: 2024-12-31 | K42: providers=world_bank; fields=gdp_per_capita_ppp, gdp_growth, gini_coefficient, ppp_private_consumption; +2 additional fields
A43: Peru | B43: 17802.42 | C43: 3.3039 | D43: 40.1 | E43: 1.94918 | F43: 0.159243 | G43: 45.668 | H43: https://api.worldbank.org/v2/country/PER/indicator/NY.GDP.PCAP.PP.CD?format=json&mrv=30 | https://api.worldbank.org/v2/country/PER/indicator/NY.GDP.MKTP.KD.ZG?format=json&mrv=30 | https://api.worldbank.org/v2/country/PER/indicator/SI.POV.GINI?format=json&mrv=30 | +3 more | I43: Tier 3 | J43: 2024-12-31 | K43: providers=world_bank; fields=gdp_per_capita_ppp, gdp_growth, gini_coefficient, ppp_private_consumption; +2 additional fields
A44: Uruguay | B44: 36417.87 | C44: 3.1083 | D44: 40 | E44: 29.298217 | F44: 0.181624 | G44: 31.0608 | H44: https://api.worldbank.org/v2/country/URY/indicator/NY.GDP.PCAP.PP.CD?format=json&mrv=30 | https://api.worldbank.org/v2/country/URY/indicator/NY.GDP.MKTP.KD.ZG?format=json&mrv=30 | https://api.worldbank.org/v2/country/URY/indicator/SI.POV.GINI?format=json&mrv=30 | +3 more | I44: Tier 3 | J44: 2024-12-31 | K44: providers=world_bank; fields=gdp_per_capita_ppp, gdp_growth, gini_coefficient, ppp_private_consumption; +2 additional fields
A45: United Arab Emirates | B45: 79228.74 | C45: 3.9918 | D45: 26.4 | E45: 2.56311 | F45: 0.006475 | G45: 67.9658 | H45: https://api.worldbank.org/v2/country/ARE/indicator/NY.GDP.PCAP.PP.CD?format=json&mrv=30 | https://api.worldbank.org/v2/country/ARE/indicator/NY.GDP.MKTP.KD.ZG?format=json&mrv=30 | https://api.worldbank.org/v2/country/ARE/indicator/SI.POV.GINI?format=json&mrv=30 | +3 more | I45: Tier 3 | J45: 2024-12-31 | K45: providers=world_bank; fields=gdp_per_capita_ppp, gdp_growth, gini_coefficient, ppp_private_consumption; +2 additional fields
A46: Qatar | B46: 126046.35 | C46: 2.3597 | D46: 35.1 | E46: 2.755487 | G46: 118.8652 | H46: https://api.worldbank.org/v2/country/QAT/indicator/NY.GDP.PCAP.PP.CD?format=json&mrv=30 | https://api.worldbank.org/v2/country/QAT/indicator/NY.GDP.MKTP.KD.ZG?format=json&mrv=30 | https://api.worldbank.org/v2/country/QAT/indicator/SI.POV.GINI?format=json&mrv=30 | +2 more | I46: Tier 3 | J46: 2024-12-31 | K46: providers=world_bank; fields=gdp_per_capita_ppp, gdp_growth, gini_coefficient, ppp_private_consumption; +1 additional fields
A47: Saudi Arabia | B47: 71375.37 | C47: 1.9965 | E47: 1.882361 | F47: 0.081847 | G47: 50.1376 | H47: https://api.worldbank.org/v2/country/SAU/indicator/NY.GDP.PCAP.PP.CD?format=json&mrv=30 | https://api.worldbank.org/v2/country/SAU/indicator/NY.GDP.MKTP.KD.ZG?format=json&mrv=30 | https://api.worldbank.org/v2/country/SAU/indicator/PA.NUS.PRVT.PP?format=json&mrv=30 | +2 more | I47: Tier 3 | J47: 2024-12-31 | K47: providers=world_bank; fields=gdp_per_capita_ppp, gdp_growth, ppp_private_consumption, tax_rate_assumption; +1 additional fields
A48: Israel | B48: 57235.78 | C48: 0.872 | D48: 37.9 | E48: 3.607983 | F48: 0.221364 | G48: 69.7497 | H48: https://api.worldbank.org/v2/country/ISR/indicator/NY.GDP.PCAP.PP.CD?format=json&mrv=30 | https://api.worldbank.org/v2/country/ISR/indicator/NY.GDP.MKTP.KD.ZG?format=json&mrv=30 | https://api.worldbank.org/v2/country/ISR/indicator/SI.POV.GINI?format=json&mrv=30 | +3 more | I48: Tier 3 | J48: 2024-12-31 | K48: providers=world_bank; fields=gdp_per_capita_ppp, gdp_growth, gini_coefficient, ppp_private_consumption; +2 additional fields
A49: Oman | B49: 41740.17 | C49: 1.6316 | E49: 0.184982 | G49: 59.7083 | H49: https://api.worldbank.org/v2/country/OMN/indicator/NY.GDP.PCAP.PP.CD?format=json&mrv=30 | https://api.worldbank.org/v2/country/OMN/indicator/NY.GDP.MKTP.KD.ZG?format=json&mrv=30 | https://api.worldbank.org/v2/country/OMN/indicator/PA.NUS.PRVT.PP?format=json&mrv=30 | +1 more | I49: Tier 3 | J49: 2024-12-31 | K49: providers=world_bank; fields=gdp_per_capita_ppp, gdp_growth, ppp_private_consumption, household_debt_proxy
A50: Bahrain | B50: 66941.24 | C50: 2.6038 | E50: 0.188671 | F50: 0.028232 | G50: 70.5501 | H50: https://api.worldbank.org/v2/country/BHR/indicator/NY.GDP.PCAP.PP.CD?format=json&mrv=30 | https://api.worldbank.org/v2/country/BHR/indicator/NY.GDP.MKTP.KD.ZG?format=json&mrv=30 | https://api.worldbank.org/v2/country/BHR/indicator/PA.NUS.PRVT.PP?format=json&mrv=30 | +2 more | I50: Tier 3 | J50: 2024-12-31 | K50: providers=world_bank; fields=gdp_per_capita_ppp, gdp_growth, ppp_private_consumption, tax_rate_assumption; +1 additional fields
A51: Kuwait | B51: 52443.6 | C51: -2.5601 | E51: 0.183789 | F51: 0.014924 | G51: 4.3975 | H51: https://api.worldbank.org/v2/country/KWT/indicator/NY.GDP.PCAP.PP.CD?format=json&mrv=30 | https://api.worldbank.org/v2/country/KWT/indicator/NY.GDP.MKTP.KD.ZG?format=json&mrv=30 | https://api.worldbank.org/v2/country/KWT/indicator/PA.NUS.PRVT.PP?format=json&mrv=30 | +2 more | I51: Tier 3 | J51: 2024-12-31 | K51: providers=world_bank; fields=gdp_per_capita_ppp, gdp_growth, ppp_private_consumption, tax_rate_assumption; +1 additional fields
A52: Jordan | B52: 10821.49 | C52: 2.4889 | D52: 33.7 | E52: 0.321203 | F52: 0.170491 | G52: 80.0729 | H52: https://api.worldbank.org/v2/country/JOR/indicator/NY.GDP.PCAP.PP.CD?format=json&mrv=30 | https://api.worldbank.org/v2/country/JOR/indicator/NY.GDP.MKTP.KD.ZG?format=json&mrv=30 | https://api.worldbank.org/v2/country/JOR/indicator/SI.POV.GINI?format=json&mrv=30 | +3 more | I52: Tier 3 | J52: 2024-12-31 | K52: providers=world_bank; fields=gdp_per_capita_ppp, gdp_growth, gini_coefficient, ppp_private_consumption; +2 additional fields
A53: South Africa | B53: 15456.2 | C53: 0.5348 | D53: 63 | E53: 7.701915 | F53: 0.254005 | G53: 57.4717 | H53: https://api.worldbank.org/v2/country/ZAF/indicator/NY.GDP.PCAP.PP.CD?format=json&mrv=30 | https://api.worldbank.org/v2/country/ZAF/indicator/NY.GDP.MKTP.KD.ZG?format=json&mrv=30 | https://api.worldbank.org/v2/country/ZAF/indicator/SI.POV.GINI?format=json&mrv=30 | +3 more | I53: Tier 3 | J53: 2024-12-31 | K53: providers=world_bank; fields=gdp_per_capita_ppp, gdp_growth, gini_coefficient, ppp_private_consumption; +2 additional fields
A54: Kenya | B54: 6644.13 | C54: 4.7247 | D54: 37.7 | E54: 44.391722 | F54: 0.140631 | G54: 31.7729 | H54: https://api.worldbank.org/v2/country/KEN/indicator/NY.GDP.PCAP.PP.CD?format=json&mrv=30 | https://api.worldbank.org/v2/country/KEN/indicator/NY.GDP.MKTP.KD.ZG?format=json&mrv=30 | https://api.worldbank.org/v2/country/KEN/indicator/SI.POV.GINI?format=json&mrv=30 | +3 more | I54: Tier 3 | J54: 2024-12-31 | K54: providers=world_bank; fields=gdp_per_capita_ppp, gdp_growth, gini_coefficient, ppp_private_consumption; +2 additional fields
A55: Rwanda | B55: 3710.86 | C55: 8.8907 | D55: 39.4 | E55: 361.39523 | F55: 0.135081 | G55: 22.5267 | H55: https://api.worldbank.org/v2/country/RWA/indicator/NY.GDP.PCAP.PP.CD?format=json&mrv=30 | https://api.worldbank.org/v2/country/RWA/indicator/NY.GDP.MKTP.KD.ZG?format=json&mrv=30 | https://api.worldbank.org/v2/country/RWA/indicator/SI.POV.GINI?format=json&mrv=30 | +3 more | I55: Tier 3 | J55: 2024-12-31 | K55: providers=world_bank; fields=gdp_per_capita_ppp, gdp_growth, gini_coefficient, ppp_private_consumption; +2 additional fields
A56: Morocco | B56: 10415.12 | C56: 3.7934 | D56: 39.5 | E56: 4.038145 | F56: 0.207439 | G56: 54.7741 | H56: https://api.worldbank.org/v2/country/MAR/indicator/NY.GDP.PCAP.PP.CD?format=json&mrv=30 | https://api.worldbank.org/v2/country/MAR/indicator/NY.GDP.MKTP.KD.ZG?format=json&mrv=30 | https://api.worldbank.org/v2/country/MAR/indicator/SI.POV.GINI?format=json&mrv=30 | +3 more | I56: Tier 3 | J56: 2024-12-31 | K56: providers=world_bank; fields=gdp_per_capita_ppp, gdp_growth, gini_coefficient, ppp_private_consumption; +2 additional fields
A57: Mauritius | B57: 31839.76 | C57: 4.9251 | D57: 36.8 | E57: 19.916335 | F57: 0.205324 | G57: 69.8221 | H57: https://api.worldbank.org/v2/country/MUS/indicator/NY.GDP.PCAP.PP.CD?format=json&mrv=30 | https://api.worldbank.org/v2/country/MUS/indicator/NY.GDP.MKTP.KD.ZG?format=json&mrv=30 | https://api.worldbank.org/v2/country/MUS/indicator/SI.POV.GINI?format=json&mrv=30 | +3 more | I57: Tier 3 | J57: 2024-12-31 | K57: providers=world_bank; fields=gdp_per_capita_ppp, gdp_growth, gini_coefficient, ppp_private_consumption; +2 additional fields
A58: Botswana | B58: 20538.13 | C58: -2.9899 | D58: 54.9 | E58: 5.312715 | F58: 0.224882 | G58: 32.8462 | H58: https://api.worldbank.org/v2/country/BWA/indicator/NY.GDP.PCAP.PP.CD?format=json&mrv=30 | https://api.worldbank.org/v2/country/BWA/indicator/NY.GDP.MKTP.KD.ZG?format=json&mrv=30 | https://api.worldbank.org/v2/country/BWA/indicator/SI.POV.GINI?format=json&mrv=30 | +3 more | I58: Tier 3 | J58: 2024-12-31 | K58: providers=world_bank; fields=gdp_per_capita_ppp, gdp_growth, gini_coefficient, ppp_private_consumption; +2 additional fields
A59: Namibia | B59: 11686.6 | C59: 3.7115 | D59: 59.1 | E59: 7.321244 | F59: 0.329629 | G59: 48.2075 | H59: https://api.worldbank.org/v2/country/NAM/indicator/NY.GDP.PCAP.PP.CD?format=json&mrv=30 | https://api.worldbank.org/v2/country/NAM/indicator/NY.GDP.MKTP.KD.ZG?format=json&mrv=30 | https://api.worldbank.org/v2/country/NAM/indicator/SI.POV.GINI?format=json&mrv=30 | +3 more | I59: Tier 3 | J59: 2024-12-31 | K59: providers=world_bank; fields=gdp_per_capita_ppp, gdp_growth, gini_coefficient, ppp_private_consumption; +2 additional fields
A60: Ghana | B60: 8020 | C60: 5.5905 | D60: 43.5 | E60: 4.721006 | F60: 0.122975 | G60: 8.6512 | H60: https://api.worldbank.org/v2/country/GHA/indicator/NY.GDP.PCAP.PP.CD?format=json&mrv=30 | https://api.worldbank.org/v2/country/GHA/indicator/NY.GDP.MKTP.KD.ZG?format=json&mrv=30 | https://api.worldbank.org/v2/country/GHA/indicator/SI.POV.GINI?format=json&mrv=30 | +3 more | I60: Tier 3 | J60: 2024-12-31 | K60: providers=world_bank; fields=gdp_per_capita_ppp, gdp_growth, gini_coefficient, ppp_private_consumption; +2 additional fields
A61: Senegal | B61: 5070.65 | C61: 6.0606 | D61: 36.2 | E61: 229.28096 | F61: 0.195371 | G61: 29.205 | H61: https://api.worldbank.org/v2/country/SEN/indicator/NY.GDP.PCAP.PP.CD?format=json&mrv=30 | https://api.worldbank.org/v2/country/SEN/indicator/NY.GDP.MKTP.KD.ZG?format=json&mrv=30 | https://api.worldbank.org/v2/country/SEN/indicator/SI.POV.GINI?format=json&mrv=30 | +3 more | I61: Tier 3 | J61: 2024-12-31 | K61: providers=world_bank; fields=gdp_per_capita_ppp, gdp_growth, gini_coefficient, ppp_private_consumption; +2 additional fields
A62: New Zealand | B62: 55551.14 | C62: 1.2886 | E62: 1.499938 | F62: 0.306678 | G62: 129.7971 | H62: https://api.worldbank.org/v2/country/NZL/indicator/NY.GDP.PCAP.PP.CD?format=json&mrv=30 | https://api.worldbank.org/v2/country/NZL/indicator/NY.GDP.MKTP.KD.ZG?format=json&mrv=30 | https://api.worldbank.org/v2/country/NZL/indicator/PA.NUS.PRVT.PP?format=json&mrv=30 | +2 more | I62: Tier 3 | J62: 2024-12-31 | K62: providers=world_bank; fields=gdp_per_capita_ppp, gdp_growth, ppp_private_consumption, tax_rate_assumption; +1 additional fields
A63: Australia | B63: 72111.18 | C63: 1.3734 | D63: 33.8 | E63: 1.427398 | F63: 0.235615 | G63: 129.3173 | H63: https://api.worldbank.org/v2/country/AUS/indicator/NY.GDP.PCAP.PP.CD?format=json&mrv=30 | https://api.worldbank.org/v2/country/AUS/indicator/NY.GDP.MKTP.KD.ZG?format=json&mrv=30 | https://api.worldbank.org/v2/country/AUS/indicator/SI.POV.GINI?format=json&mrv=30 | +3 more | I63: Tier 3 | J63: 2024-12-31 | K63: providers=world_bank; fields=gdp_per_capita_ppp, gdp_growth, gini_coefficient, ppp_private_consumption; +2 additional fields
A64: Fiji | B64: 15450.3 | C64: 3.5309 | D64: 30.7 | E64: 0.910728 | F64: 0.20538 | G64: 75.9993 | H64: https://api.worldbank.org/v2/country/FJI/indicator/NY.GDP.PCAP.PP.CD?format=json&mrv=30 | https://api.worldbank.org/v2/country/FJI/indicator/NY.GDP.MKTP.KD.ZG?format=json&mrv=30 | https://api.worldbank.org/v2/country/FJI/indicator/SI.POV.GINI?format=json&mrv=30 | +3 more | I64: Tier 3 | J64: 2024-12-31 | K64: providers=world_bank; fields=gdp_per_capita_ppp, gdp_growth, gini_coefficient, ppp_private_consumption; +2 additional fields

Sheet City_Inputs
A1: city_id | B1: display_name | C1: country | D1: cohort | E1: city_type | F1: manifest_status | G1: gross_income | H1: rent | I1: utilities | J1: transit_cost | K1: internet_cost | L1: food_cost | M1: di_ppp_raw | N1: housing_burden_raw | O1: household_debt_burden_raw | P1: household_debt_effective_raw | Q1: working_time_pressure_raw | R1: suicide_mental_strain_raw | S1: personal_safety_raw | T1: transit_access_commute_raw | U1: clean_air_raw | V1: water_sanitation_utility_raw | W1: digital_infrastructure_raw | X1: healthcare_quality_raw | Y1: education_quality_raw | Z1: equal_opportunity_raw | AA1: hospitality_belonging_raw | AB1: tolerance_pluralism_raw | AC1: cultural_public_life_raw | AD1: entrepreneurial_dynamism_raw | AE1: innovation_research_intensity_raw | AF1: investment_signal_raw | AG1: administrative_investment_friction_raw | AH1: visitor_flow_context_raw | AI1: gdp_per_capita_ppp_context | AJ1: gdp_growth_context | AK1: gini_coefficient_context | AL1: ppp_private_consumption_context | AM1: tax_rate_context | AN1: household_debt_proxy_context | AO1: pressure_source_url | AP1: pressure_source_tier | AQ1: pressure_source_date | AR1: pressure_notes | AS1: viability_source_url | AT1: viability_source_tier | AU1: viability_source_date | AV1: viability_notes | AW1: capability_source_url | AX1: capability_source_tier | AY1: capability_source_date | AZ1: capability_notes | BA1: community_source_url | BB1: community_source_tier | BC1: community_source_date | BD1: community_notes | BE1: creative_source_url | BF1: creative_source_tier | BG1: creative_source_date | BH1: creative_notes
A2: th-bangkok | B2: Bangkok | C2: Thailand | D2: Southeast Asia | E2: primary | F2: locked | M2: =IF(OR($G2="",$H2="",$I2="",$J2="",$K2="",$L2="",$AL2="",$AM2=""),"",((($G2*(1-$AM2))-$H2-$I2-$J2-$K2-$L2)/$AL2)) | P2: =IF($O2<>"",$O2,$AN2) | AI2: =IFERROR(INDEX(Country_Context!$B$2:$B$64,MATCH($C2,Country_Context!$A$2:$A$64,0)),"") | AJ2: =IFERROR(INDEX(Country_Context!$C$2:$C$64,MATCH($C2,Country_Context!$A$2:$A$64,0)),"") | AK2: =IFERROR(INDEX(Country_Context!$D$2:$D$64,MATCH($C2,Country_Context!$A$2:$A$64,0)),"") | AL2: =IFERROR(INDEX(Country_Context!$E$2:$E$64,MATCH($C2,Country_Context!$A$2:$A$64,0)),"") | AM2: =IFERROR(INDEX(Country_Context!$F$2:$F$64,MATCH($C2,Country_Context!$A$2:$A$64,0)),"") | AN2: =IFERROR(INDEX(Country_Context!$G$2:$G$64,MATCH($C2,Country_Context!$A$2:$A$64,0)),"") | AO2: https://api.worldbank.org/v2/country/THA/indicator/PA.NUS.PRVT.PP?format=json&mrv=30 | https://api.worldbank.org/v2/country/THA/indicator/GC.TAX.TOTL.GD.ZS?format=json&mrv=30 | https://api.worldbank.org/v2/country/THA/indicator/FD.AST.PRVT.GD.ZS?format=json&mrv=30 | AP2: Tier 3 | AQ2: 2024-12-31 | AR2: providers=world_bank; fields=ppp_private_consumption, tax_rate_assumption, household_debt_proxy | AW2: https://api.worldbank.org/v2/country/THA/indicator/SI.POV.GINI?format=json&mrv=30 | AX2: Tier 3 | AY2: 2023-12-31 | AZ2: providers=world_bank; fields=gini_coefficient | BE2: https://api.worldbank.org/v2/country/THA/indicator/NY.GDP.PCAP.PP.CD?format=json&mrv=30 | https://api.worldbank.org/v2/country/THA/indicator/NY.GDP.MKTP.KD.ZG?format=json&mrv=30 | BF2: Tier 3 | BG2: 2024-12-31 | BH2: providers=world_bank; fields=gdp_per_capita_ppp, gdp_growth
A3: sg-singapore | B3: Singapore | C3: Singapore | D3: Southeast Asia | E3: primary | F3: locked | M3: =IF(OR($G3="",$H3="",$I3="",$J3="",$K3="",$L3="",$AL3="",$AM3=""),"",((($G3*(1-$AM3))-$H3-$I3-$J3-$K3-$L3)/$AL3)) | P3: =IF($O3<>"",$O3,$AN3) | AI3: =IFERROR(INDEX(Country_Context!$B$2:$B$64,MATCH($C3,Country_Context!$A$2:$A$64,0)),"") | AJ3: =IFERROR(INDEX(Country_Context!$C$2:$C$64,MATCH($C3,Country_Context!$A$2:$A$64,0)),"") | AK3: =IFERROR(INDEX(Country_Context!$D$2:$D$64,MATCH($C3,Country_Context!$A$2:$A$64,0)),"") | AL3: =IFERROR(INDEX(Country_Context!$E$2:$E$64,MATCH($C3,Country_Context!$A$2:$A$64,0)),"") | AM3: =IFERROR(INDEX(Country_Context!$F$2:$F$64,MATCH($C3,Country_Context!$A$2:$A$64,0)),"") | AN3: =IFERROR(INDEX(Country_Context!$G$2:$G$64,MATCH($C3,Country_Context!$A$2:$A$64,0)),"") | AO3: https://api.worldbank.org/v2/country/SGP/indicator/PA.NUS.PRVT.PP?format=json&mrv=30 | https://api.worldbank.org/v2/country/SGP/indicator/GC.TAX.TOTL.GD.ZS?format=json&mrv=30 | https://api.worldbank.org/v2/country/SGP/indicator/FD.AST.PRVT.GD.ZS?format=json&mrv=30 | AP3: Tier 3 | AQ3: 2024-12-31 | AR3: providers=world_bank; fields=ppp_private_consumption, tax_rate_assumption, household_debt_proxy | BE3: https://api.worldbank.org/v2/country/SGP/indicator/NY.GDP.PCAP.PP.CD?format=json&mrv=30 | https://api.worldbank.org/v2/country/SGP/indicator/NY.GDP.MKTP.KD.ZG?format=json&mrv=30 | BF3: Tier 3 | BG3: 2024-12-31 | BH3: providers=world_bank; fields=gdp_per_capita_ppp, gdp_growth
A4: my-kuala-lumpur | B4: Kuala Lumpur | C4: Malaysia | D4: Southeast Asia | E4: primary | F4: locked | M4: =IF(OR($G4="",$H4="",$I4="",$J4="",$K4="",$L4="",$AL4="",$AM4=""),"",((($G4*(1-$AM4))-$H4-$I4-$J4-$K4-$L4)/$AL4)) | P4: =IF($O4<>"",$O4,$AN4) | AI4: =IFERROR(INDEX(Country_Context!$B$2:$B$64,MATCH($C4,Country_Context!$A$2:$A$64,0)),"") | AJ4: =IFERROR(INDEX(Country_Context!$C$2:$C$64,MATCH($C4,Country_Context!$A$2:$A$64,0)),"") | AK4: =IFERROR(INDEX(Country_Context!$D$2:$D$64,MATCH($C4,Country_Context!$A$2:$A$64,0)),"") | AL4: =IFERROR(INDEX(Country_Context!$E$2:$E$64,MATCH($C4,Country_Context!$A$2:$A$64,0)),"") | AM4: =IFERROR(INDEX(Country_Context!$F$2:$F$64,MATCH($C4,Country_Context!$A$2:$A$64,0)),"") | AN4: =IFERROR(INDEX(Country_Context!$G$2:$G$64,MATCH($C4,Country_Context!$A$2:$A$64,0)),"") | AO4: https://api.worldbank.org/v2/country/MYS/indicator/PA.NUS.PRVT.PP?format=json&mrv=30 | https://api.worldbank.org/v2/country/MYS/indicator/GC.TAX.TOTL.GD.ZS?format=json&mrv=30 | https://api.worldbank.org/v2/country/MYS/indicator/FD.AST.PRVT.GD.ZS?format=json&mrv=30 | AP4: Tier 3 | AQ4: 2024-12-31 | AR4: providers=world_bank; fields=ppp_private_consumption, tax_rate_assumption, household_debt_proxy | AW4: https://api.worldbank.org/v2/country/MYS/indicator/SI.POV.GINI?format=json&mrv=30 | AX4: Tier 3 | AY4: 2021-12-31 | AZ4: providers=world_bank; fields=gini_coefficient | BE4: https://api.worldbank.org/v2/country/MYS/indicator/NY.GDP.PCAP.PP.CD?format=json&mrv=30 | https://api.worldbank.org/v2/country/MYS/indicator/NY.GDP.MKTP.KD.ZG?format=json&mrv=30 | BF4: Tier 3 | BG4: 2024-12-31 | BH4: providers=world_bank; fields=gdp_per_capita_ppp, gdp_growth
A5: id-jakarta | B5: Jakarta | C5: Indonesia | D5: Southeast Asia | E5: primary | F5: provisional | M5: =IF(OR($G5="",$H5="",$I5="",$J5="",$K5="",$L5="",$AL5="",$AM5=""),"",((($G5*(1-$AM5))-$H5-$I5-$J5-$K5-$L5)/$AL5)) | P5: =IF($O5<>"",$O5,$AN5) | AI5: =IFERROR(INDEX(Country_Context!$B$2:$B$64,MATCH($C5,Country_Context!$A$2:$A$64,0)),"") | AJ5: =IFERROR(INDEX(Country_Context!$C$2:$C$64,MATCH($C5,Country_Context!$A$2:$A$64,0)),"") | AK5: =IFERROR(INDEX(Country_Context!$D$2:$D$64,MATCH($C5,Country_Context!$A$2:$A$64,0)),"") | AL5: =IFERROR(INDEX(Country_Context!$E$2:$E$64,MATCH($C5,Country_Context!$A$2:$A$64,0)),"") | AM5: =IFERROR(INDEX(Country_Context!$F$2:$F$64,MATCH($C5,Country_Context!$A$2:$A$64,0)),"") | AN5: =IFERROR(INDEX(Country_Context!$G$2:$G$64,MATCH($C5,Country_Context!$A$2:$A$64,0)),"") | AO5: https://api.worldbank.org/v2/country/IDN/indicator/PA.NUS.PRVT.PP?format=json&mrv=30 | https://api.worldbank.org/v2/country/IDN/indicator/GC.TAX.TOTL.GD.ZS?format=json&mrv=30 | https://api.worldbank.org/v2/country/IDN/indicator/FD.AST.PRVT.GD.ZS?format=json&mrv=30 | AP5: Tier 3 | AQ5: 2024-12-31 | AR5: providers=world_bank; fields=ppp_private_consumption, tax_rate_assumption, household_debt_proxy | AW5: https://api.worldbank.org/v2/country/IDN/indicator/SI.POV.GINI?format=json&mrv=30 | AX5: Tier 3 | AY5: 2024-12-31 | AZ5: providers=world_bank; fields=gini_coefficient | BE5: https://api.worldbank.org/v2/country/IDN/indicator/NY.GDP.PCAP.PP.CD?format=json&mrv=30 | https://api.worldbank.org/v2/country/IDN/indicator/NY.GDP.MKTP.KD.ZG?format=json&mrv=30 | BF5: Tier 3 | BG5: 2024-12-31 | BH5: providers=world_bank; fields=gdp_per_capita_ppp, gdp_growth
A6: ph-makati | B6: Makati | C6: Philippines | D6: Southeast Asia | E6: primary | F6: provisional | M6: =IF(OR($G6="",$H6="",$I6="",$J6="",$K6="",$L6="",$AL6="",$AM6=""),"",((($G6*(1-$AM6))-$H6-$I6-$J6-$K6-$L6)/$AL6)) | P6: =IF($O6<>"",$O6,$AN6) | AI6: =IFERROR(INDEX(Country_Context!$B$2:$B$64,MATCH($C6,Country_Context!$A$2:$A$64,0)),"") | AJ6: =IFERROR(INDEX(Country_Context!$C$2:$C$64,MATCH($C6,Country_Context!$A$2:$A$64,0)),"") | AK6: =IFERROR(INDEX(Country_Context!$D$2:$D$64,MATCH($C6,Country_Context!$A$2:$A$64,0)),"") | AL6: =IFERROR(INDEX(Country_Context!$E$2:$E$64,MATCH($C6,Country_Context!$A$2:$A$64,0)),"") | AM6: =IFERROR(INDEX(Country_Context!$F$2:$F$64,MATCH($C6,Country_Context!$A$2:$A$64,0)),"") | AN6: =IFERROR(INDEX(Country_Context!$G$2:$G$64,MATCH($C6,Country_Context!$A$2:$A$64,0)),"") | AO6: https://api.worldbank.org/v2/country/PHL/indicator/PA.NUS.PRVT.PP?format=json&mrv=30 | https://api.worldbank.org/v2/country/PHL/indicator/GC.TAX.TOTL.GD.ZS?format=json&mrv=30 | https://api.worldbank.org/v2/country/PHL/indicator/FD.AST.PRVT.GD.ZS?format=json&mrv=30 | AP6: Tier 3 | AQ6: 2024-12-31 | AR6: providers=world_bank; fields=ppp_private_consumption, tax_rate_assumption, household_debt_proxy | AW6: https://api.worldbank.org/v2/country/PHL/indicator/SI.POV.GINI?format=json&mrv=30 | AX6: Tier 3 | AY6: 2023-12-31 | AZ6: providers=world_bank; fields=gini_coefficient | BE6: https://api.worldbank.org/v2/country/PHL/indicator/NY.GDP.PCAP.PP.CD?format=json&mrv=30 | https://api.worldbank.org/v2/country/PHL/indicator/NY.GDP.MKTP.KD.ZG?format=json&mrv=30 | BF6: Tier 3 | BG6: 2024-12-31 | BH6: providers=world_bank; fields=gdp_per_capita_ppp, gdp_growth
A7: my-george-town | B7: George Town | C7: Malaysia | D7: Southeast Asia | E7: secondary | F7: locked | M7: =IF(OR($G7="",$H7="",$I7="",$J7="",$K7="",$L7="",$AL7="",$AM7=""),"",((($G7*(1-$AM7))-$H7-$I7-$J7-$K7-$L7)/$AL7)) | P7: =IF($O7<>"",$O7,$AN7) | AI7: =IFERROR(INDEX(Country_Context!$B$2:$B$64,MATCH($C7,Country_Context!$A$2:$A$64,0)),"") | AJ7: =IFERROR(INDEX(Country_Context!$C$2:$C$64,MATCH($C7,Country_Context!$A$2:$A$64,0)),"") | AK7: =IFERROR(INDEX(Country_Context!$D$2:$D$64,MATCH($C7,Country_Context!$A$2:$A$64,0)),"") | AL7: =IFERROR(INDEX(Country_Context!$E$2:$E$64,MATCH($C7,Country_Context!$A$2:$A$64,0)),"") | AM7: =IFERROR(INDEX(Country_Context!$F$2:$F$64,MATCH($C7,Country_Context!$A$2:$A$64,0)),"") | AN7: =IFERROR(INDEX(Country_Context!$G$2:$G$64,MATCH($C7,Country_Context!$A$2:$A$64,0)),"") | AO7: https://api.worldbank.org/v2/country/MYS/indicator/PA.NUS.PRVT.PP?format=json&mrv=30 | https://api.worldbank.org/v2/country/MYS/indicator/GC.TAX.TOTL.GD.ZS?format=json&mrv=30 | https://api.worldbank.org/v2/country/MYS/indicator/FD.AST.PRVT.GD.ZS?format=json&mrv=30 | AP7: Tier 3 | AQ7: 2024-12-31 | AR7: providers=world_bank; fields=ppp_private_consumption, tax_rate_assumption, household_debt_proxy | AW7: https://api.worldbank.org/v2/country/MYS/indicator/SI.POV.GINI?format=json&mrv=30 | AX7: Tier 3 | AY7: 2021-12-31 | AZ7: providers=world_bank; fields=gini_coefficient | BE7: https://api.worldbank.org/v2/country/MYS/indicator/NY.GDP.PCAP.PP.CD?format=json&mrv=30 | https://api.worldbank.org/v2/country/MYS/indicator/NY.GDP.MKTP.KD.ZG?format=json&mrv=30 | BF7: Tier 3 | BG7: 2024-12-31 | BH7: providers=world_bank; fields=gdp_per_capita_ppp, gdp_growth
A8: th-phuket | B8: Phuket | C8: Thailand | D8: Southeast Asia | E8: secondary | F8: locked | M8: =IF(OR($G8="",$H8="",$I8="",$J8="",$K8="",$L8="",$AL8="",$AM8=""),"",((($G8*(1-$AM8))-$H8-$I8-$J8-$K8-$L8)/$AL8)) | P8: =IF($O8<>"",$O8,$AN8) | AI8: =IFERROR(INDEX(Country_Context!$B$2:$B$64,MATCH($C8,Country_Context!$A$2:$A$64,0)),"") | AJ8: =IFERROR(INDEX(Country_Context!$C$2:$C$64,MATCH($C8,Country_Context!$A$2:$A$64,0)),"") | AK8: =IFERROR(INDEX(Country_Context!$D$2:$D$64,MATCH($C8,Country_Context!$A$2:$A$64,0)),"") | AL8: =IFERROR(INDEX(Country_Context!$E$2:$E$64,MATCH($C8,Country_Context!$A$2:$A$64,0)),"") | AM8: =IFERROR(INDEX(Country_Context!$F$2:$F$64,MATCH($C8,Country_Context!$A$2:$A$64,0)),"") | AN8: =IFERROR(INDEX(Country_Context!$G$2:$G$64,MATCH($C8,Country_Context!$A$2:$A$64,0)),"") | AO8: https://api.worldbank.org/v2/country/THA/indicator/PA.NUS.PRVT.PP?format=json&mrv=30 | https://api.worldbank.org/v2/country/THA/indicator/GC.TAX.TOTL.GD.ZS?format=json&mrv=30 | https://api.worldbank.org/v2/country/THA/indicator/FD.AST.PRVT.GD.ZS?format=json&mrv=30 | AP8: Tier 3 | AQ8: 2024-12-31 | AR8: providers=world_bank; fields=ppp_private_consumption, tax_rate_assumption, household_debt_proxy | AW8: https://api.worldbank.org/v2/country/THA/indicator/SI.POV.GINI?format=json&mrv=30 | AX8: Tier 3 | AY8: 2023-12-31 | AZ8: providers=world_bank; fields=gini_coefficient | BE8: https://api.worldbank.org/v2/country/THA/indicator/NY.GDP.PCAP.PP.CD?format=json&mrv=30 | https://api.worldbank.org/v2/country/THA/indicator/NY.GDP.MKTP.KD.ZG?format=json&mrv=30 | BF8: Tier 3 | BG8: 2024-12-31 | BH8: providers=world_bank; fields=gdp_per_capita_ppp, gdp_growth
A9: th-chiang-mai | B9: Chiang Mai | C9: Thailand | D9: Southeast Asia | E9: secondary | F9: locked | M9: =IF(OR($G9="",$H9="",$I9="",$J9="",$K9="",$L9="",$AL9="",$AM9=""),"",((($G9*(1-$AM9))-$H9-$I9-$J9-$K9-$L9)/$AL9)) | P9: =IF($O9<>"",$O9,$AN9) | AI9: =IFERROR(INDEX(Country_Context!$B$2:$B$64,MATCH($C9,Country_Context!$A$2:$A$64,0)),"") | AJ9: =IFERROR(INDEX(Country_Context!$C$2:$C$64,MATCH($C9,Country_Context!$A$2:$A$64,0)),"") | AK9: =IFERROR(INDEX(Country_Context!$D$2:$D$64,MATCH($C9,Country_Context!$A$2:$A$64,0)),"") | AL9: =IFERROR(INDEX(Country_Context!$E$2:$E$64,MATCH($C9,Country_Context!$A$2:$A$64,0)),"") | AM9: =IFERROR(INDEX(Country_Context!$F$2:$F$64,MATCH($C9,Country_Context!$A$2:$A$64,0)),"") | AN9: =IFERROR(INDEX(Country_Context!$G$2:$G$64,MATCH($C9,Country_Context!$A$2:$A$64,0)),"") | AO9: https://api.worldbank.org/v2/country/THA/indicator/PA.NUS.PRVT.PP?format=json&mrv=30 | https://api.worldbank.org/v2/country/THA/indicator/GC.TAX.TOTL.GD.ZS?format=json&mrv=30 | https://api.worldbank.org/v2/country/THA/indicator/FD.AST.PRVT.GD.ZS?format=json&mrv=30 | AP9: Tier 3 | AQ9: 2024-12-31 | AR9: providers=world_bank; fields=ppp_private_consumption, tax_rate_assumption, household_debt_proxy | AW9: https://api.worldbank.org/v2/country/THA/indicator/SI.POV.GINI?format=json&mrv=30 | AX9: Tier 3 | AY9: 2023-12-31 | AZ9: providers=world_bank; fields=gini_coefficient | BE9: https://api.worldbank.org/v2/country/THA/indicator/NY.GDP.PCAP.PP.CD?format=json&mrv=30 | https://api.worldbank.org/v2/country/THA/indicator/NY.GDP.MKTP.KD.ZG?format=json&mrv=30 | BF9: Tier 3 | BG9: 2024-12-31 | BH9: providers=world_bank; fields=gdp_per_capita_ppp, gdp_growth
A10: my-kuching | B10: Kuching | C10: Malaysia | D10: Southeast Asia | E10: secondary | F10: locked | M10: =IF(OR($G10="",$H10="",$I10="",$J10="",$K10="",$L10="",$AL10="",$AM10=""),"",((($G10*(1-$AM10))-$H10-$I10-$J10-$K10-$L10)/$AL10)) | P10: =IF($O10<>"",$O10,$AN10) | AI10: =IFERROR(INDEX(Country_Context!$B$2:$B$64,MATCH($C10,Country_Context!$A$2:$A$64,0)),"") | AJ10: =IFERROR(INDEX(Country_Context!$C$2:$C$64,MATCH($C10,Country_Context!$A$2:$A$64,0)),"") | AK10: =IFERROR(INDEX(Country_Context!$D$2:$D$64,MATCH($C10,Country_Context!$A$2:$A$64,0)),"") | AL10: =IFERROR(INDEX(Country_Context!$E$2:$E$64,MATCH($C10,Country_Context!$A$2:$A$64,0)),"") | AM10: =IFERROR(INDEX(Country_Context!$F$2:$F$64,MATCH($C10,Country_Context!$A$2:$A$64,0)),"") | AN10: =IFERROR(INDEX(Country_Context!$G$2:$G$64,MATCH($C10,Country_Context!$A$2:$A$64,0)),"") | AO10: https://api.worldbank.org/v2/country/MYS/indicator/PA.NUS.PRVT.PP?format=json&mrv=30 | https://api.worldbank.org/v2/country/MYS/indicator/GC.TAX.TOTL.GD.ZS?format=json&mrv=30 | https://api.worldbank.org/v2/country/MYS/indicator/FD.AST.PRVT.GD.ZS?format=json&mrv=30 | AP10: Tier 3 | AQ10: 2024-12-31 | AR10: providers=world_bank; fields=ppp_private_consumption, tax_rate_assumption, household_debt_proxy | AW10: https://api.worldbank.org/v2/country/MYS/indicator/SI.POV.GINI?format=json&mrv=30 | AX10: Tier 3 | AY10: 2021-12-31 | AZ10: providers=world_bank; fields=gini_coefficient | BE10: https://api.worldbank.org/v2/country/MYS/indicator/NY.GDP.PCAP.PP.CD?format=json&mrv=30 | https://api.worldbank.org/v2/country/MYS/indicator/NY.GDP.MKTP.KD.ZG?format=json&mrv=30 | BF10: Tier 3 | BG10: 2024-12-31 | BH10: providers=world_bank; fields=gdp_per_capita_ppp, gdp_growth
A11: th-hat-yai | B11: Hat Yai | C11: Thailand | D11: Southeast Asia | E11: secondary | F11: provisional | M11: =IF(OR($G11="",$H11="",$I11="",$J11="",$K11="",$L11="",$AL11="",$AM11=""),"",((($G11*(1-$AM11))-$H11-$I11-$J11-$K11-$L11)/$AL11)) | P11: =IF($O11<>"",$O11,$AN11) | AI11: =IFERROR(INDEX(Country_Context!$B$2:$B$64,MATCH($C11,Country_Context!$A$2:$A$64,0)),"") | AJ11: =IFERROR(INDEX(Country_Context!$C$2:$C$64,MATCH($C11,Country_Context!$A$2:$A$64,0)),"") | AK11: =IFERROR(INDEX(Country_Context!$D$2:$D$64,MATCH($C11,Country_Context!$A$2:$A$64,0)),"") | AL11: =IFERROR(INDEX(Country_Context!$E$2:$E$64,MATCH($C11,Country_Context!$A$2:$A$64,0)),"") | AM11: =IFERROR(INDEX(Country_Context!$F$2:$F$64,MATCH($C11,Country_Context!$A$2:$A$64,0)),"") | AN11: =IFERROR(INDEX(Country_Context!$G$2:$G$64,MATCH($C11,Country_Context!$A$2:$A$64,0)),"") | AO11: https://api.worldbank.org/v2/country/THA/indicator/PA.NUS.PRVT.PP?format=json&mrv=30 | https://api.worldbank.org/v2/country/THA/indicator/GC.TAX.TOTL.GD.ZS?format=json&mrv=30 | https://api.worldbank.org/v2/country/THA/indicator/FD.AST.PRVT.GD.ZS?format=json&mrv=30 | AP11: Tier 3 | AQ11: 2024-12-31 | AR11: providers=world_bank; fields=ppp_private_consumption, tax_rate_assumption, household_debt_proxy | AW11: https://api.worldbank.org/v2/country/THA/indicator/SI.POV.GINI?format=json&mrv=30 | AX11: Tier 3 | AY11: 2023-12-31 | AZ11: providers=world_bank; fields=gini_coefficient | BE11: https://api.worldbank.org/v2/country/THA/indicator/NY.GDP.PCAP.PP.CD?format=json&mrv=30 | https://api.worldbank.org/v2/country/THA/indicator/NY.GDP.MKTP.KD.ZG?format=json&mrv=30 | BF11: Tier 3 | BG11: 2024-12-31 | BH11: providers=world_bank; fields=gdp_per_capita_ppp, gdp_growth
A12: tw-taipei | B12: Taipei | C12: Taiwan | D12: East Asia | E12: primary | F12: locked | M12: =IF(OR($G12="",$H12="",$I12="",$J12="",$K12="",$L12="",$AL12="",$AM12=""),"",((($G12*(1-$AM12))-$H12-$I12-$J12-$K12-$L12)/$AL12)) | P12: =IF($O12<>"",$O12,$AN12) | AI12: =IFERROR(INDEX(Country_Context!$B$2:$B$64,MATCH($C12,Country_Context!$A$2:$A$64,0)),"") | AJ12: =IFERROR(INDEX(Country_Context!$C$2:$C$64,MATCH($C12,Country_Context!$A$2:$A$64,0)),"") | AK12: =IFERROR(INDEX(Country_Context!$D$2:$D$64,MATCH($C12,Country_Context!$A$2:$A$64,0)),"") | AL12: =IFERROR(INDEX(Country_Context!$E$2:$E$64,MATCH($C12,Country_Context!$A$2:$A$64,0)),"") | AM12: =IFERROR(INDEX(Country_Context!$F$2:$F$64,MATCH($C12,Country_Context!$A$2:$A$64,0)),"") | AN12: =IFERROR(INDEX(Country_Context!$G$2:$G$64,MATCH($C12,Country_Context!$A$2:$A$64,0)),"")
A13: kr-busan | B13: Busan | C13: South Korea | D13: East Asia | E13: primary | F13: locked | M13: =IF(OR($G13="",$H13="",$I13="",$J13="",$K13="",$L13="",$AL13="",$AM13=""),"",((($G13*(1-$AM13))-$H13-$I13-$J13-$K13-$L13)/$AL13)) | P13: =IF($O13<>"",$O13,$AN13) | AI13: =IFERROR(INDEX(Country_Context!$B$2:$B$64,MATCH($C13,Country_Context!$A$2:$A$64,0)),"") | AJ13: =IFERROR(INDEX(Country_Context!$C$2:$C$64,MATCH($C13,Country_Context!$A$2:$A$64,0)),"") | AK13: =IFERROR(INDEX(Country_Context!$D$2:$D$64,MATCH($C13,Country_Context!$A$2:$A$64,0)),"") | AL13: =IFERROR(INDEX(Country_Context!$E$2:$E$64,MATCH($C13,Country_Context!$A$2:$A$64,0)),"") | AM13: =IFERROR(INDEX(Country_Context!$F$2:$F$64,MATCH($C13,Country_Context!$A$2:$A$64,0)),"") | AN13: =IFERROR(INDEX(Country_Context!$G$2:$G$64,MATCH($C13,Country_Context!$A$2:$A$64,0)),"") | AO13: https://api.worldbank.org/v2/country/KOR/indicator/PA.NUS.PRVT.PP?format=json&mrv=30 | https://api.worldbank.org/v2/country/KOR/indicator/GC.TAX.TOTL.GD.ZS?format=json&mrv=30 | https://api.worldbank.org/v2/country/KOR/indicator/FD.AST.PRVT.GD.ZS?format=json&mrv=30 | AP13: Tier 3 | AQ13: 2024-12-31 | AR13: providers=world_bank; fields=ppp_private_consumption, tax_rate_assumption, household_debt_proxy | AW13: https://api.worldbank.org/v2/country/KOR/indicator/SI.POV.GINI?format=json&mrv=30 | AX13: Tier 3 | AY13: 2021-12-31 | AZ13: providers=world_bank; fields=gini_coefficient | BE13: https://api.worldbank.org/v2/country/KOR/indicator/NY.GDP.PCAP.PP.CD?format=json&mrv=30 | https://api.worldbank.org/v2/country/KOR/indicator/NY.GDP.MKTP.KD.ZG?format=json&mrv=30 | BF13: Tier 3 | BG13: 2024-12-31 | BH13: providers=world_bank; fields=gdp_per_capita_ppp, gdp_growth
A14: cn-shanghai | B14: Shanghai | C14: China | D14: East Asia | E14: primary | F14: provisional | M14: =IF(OR($G14="",$H14="",$I14="",$J14="",$K14="",$L14="",$AL14="",$AM14=""),"",((($G14*(1-$AM14))-$H14-$I14-$J14-$K14-$L14)/$AL14)) | P14: =IF($O14<>"",$O14,$AN14) | AI14: =IFERROR(INDEX(Country_Context!$B$2:$B$64,MATCH($C14,Country_Context!$A$2:$A$64,0)),"") | AJ14: =IFERROR(INDEX(Country_Context!$C$2:$C$64,MATCH($C14,Country_Context!$A$2:$A$64,0)),"") | AK14: =IFERROR(INDEX(Country_Context!$D$2:$D$64,MATCH($C14,Country_Context!$A$2:$A$64,0)),"") | AL14: =IFERROR(INDEX(Country_Context!$E$2:$E$64,MATCH($C14,Country_Context!$A$2:$A$64,0)),"") | AM14: =IFERROR(INDEX(Country_Context!$F$2:$F$64,MATCH($C14,Country_Context!$A$2:$A$64,0)),"") | AN14: =IFERROR(INDEX(Country_Context!$G$2:$G$64,MATCH($C14,Country_Context!$A$2:$A$64,0)),"") | AO14: https://api.worldbank.org/v2/country/CHN/indicator/PA.NUS.PRVT.PP?format=json&mrv=30 | https://api.worldbank.org/v2/country/CHN/indicator/GC.TAX.TOTL.GD.ZS?format=json&mrv=30 | https://api.worldbank.org/v2/country/CHN/indicator/FD.AST.PRVT.GD.ZS?format=json&mrv=30 | AP14: Tier 3 | AQ14: 2024-12-31 | AR14: providers=world_bank; fields=ppp_private_consumption, tax_rate_assumption, household_debt_proxy | AW14: https://api.worldbank.org/v2/country/CHN/indicator/SI.POV.GINI?format=json&mrv=30 | AX14: Tier 3 | AY14: 2022-12-31 | AZ14: providers=world_bank; fields=gini_coefficient | BE14: https://api.worldbank.org/v2/country/CHN/indicator/NY.GDP.PCAP.PP.CD?format=json&mrv=30 | https://api.worldbank.org/v2/country/CHN/indicator/NY.GDP.MKTP.KD.ZG?format=json&mrv=30 | BF14: Tier 3 | BG14: 2024-12-31 | BH14: providers=world_bank; fields=gdp_per_capita_ppp, gdp_growth
A15: cn-shenzhen | B15: Shenzhen | C15: China | D15: East Asia | E15: primary | F15: provisional | M15: =IF(OR($G15="",$H15="",$I15="",$J15="",$K15="",$L15="",$AL15="",$AM15=""),"",((($G15*(1-$AM15))-$H15-$I15-$J15-$K15-$L15)/$AL15)) | P15: =IF($O15<>"",$O15,$AN15) | AI15: =IFERROR(INDEX(Country_Context!$B$2:$B$64,MATCH($C15,Country_Context!$A$2:$A$64,0)),"") | AJ15: =IFERROR(INDEX(Country_Context!$C$2:$C$64,MATCH($C15,Country_Context!$A$2:$A$64,0)),"") | AK15: =IFERROR(INDEX(Country_Context!$D$2:$D$64,MATCH($C15,Country_Context!$A$2:$A$64,0)),"") | AL15: =IFERROR(INDEX(Country_Context!$E$2:$E$64,MATCH($C15,Country_Context!$A$2:$A$64,0)),"") | AM15: =IFERROR(INDEX(Country_Context!$F$2:$F$64,MATCH($C15,Country_Context!$A$2:$A$64,0)),"") | AN15: =IFERROR(INDEX(Country_Context!$G$2:$G$64,MATCH($C15,Country_Context!$A$2:$A$64,0)),"") | AO15: https://api.worldbank.org/v2/country/CHN/indicator/PA.NUS.PRVT.PP?format=json&mrv=30 | https://api.worldbank.org/v2/country/CHN/indicator/GC.TAX.TOTL.GD.ZS?format=json&mrv=30 | https://api.worldbank.org/v2/country/CHN/indicator/FD.AST.PRVT.GD.ZS?format=json&mrv=30 | AP15: Tier 3 | AQ15: 2024-12-31 | AR15: providers=world_bank; fields=ppp_private_consumption, tax_rate_assumption, household_debt_proxy | AW15: https://api.worldbank.org/v2/country/CHN/indicator/SI.POV.GINI?format=json&mrv=30 | AX15: Tier 3 | AY15: 2022-12-31 | AZ15: providers=world_bank; fields=gini_coefficient | BE15: https://api.worldbank.org/v2/country/CHN/indicator/NY.GDP.PCAP.PP.CD?format=json&mrv=30 | https://api.worldbank.org/v2/country/CHN/indicator/NY.GDP.MKTP.KD.ZG?format=json&mrv=30 | BF15: Tier 3 | BG15: 2024-12-31 | BH15: providers=world_bank; fields=gdp_per_capita_ppp, gdp_growth
A16: jp-hiroshima | B16: Hiroshima | C16: Japan | D16: East Asia | E16: primary | F16: provisional | M16: =IF(OR($G16="",$H16="",$I16="",$J16="",$K16="",$L16="",$AL16="",$AM16=""),"",((($G16*(1-$AM16))-$H16-$I16-$J16-$K16-$L16)/$AL16)) | P16: =IF($O16<>"",$O16,$AN16) | AI16: =IFERROR(INDEX(Country_Context!$B$2:$B$64,MATCH($C16,Country_Context!$A$2:$A$64,0)),"") | AJ16: =IFERROR(INDEX(Country_Context!$C$2:$C$64,MATCH($C16,Country_Context!$A$2:$A$64,0)),"") | AK16: =IFERROR(INDEX(Country_Context!$D$2:$D$64,MATCH($C16,Country_Context!$A$2:$A$64,0)),"") | AL16: =IFERROR(INDEX(Country_Context!$E$2:$E$64,MATCH($C16,Country_Context!$A$2:$A$64,0)),"") | AM16: =IFERROR(INDEX(Country_Context!$F$2:$F$64,MATCH($C16,Country_Context!$A$2:$A$64,0)),"") | AN16: =IFERROR(INDEX(Country_Context!$G$2:$G$64,MATCH($C16,Country_Context!$A$2:$A$64,0)),"") | AO16: https://api.worldbank.org/v2/country/JPN/indicator/PA.NUS.PRVT.PP?format=json&mrv=30 | https://api.worldbank.org/v2/country/JPN/indicator/FD.AST.PRVT.GD.ZS?format=json&mrv=30 | AP16: Tier 3 | AQ16: 2024-12-31 | AR16: providers=world_bank; fields=ppp_private_consumption, household_debt_proxy | AW16: https://api.worldbank.org/v2/country/JPN/indicator/SI.POV.GINI?format=json&mrv=30 | AX16: Tier 3 | AY16: 2020-12-31 | AZ16: providers=world_bank; fields=gini_coefficient | BE16: https://api.worldbank.org/v2/country/JPN/indicator/NY.GDP.PCAP.PP.CD?format=json&mrv=30 | https://api.worldbank.org/v2/country/JPN/indicator/NY.GDP.MKTP.KD.ZG?format=json&mrv=30 | BF16: Tier 3 | BG16: 2024-12-31 | BH16: providers=world_bank; fields=gdp_per_capita_ppp, gdp_growth
A17: kr-jeju-city | B17: Jeju City | C17: South Korea | D17: East Asia | E17: secondary | F17: locked | M17: =IF(OR($G17="",$H17="",$I17="",$J17="",$K17="",$L17="",$AL17="",$AM17=""),"",((($G17*(1-$AM17))-$H17-$I17-$J17-$K17-$L17)/$AL17)) | P17: =IF($O17<>"",$O17,$AN17) | AI17: =IFERROR(INDEX(Country_Context!$B$2:$B$64,MATCH($C17,Country_Context!$A$2:$A$64,0)),"") | AJ17: =IFERROR(INDEX(Country_Context!$C$2:$C$64,MATCH($C17,Country_Context!$A$2:$A$64,0)),"") | AK17: =IFERROR(INDEX(Country_Context!$D$2:$D$64,MATCH($C17,Country_Context!$A$2:$A$64,0)),"") | AL17: =IFERROR(INDEX(Country_Context!$E$2:$E$64,MATCH($C17,Country_Context!$A$2:$A$64,0)),"") | AM17: =IFERROR(INDEX(Country_Context!$F$2:$F$64,MATCH($C17,Country_Context!$A$2:$A$64,0)),"") | AN17: =IFERROR(INDEX(Country_Context!$G$2:$G$64,MATCH($C17,Country_Context!$A$2:$A$64,0)),"") | AO17: https://api.worldbank.org/v2/country/KOR/indicator/PA.NUS.PRVT.PP?format=json&mrv=30 | https://api.worldbank.org/v2/country/KOR/indicator/GC.TAX.TOTL.GD.ZS?format=json&mrv=30 | https://api.worldbank.org/v2/country/KOR/indicator/FD.AST.PRVT.GD.ZS?format=json&mrv=30 | AP17: Tier 3 | AQ17: 2024-12-31 | AR17: providers=world_bank; fields=ppp_private_consumption, tax_rate_assumption, household_debt_proxy | AW17: https://api.worldbank.org/v2/country/KOR/indicator/SI.POV.GINI?format=json&mrv=30 | AX17: Tier 3 | AY17: 2021-12-31 | AZ17: providers=world_bank; fields=gini_coefficient | BE17: https://api.worldbank.org/v2/country/KOR/indicator/NY.GDP.PCAP.PP.CD?format=json&mrv=30 | https://api.worldbank.org/v2/country/KOR/indicator/NY.GDP.MKTP.KD.ZG?format=json&mrv=30 | BF17: Tier 3 | BG17: 2024-12-31 | BH17: providers=world_bank; fields=gdp_per_capita_ppp, gdp_growth
A18: jp-fukuoka | B18: Fukuoka | C18: Japan | D18: East Asia | E18: secondary | F18: locked | M18: =IF(OR($G18="",$H18="",$I18="",$J18="",$K18="",$L18="",$AL18="",$AM18=""),"",((($G18*(1-$AM18))-$H18-$I18-$J18-$K18-$L18)/$AL18)) | P18: =IF($O18<>"",$O18,$AN18) | AI18: =IFERROR(INDEX(Country_Context!$B$2:$B$64,MATCH($C18,Country_Context!$A$2:$A$64,0)),"") | AJ18: =IFERROR(INDEX(Country_Context!$C$2:$C$64,MATCH($C18,Country_Context!$A$2:$A$64,0)),"") | AK18: =IFERROR(INDEX(Country_Context!$D$2:$D$64,MATCH($C18,Country_Context!$A$2:$A$64,0)),"") | AL18: =IFERROR(INDEX(Country_Context!$E$2:$E$64,MATCH($C18,Country_Context!$A$2:$A$64,0)),"") | AM18: =IFERROR(INDEX(Country_Context!$F$2:$F$64,MATCH($C18,Country_Context!$A$2:$A$64,0)),"") | AN18: =IFERROR(INDEX(Country_Context!$G$2:$G$64,MATCH($C18,Country_Context!$A$2:$A$64,0)),"") | AO18: https://api.worldbank.org/v2/country/JPN/indicator/PA.NUS.PRVT.PP?format=json&mrv=30 | https://api.worldbank.org/v2/country/JPN/indicator/FD.AST.PRVT.GD.ZS?format=json&mrv=30 | AP18: Tier 3 | AQ18: 2024-12-31 | AR18: providers=world_bank; fields=ppp_private_consumption, household_debt_proxy | AW18: https://api.worldbank.org/v2/country/JPN/indicator/SI.POV.GINI?format=json&mrv=30 | AX18: Tier 3 | AY18: 2020-12-31 | AZ18: providers=world_bank; fields=gini_coefficient | BE18: https://api.worldbank.org/v2/country/JPN/indicator/NY.GDP.PCAP.PP.CD?format=json&mrv=30 | https://api.worldbank.org/v2/country/JPN/indicator/NY.GDP.MKTP.KD.ZG?format=json&mrv=30 | BF18: Tier 3 | BG18: 2024-12-31 | BH18: providers=world_bank; fields=gdp_per_capita_ppp, gdp_growth
A19: jp-kobe | B19: Kobe | C19: Japan | D19: East Asia | E19: secondary | F19: locked | M19: =IF(OR($G19="",$H19="",$I19="",$J19="",$K19="",$L19="",$AL19="",$AM19=""),"",((($G19*(1-$AM19))-$H19-$I19-$J19-$K19-$L19)/$AL19)) | P19: =IF($O19<>"",$O19,$AN19) | AI19: =IFERROR(INDEX(Country_Context!$B$2:$B$64,MATCH($C19,Country_Context!$A$2:$A$64,0)),"") | AJ19: =IFERROR(INDEX(Country_Context!$C$2:$C$64,MATCH($C19,Country_Context!$A$2:$A$64,0)),"") | AK19: =IFERROR(INDEX(Country_Context!$D$2:$D$64,MATCH($C19,Country_Context!$A$2:$A$64,0)),"") | AL19: =IFERROR(INDEX(Country_Context!$E$2:$E$64,MATCH($C19,Country_Context!$A$2:$A$64,0)),"") | AM19: =IFERROR(INDEX(Country_Context!$F$2:$F$64,MATCH($C19,Country_Context!$A$2:$A$64,0)),"") | AN19: =IFERROR(INDEX(Country_Context!$G$2:$G$64,MATCH($C19,Country_Context!$A$2:$A$64,0)),"") | AO19: https://api.worldbank.org/v2/country/JPN/indicator/PA.NUS.PRVT.PP?format=json&mrv=30 | https://api.worldbank.org/v2/country/JPN/indicator/FD.AST.PRVT.GD.ZS?format=json&mrv=30 | AP19: Tier 3 | AQ19: 2024-12-31 | AR19: providers=world_bank; fields=ppp_private_consumption, household_debt_proxy | AW19: https://api.worldbank.org/v2/country/JPN/indicator/SI.POV.GINI?format=json&mrv=30 | AX19: Tier 3 | AY19: 2020-12-31 | AZ19: providers=world_bank; fields=gini_coefficient | BE19: https://api.worldbank.org/v2/country/JPN/indicator/NY.GDP.PCAP.PP.CD?format=json&mrv=30 | https://api.worldbank.org/v2/country/JPN/indicator/NY.GDP.MKTP.KD.ZG?format=json&mrv=30 | BF19: Tier 3 | BG19: 2024-12-31 | BH19: providers=world_bank; fields=gdp_per_capita_ppp, gdp_growth
A20: jp-sapporo | B20: Sapporo | C20: Japan | D20: East Asia | E20: secondary | F20: locked | M20: =IF(OR($G20="",$H20="",$I20="",$J20="",$K20="",$L20="",$AL20="",$AM20=""),"",((($G20*(1-$AM20))-$H20-$I20-$J20-$K20-$L20)/$AL20)) | P20: =IF($O20<>"",$O20,$AN20) | AI20: =IFERROR(INDEX(Country_Context!$B$2:$B$64,MATCH($C20,Country_Context!$A$2:$A$64,0)),"") | AJ20: =IFERROR(INDEX(Country_Context!$C$2:$C$64,MATCH($C20,Country_Context!$A$2:$A$64,0)),"") | AK20: =IFERROR(INDEX(Country_Context!$D$2:$D$64,MATCH($C20,Country_Context!$A$2:$A$64,0)),"") | AL20: =IFERROR(INDEX(Country_Context!$E$2:$E$64,MATCH($C20,Country_Context!$A$2:$A$64,0)),"") | AM20: =IFERROR(INDEX(Country_Context!$F$2:$F$64,MATCH($C20,Country_Context!$A$2:$A$64,0)),"") | AN20: =IFERROR(INDEX(Country_Context!$G$2:$G$64,MATCH($C20,Country_Context!$A$2:$A$64,0)),"") | AO20: https://api.worldbank.org/v2/country/JPN/indicator/PA.NUS.PRVT.PP?format=json&mrv=30 | https://api.worldbank.org/v2/country/JPN/indicator/FD.AST.PRVT.GD.ZS?format=json&mrv=30 | AP20: Tier 3 | AQ20: 2024-12-31 | AR20: providers=world_bank; fields=ppp_private_consumption, household_debt_proxy | AW20: https://api.worldbank.org/v2/country/JPN/indicator/SI.POV.GINI?format=json&mrv=30 | AX20: Tier 3 | AY20: 2020-12-31 | AZ20: providers=world_bank; fields=gini_coefficient | BE20: https://api.worldbank.org/v2/country/JPN/indicator/NY.GDP.PCAP.PP.CD?format=json&mrv=30 | https://api.worldbank.org/v2/country/JPN/indicator/NY.GDP.MKTP.KD.ZG?format=json&mrv=30 | BF20: Tier 3 | BG20: 2024-12-31 | BH20: providers=world_bank; fields=gdp_per_capita_ppp, gdp_growth
A21: cn-tianjin | B21: Tianjin | C21: China | D21: East Asia | E21: secondary | F21: provisional | M21: =IF(OR($G21="",$H21="",$I21="",$J21="",$K21="",$L21="",$AL21="",$AM21=""),"",((($G21*(1-$AM21))-$H21-$I21-$J21-$K21-$L21)/$AL21)) | P21: =IF($O21<>"",$O21,$AN21) | AI21: =IFERROR(INDEX(Country_Context!$B$2:$B$64,MATCH($C21,Country_Context!$A$2:$A$64,0)),"") | AJ21: =IFERROR(INDEX(Country_Context!$C$2:$C$64,MATCH($C21,Country_Context!$A$2:$A$64,0)),"") | AK21: =IFERROR(INDEX(Country_Context!$D$2:$D$64,MATCH($C21,Country_Context!$A$2:$A$64,0)),"") | AL21: =IFERROR(INDEX(Country_Context!$E$2:$E$64,MATCH($C21,Country_Context!$A$2:$A$64,0)),"") | AM21: =IFERROR(INDEX(Country_Context!$F$2:$F$64,MATCH($C21,Country_Context!$A$2:$A$64,0)),"") | AN21: =IFERROR(INDEX(Country_Context!$G$2:$G$64,MATCH($C21,Country_Context!$A$2:$A$64,0)),"") | AO21: https://api.worldbank.org/v2/country/CHN/indicator/PA.NUS.PRVT.PP?format=json&mrv=30 | https://api.worldbank.org/v2/country/CHN/indicator/GC.TAX.TOTL.GD.ZS?format=json&mrv=30 | https://api.worldbank.org/v2/country/CHN/indicator/FD.AST.PRVT.GD.ZS?format=json&mrv=30 | AP21: Tier 3 | AQ21: 2024-12-31 | AR21: providers=world_bank; fields=ppp_private_consumption, tax_rate_assumption, household_debt_proxy | AW21: https://api.worldbank.org/v2/country/CHN/indicator/SI.POV.GINI?format=json&mrv=30 | AX21: Tier 3 | AY21: 2022-12-31 | AZ21: providers=world_bank; fields=gini_coefficient | BE21: https://api.worldbank.org/v2/country/CHN/indicator/NY.GDP.PCAP.PP.CD?format=json&mrv=30 | https://api.worldbank.org/v2/country/CHN/indicator/NY.GDP.MKTP.KD.ZG?format=json&mrv=30 | BF21: Tier 3 | BG21: 2024-12-31 | BH21: providers=world_bank; fields=gdp_per_capita_ppp, gdp_growth
A22: in-bengaluru | B22: Bengaluru | C22: India | D22: South Asia | E22: primary | F22: locked | M22: =IF(OR($G22="",$H22="",$I22="",$J22="",$K22="",$L22="",$AL22="",$AM22=""),"",((($G22*(1-$AM22))-$H22-$I22-$J22-$K22-$L22)/$AL22)) | P22: =IF($O22<>"",$O22,$AN22) | AI22: =IFERROR(INDEX(Country_Context!$B$2:$B$64,MATCH($C22,Country_Context!$A$2:$A$64,0)),"") | AJ22: =IFERROR(INDEX(Country_Context!$C$2:$C$64,MATCH($C22,Country_Context!$A$2:$A$64,0)),"") | AK22: =IFERROR(INDEX(Country_Context!$D$2:$D$64,MATCH($C22,Country_Context!$A$2:$A$64,0)),"") | AL22: =IFERROR(INDEX(Country_Context!$E$2:$E$64,MATCH($C22,Country_Context!$A$2:$A$64,0)),"") | AM22: =IFERROR(INDEX(Country_Context!$F$2:$F$64,MATCH($C22,Country_Context!$A$2:$A$64,0)),"") | AN22: =IFERROR(INDEX(Country_Context!$G$2:$G$64,MATCH($C22,Country_Context!$A$2:$A$64,0)),"") | AO22: https://api.worldbank.org/v2/country/IND/indicator/PA.NUS.PRVT.PP?format=json&mrv=30 | https://api.worldbank.org/v2/country/IND/indicator/GC.TAX.TOTL.GD.ZS?format=json&mrv=30 | https://api.worldbank.org/v2/country/IND/indicator/FD.AST.PRVT.GD.ZS?format=json&mrv=30 | AP22: Tier 3 | AQ22: 2024-12-31 | AR22: providers=world_bank; fields=ppp_private_consumption, tax_rate_assumption, household_debt_proxy | AW22: https://api.worldbank.org/v2/country/IND/indicator/SI.POV.GINI?format=json&mrv=30 | AX22: Tier 3 | AY22: 2022-12-31 | AZ22: providers=world_bank; fields=gini_coefficient | BE22: https://api.worldbank.org/v2/country/IND/indicator/NY.GDP.PCAP.PP.CD?format=json&mrv=30 | https://api.worldbank.org/v2/country/IND/indicator/NY.GDP.MKTP.KD.ZG?format=json&mrv=30 | BF22: Tier 3 | BG22: 2024-12-31 | BH22: providers=world_bank; fields=gdp_per_capita_ppp, gdp_growth
A23: in-hyderabad | B23: Hyderabad | C23: India | D23: South Asia | E23: primary | F23: locked | M23: =IF(OR($G23="",$H23="",$I23="",$J23="",$K23="",$L23="",$AL23="",$AM23=""),"",((($G23*(1-$AM23))-$H23-$I23-$J23-$K23-$L23)/$AL23)) | P23: =IF($O23<>"",$O23,$AN23) | AI23: =IFERROR(INDEX(Country_Context!$B$2:$B$64,MATCH($C23,Country_Context!$A$2:$A$64,0)),"") | AJ23: =IFERROR(INDEX(Country_Context!$C$2:$C$64,MATCH($C23,Country_Context!$A$2:$A$64,0)),"") | AK23: =IFERROR(INDEX(Country_Context!$D$2:$D$64,MATCH($C23,Country_Context!$A$2:$A$64,0)),"") | AL23: =IFERROR(INDEX(Country_Context!$E$2:$E$64,MATCH($C23,Country_Context!$A$2:$A$64,0)),"") | AM23: =IFERROR(INDEX(Country_Context!$F$2:$F$64,MATCH($C23,Country_Context!$A$2:$A$64,0)),"") | AN23: =IFERROR(INDEX(Country_Context!$G$2:$G$64,MATCH($C23,Country_Context!$A$2:$A$64,0)),"") | AO23: https://api.worldbank.org/v2/country/IND/indicator/PA.NUS.PRVT.PP?format=json&mrv=30 | https://api.worldbank.org/v2/country/IND/indicator/GC.TAX.TOTL.GD.ZS?format=json&mrv=30 | https://api.worldbank.org/v2/country/IND/indicator/FD.AST.PRVT.GD.ZS?format=json&mrv=30 | AP23: Tier 3 | AQ23: 2024-12-31 | AR23: providers=world_bank; fields=ppp_private_consumption, tax_rate_assumption, household_debt_proxy | AW23: https://api.worldbank.org/v2/country/IND/indicator/SI.POV.GINI?format=json&mrv=30 | AX23: Tier 3 | AY23: 2022-12-31 | AZ23: providers=world_bank; fields=gini_coefficient | BE23: https://api.worldbank.org/v2/country/IND/indicator/NY.GDP.PCAP.PP.CD?format=json&mrv=30 | https://api.worldbank.org/v2/country/IND/indicator/NY.GDP.MKTP.KD.ZG?format=json&mrv=30 | BF23: Tier 3 | BG23: 2024-12-31 | BH23: providers=world_bank; fields=gdp_per_capita_ppp, gdp_growth
A24: lk-colombo | B24: Colombo | C24: Sri Lanka | D24: South Asia | E24: primary | F24: locked | M24: =IF(OR($G24="",$H24="",$I24="",$J24="",$K24="",$L24="",$AL24="",$AM24=""),"",((($G24*(1-$AM24))-$H24-$I24-$J24-$K24-$L24)/$AL24)) | P24: =IF($O24<>"",$O24,$AN24) | AI24: =IFERROR(INDEX(Country_Context!$B$2:$B$64,MATCH($C24,Country_Context!$A$2:$A$64,0)),"") | AJ24: =IFERROR(INDEX(Country_Context!$C$2:$C$64,MATCH($C24,Country_Context!$A$2:$A$64,0)),"") | AK24: =IFERROR(INDEX(Country_Context!$D$2:$D$64,MATCH($C24,Country_Context!$A$2:$A$64,0)),"") | AL24: =IFERROR(INDEX(Country_Context!$E$2:$E$64,MATCH($C24,Country_Context!$A$2:$A$64,0)),"") | AM24: =IFERROR(INDEX(Country_Context!$F$2:$F$64,MATCH($C24,Country_Context!$A$2:$A$64,0)),"") | AN24: =IFERROR(INDEX(Country_Context!$G$2:$G$64,MATCH($C24,Country_Context!$A$2:$A$64,0)),"") | AO24: https://api.worldbank.org/v2/country/LKA/indicator/PA.NUS.PRVT.PP?format=json&mrv=30 | https://api.worldbank.org/v2/country/LKA/indicator/GC.TAX.TOTL.GD.ZS?format=json&mrv=30 | https://api.worldbank.org/v2/country/LKA/indicator/FD.AST.PRVT.GD.ZS?format=json&mrv=30 | AP24: Tier 3 | AQ24: 2024-12-31 | AR24: providers=world_bank; fields=ppp_private_consumption, tax_rate_assumption, household_debt_proxy | AW24: https://api.worldbank.org/v2/country/LKA/indicator/SI.POV.GINI?format=json&mrv=30 | AX24: Tier 3 | AY24: 2019-12-31 | AZ24: providers=world_bank; fields=gini_coefficient | BE24: https://api.worldbank.org/v2/country/LKA/indicator/NY.GDP.PCAP.PP.CD?format=json&mrv=30 | https://api.worldbank.org/v2/country/LKA/indicator/NY.GDP.MKTP.KD.ZG?format=json&mrv=30 | BF24: Tier 3 | BG24: 2024-12-31 | BH24: providers=world_bank; fields=gdp_per_capita_ppp, gdp_growth
... A36: dk-copenhagen | B36: Copenhagen | C36: Denmark | D36: Western, Northern, and Southern Europe | E36: primary | F36: provisional | M36: =IF(OR($G36="",$H36="",$I36="",$J36="",$K36="",$L36="",$AL36="",$AM36=""),"",((($G36*(1-$AM36))-$H36-$I36-$J36-$K36-$L36)/$AL36)) | P36: =IF($O36<>"",$O36,$AN36) | AI36: =IFERROR(INDEX(Country_Context!$B$2:$B$64,MATCH($C36,Country_Context!$A$2:$A$64,0)),"") | AJ36: =IFERROR(INDEX(Country_Context!$C$2:$C$64,MATCH($C36,Country_Context!$A$2:$A$64,0)),"") | AK36: =IFERROR(INDEX(Country_Context!$D$2:$D$64,MATCH($C36,Country_Context!$A$2:$A$64,0)),"") | AL36: =IFERROR(INDEX(Country_Context!$E$2:$E$64,MATCH($C36,Country_Context!$A$2:$A$64,0)),"") | AM36: =IFERROR(INDEX(Country_Context!$F$2:$F$64,MATCH($C36,Country_Context!$A$2:$A$64,0)),"") | AN36: =IFERROR(INDEX(Country_Context!$G$2:$G$64,MATCH($C36,Country_Context!$A$2:$A$64,0)),"") | AO36: https://api.worldbank.org/v2/country/DNK/indicator/PA.NUS.PRVT.PP?format=json&mrv=30 | https://api.worldbank.org/v2/country/DNK/indicator/GC.TAX.TOTL.GD.ZS?format=json&mrv=30 | https://api.worldbank.org/v2/country/DNK/indicator/FD.AST.PRVT.GD.ZS?format=json&mrv=30 | AP36: Tier 3 | AQ36: 2024-12-31 | AR36: providers=world_bank; fields=ppp_private_consumption, tax_rate_assumption, household_debt_proxy | AW36: https://api.worldbank.org/v2/country/DNK/indicator/SI.POV.GINI?format=json&mrv=30 | AX36: Tier 3 | AY36: 2023-12-31 | AZ36: providers=world_bank; fields=gini_coefficient | BE36: https://api.worldbank.org/v2/country/DNK/indicator/NY.GDP.PCAP.PP.CD?format=json&mrv=30 | https://api.worldbank.org/v2/country/DNK/indicator/NY.GDP.MKTP.KD.ZG?format=json&mrv=30 | BF36: Tier 3 | BG36: 2024-12-31 | BH36: providers=world_bank; fields=gdp_per_capita_ppp, gdp_growth
A37: it-milan | B37: Milan | C37: Italy | D37: Western, Northern, and Southern Europe | E37: primary | F37: provisional | G37: 39023.18 | J37: 330 | M37: =IF(OR($G37="",$H37="",$I37="",$J37="",$K37="",$L37="",$AL37="",$AM37=""),"",((($G37*(1-$AM37))-$H37-$I37-$J37-$K37-$L37)/$AL37)) | P37: =IF($O37<>"",$O37,$AN37) | S37: 102.95 | T37: 75.43 | U37: 21 | X37: 6.45 | AD37: 135.84 | AH37: 16491113 | AI37: =IFERROR(INDEX(Country_Context!$B$2:$B$64,MATCH($C37,Country_Context!$A$2:$A$64,0)),"") | AJ37: =IFERROR(INDEX(Country_Context!$C$2:$C$64,MATCH($C37,Country_Context!$A$2:$A$64,0)),"") | AK37: =IFERROR(INDEX(Country_Context!$D$2:$D$64,MATCH($C37,Country_Context!$A$2:$A$64,0)),"") | AL37: =IFERROR(INDEX(Country_Context!$E$2:$E$64,MATCH($C37,Country_Context!$A$2:$A$64,0)),"") | AM37: =IFERROR(INDEX(Country_Context!$F$2:$F$64,MATCH($C37,Country_Context!$A$2:$A$64,0)),"") | AN37: =IFERROR(INDEX(Country_Context!$G$2:$G$64,MATCH($C37,Country_Context!$A$2:$A$64,0)),"") | AO37: https://dati.comune.milano.it/dataset/edfe847d-05f1-4d25-ba44-283d22b1ec73/resource/76b54f5a-24a6-4f7f-a3a9-a6152d8da601/download/redditi_e_principali_variabili_irpef_su_base_comunale_csv_2023.csv | https://www.atm.it/en/ViaggiaConNoi/Abbonamenti/Pages/Tipologie.aspx | https://api.worldbank.org/v2/country/ITA/indicator/PA.NUS.PRVT.PP?format=json&mrv=30 | +2 more | AP37: Tier 1, Tier 3 | AQ37: 2026-03-12 | AR37: providers=comune_milano_open_data, atm_milano, world_bank; fields=gross_income, transit_cost, ppp_private_consumption, tax_rate_assumption; +1 additional fields | AS37: https://dati.comune.milano.it/dataset/34e2d2af-5c3b-4768-918b-ab7e5c0d15da/resource/8b03b9f2-f2d7-4408-b439-bc6efc093cff/download/ds564_reati_denunciati_2004_2023.csv | https://dati.comune.milano.it/dataset/0ac0f655-1858-410a-9873-70fd057ef65d/resource/39d6ef17-8882-49b6-b2de-dd4a8486d923/download/ds393_popolazione_pendolari_movimenti_interni_mezzo_tempo_orario_uscita_genere__2011c.csv | https://www.arpalombardia.it/agenda/notizie/2026/qualita-dell-aria-prosegue-il-miglioramento-anche-nell-anno-2025/ | AT37: Tier 1, Tier 2 | AU37: 2026-03-12 | AV37: providers=comune_milano_open_data, arpa_lombardia; fields=personal_safety_raw, transit_access_commute_raw, clean_air_raw | AW37: https://dati.comune.milano.it/dataset/71477d58-03a6-468b-81de-b168a264c82c/resource/7632c319-4a2a-4ab5-a39d-74d6ecc7323d/download/ds683_posti_letto_strutture_milano_010925_.csv | https://api.worldbank.org/v2/country/ITA/indicator/SI.POV.GINI?format=json&mrv=30 | AX37: Tier 1, Tier 3 | AY37: 2026-03-12 | AZ37: providers=comune_milano_open_data, world_bank; fields=healthcare_quality_raw, gini_coefficient | BE37: https://dati.comune.milano.it/dataset/8d8a4d19-0004-48a8-9425-e892deffde10/resource/68ebcbed-a736-4f0a-b654-17232b18deb0/download/ds691_imprese.csv | https://dati.comune.milano.it/dataset/645e64c2-0a51-4823-8a40-633cc162b4af/resource/89f7c6c4-fd98-4e5e-8e9a-041b92bac9d8/download/ds215_presenze_mensili-1.csv | https://api.worldbank.org/v2/country/ITA/indicator/NY.GDP.PCAP.PP.CD?format=json&mrv=30 | +1 more | BF37: Tier 1, Tier 3 | BG37: 2026-03-12 | BH37: providers=comune_milano_open_data, world_bank; fields=entrepreneurial_dynamism_raw, visitor_flow_context_raw, gdp_per_capita_ppp, gdp_growth
A38: at-graz | B38: Graz | C38: Austria | D38: Western, Northern, and Southern Europe | E38: secondary | F38: locked | M38: =IF(OR($G38="",$H38="",$I38="",$J38="",$K38="",$L38="",$AL38="",$AM38=""),"",((($G38*(1-$AM38))-$H38-$I38-$J38-$K38-$L38)/$AL38)) | P38: =IF($O38<>"",$O38,$AN38) | AI38: =IFERROR(INDEX(Country_Context!$B$2:$B$64,MATCH($C38,Country_Context!$A$2:$A$64,0)),"") | AJ38: =IFERROR(INDEX(Country_Context!$C$2:$C$64,MATCH($C38,Country_Context!$A$2:$A$64,0)),"") | AK38: =IFERROR(INDEX(Country_Context!$D$2:$D$64,MATCH($C38,Country_Context!$A$2:$A$64,0)),"") | AL38: =IFERROR(INDEX(Country_Context!$E$2:$E$64,MATCH($C38,Country_Context!$A$2:$A$64,0)),"") | AM38: =IFERROR(INDEX(Country_Context!$F$2:$F$64,MATCH($C38,Country_Context!$A$2:$A$64,0)),"") | AN38: =IFERROR(INDEX(Country_Context!$G$2:$G$64,MATCH($C38,Country_Context!$A$2:$A$64,0)),"") | AO38: https://api.worldbank.org/v2/country/AUT/indicator/PA.NUS.PRVT.PP?format=json&mrv=30 | https://api.worldbank.org/v2/country/AUT/indicator/GC.TAX.TOTL.GD.ZS?format=json&mrv=30 | https://api.worldbank.org/v2/country/AUT/indicator/FD.AST.PRVT.GD.ZS?format=json&mrv=30 | AP38: Tier 3 | AQ38: 2024-12-31 | AR38: providers=world_bank; fields=ppp_private_consumption, tax_rate_assumption, household_debt_proxy | AW38: https://api.worldbank.org/v2/country/AUT/indicator/SI.POV.GINI?format=json&mrv=30 | AX38: Tier 3 | AY38: 2023-12-31 | AZ38: providers=world_bank; fields=gini_coefficient | BE38: https://api.worldbank.org/v2/country/AUT/indicator/NY.GDP.PCAP.PP.CD?format=json&mrv=30 | https://api.worldbank.org/v2/country/AUT/indicator/NY.GDP.MKTP.KD.ZG?format=json&mrv=30 | BF38: Tier 3 | BG38: 2024-12-31 | BH38: providers=world_bank; fields=gdp_per_capita_ppp, gdp_growth
A39: pt-porto | B39: Porto | C39: Portugal | D39: Western, Northern, and Southern Europe | E39: secondary | F39: locked | M39: =IF(OR($G39="",$H39="",$I39="",$J39="",$K39="",$L39="",$AL39="",$AM39=""),"",((($G39*(1-$AM39))-$H39-$I39-$J39-$K39-$L39)/$AL39)) | P39: =IF($O39<>"",$O39,$AN39) | AI39: =IFERROR(INDEX(Country_Context!$B$2:$B$64,MATCH($C39,Country_Context!$A$2:$A$64,0)),"") | AJ39: =IFERROR(INDEX(Country_Context!$C$2:$C$64,MATCH($C39,Country_Context!$A$2:$A$64,0)),"") | AK39: =IFERROR(INDEX(Country_Context!$D$2:$D$64,MATCH($C39,Country_Context!$A$2:$A$64,0)),"") | AL39: =IFERROR(INDEX(Country_Context!$E$2:$E$64,MATCH($C39,Country_Context!$A$2:$A$64,0)),"") | AM39: =IFERROR(INDEX(Country_Context!$F$2:$F$64,MATCH($C39,Country_Context!$A$2:$A$64,0)),"") | AN39: =IFERROR(INDEX(Country_Context!$G$2:$G$64,MATCH($C39,Country_Context!$A$2:$A$64,0)),"") | AO39: https://api.worldbank.org/v2/country/PRT/indicator/PA.NUS.PRVT.PP?format=json&mrv=30 | https://api.worldbank.org/v2/country/PRT/indicator/GC.TAX.TOTL.GD.ZS?format=json&mrv=30 | https://api.worldbank.org/v2/country/PRT/indicator/FD.AST.PRVT.GD.ZS?format=json&mrv=30 | AP39: Tier 3 | AQ39: 2024-12-31 | AR39: providers=world_bank; fields=ppp_private_consumption, tax_rate_assumption, household_debt_proxy | AW39: https://api.worldbank.org/v2/country/PRT/indicator/SI.POV.GINI?format=json&mrv=30 | AX39: Tier 3 | AY39: 2023-12-31 | AZ39: providers=world_bank; fields=gini_coefficient | BE39: https://api.worldbank.org/v2/country/PRT/indicator/NY.GDP.PCAP.PP.CD?format=json&mrv=30 | https://api.worldbank.org/v2/country/PRT/indicator/NY.GDP.MKTP.KD.ZG?format=json&mrv=30 | BF39: Tier 3 | BG39: 2024-12-31 | BH39: providers=world_bank; fields=gdp_per_capita_ppp, gdp_growth
A40: pt-braga | B40: Braga | C40: Portugal | D40: Western, Northern, and Southern Europe | E40: secondary | F40: locked | M40: =IF(OR($G40="",$H40="",$I40="",$J40="",$K40="",$L40="",$AL40="",$AM40=""),"",((($G40*(1-$AM40))-$H40-$I40-$J40-$K40-$L40)/$AL40)) | P40: =IF($O40<>"",$O40,$AN40) | AI40: =IFERROR(INDEX(Country_Context!$B$2:$B$64,MATCH($C40,Country_Context!$A$2:$A$64,0)),"") | AJ40: =IFERROR(INDEX(Country_Context!$C$2:$C$64,MATCH($C40,Country_Context!$A$2:$A$64,0)),"") | AK40: =IFERROR(INDEX(Country_Context!$D$2:$D$64,MATCH($C40,Country_Context!$A$2:$A$64,0)),"") | AL40: =IFERROR(INDEX(Country_Context!$E$2:$E$64,MATCH($C40,Country_Context!$A$2:$A$64,0)),"") | AM40: =IFERROR(INDEX(Country_Context!$F$2:$F$64,MATCH($C40,Country_Context!$A$2:$A$64,0)),"") | AN40: =IFERROR(INDEX(Country_Context!$G$2:$G$64,MATCH($C40,Country_Context!$A$2:$A$64,0)),"") | AO40: https://api.worldbank.org/v2/country/PRT/indicator/PA.NUS.PRVT.PP?format=json&mrv=30 | https://api.worldbank.org/v2/country/PRT/indicator/GC.TAX.TOTL.GD.ZS?format=json&mrv=30 | https://api.worldbank.org/v2/country/PRT/indicator/FD.AST.PRVT.GD.ZS?format=json&mrv=30 | AP40: Tier 3 | AQ40: 2024-12-31 | AR40: providers=world_bank; fields=ppp_private_consumption, tax_rate_assumption, household_debt_proxy | AW40: https://api.worldbank.org/v2/country/PRT/indicator/SI.POV.GINI?format=json&mrv=30 | AX40: Tier 3 | AY40: 2023-12-31 | AZ40: providers=world_bank; fields=gini_coefficient | BE40: https://api.worldbank.org/v2/country/PRT/indicator/NY.GDP.PCAP.PP.CD?format=json&mrv=30 | https://api.worldbank.org/v2/country/PRT/indicator/NY.GDP.MKTP.KD.ZG?format=json&mrv=30 | BF40: Tier 3 | BG40: 2024-12-31 | BH40: providers=world_bank; fields=gdp_per_capita_ppp, gdp_growth
A41: ee-tallinn | B41: Tallinn | C41: Estonia | D41: Western, Northern, and Southern Europe | E41: secondary | F41: locked | M41: =IF(OR($G41="",$H41="",$I41="",$J41="",$K41="",$L41="",$AL41="",$AM41=""),"",((($G41*(1-$AM41))-$H41-$I41-$J41-$K41-$L41)/$AL41)) | P41: =IF($O41<>"",$O41,$AN41) | AI41: =IFERROR(INDEX(Country_Context!$B$2:$B$64,MATCH($C41,Country_Context!$A$2:$A$64,0)),"") | AJ41: =IFERROR(INDEX(Country_Context!$C$2:$C$64,MATCH($C41,Country_Context!$A$2:$A$64,0)),"") | AK41: =IFERROR(INDEX(Country_Context!$D$2:$D$64,MATCH($C41,Country_Context!$A$2:$A$64,0)),"") | AL41: =IFERROR(INDEX(Country_Context!$E$2:$E$64,MATCH($C41,Country_Context!$A$2:$A$64,0)),"") | AM41: =IFERROR(INDEX(Country_Context!$F$2:$F$64,MATCH($C41,Country_Context!$A$2:$A$64,0)),"") | AN41: =IFERROR(INDEX(Country_Context!$G$2:$G$64,MATCH($C41,Country_Context!$A$2:$A$64,0)),"") | AO41: https://api.worldbank.org/v2/country/EST/indicator/PA.NUS.PRVT.PP?format=json&mrv=30 | https://api.worldbank.org/v2/country/EST/indicator/GC.TAX.TOTL.GD.ZS?format=json&mrv=30 | https://api.worldbank.org/v2/country/EST/indicator/FD.AST.PRVT.GD.ZS?format=json&mrv=30 | AP41: Tier 3 | AQ41: 2024-12-31 | AR41: providers=world_bank; fields=ppp_private_consumption, tax_rate_assumption, household_debt_proxy | AW41: https://api.worldbank.org/v2/country/EST/indicator/SI.POV.GINI?format=json&mrv=30 | AX41: Tier 3 | AY41: 2023-12-31 | AZ41: providers=world_bank; fields=gini_coefficient | BE41: https://api.worldbank.org/v2/country/EST/indicator/NY.GDP.PCAP.PP.CD?format=json&mrv=30 | https://api.worldbank.org/v2/country/EST/indicator/NY.GDP.MKTP.KD.ZG?format=json&mrv=30 | BF41: Tier 3 | BG41: 2024-12-31 | BH41: providers=world_bank; fields=gdp_per_capita_ppp, gdp_growth
A42: fi-helsinki | B42: Helsinki | C42: Finland | D42: Western, Northern, and Southern Europe | E42: secondary | F42: provisional | M42: =IF(OR($G42="",$H42="",$I42="",$J42="",$K42="",$L42="",$AL42="",$AM42=""),"",((($G42*(1-$AM42))-$H42-$I42-$J42-$K42-$L42)/$AL42)) | P42: =IF($O42<>"",$O42,$AN42) | AI42: =IFERROR(INDEX(Country_Context!$B$2:$B$64,MATCH($C42,Country_Context!$A$2:$A$64,0)),"") | AJ42: =IFERROR(INDEX(Country_Context!$C$2:$C$64,MATCH($C42,Country_Context!$A$2:$A$64,0)),"") | AK42: =IFERROR(INDEX(Country_Context!$D$2:$D$64,MATCH($C42,Country_Context!$A$2:$A$64,0)),"") | AL42: =IFERROR(INDEX(Country_Context!$E$2:$E$64,MATCH($C42,Country_Context!$A$2:$A$64,0)),"") | AM42: =IFERROR(INDEX(Country_Context!$F$2:$F$64,MATCH($C42,Country_Context!$A$2:$A$64,0)),"") | AN42: =IFERROR(INDEX(Country_Context!$G$2:$G$64,MATCH($C42,Country_Context!$A$2:$A$64,0)),"") | AO42: https://api.worldbank.org/v2/country/FIN/indicator/PA.NUS.PRVT.PP?format=json&mrv=30 | https://api.worldbank.org/v2/country/FIN/indicator/GC.TAX.TOTL.GD.ZS?format=json&mrv=30 | https://api.worldbank.org/v2/country/FIN/indicator/FD.AST.PRVT.GD.ZS?format=json&mrv=30 | AP42: Tier 3 | AQ42: 2024-12-31 | AR42: providers=world_bank; fields=ppp_private_consumption, tax_rate_assumption, household_debt_proxy | AW42: https://api.worldbank.org/v2/country/FIN/indicator/SI.POV.GINI?format=json&mrv=30 | AX42: Tier 3 | AY42: 2023-12-31 | AZ42: providers=world_bank; fields=gini_coefficient | BE42: https://api.worldbank.org/v2/country/FIN/indicator/NY.GDP.PCAP.PP.CD?format=json&mrv=30 | https://api.worldbank.org/v2/country/FIN/indicator/NY.GDP.MKTP.KD.ZG?format=json&mrv=30 | BF42: Tier 3 | BG42: 2024-12-31 | BH42: providers=world_bank; fields=gdp_per_capita_ppp, gdp_growth
A43: it-bologna | B43: Bologna | C43: Italy | D43: Western, Northern, and Southern Europe | E43: secondary | F43: provisional | M43: =IF(OR($G43="",$H43="",$I43="",$J43="",$K43="",$L43="",$AL43="",$AM43=""),"",((($G43*(1-$AM43))-$H43-$I43-$J43-$K43-$L43)/$AL43)) | P43: =IF($O43<>"",$O43,$AN43) | AI43: =IFERROR(INDEX(Country_Context!$B$2:$B$64,MATCH($C43,Country_Context!$A$2:$A$64,0)),"") | AJ43: =IFERROR(INDEX(Country_Context!$C$2:$C$64,MATCH($C43,Country_Context!$A$2:$A$64,0)),"") | AK43: =IFERROR(INDEX(Country_Context!$D$2:$D$64,MATCH($C43,Country_Context!$A$2:$A$64,0)),"") | AL43: =IFERROR(INDEX(Country_Context!$E$2:$E$64,MATCH($C43,Country_Context!$A$2:$A$64,0)),"") | AM43: =IFERROR(INDEX(Country_Context!$F$2:$F$64,MATCH($C43,Country_Context!$A$2:$A$64,0)),"") | AN43: =IFERROR(INDEX(Country_Context!$G$2:$G$64,MATCH($C43,Country_Context!$A$2:$A$64,0)),"") | AO43: https://api.worldbank.org/v2/country/ITA/indicator/PA.NUS.PRVT.PP?format=json&mrv=30 | https://api.worldbank.org/v2/country/ITA/indicator/GC.TAX.TOTL.GD.ZS?format=json&mrv=30 | https://api.worldbank.org/v2/country/ITA/indicator/FD.AST.PRVT.GD.ZS?format=json&mrv=30 | AP43: Tier 3 | AQ43: 2024-12-31 | AR43: providers=world_bank; fields=ppp_private_consumption, tax_rate_assumption, household_debt_proxy | AW43: https://api.worldbank.org/v2/country/ITA/indicator/SI.POV.GINI?format=json&mrv=30 | AX43: Tier 3 | AY43: 2023-12-31 | AZ43: providers=world_bank; fields=gini_coefficient | BE43: https://api.worldbank.org/v2/country/ITA/indicator/NY.GDP.PCAP.PP.CD?format=json&mrv=30 | https://api.worldbank.org/v2/country/ITA/indicator/NY.GDP.MKTP.KD.ZG?format=json&mrv=30 | BF43: Tier 3 | BG43: 2024-12-31 | BH43: providers=world_bank; fields=gdp_per_capita_ppp, gdp_growth
A44: ru-moscow | B44: Moscow | C44: Russia | D44: Southern/Eastern Europe and Eurasia | E44: primary | F44: locked | M44: =IF(OR($G44="",$H44="",$I44="",$J44="",$K44="",$L44="",$AL44="",$AM44=""),"",((($G44*(1-$AM44))-$H44-$I44-$J44-$K44-$L44)/$AL44)) | P44: =IF($O44<>"",$O44,$AN44) | AI44: =IFERROR(INDEX(Country_Context!$B$2:$B$64,MATCH($C44,Country_Context!$A$2:$A$64,0)),"") | AJ44: =IFERROR(INDEX(Country_Context!$C$2:$C$64,MATCH($C44,Country_Context!$A$2:$A$64,0)),"") | AK44: =IFERROR(INDEX(Country_Context!$D$2:$D$64,MATCH($C44,Country_Context!$A$2:$A$64,0)),"") | AL44: =IFERROR(INDEX(Country_Context!$E$2:$E$64,MATCH($C44,Country_Context!$A$2:$A$64,0)),"") | AM44: =IFERROR(INDEX(Country_Context!$F$2:$F$64,MATCH($C44,Country_Context!$A$2:$A$64,0)),"") | AN44: =IFERROR(INDEX(Country_Context!$G$2:$G$64,MATCH($C44,Country_Context!$A$2:$A$64,0)),"") | AO44: https://api.worldbank.org/v2/country/RUS/indicator/PA.NUS.PRVT.PP?format=json&mrv=30 | https://api.worldbank.org/v2/country/RUS/indicator/GC.TAX.TOTL.GD.ZS?format=json&mrv=30 | https://api.worldbank.org/v2/country/RUS/indicator/FD.AST.PRVT.GD.ZS?format=json&mrv=30 | AP44: Tier 3 | AQ44: 2024-12-31 | AR44: providers=world_bank; fields=ppp_private_consumption, tax_rate_assumption, household_debt_proxy | AW44: https://api.worldbank.org/v2/country/RUS/indicator/SI.POV.GINI?format=json&mrv=30 | AX44: Tier 3 | AY44: 2023-12-31 | AZ44: providers=world_bank; fields=gini_coefficient | BE44: https://api.worldbank.org/v2/country/RUS/indicator/NY.GDP.PCAP.PP.CD?format=json&mrv=30 | https://api.worldbank.org/v2/country/RUS/indicator/NY.GDP.MKTP.KD.ZG?format=json&mrv=30 | BF44: Tier 3 | BG44: 2024-12-31 | BH44: providers=world_bank; fields=gdp_per_capita_ppp, gdp_growth
A45: hu-budapest | B45: Budapest | C45: Hungary | D45: Southern/Eastern Europe and Eurasia | E45: primary | F45: locked | M45: =IF(OR($G45="",$H45="",$I45="",$J45="",$K45="",$L45="",$AL45="",$AM45=""),"",((($G45*(1-$AM45))-$H45-$I45-$J45-$K45-$L45)/$AL45)) | P45: =IF($O45<>"",$O45,$AN45) | AI45: =IFERROR(INDEX(Country_Context!$B$2:$B$64,MATCH($C45,Country_Context!$A$2:$A$64,0)),"") | AJ45: =IFERROR(INDEX(Country_Context!$C$2:$C$64,MATCH($C45,Country_Context!$A$2:$A$64,0)),"") | AK45: =IFERROR(INDEX(Country_Context!$D$2:$D$64,MATCH($C45,Country_Context!$A$2:$A$64,0)),"") | AL45: =IFERROR(INDEX(Country_Context!$E$2:$E$64,MATCH($C45,Country_Context!$A$2:$A$64,0)),"") | AM45: =IFERROR(INDEX(Country_Context!$F$2:$F$64,MATCH($C45,Country_Context!$A$2:$A$64,0)),"") | AN45: =IFERROR(INDEX(Country_Context!$G$2:$G$64,MATCH($C45,Country_Context!$A$2:$A$64,0)),"") | AO45: https://api.worldbank.org/v2/country/HUN/indicator/PA.NUS.PRVT.PP?format=json&mrv=30 | https://api.worldbank.org/v2/country/HUN/indicator/GC.TAX.TOTL.GD.ZS?format=json&mrv=30 | https://api.worldbank.org/v2/country/HUN/indicator/FD.AST.PRVT.GD.ZS?format=json&mrv=30 | AP45: Tier 3 | AQ45: 2024-12-31 | AR45: providers=world_bank; fields=ppp_private_consumption, tax_rate_assumption, household_debt_proxy | AW45: https://api.worldbank.org/v2/country/HUN/indicator/SI.POV.GINI?format=json&mrv=30 | AX45: Tier 3 | AY45: 2017-12-31 | AZ45: providers=world_bank; fields=gini_coefficient | BE45: https://api.worldbank.org/v2/country/HUN/indicator/NY.GDP.PCAP.PP.CD?format=json&mrv=30 | https://api.worldbank.org/v2/country/HUN/indicator/NY.GDP.MKTP.KD.ZG?format=json&mrv=30 | BF45: Tier 3 | BG45: 2024-12-31 | BH45: providers=world_bank; fields=gdp_per_capita_ppp, gdp_growth
A46: pl-krakow | B46: Krakow | C46: Poland | D46: Southern/Eastern Europe and Eurasia | E46: primary | F46: locked | M46: =IF(OR($G46="",$H46="",$I46="",$J46="",$K46="",$L46="",$AL46="",$AM46=""),"",((($G46*(1-$AM46))-$H46-$I46-$J46-$K46-$L46)/$AL46)) | P46: =IF($O46<>"",$O46,$AN46) | AI46: =IFERROR(INDEX(Country_Context!$B$2:$B$64,MATCH($C46,Country_Context!$A$2:$A$64,0)),"") | AJ46: =IFERROR(INDEX(Country_Context!$C$2:$C$64,MATCH($C46,Country_Context!$A$2:$A$64,0)),"") | AK46: =IFERROR(INDEX(Country_Context!$D$2:$D$64,MATCH($C46,Country_Context!$A$2:$A$64,0)),"") | AL46: =IFERROR(INDEX(Country_Context!$E$2:$E$64,MATCH($C46,Country_Context!$A$2:$A$64,0)),"") | AM46: =IFERROR(INDEX(Country_Context!$F$2:$F$64,MATCH($C46,Country_Context!$A$2:$A$64,0)),"") | AN46: =IFERROR(INDEX(Country_Context!$G$2:$G$64,MATCH($C46,Country_Context!$A$2:$A$64,0)),"") | AO46: https://api.worldbank.org/v2/country/POL/indicator/PA.NUS.PRVT.PP?format=json&mrv=30 | https://api.worldbank.org/v2/country/POL/indicator/GC.TAX.TOTL.GD.ZS?format=json&mrv=30 | https://api.worldbank.org/v2/country/POL/indicator/FD.AST.PRVT.GD.ZS?format=json&mrv=30 | AP46: Tier 3 | AQ46: 2024-12-31 | AR46: providers=world_bank; fields=ppp_private_consumption, tax_rate_assumption, household_debt_proxy | AW46: https://api.worldbank.org/v2/country/POL/indicator/SI.POV.GINI?format=json&mrv=30 | AX46: Tier 3 | AY46: 2023-12-31 | AZ46: providers=world_bank; fields=gini_coefficient | BE46: https://api.worldbank.org/v2/country/POL/indicator/NY.GDP.PCAP.PP.CD?format=json&mrv=30 | https://api.worldbank.org/v2/country/POL/indicator/NY.GDP.MKTP.KD.ZG?format=json&mrv=30 | BF46: Tier 3 | BG46: 2024-12-31 | BH46: providers=world_bank; fields=gdp_per_capita_ppp, gdp_growth
A47: ro-bucharest | B47: Bucharest | C47: Romania | D47: Southern/Eastern Europe and Eurasia | E47: primary | F47: locked | M47: =IF(OR($G47="",$H47="",$I47="",$J47="",$K47="",$L47="",$AL47="",$AM47=""),"",((($G47*(1-$AM47))-$H47-$I47-$J47-$K47-$L47)/$AL47)) | P47: =IF($O47<>"",$O47,$AN47) | AI47: =IFERROR(INDEX(Country_Context!$B$2:$B$64,MATCH($C47,Country_Context!$A$2:$A$64,0)),"") | AJ47: =IFERROR(INDEX(Country_Context!$C$2:$C$64,MATCH($C47,Country_Context!$A$2:$A$64,0)),"") | AK47: =IFERROR(INDEX(Country_Context!$D$2:$D$64,MATCH($C47,Country_Context!$A$2:$A$64,0)),"") | AL47: =IFERROR(INDEX(Country_Context!$E$2:$E$64,MATCH($C47,Country_Context!$A$2:$A$64,0)),"") | AM47: =IFERROR(INDEX(Country_Context!$F$2:$F$64,MATCH($C47,Country_Context!$A$2:$A$64,0)),"") | AN47: =IFERROR(INDEX(Country_Context!$G$2:$G$64,MATCH($C47,Country_Context!$A$2:$A$64,0)),"") | AO47: https://api.worldbank.org/v2/country/ROU/indicator/PA.NUS.PRVT.PP?format=json&mrv=30 | https://api.worldbank.org/v2/country/ROU/indicator/GC.TAX.TOTL.GD.ZS?format=json&mrv=30 | https://api.worldbank.org/v2/country/ROU/indicator/FD.AST.PRVT.GD.ZS?format=json&mrv=30 | AP47: Tier 3 | AQ47: 2024-12-31 | AR47: providers=world_bank; fields=ppp_private_consumption, tax_rate_assumption, household_debt_proxy | AW47: https://api.worldbank.org/v2/country/ROU/indicator/SI.POV.GINI?format=json&mrv=30 | AX47: Tier 3 | AY47: 2023-12-31 | AZ47: providers=world_bank; fields=gini_coefficient | BE47: https://api.worldbank.org/v2/country/ROU/indicator/NY.GDP.PCAP.PP.CD?format=json&mrv=30 | https://api.worldbank.org/v2/country/ROU/indicator/NY.GDP.MKTP.KD.ZG?format=json&mrv=30 | BF47: Tier 3 | BG47: 2024-12-31 | BH47: providers=world_bank; fields=gdp_per_capita_ppp, gdp_growth
A48: rs-belgrade | B48: Belgrade | C48: Serbia | D48: Southern/Eastern Europe and Eurasia | E48: primary | F48: locked | M48: =IF(OR($G48="",$H48="",$I48="",$J48="",$K48="",$L48="",$AL48="",$AM48=""),"",((($G48*(1-$AM48))-$H48-$I48-$J48-$K48-$L48)/$AL48)) | P48: =IF($O48<>"",$O48,$AN48) | AI48: =IFERROR(INDEX(Country_Context!$B$2:$B$64,MATCH($C48,Country_Context!$A$2:$A$64,0)),"") | AJ48: =IFERROR(INDEX(Country_Context!$C$2:$C$64,MATCH($C48,Country_Context!$A$2:$A$64,0)),"") | AK48: =IFERROR(INDEX(Country_Context!$D$2:$D$64,MATCH($C48,Country_Context!$A$2:$A$64,0)),"") | AL48: =IFERROR(INDEX(Country_Context!$E$2:$E$64,MATCH($C48,Country_Context!$A$2:$A$64,0)),"") | AM48: =IFERROR(INDEX(Country_Context!$F$2:$F$64,MATCH($C48,Country_Context!$A$2:$A$64,0)),"") | AN48: =IFERROR(INDEX(Country_Context!$G$2:$G$64,MATCH($C48,Country_Context!$A$2:$A$64,0)),"") | AO48: https://api.worldbank.org/v2/country/SRB/indicator/PA.NUS.PRVT.PP?format=json&mrv=30 | https://api.worldbank.org/v2/country/SRB/indicator/GC.TAX.TOTL.GD.ZS?format=json&mrv=30 | https://api.worldbank.org/v2/country/SRB/indicator/FD.AST.PRVT.GD.ZS?format=json&mrv=30 | AP48: Tier 3 | AQ48: 2024-12-31 | AR48: providers=world_bank; fields=ppp_private_consumption, tax_rate_assumption, household_debt_proxy | AW48: https://api.worldbank.org/v2/country/SRB/indicator/SI.POV.GINI?format=json&mrv=30 | AX48: Tier 3 | AY48: 2022-12-31 | AZ48: providers=world_bank; fields=gini_coefficient | BE48: https://api.worldbank.org/v2/country/SRB/indicator/NY.GDP.PCAP.PP.CD?format=json&mrv=30 | https://api.worldbank.org/v2/country/SRB/indicator/NY.GDP.MKTP.KD.ZG?format=json&mrv=30 | BF48: Tier 3 | BG48: 2024-12-31 | BH48: providers=world_bank; fields=gdp_per_capita_ppp, gdp_growth
A49: ru-nizhny-novgorod | B49: Nizhny Novgorod | C49: Russia | D49: Southern/Eastern Europe and Eurasia | E49: secondary | F49: provisional | M49: =IF(OR($G49="",$H49="",$I49="",$J49="",$K49="",$L49="",$AL49="",$AM49=""),"",((($G49*(1-$AM49))-$H49-$I49-$J49-$K49-$L49)/$AL49)) | P49: =IF($O49<>"",$O49,$AN49) | AI49: =IFERROR(INDEX(Country_Context!$B$2:$B$64,MATCH($C49,Country_Context!$A$2:$A$64,0)),"") | AJ49: =IFERROR(INDEX(Country_Context!$C$2:$C$64,MATCH($C49,Country_Context!$A$2:$A$64,0)),"") | AK49: =IFERROR(INDEX(Country_Context!$D$2:$D$64,MATCH($C49,Country_Context!$A$2:$A$64,0)),"") | AL49: =IFERROR(INDEX(Country_Context!$E$2:$E$64,MATCH($C49,Country_Context!$A$2:$A$64,0)),"") | AM49: =IFERROR(INDEX(Country_Context!$F$2:$F$64,MATCH($C49,Country_Context!$A$2:$A$64,0)),"") | AN49: =IFERROR(INDEX(Country_Context!$G$2:$G$64,MATCH($C49,Country_Context!$A$2:$A$64,0)),"") | AO49: https://api.worldbank.org/v2/country/RUS/indicator/PA.NUS.PRVT.PP?format=json&mrv=30 | https://api.worldbank.org/v2/country/RUS/indicator/GC.TAX.TOTL.GD.ZS?format=json&mrv=30 | https://api.worldbank.org/v2/country/RUS/indicator/FD.AST.PRVT.GD.ZS?format=json&mrv=30 | AP49: Tier 3 | AQ49: 2024-12-31 | AR49: providers=world_bank; fields=ppp_private_consumption, tax_rate_assumption, household_debt_proxy | AW49: https://api.worldbank.org/v2/country/RUS/indicator/SI.POV.GINI?format=json&mrv=30 | AX49: Tier 3 | AY49: 2023-12-31 | AZ49: providers=world_bank; fields=gini_coefficient | BE49: https://api.worldbank.org/v2/country/RUS/indicator/NY.GDP.PCAP.PP.CD?format=json&mrv=30 | https://api.worldbank.org/v2/country/RUS/indicator/NY.GDP.MKTP.KD.ZG?format=json&mrv=30 | BF49: Tier 3 | BG49: 2024-12-31 | BH49: providers=world_bank; fields=gdp_per_capita_ppp, gdp_growth
... A61: mx-guadalajara | B61: Guadalajara | C61: Mexico | D61: North America | E61: secondary | F61: locked | M61: =IF(OR($G61="",$H61="",$I61="",$J61="",$K61="",$L61="",$AL61="",$AM61=""),"",((($G61*(1-$AM61))-$H61-$I61-$J61-$K61-$L61)/$AL61)) | P61: =IF($O61<>"",$O61,$AN61) | AI61: =IFERROR(INDEX(Country_Context!$B$2:$B$64,MATCH($C61,Country_Context!$A$2:$A$64,0)),"") | AJ61: =IFERROR(INDEX(Country_Context!$C$2:$C$64,MATCH($C61,Country_Context!$A$2:$A$64,0)),"") | AK61: =IFERROR(INDEX(Country_Context!$D$2:$D$64,MATCH($C61,Country_Context!$A$2:$A$64,0)),"") | AL61: =IFERROR(INDEX(Country_Context!$E$2:$E$64,MATCH($C61,Country_Context!$A$2:$A$64,0)),"") | AM61: =IFERROR(INDEX(Country_Context!$F$2:$F$64,MATCH($C61,Country_Context!$A$2:$A$64,0)),"") | AN61: =IFERROR(INDEX(Country_Context!$G$2:$G$64,MATCH($C61,Country_Context!$A$2:$A$64,0)),"") | AO61: https://api.worldbank.org/v2/country/MEX/indicator/PA.NUS.PRVT.PP?format=json&mrv=30 | https://api.worldbank.org/v2/country/MEX/indicator/GC.TAX.TOTL.GD.ZS?format=json&mrv=30 | https://api.worldbank.org/v2/country/MEX/indicator/FD.AST.PRVT.GD.ZS?format=json&mrv=30 | AP61: Tier 3 | AQ61: 2024-12-31 | AR61: providers=world_bank; fields=ppp_private_consumption, tax_rate_assumption, household_debt_proxy | AW61: https://api.worldbank.org/v2/country/MEX/indicator/SI.POV.GINI?format=json&mrv=30 | AX61: Tier 3 | AY61: 2022-12-31 | AZ61: providers=world_bank; fields=gini_coefficient | BE61: https://api.worldbank.org/v2/country/MEX/indicator/NY.GDP.PCAP.PP.CD?format=json&mrv=30 | https://api.worldbank.org/v2/country/MEX/indicator/NY.GDP.MKTP.KD.ZG?format=json&mrv=30 | BF61: Tier 3 | BG61: 2024-12-31 | BH61: providers=world_bank; fields=gdp_per_capita_ppp, gdp_growth
A62: pr-san-juan | B62: San Juan | C62: Puerto Rico | D62: North America | E62: secondary | F62: provisional | M62: =IF(OR($G62="",$H62="",$I62="",$J62="",$K62="",$L62="",$AL62="",$AM62=""),"",((($G62*(1-$AM62))-$H62-$I62-$J62-$K62-$L62)/$AL62)) | P62: =IF($O62<>"",$O62,$AN62) | AI62: =IFERROR(INDEX(Country_Context!$B$2:$B$64,MATCH($C62,Country_Context!$A$2:$A$64,0)),"") | AJ62: =IFERROR(INDEX(Country_Context!$C$2:$C$64,MATCH($C62,Country_Context!$A$2:$A$64,0)),"") | AK62: =IFERROR(INDEX(Country_Context!$D$2:$D$64,MATCH($C62,Country_Context!$A$2:$A$64,0)),"") | AL62: =IFERROR(INDEX(Country_Context!$E$2:$E$64,MATCH($C62,Country_Context!$A$2:$A$64,0)),"") | AM62: =IFERROR(INDEX(Country_Context!$F$2:$F$64,MATCH($C62,Country_Context!$A$2:$A$64,0)),"") | AN62: =IFERROR(INDEX(Country_Context!$G$2:$G$64,MATCH($C62,Country_Context!$A$2:$A$64,0)),"") | AO62: https://api.worldbank.org/v2/country/PRI/indicator/PA.NUS.PRVT.PP?format=json&mrv=30 | AP62: Tier 3 | AQ62: 2021-12-31 | AR62: providers=world_bank; fields=ppp_private_consumption | BE62: https://api.worldbank.org/v2/country/PRI/indicator/NY.GDP.PCAP.PP.CD?format=json&mrv=30 | https://api.worldbank.org/v2/country/PRI/indicator/NY.GDP.MKTP.KD.ZG?format=json&mrv=30 | BF62: Tier 3 | BG62: 2024-12-31 | BH62: providers=world_bank; fields=gdp_per_capita_ppp, gdp_growth
A63: mx-merida | B63: Merida | C63: Mexico | D63: North America | E63: secondary | F63: provisional | M63: =IF(OR($G63="",$H63="",$I63="",$J63="",$K63="",$L63="",$AL63="",$AM63=""),"",((($G63*(1-$AM63))-$H63-$I63-$J63-$K63-$L63)/$AL63)) | P63: =IF($O63<>"",$O63,$AN63) | AI63: =IFERROR(INDEX(Country_Context!$B$2:$B$64,MATCH($C63,Country_Context!$A$2:$A$64,0)),"") | AJ63: =IFERROR(INDEX(Country_Context!$C$2:$C$64,MATCH($C63,Country_Context!$A$2:$A$64,0)),"") | AK63: =IFERROR(INDEX(Country_Context!$D$2:$D$64,MATCH($C63,Country_Context!$A$2:$A$64,0)),"") | AL63: =IFERROR(INDEX(Country_Context!$E$2:$E$64,MATCH($C63,Country_Context!$A$2:$A$64,0)),"") | AM63: =IFERROR(INDEX(Country_Context!$F$2:$F$64,MATCH($C63,Country_Context!$A$2:$A$64,0)),"") | AN63: =IFERROR(INDEX(Country_Context!$G$2:$G$64,MATCH($C63,Country_Context!$A$2:$A$64,0)),"") | AO63: https://api.worldbank.org/v2/country/MEX/indicator/PA.NUS.PRVT.PP?format=json&mrv=30 | https://api.worldbank.org/v2/country/MEX/indicator/GC.TAX.TOTL.GD.ZS?format=json&mrv=30 | https://api.worldbank.org/v2/country/MEX/indicator/FD.AST.PRVT.GD.ZS?format=json&mrv=30 | AP63: Tier 3 | AQ63: 2024-12-31 | AR63: providers=world_bank; fields=ppp_private_consumption, tax_rate_assumption, household_debt_proxy | AW63: https://api.worldbank.org/v2/country/MEX/indicator/SI.POV.GINI?format=json&mrv=30 | AX63: Tier 3 | AY63: 2022-12-31 | AZ63: providers=world_bank; fields=gini_coefficient | BE63: https://api.worldbank.org/v2/country/MEX/indicator/NY.GDP.PCAP.PP.CD?format=json&mrv=30 | https://api.worldbank.org/v2/country/MEX/indicator/NY.GDP.MKTP.KD.ZG?format=json&mrv=30 | BF63: Tier 3 | BG63: 2024-12-31 | BH63: providers=world_bank; fields=gdp_per_capita_ppp, gdp_growth
A64: br-sao-paulo | B64: Sao Paulo | C64: Brazil | D64: Latin America | E64: primary | F64: locked | M64: =IF(OR($G64="",$H64="",$I64="",$J64="",$K64="",$L64="",$AL64="",$AM64=""),"",((($G64*(1-$AM64))-$H64-$I64-$J64-$K64-$L64)/$AL64)) | P64: =IF($O64<>"",$O64,$AN64) | AI64: =IFERROR(INDEX(Country_Context!$B$2:$B$64,MATCH($C64,Country_Context!$A$2:$A$64,0)),"") | AJ64: =IFERROR(INDEX(Country_Context!$C$2:$C$64,MATCH($C64,Country_Context!$A$2:$A$64,0)),"") | AK64: =IFERROR(INDEX(Country_Context!$D$2:$D$64,MATCH($C64,Country_Context!$A$2:$A$64,0)),"") | AL64: =IFERROR(INDEX(Country_Context!$E$2:$E$64,MATCH($C64,Country_Context!$A$2:$A$64,0)),"") | AM64: =IFERROR(INDEX(Country_Context!$F$2:$F$64,MATCH($C64,Country_Context!$A$2:$A$64,0)),"") | AN64: =IFERROR(INDEX(Country_Context!$G$2:$G$64,MATCH($C64,Country_Context!$A$2:$A$64,0)),"") | AO64: https://api.worldbank.org/v2/country/BRA/indicator/PA.NUS.PRVT.PP?format=json&mrv=30 | https://api.worldbank.org/v2/country/BRA/indicator/GC.TAX.TOTL.GD.ZS?format=json&mrv=30 | https://api.worldbank.org/v2/country/BRA/indicator/FD.AST.PRVT.GD.ZS?format=json&mrv=30 | AP64: Tier 3 | AQ64: 2024-12-31 | AR64: providers=world_bank; fields=ppp_private_consumption, tax_rate_assumption, household_debt_proxy | AW64: https://api.worldbank.org/v2/country/BRA/indicator/SI.POV.GINI?format=json&mrv=30 | AX64: Tier 3 | AY64: 2023-12-31 | AZ64: providers=world_bank; fields=gini_coefficient | BE64: https://api.worldbank.org/v2/country/BRA/indicator/NY.GDP.PCAP.PP.CD?format=json&mrv=30 | https://api.worldbank.org/v2/country/BRA/indicator/NY.GDP.MKTP.KD.ZG?format=json&mrv=30 | BF64: Tier 3 | BG64: 2024-12-31 | BH64: providers=world_bank; fields=gdp_per_capita_ppp, gdp_growth
A65: ar-buenos-aires | B65: Buenos Aires | C65: Argentina | D65: Latin America | E65: primary | F65: locked | M65: =IF(OR($G65="",$H65="",$I65="",$J65="",$K65="",$L65="",$AL65="",$AM65=""),"",((($G65*(1-$AM65))-$H65-$I65-$J65-$K65-$L65)/$AL65)) | P65: =IF($O65<>"",$O65,$AN65) | AI65: =IFERROR(INDEX(Country_Context!$B$2:$B$64,MATCH($C65,Country_Context!$A$2:$A$64,0)),"") | AJ65: =IFERROR(INDEX(Country_Context!$C$2:$C$64,MATCH($C65,Country_Context!$A$2:$A$64,0)),"") | AK65: =IFERROR(INDEX(Country_Context!$D$2:$D$64,MATCH($C65,Country_Context!$A$2:$A$64,0)),"") | AL65: =IFERROR(INDEX(Country_Context!$E$2:$E$64,MATCH($C65,Country_Context!$A$2:$A$64,0)),"") | AM65: =IFERROR(INDEX(Country_Context!$F$2:$F$64,MATCH($C65,Country_Context!$A$2:$A$64,0)),"") | AN65: =IFERROR(INDEX(Country_Context!$G$2:$G$64,MATCH($C65,Country_Context!$A$2:$A$64,0)),"") | AO65: https://api.worldbank.org/v2/country/ARG/indicator/PA.NUS.PRVT.PP?format=json&mrv=30 | https://api.worldbank.org/v2/country/ARG/indicator/GC.TAX.TOTL.GD.ZS?format=json&mrv=30 | https://api.worldbank.org/v2/country/ARG/indicator/FD.AST.PRVT.GD.ZS?format=json&mrv=30 | AP65: Tier 3 | AQ65: 2024-12-31 | AR65: providers=world_bank; fields=ppp_private_consumption, tax_rate_assumption, household_debt_proxy | AW65: https://api.worldbank.org/v2/country/ARG/indicator/SI.POV.GINI?format=json&mrv=30 | AX65: Tier 3 | AY65: 2024-12-31 | AZ65: providers=world_bank; fields=gini_coefficient | BE65: https://api.worldbank.org/v2/country/ARG/indicator/NY.GDP.PCAP.PP.CD?format=json&mrv=30 | https://api.worldbank.org/v2/country/ARG/indicator/NY.GDP.MKTP.KD.ZG?format=json&mrv=30 | BF65: Tier 3 | BG65: 2024-12-31 | BH65: providers=world_bank; fields=gdp_per_capita_ppp, gdp_growth
A66: cl-santiago | B66: Santiago | C66: Chile | D66: Latin America | E66: primary | F66: locked | M66: =IF(OR($G66="",$H66="",$I66="",$J66="",$K66="",$L66="",$AL66="",$AM66=""),"",((($G66*(1-$AM66))-$H66-$I66-$J66-$K66-$L66)/$AL66)) | P66: =IF($O66<>"",$O66,$AN66) | AI66: =IFERROR(INDEX(Country_Context!$B$2:$B$64,MATCH($C66,Country_Context!$A$2:$A$64,0)),"") | AJ66: =IFERROR(INDEX(Country_Context!$C$2:$C$64,MATCH($C66,Country_Context!$A$2:$A$64,0)),"") | AK66: =IFERROR(INDEX(Country_Context!$D$2:$D$64,MATCH($C66,Country_Context!$A$2:$A$64,0)),"") | AL66: =IFERROR(INDEX(Country_Context!$E$2:$E$64,MATCH($C66,Country_Context!$A$2:$A$64,0)),"") | AM66: =IFERROR(INDEX(Country_Context!$F$2:$F$64,MATCH($C66,Country_Context!$A$2:$A$64,0)),"") | AN66: =IFERROR(INDEX(Country_Context!$G$2:$G$64,MATCH($C66,Country_Context!$A$2:$A$64,0)),"") | AO66: https://api.worldbank.org/v2/country/CHL/indicator/PA.NUS.PRVT.PP?format=json&mrv=30 | https://api.worldbank.org/v2/country/CHL/indicator/GC.TAX.TOTL.GD.ZS?format=json&mrv=30 | https://api.worldbank.org/v2/country/CHL/indicator/FD.AST.PRVT.GD.ZS?format=json&mrv=30 | AP66: Tier 3 | AQ66: 2024-12-31 | AR66: providers=world_bank; fields=ppp_private_consumption, tax_rate_assumption, household_debt_proxy | AW66: https://api.worldbank.org/v2/country/CHL/indicator/SI.POV.GINI?format=json&mrv=30 | AX66: Tier 3 | AY66: 2022-12-31 | AZ66: providers=world_bank; fields=gini_coefficient | BE66: https://api.worldbank.org/v2/country/CHL/indicator/NY.GDP.PCAP.PP.CD?format=json&mrv=30 | https://api.worldbank.org/v2/country/CHL/indicator/NY.GDP.MKTP.KD.ZG?format=json&mrv=30 | BF66: Tier 3 | BG66: 2024-12-31 | BH66: providers=world_bank; fields=gdp_per_capita_ppp, gdp_growth
A67: co-bogota | B67: Bogota | C67: Colombia | D67: Latin America | E67: primary | F67: locked | M67: =IF(OR($G67="",$H67="",$I67="",$J67="",$K67="",$L67="",$AL67="",$AM67=""),"",((($G67*(1-$AM67))-$H67-$I67-$J67-$K67-$L67)/$AL67)) | P67: =IF($O67<>"",$O67,$AN67) | AI67: =IFERROR(INDEX(Country_Context!$B$2:$B$64,MATCH($C67,Country_Context!$A$2:$A$64,0)),"") | AJ67: =IFERROR(INDEX(Country_Context!$C$2:$C$64,MATCH($C67,Country_Context!$A$2:$A$64,0)),"") | AK67: =IFERROR(INDEX(Country_Context!$D$2:$D$64,MATCH($C67,Country_Context!$A$2:$A$64,0)),"") | AL67: =IFERROR(INDEX(Country_Context!$E$2:$E$64,MATCH($C67,Country_Context!$A$2:$A$64,0)),"") | AM67: =IFERROR(INDEX(Country_Context!$F$2:$F$64,MATCH($C67,Country_Context!$A$2:$A$64,0)),"") | AN67: =IFERROR(INDEX(Country_Context!$G$2:$G$64,MATCH($C67,Country_Context!$A$2:$A$64,0)),"") | AO67: https://api.worldbank.org/v2/country/COL/indicator/PA.NUS.PRVT.PP?format=json&mrv=30 | https://api.worldbank.org/v2/country/COL/indicator/GC.TAX.TOTL.GD.ZS?format=json&mrv=30 | https://api.worldbank.org/v2/country/COL/indicator/FD.AST.PRVT.GD.ZS?format=json&mrv=30 | AP67: Tier 3 | AQ67: 2024-12-31 | AR67: providers=world_bank; fields=ppp_private_consumption, tax_rate_assumption, household_debt_proxy | AW67: https://api.worldbank.org/v2/country/COL/indicator/SI.POV.GINI?format=json&mrv=30 | AX67: Tier 3 | AY67: 2023-12-31 | AZ67: providers=world_bank; fields=gini_coefficient | BE67: https://api.worldbank.org/v2/country/COL/indicator/NY.GDP.PCAP.PP.CD?format=json&mrv=30 | https://api.worldbank.org/v2/country/COL/indicator/NY.GDP.MKTP.KD.ZG?format=json&mrv=30 | BF67: Tier 3 | BG67: 2024-12-31 | BH67: providers=world_bank; fields=gdp_per_capita_ppp, gdp_growth
A68: pe-lima | B68: Lima | C68: Peru | D68: Latin America | E68: primary | F68: provisional | M68: =IF(OR($G68="",$H68="",$I68="",$J68="",$K68="",$L68="",$AL68="",$AM68=""),"",((($G68*(1-$AM68))-$H68-$I68-$J68-$K68-$L68)/$AL68)) | P68: =IF($O68<>"",$O68,$AN68) | AI68: =IFERROR(INDEX(Country_Context!$B$2:$B$64,MATCH($C68,Country_Context!$A$2:$A$64,0)),"") | AJ68: =IFERROR(INDEX(Country_Context!$C$2:$C$64,MATCH($C68,Country_Context!$A$2:$A$64,0)),"") | AK68: =IFERROR(INDEX(Country_Context!$D$2:$D$64,MATCH($C68,Country_Context!$A$2:$A$64,0)),"") | AL68: =IFERROR(INDEX(Country_Context!$E$2:$E$64,MATCH($C68,Country_Context!$A$2:$A$64,0)),"") | AM68: =IFERROR(INDEX(Country_Context!$F$2:$F$64,MATCH($C68,Country_Context!$A$2:$A$64,0)),"") | AN68: =IFERROR(INDEX(Country_Context!$G$2:$G$64,MATCH($C68,Country_Context!$A$2:$A$64,0)),"") | AO68: https://api.worldbank.org/v2/country/PER/indicator/PA.NUS.PRVT.PP?format=json&mrv=30 | https://api.worldbank.org/v2/country/PER/indicator/GC.TAX.TOTL.GD.ZS?format=json&mrv=30 | https://api.worldbank.org/v2/country/PER/indicator/FD.AST.PRVT.GD.ZS?format=json&mrv=30 | AP68: Tier 3 | AQ68: 2024-12-31 | AR68: providers=world_bank; fields=ppp_private_consumption, tax_rate_assumption, household_debt_proxy | AW68: https://api.worldbank.org/v2/country/PER/indicator/SI.POV.GINI?format=json&mrv=30 | AX68: Tier 3 | AY68: 2024-12-31 | AZ68: providers=world_bank; fields=gini_coefficient | BE68: https://api.worldbank.org/v2/country/PER/indicator/NY.GDP.PCAP.PP.CD?format=json&mrv=30 | https://api.worldbank.org/v2/country/PER/indicator/NY.GDP.MKTP.KD.ZG?format=json&mrv=30 | BF68: Tier 3 | BG68: 2024-12-31 | BH68: providers=world_bank; fields=gdp_per_capita_ppp, gdp_growth
A69: br-curitiba | B69: Curitiba | C69: Brazil | D69: Latin America | E69: secondary | F69: locked | M69: =IF(OR($G69="",$H69="",$I69="",$J69="",$K69="",$L69="",$AL69="",$AM69=""),"",((($G69*(1-$AM69))-$H69-$I69-$J69-$K69-$L69)/$AL69)) | P69: =IF($O69<>"",$O69,$AN69) | AI69: =IFERROR(INDEX(Country_Context!$B$2:$B$64,MATCH($C69,Country_Context!$A$2:$A$64,0)),"") | AJ69: =IFERROR(INDEX(Country_Context!$C$2:$C$64,MATCH($C69,Country_Context!$A$2:$A$64,0)),"") | AK69: =IFERROR(INDEX(Country_Context!$D$2:$D$64,MATCH($C69,Country_Context!$A$2:$A$64,0)),"") | AL69: =IFERROR(INDEX(Country_Context!$E$2:$E$64,MATCH($C69,Country_Context!$A$2:$A$64,0)),"") | AM69: =IFERROR(INDEX(Country_Context!$F$2:$F$64,MATCH($C69,Country_Context!$A$2:$A$64,0)),"") | AN69: =IFERROR(INDEX(Country_Context!$G$2:$G$64,MATCH($C69,Country_Context!$A$2:$A$64,0)),"") | AO69: https://api.worldbank.org/v2/country/BRA/indicator/PA.NUS.PRVT.PP?format=json&mrv=30 | https://api.worldbank.org/v2/country/BRA/indicator/GC.TAX.TOTL.GD.ZS?format=json&mrv=30 | https://api.worldbank.org/v2/country/BRA/indicator/FD.AST.PRVT.GD.ZS?format=json&mrv=30 | AP69: Tier 3 | AQ69: 2024-12-31 | AR69: providers=world_bank; fields=ppp_private_consumption, tax_rate_assumption, household_debt_proxy | AW69: https://api.worldbank.org/v2/country/BRA/indicator/SI.POV.GINI?format=json&mrv=30 | AX69: Tier 3 | AY69: 2023-12-31 | AZ69: providers=world_bank; fields=gini_coefficient | BE69: https://api.worldbank.org/v2/country/BRA/indicator/NY.GDP.PCAP.PP.CD?format=json&mrv=30 | https://api.worldbank.org/v2/country/BRA/indicator/NY.GDP.MKTP.KD.ZG?format=json&mrv=30 | BF69: Tier 3 | BG69: 2024-12-31 | BH69: providers=world_bank; fields=gdp_per_capita_ppp, gdp_growth
A70: co-medellin | B70: Medellin | C70: Colombia | D70: Latin America | E70: secondary | F70: locked | M70: =IF(OR($G70="",$H70="",$I70="",$J70="",$K70="",$L70="",$AL70="",$AM70=""),"",((($G70*(1-$AM70))-$H70-$I70-$J70-$K70-$L70)/$AL70)) | P70: =IF($O70<>"",$O70,$AN70) | AI70: =IFERROR(INDEX(Country_Context!$B$2:$B$64,MATCH($C70,Country_Context!$A$2:$A$64,0)),"") | AJ70: =IFERROR(INDEX(Country_Context!$C$2:$C$64,MATCH($C70,Country_Context!$A$2:$A$64,0)),"") | AK70: =IFERROR(INDEX(Country_Context!$D$2:$D$64,MATCH($C70,Country_Context!$A$2:$A$64,0)),"") | AL70: =IFERROR(INDEX(Country_Context!$E$2:$E$64,MATCH($C70,Country_Context!$A$2:$A$64,0)),"") | AM70: =IFERROR(INDEX(Country_Context!$F$2:$F$64,MATCH($C70,Country_Context!$A$2:$A$64,0)),"") | AN70: =IFERROR(INDEX(Country_Context!$G$2:$G$64,MATCH($C70,Country_Context!$A$2:$A$64,0)),"") | AO70: https://api.worldbank.org/v2/country/COL/indicator/PA.NUS.PRVT.PP?format=json&mrv=30 | https://api.worldbank.org/v2/country/COL/indicator/GC.TAX.TOTL.GD.ZS?format=json&mrv=30 | https://api.worldbank.org/v2/country/COL/indicator/FD.AST.PRVT.GD.ZS?format=json&mrv=30 | AP70: Tier 3 | AQ70: 2024-12-31 | AR70: providers=world_bank; fields=ppp_private_consumption, tax_rate_assumption, household_debt_proxy | AW70: https://api.worldbank.org/v2/country/COL/indicator/SI.POV.GINI?format=json&mrv=30 | AX70: Tier 3 | AY70: 2023-12-31 | AZ70: providers=world_bank; fields=gini_coefficient | BE70: https://api.worldbank.org/v2/country/COL/indicator/NY.GDP.PCAP.PP.CD?format=json&mrv=30 | https://api.worldbank.org/v2/country/COL/indicator/NY.GDP.MKTP.KD.ZG?format=json&mrv=30 | BF70: Tier 3 | BG70: 2024-12-31 | BH70: providers=world_bank; fields=gdp_per_capita_ppp, gdp_growth
A71: uy-montevideo | B71: Montevideo | C71: Uruguay | D71: Latin America | E71: secondary | F71: locked | M71: =IF(OR($G71="",$H71="",$I71="",$J71="",$K71="",$L71="",$AL71="",$AM71=""),"",((($G71*(1-$AM71))-$H71-$I71-$J71-$K71-$L71)/$AL71)) | P71: =IF($O71<>"",$O71,$AN71) | AI71: =IFERROR(INDEX(Country_Context!$B$2:$B$64,MATCH($C71,Country_Context!$A$2:$A$64,0)),"") | AJ71: =IFERROR(INDEX(Country_Context!$C$2:$C$64,MATCH($C71,Country_Context!$A$2:$A$64,0)),"") | AK71: =IFERROR(INDEX(Country_Context!$D$2:$D$64,MATCH($C71,Country_Context!$A$2:$A$64,0)),"") | AL71: =IFERROR(INDEX(Country_Context!$E$2:$E$64,MATCH($C71,Country_Context!$A$2:$A$64,0)),"") | AM71: =IFERROR(INDEX(Country_Context!$F$2:$F$64,MATCH($C71,Country_Context!$A$2:$A$64,0)),"") | AN71: =IFERROR(INDEX(Country_Context!$G$2:$G$64,MATCH($C71,Country_Context!$A$2:$A$64,0)),"") | AO71: https://api.worldbank.org/v2/country/URY/indicator/PA.NUS.PRVT.PP?format=json&mrv=30 | https://api.worldbank.org/v2/country/URY/indicator/GC.TAX.TOTL.GD.ZS?format=json&mrv=30 | https://api.worldbank.org/v2/country/URY/indicator/FD.AST.PRVT.GD.ZS?format=json&mrv=30 | AP71: Tier 3 | AQ71: 2024-12-31 | AR71: providers=world_bank; fields=ppp_private_consumption, tax_rate_assumption, household_debt_proxy | AW71: https://api.worldbank.org/v2/country/URY/indicator/SI.POV.GINI?format=json&mrv=30 | AX71: Tier 3 | AY71: 2024-12-31 | AZ71: providers=world_bank; fields=gini_coefficient | BE71: https://api.worldbank.org/v2/country/URY/indicator/NY.GDP.PCAP.PP.CD?format=json&mrv=30 | https://api.worldbank.org/v2/country/URY/indicator/NY.GDP.MKTP.KD.ZG?format=json&mrv=30 | BF71: Tier 3 | BG71: 2024-12-31 | BH71: providers=world_bank; fields=gdp_per_capita_ppp, gdp_growth
A72: ar-cordoba | B72: Cordoba | C72: Argentina | D72: Latin America | E72: secondary | F72: provisional | M72: =IF(OR($G72="",$H72="",$I72="",$J72="",$K72="",$L72="",$AL72="",$AM72=""),"",((($G72*(1-$AM72))-$H72-$I72-$J72-$K72-$L72)/$AL72)) | P72: =IF($O72<>"",$O72,$AN72) | AI72: =IFERROR(INDEX(Country_Context!$B$2:$B$64,MATCH($C72,Country_Context!$A$2:$A$64,0)),"") | AJ72: =IFERROR(INDEX(Country_Context!$C$2:$C$64,MATCH($C72,Country_Context!$A$2:$A$64,0)),"") | AK72: =IFERROR(INDEX(Country_Context!$D$2:$D$64,MATCH($C72,Country_Context!$A$2:$A$64,0)),"") | AL72: =IFERROR(INDEX(Country_Context!$E$2:$E$64,MATCH($C72,Country_Context!$A$2:$A$64,0)),"") | AM72: =IFERROR(INDEX(Country_Context!$F$2:$F$64,MATCH($C72,Country_Context!$A$2:$A$64,0)),"") | AN72: =IFERROR(INDEX(Country_Context!$G$2:$G$64,MATCH($C72,Country_Context!$A$2:$A$64,0)),"") | AO72: https://api.worldbank.org/v2/country/ARG/indicator/PA.NUS.PRVT.PP?format=json&mrv=30 | https://api.worldbank.org/v2/country/ARG/indicator/GC.TAX.TOTL.GD.ZS?format=json&mrv=30 | https://api.worldbank.org/v2/country/ARG/indicator/FD.AST.PRVT.GD.ZS?format=json&mrv=30 | AP72: Tier 3 | AQ72: 2024-12-31 | AR72: providers=world_bank; fields=ppp_private_consumption, tax_rate_assumption, household_debt_proxy | AW72: https://api.worldbank.org/v2/country/ARG/indicator/SI.POV.GINI?format=json&mrv=30 | AX72: Tier 3 | AY72: 2024-12-31 | AZ72: providers=world_bank; fields=gini_coefficient | BE72: https://api.worldbank.org/v2/country/ARG/indicator/NY.GDP.PCAP.PP.CD?format=json&mrv=30 | https://api.worldbank.org/v2/country/ARG/indicator/NY.GDP.MKTP.KD.ZG?format=json&mrv=30 | BF72: Tier 3 | BG72: 2024-12-31 | BH72: providers=world_bank; fields=gdp_per_capita_ppp, gdp_growth
A73: cl-valparaiso | B73: Valparaiso | C73: Chile | D73: Latin America | E73: secondary | F73: provisional | M73: =IF(OR($G73="",$H73="",$I73="",$J73="",$K73="",$L73="",$AL73="",$AM73=""),"",((($G73*(1-$AM73))-$H73-$I73-$J73-$K73-$L73)/$AL73)) | P73: =IF($O73<>"",$O73,$AN73) | AI73: =IFERROR(INDEX(Country_Context!$B$2:$B$64,MATCH($C73,Country_Context!$A$2:$A$64,0)),"") | AJ73: =IFERROR(INDEX(Country_Context!$C$2:$C$64,MATCH($C73,Country_Context!$A$2:$A$64,0)),"") | AK73: =IFERROR(INDEX(Country_Context!$D$2:$D$64,MATCH($C73,Country_Context!$A$2:$A$64,0)),"") | AL73: =IFERROR(INDEX(Country_Context!$E$2:$E$64,MATCH($C73,Country_Context!$A$2:$A$64,0)),"") | AM73: =IFERROR(INDEX(Country_Context!$F$2:$F$64,MATCH($C73,Country_Context!$A$2:$A$64,0)),"") | AN73: =IFERROR(INDEX(Country_Context!$G$2:$G$64,MATCH($C73,Country_Context!$A$2:$A$64,0)),"") | AO73: https://api.worldbank.org/v2/country/CHL/indicator/PA.NUS.PRVT.PP?format=json&mrv=30 | https://api.worldbank.org/v2/country/CHL/indicator/GC.TAX.TOTL.GD.ZS?format=json&mrv=30 | https://api.worldbank.org/v2/country/CHL/indicator/FD.AST.PRVT.GD.ZS?format=json&mrv=30 | AP73: Tier 3 | AQ73: 2024-12-31 | AR73: providers=world_bank; fields=ppp_private_consumption, tax_rate_assumption, household_debt_proxy | AW73: https://api.worldbank.org/v2/country/CHL/indicator/SI.POV.GINI?format=json&mrv=30 | AX73: Tier 3 | AY73: 2022-12-31 | AZ73: providers=world_bank; fields=gini_coefficient | BE73: https://api.worldbank.org/v2/country/CHL/indicator/NY.GDP.PCAP.PP.CD?format=json&mrv=30 | https://api.worldbank.org/v2/country/CHL/indicator/NY.GDP.MKTP.KD.ZG?format=json&mrv=30 | BF73: Tier 3 | BG73: 2024-12-31 | BH73: providers=world_bank; fields=gdp_per_capita_ppp, gdp_growth
A74: ae-dubai | B74: Dubai | C74: United Arab Emirates | D74: Middle East | E74: primary | F74: locked | M74: =IF(OR($G74="",$H74="",$I74="",$J74="",$K74="",$L74="",$AL74="",$AM74=""),"",((($G74*(1-$AM74))-$H74-$I74-$J74-$K74-$L74)/$AL74)) | P74: =IF($O74<>"",$O74,$AN74) | AI74: =IFERROR(INDEX(Country_Context!$B$2:$B$64,MATCH($C74,Country_Context!$A$2:$A$64,0)),"") | AJ74: =IFERROR(INDEX(Country_Context!$C$2:$C$64,MATCH($C74,Country_Context!$A$2:$A$64,0)),"") | AK74: =IFERROR(INDEX(Country_Context!$D$2:$D$64,MATCH($C74,Country_Context!$A$2:$A$64,0)),"") | AL74: =IFERROR(INDEX(Country_Context!$E$2:$E$64,MATCH($C74,Country_Context!$A$2:$A$64,0)),"") | AM74: =IFERROR(INDEX(Country_Context!$F$2:$F$64,MATCH($C74,Country_Context!$A$2:$A$64,0)),"") | AN74: =IFERROR(INDEX(Country_Context!$G$2:$G$64,MATCH($C74,Country_Context!$A$2:$A$64,0)),"") | AO74: https://api.worldbank.org/v2/country/ARE/indicator/PA.NUS.PRVT.PP?format=json&mrv=30 | https://api.worldbank.org/v2/country/ARE/indicator/GC.TAX.TOTL.GD.ZS?format=json&mrv=30 | https://api.worldbank.org/v2/country/ARE/indicator/FD.AST.PRVT.GD.ZS?format=json&mrv=30 | AP74: Tier 3 | AQ74: 2024-12-31 | AR74: providers=world_bank; fields=ppp_private_consumption, tax_rate_assumption, household_debt_proxy | AW74: https://api.worldbank.org/v2/country/ARE/indicator/SI.POV.GINI?format=json&mrv=30 | AX74: Tier 3 | AY74: 2018-12-31 | AZ74: providers=world_bank; fields=gini_coefficient | BE74: https://api.worldbank.org/v2/country/ARE/indicator/NY.GDP.PCAP.PP.CD?format=json&mrv=30 | https://api.worldbank.org/v2/country/ARE/indicator/NY.GDP.MKTP.KD.ZG?format=json&mrv=30 | BF74: Tier 3 | BG74: 2024-12-31 | BH74: providers=world_bank; fields=gdp_per_capita_ppp, gdp_growth
... A76: qa-doha | B76: Doha | C76: Qatar | D76: Middle East | E76: primary | F76: locked | M76: =IF(OR($G76="",$H76="",$I76="",$J76="",$K76="",$L76="",$AL76="",$AM76=""),"",((($G76*(1-$AM76))-$H76-$I76-$J76-$K76-$L76)/$AL76)) | P76: =IF($O76<>"",$O76,$AN76) | AI76: =IFERROR(INDEX(Country_Context!$B$2:$B$64,MATCH($C76,Country_Context!$A$2:$A$64,0)),"") | AJ76: =IFERROR(INDEX(Country_Context!$C$2:$C$64,MATCH($C76,Country_Context!$A$2:$A$64,0)),"") | AK76: =IFERROR(INDEX(Country_Context!$D$2:$D$64,MATCH($C76,Country_Context!$A$2:$A$64,0)),"") | AL76: =IFERROR(INDEX(Country_Context!$E$2:$E$64,MATCH($C76,Country_Context!$A$2:$A$64,0)),"") | AM76: =IFERROR(INDEX(Country_Context!$F$2:$F$64,MATCH($C76,Country_Context!$A$2:$A$64,0)),"") | AN76: =IFERROR(INDEX(Country_Context!$G$2:$G$64,MATCH($C76,Country_Context!$A$2:$A$64,0)),"") | AO76: https://api.worldbank.org/v2/country/QAT/indicator/PA.NUS.PRVT.PP?format=json&mrv=30 | https://api.worldbank.org/v2/country/QAT/indicator/FD.AST.PRVT.GD.ZS?format=json&mrv=30 | AP76: Tier 3 | AQ76: 2024-12-31 | AR76: providers=world_bank; fields=ppp_private_consumption, household_debt_proxy | AW76: https://api.worldbank.org/v2/country/QAT/indicator/SI.POV.GINI?format=json&mrv=30 | AX76: Tier 3 | AY76: 2017-12-31 | AZ76: providers=world_bank; fields=gini_coefficient | BE76: https://api.worldbank.org/v2/country/QAT/indicator/NY.GDP.PCAP.PP.CD?format=json&mrv=30 | https://api.worldbank.org/v2/country/QAT/indicator/NY.GDP.MKTP.KD.ZG?format=json&mrv=30 | BF76: Tier 3 | BG76: 2024-12-31 | BH76: providers=world_bank; fields=gdp_per_capita_ppp, gdp_growth
A77: sa-riyadh | B77: Riyadh | C77: Saudi Arabia | D77: Middle East | E77: primary | F77: provisional | M77: =IF(OR($G77="",$H77="",$I77="",$J77="",$K77="",$L77="",$AL77="",$AM77=""),"",((($G77*(1-$AM77))-$H77-$I77-$J77-$K77-$L77)/$AL77)) | P77: =IF($O77<>"",$O77,$AN77) | AI77: =IFERROR(INDEX(Country_Context!$B$2:$B$64,MATCH($C77,Country_Context!$A$2:$A$64,0)),"") | AJ77: =IFERROR(INDEX(Country_Context!$C$2:$C$64,MATCH($C77,Country_Context!$A$2:$A$64,0)),"") | AK77: =IFERROR(INDEX(Country_Context!$D$2:$D$64,MATCH($C77,Country_Context!$A$2:$A$64,0)),"") | AL77: =IFERROR(INDEX(Country_Context!$E$2:$E$64,MATCH($C77,Country_Context!$A$2:$A$64,0)),"") | AM77: =IFERROR(INDEX(Country_Context!$F$2:$F$64,MATCH($C77,Country_Context!$A$2:$A$64,0)),"") | AN77: =IFERROR(INDEX(Country_Context!$G$2:$G$64,MATCH($C77,Country_Context!$A$2:$A$64,0)),"") | AO77: https://api.worldbank.org/v2/country/SAU/indicator/PA.NUS.PRVT.PP?format=json&mrv=30 | https://api.worldbank.org/v2/country/SAU/indicator/GC.TAX.TOTL.GD.ZS?format=json&mrv=30 | https://api.worldbank.org/v2/country/SAU/indicator/FD.AST.PRVT.GD.ZS?format=json&mrv=30 | AP77: Tier 3 | AQ77: 2024-12-31 | AR77: providers=world_bank; fields=ppp_private_consumption, tax_rate_assumption, household_debt_proxy | BE77: https://api.worldbank.org/v2/country/SAU/indicator/NY.GDP.PCAP.PP.CD?format=json&mrv=30 | https://api.worldbank.org/v2/country/SAU/indicator/NY.GDP.MKTP.KD.ZG?format=json&mrv=30 | BF77: Tier 3 | BG77: 2024-12-31 | BH77: providers=world_bank; fields=gdp_per_capita_ppp, gdp_growth
A78: il-tel-aviv | B78: Tel Aviv | C78: Israel | D78: Middle East | E78: primary | F78: provisional | M78: =IF(OR($G78="",$H78="",$I78="",$J78="",$K78="",$L78="",$AL78="",$AM78=""),"",((($G78*(1-$AM78))-$H78-$I78-$J78-$K78-$L78)/$AL78)) | P78: =IF($O78<>"",$O78,$AN78) | AI78: =IFERROR(INDEX(Country_Context!$B$2:$B$64,MATCH($C78,Country_Context!$A$2:$A$64,0)),"") | AJ78: =IFERROR(INDEX(Country_Context!$C$2:$C$64,MATCH($C78,Country_Context!$A$2:$A$64,0)),"") | AK78: =IFERROR(INDEX(Country_Context!$D$2:$D$64,MATCH($C78,Country_Context!$A$2:$A$64,0)),"") | AL78: =IFERROR(INDEX(Country_Context!$E$2:$E$64,MATCH($C78,Country_Context!$A$2:$A$64,0)),"") | AM78: =IFERROR(INDEX(Country_Context!$F$2:$F$64,MATCH($C78,Country_Context!$A$2:$A$64,0)),"") | AN78: =IFERROR(INDEX(Country_Context!$G$2:$G$64,MATCH($C78,Country_Context!$A$2:$A$64,0)),"") | AO78: https://api.worldbank.org/v2/country/ISR/indicator/PA.NUS.PRVT.PP?format=json&mrv=30 | https://api.worldbank.org/v2/country/ISR/indicator/GC.TAX.TOTL.GD.ZS?format=json&mrv=30 | https://api.worldbank.org/v2/country/ISR/indicator/FD.AST.PRVT.GD.ZS?format=json&mrv=30 | AP78: Tier 3 | AQ78: 2024-12-31 | AR78: providers=world_bank; fields=ppp_private_consumption, tax_rate_assumption, household_debt_proxy | AW78: https://api.worldbank.org/v2/country/ISR/indicator/SI.POV.GINI?format=json&mrv=30 | AX78: Tier 3 | AY78: 2021-12-31 | AZ78: providers=world_bank; fields=gini_coefficient | BE78: https://api.worldbank.org/v2/country/ISR/indicator/NY.GDP.PCAP.PP.CD?format=json&mrv=30 | https://api.worldbank.org/v2/country/ISR/indicator/NY.GDP.MKTP.KD.ZG?format=json&mrv=30 | BF78: Tier 3 | BG78: 2024-12-31 | BH78: providers=world_bank; fields=gdp_per_capita_ppp, gdp_growth
A79: om-muscat | B79: Muscat | C79: Oman | D79: Middle East | E79: secondary | F79: locked | M79: =IF(OR($G79="",$H79="",$I79="",$J79="",$K79="",$L79="",$AL79="",$AM79=""),"",((($G79*(1-$AM79))-$H79-$I79-$J79-$K79-$L79)/$AL79)) | P79: =IF($O79<>"",$O79,$AN79) | AI79: =IFERROR(INDEX(Country_Context!$B$2:$B$64,MATCH($C79,Country_Context!$A$2:$A$64,0)),"") | AJ79: =IFERROR(INDEX(Country_Context!$C$2:$C$64,MATCH($C79,Country_Context!$A$2:$A$64,0)),"") | AK79: =IFERROR(INDEX(Country_Context!$D$2:$D$64,MATCH($C79,Country_Context!$A$2:$A$64,0)),"") | AL79: =IFERROR(INDEX(Country_Context!$E$2:$E$64,MATCH($C79,Country_Context!$A$2:$A$64,0)),"") | AM79: =IFERROR(INDEX(Country_Context!$F$2:$F$64,MATCH($C79,Country_Context!$A$2:$A$64,0)),"") | AN79: =IFERROR(INDEX(Country_Context!$G$2:$G$64,MATCH($C79,Country_Context!$A$2:$A$64,0)),"") | AO79: https://api.worldbank.org/v2/country/OMN/indicator/PA.NUS.PRVT.PP?format=json&mrv=30 | https://api.worldbank.org/v2/country/OMN/indicator/FD.AST.PRVT.GD.ZS?format=json&mrv=30 | AP79: Tier 3 | AQ79: 2024-12-31 | AR79: providers=world_bank; fields=ppp_private_consumption, household_debt_proxy | BE79: https://api.worldbank.org/v2/country/OMN/indicator/NY.GDP.PCAP.PP.CD?format=json&mrv=30 | https://api.worldbank.org/v2/country/OMN/indicator/NY.GDP.MKTP.KD.ZG?format=json&mrv=30 | BF79: Tier 3 | BG79: 2024-12-31 | BH79: providers=world_bank; fields=gdp_per_capita_ppp, gdp_growth
A80: bh-manama | B80: Manama | C80: Bahrain | D80: Middle East | E80: secondary | F80: locked | M80: =IF(OR($G80="",$H80="",$I80="",$J80="",$K80="",$L80="",$AL80="",$AM80=""),"",((($G80*(1-$AM80))-$H80-$I80-$J80-$K80-$L80)/$AL80)) | P80: =IF($O80<>"",$O80,$AN80) | AI80: =IFERROR(INDEX(Country_Context!$B$2:$B$64,MATCH($C80,Country_Context!$A$2:$A$64,0)),"") | AJ80: =IFERROR(INDEX(Country_Context!$C$2:$C$64,MATCH($C80,Country_Context!$A$2:$A$64,0)),"") | AK80: =IFERROR(INDEX(Country_Context!$D$2:$D$64,MATCH($C80,Country_Context!$A$2:$A$64,0)),"") | AL80: =IFERROR(INDEX(Country_Context!$E$2:$E$64,MATCH($C80,Country_Context!$A$2:$A$64,0)),"") | AM80: =IFERROR(INDEX(Country_Context!$F$2:$F$64,MATCH($C80,Country_Context!$A$2:$A$64,0)),"") | AN80: =IFERROR(INDEX(Country_Context!$G$2:$G$64,MATCH($C80,Country_Context!$A$2:$A$64,0)),"") | AO80: https://api.worldbank.org/v2/country/BHR/indicator/PA.NUS.PRVT.PP?format=json&mrv=30 | https://api.worldbank.org/v2/country/BHR/indicator/GC.TAX.TOTL.GD.ZS?format=json&mrv=30 | https://api.worldbank.org/v2/country/BHR/indicator/FD.AST.PRVT.GD.ZS?format=json&mrv=30 | AP80: Tier 3 | AQ80: 2024-12-31 | AR80: providers=world_bank; fields=ppp_private_consumption, tax_rate_assumption, household_debt_proxy | BE80: https://api.worldbank.org/v2/country/BHR/indicator/NY.GDP.PCAP.PP.CD?format=json&mrv=30 | https://api.worldbank.org/v2/country/BHR/indicator/NY.GDP.MKTP.KD.ZG?format=json&mrv=30 | BF80: Tier 3 | BG80: 2024-12-31 | BH80: providers=world_bank; fields=gdp_per_capita_ppp, gdp_growth
A81: sa-jeddah | B81: Jeddah | C81: Saudi Arabia | D81: Middle East | E81: secondary | F81: locked | M81: =IF(OR($G81="",$H81="",$I81="",$J81="",$K81="",$L81="",$AL81="",$AM81=""),"",((($G81*(1-$AM81))-$H81-$I81-$J81-$K81-$L81)/$AL81)) | P81: =IF($O81<>"",$O81,$AN81) | AI81: =IFERROR(INDEX(Country_Context!$B$2:$B$64,MATCH($C81,Country_Context!$A$2:$A$64,0)),"") | AJ81: =IFERROR(INDEX(Country_Context!$C$2:$C$64,MATCH($C81,Country_Context!$A$2:$A$64,0)),"") | AK81: =IFERROR(INDEX(Country_Context!$D$2:$D$64,MATCH($C81,Country_Context!$A$2:$A$64,0)),"") | AL81: =IFERROR(INDEX(Country_Context!$E$2:$E$64,MATCH($C81,Country_Context!$A$2:$A$64,0)),"") | AM81: =IFERROR(INDEX(Country_Context!$F$2:$F$64,MATCH($C81,Country_Context!$A$2:$A$64,0)),"") | AN81: =IFERROR(INDEX(Country_Context!$G$2:$G$64,MATCH($C81,Country_Context!$A$2:$A$64,0)),"") | AO81: https://api.worldbank.org/v2/country/SAU/indicator/PA.NUS.PRVT.PP?format=json&mrv=30 | https://api.worldbank.org/v2/country/SAU/indicator/GC.TAX.TOTL.GD.ZS?format=json&mrv=30 | https://api.worldbank.org/v2/country/SAU/indicator/FD.AST.PRVT.GD.ZS?format=json&mrv=30 | AP81: Tier 3 | AQ81: 2024-12-31 | AR81: providers=world_bank; fields=ppp_private_consumption, tax_rate_assumption, household_debt_proxy | BE81: https://api.worldbank.org/v2/country/SAU/indicator/NY.GDP.PCAP.PP.CD?format=json&mrv=30 | https://api.worldbank.org/v2/country/SAU/indicator/NY.GDP.MKTP.KD.ZG?format=json&mrv=30 | BF81: Tier 3 | BG81: 2024-12-31 | BH81: providers=world_bank; fields=gdp_per_capita_ppp, gdp_growth
A82: kw-kuwait-city | B82: Kuwait City | C82: Kuwait | D82: Middle East | E82: secondary | F82: locked | M82: =IF(OR($G82="",$H82="",$I82="",$J82="",$K82="",$L82="",$AL82="",$AM82=""),"",((($G82*(1-$AM82))-$H82-$I82-$J82-$K82-$L82)/$AL82)) | P82: =IF($O82<>"",$O82,$AN82) | AI82: =IFERROR(INDEX(Country_Context!$B$2:$B$64,MATCH($C82,Country_Context!$A$2:$A$64,0)),"") | AJ82: =IFERROR(INDEX(Country_Context!$C$2:$C$64,MATCH($C82,Country_Context!$A$2:$A$64,0)),"") | AK82: =IFERROR(INDEX(Country_Context!$D$2:$D$64,MATCH($C82,Country_Context!$A$2:$A$64,0)),"") | AL82: =IFERROR(INDEX(Country_Context!$E$2:$E$64,MATCH($C82,Country_Context!$A$2:$A$64,0)),"") | AM82: =IFERROR(INDEX(Country_Context!$F$2:$F$64,MATCH($C82,Country_Context!$A$2:$A$64,0)),"") | AN82: =IFERROR(INDEX(Country_Context!$G$2:$G$64,MATCH($C82,Country_Context!$A$2:$A$64,0)),"") | AO82: https://api.worldbank.org/v2/country/KWT/indicator/PA.NUS.PRVT.PP?format=json&mrv=30 | https://api.worldbank.org/v2/country/KWT/indicator/GC.TAX.TOTL.GD.ZS?format=json&mrv=30 | https://api.worldbank.org/v2/country/KWT/indicator/FD.AST.PRVT.GD.ZS?format=json&mrv=30 | AP82: Tier 3 | AQ82: 2024-12-31 | AR82: providers=world_bank; fields=ppp_private_consumption, tax_rate_assumption, household_debt_proxy | BE82: https://api.worldbank.org/v2/country/KWT/indicator/NY.GDP.PCAP.PP.CD?format=json&mrv=30 | https://api.worldbank.org/v2/country/KWT/indicator/NY.GDP.MKTP.KD.ZG?format=json&mrv=30 | BF82: Tier 3 | BG82: 2024-12-31 | BH82: providers=world_bank; fields=gdp_per_capita_ppp, gdp_growth
A83: jo-amman | B83: Amman | C83: Jordan | D83: Middle East | E83: secondary | F83: provisional | M83: =IF(OR($G83="",$H83="",$I83="",$J83="",$K83="",$L83="",$AL83="",$AM83=""),"",((($G83*(1-$AM83))-$H83-$I83-$J83-$K83-$L83)/$AL83)) | P83: =IF($O83<>"",$O83,$AN83) | AI83: =IFERROR(INDEX(Country_Context!$B$2:$B$64,MATCH($C83,Country_Context!$A$2:$A$64,0)),"") | AJ83: =IFERROR(INDEX(Country_Context!$C$2:$C$64,MATCH($C83,Country_Context!$A$2:$A$64,0)),"") | AK83: =IFERROR(INDEX(Country_Context!$D$2:$D$64,MATCH($C83,Country_Context!$A$2:$A$64,0)),"") | AL83: =IFERROR(INDEX(Country_Context!$E$2:$E$64,MATCH($C83,Country_Context!$A$2:$A$64,0)),"") | AM83: =IFERROR(INDEX(Country_Context!$F$2:$F$64,MATCH($C83,Country_Context!$A$2:$A$64,0)),"") | AN83: =IFERROR(INDEX(Country_Context!$G$2:$G$64,MATCH($C83,Country_Context!$A$2:$A$64,0)),"") | AO83: https://api.worldbank.org/v2/country/JOR/indicator/PA.NUS.PRVT.PP?format=json&mrv=30 | https://api.worldbank.org/v2/country/JOR/indicator/GC.TAX.TOTL.GD.ZS?format=json&mrv=30 | https://api.worldbank.org/v2/country/JOR/indicator/FD.AST.PRVT.GD.ZS?format=json&mrv=30 | AP83: Tier 3 | AQ83: 2024-12-31 | AR83: providers=world_bank; fields=ppp_private_consumption, tax_rate_assumption, household_debt_proxy | AW83: https://api.worldbank.org/v2/country/JOR/indicator/SI.POV.GINI?format=json&mrv=30 | AX83: Tier 3 | AY83: 2010-12-31 | AZ83: providers=world_bank; fields=gini_coefficient | BE83: https://api.worldbank.org/v2/country/JOR/indicator/NY.GDP.PCAP.PP.CD?format=json&mrv=30 | https://api.worldbank.org/v2/country/JOR/indicator/NY.GDP.MKTP.KD.ZG?format=json&mrv=30 | BF83: Tier 3 | BG83: 2024-12-31 | BH83: providers=world_bank; fields=gdp_per_capita_ppp, gdp_growth
A84: za-cape-town | B84: Cape Town | C84: South Africa | D84: Africa | E84: primary | F84: locked | M84: =IF(OR($G84="",$H84="",$I84="",$J84="",$K84="",$L84="",$AL84="",$AM84=""),"",((($G84*(1-$AM84))-$H84-$I84-$J84-$K84-$L84)/$AL84)) | P84: =IF($O84<>"",$O84,$AN84) | AI84: =IFERROR(INDEX(Country_Context!$B$2:$B$64,MATCH($C84,Country_Context!$A$2:$A$64,0)),"") | AJ84: =IFERROR(INDEX(Country_Context!$C$2:$C$64,MATCH($C84,Country_Context!$A$2:$A$64,0)),"") | AK84: =IFERROR(INDEX(Country_Context!$D$2:$D$64,MATCH($C84,Country_Context!$A$2:$A$64,0)),"") | AL84: =IFERROR(INDEX(Country_Context!$E$2:$E$64,MATCH($C84,Country_Context!$A$2:$A$64,0)),"") | AM84: =IFERROR(INDEX(Country_Context!$F$2:$F$64,MATCH($C84,Country_Context!$A$2:$A$64,0)),"") | AN84: =IFERROR(INDEX(Country_Context!$G$2:$G$64,MATCH($C84,Country_Context!$A$2:$A$64,0)),"") | AO84: https://api.worldbank.org/v2/country/ZAF/indicator/PA.NUS.PRVT.PP?format=json&mrv=30 | https://api.worldbank.org/v2/country/ZAF/indicator/GC.TAX.TOTL.GD.ZS?format=json&mrv=30 | https://api.worldbank.org/v2/country/ZAF/indicator/FD.AST.PRVT.GD.ZS?format=json&mrv=30 | AP84: Tier 3 | AQ84: 2024-12-31 | AR84: providers=world_bank; fields=ppp_private_consumption, tax_rate_assumption, household_debt_proxy | AW84: https://api.worldbank.org/v2/country/ZAF/indicator/SI.POV.GINI?format=json&mrv=30 | AX84: Tier 3 | AY84: 2014-12-31 | AZ84: providers=world_bank; fields=gini_coefficient | BE84: https://api.worldbank.org/v2/country/ZAF/indicator/NY.GDP.PCAP.PP.CD?format=json&mrv=30 | https://api.worldbank.org/v2/country/ZAF/indicator/NY.GDP.MKTP.KD.ZG?format=json&mrv=30 | BF84: Tier 3 | BG84: 2024-12-31 | BH84: providers=world_bank; fields=gdp_per_capita_ppp, gdp_growth
A85: za-johannesburg | B85: Johannesburg | C85: South Africa | D85: Africa | E85: primary | F85: provisional | M85: =IF(OR($G85="",$H85="",$I85="",$J85="",$K85="",$L85="",$AL85="",$AM85=""),"",((($G85*(1-$AM85))-$H85-$I85-$J85-$K85-$L85)/$AL85)) | P85: =IF($O85<>"",$O85,$AN85) | AI85: =IFERROR(INDEX(Country_Context!$B$2:$B$64,MATCH($C85,Country_Context!$A$2:$A$64,0)),"") | AJ85: =IFERROR(INDEX(Country_Context!$C$2:$C$64,MATCH($C85,Country_Context!$A$2:$A$64,0)),"") | AK85: =IFERROR(INDEX(Country_Context!$D$2:$D$64,MATCH($C85,Country_Context!$A$2:$A$64,0)),"") | AL85: =IFERROR(INDEX(Country_Context!$E$2:$E$64,MATCH($C85,Country_Context!$A$2:$A$64,0)),"") | AM85: =IFERROR(INDEX(Country_Context!$F$2:$F$64,MATCH($C85,Country_Context!$A$2:$A$64,0)),"") | AN85: =IFERROR(INDEX(Country_Context!$G$2:$G$64,MATCH($C85,Country_Context!$A$2:$A$64,0)),"") | AO85: https://api.worldbank.org/v2/country/ZAF/indicator/PA.NUS.PRVT.PP?format=json&mrv=30 | https://api.worldbank.org/v2/country/ZAF/indicator/GC.TAX.TOTL.GD.ZS?format=json&mrv=30 | https://api.worldbank.org/v2/country/ZAF/indicator/FD.AST.PRVT.GD.ZS?format=json&mrv=30 | AP85: Tier 3 | AQ85: 2024-12-31 | AR85: providers=world_bank; fields=ppp_private_consumption, tax_rate_assumption, household_debt_proxy | AW85: https://api.worldbank.org/v2/country/ZAF/indicator/SI.POV.GINI?format=json&mrv=30 | AX85: Tier 3 | AY85: 2014-12-31 | AZ85: providers=world_bank; fields=gini_coefficient | BE85: https://api.worldbank.org/v2/country/ZAF/indicator/NY.GDP.PCAP.PP.CD?format=json&mrv=30 | https://api.worldbank.org/v2/country/ZAF/indicator/NY.GDP.MKTP.KD.ZG?format=json&mrv=30 | BF85: Tier 3 | BG85: 2024-12-31 | BH85: providers=world_bank; fields=gdp_per_capita_ppp, gdp_growth
A86: ke-nairobi | B86: Nairobi | C86: Kenya | D86: Africa | E86: primary | F86: locked | M86: =IF(OR($G86="",$H86="",$I86="",$J86="",$K86="",$L86="",$AL86="",$AM86=""),"",((($G86*(1-$AM86))-$H86-$I86-$J86-$K86-$L86)/$AL86)) | P86: =IF($O86<>"",$O86,$AN86) | AI86: =IFERROR(INDEX(Country_Context!$B$2:$B$64,MATCH($C86,Country_Context!$A$2:$A$64,0)),"") | AJ86: =IFERROR(INDEX(Country_Context!$C$2:$C$64,MATCH($C86,Country_Context!$A$2:$A$64,0)),"") | AK86: =IFERROR(INDEX(Country_Context!$D$2:$D$64,MATCH($C86,Country_Context!$A$2:$A$64,0)),"") | AL86: =IFERROR(INDEX(Country_Context!$E$2:$E$64,MATCH($C86,Country_Context!$A$2:$A$64,0)),"") | AM86: =IFERROR(INDEX(Country_Context!$F$2:$F$64,MATCH($C86,Country_Context!$A$2:$A$64,0)),"") | AN86: =IFERROR(INDEX(Country_Context!$G$2:$G$64,MATCH($C86,Country_Context!$A$2:$A$64,0)),"") | AO86: https://api.worldbank.org/v2/country/KEN/indicator/PA.NUS.PRVT.PP?format=json&mrv=30 | https://api.worldbank.org/v2/country/KEN/indicator/GC.TAX.TOTL.GD.ZS?format=json&mrv=30 | https://api.worldbank.org/v2/country/KEN/indicator/FD.AST.PRVT.GD.ZS?format=json&mrv=30 | AP86: Tier 3 | AQ86: 2024-12-31 | AR86: providers=world_bank; fields=ppp_private_consumption, tax_rate_assumption, household_debt_proxy | AW86: https://api.worldbank.org/v2/country/KEN/indicator/SI.POV.GINI?format=json&mrv=30 | AX86: Tier 3 | AY86: 2022-12-31 | AZ86: providers=world_bank; fields=gini_coefficient | BE86: https://api.worldbank.org/v2/country/KEN/indicator/NY.GDP.PCAP.PP.CD?format=json&mrv=30 | https://api.worldbank.org/v2/country/KEN/indicator/NY.GDP.MKTP.KD.ZG?format=json&mrv=30 | BF86: Tier 3 | BG86: 2024-12-31 | BH86: providers=world_bank; fields=gdp_per_capita_ppp, gdp_growth
A87: rw-kigali | B87: Kigali | C87: Rwanda | D87: Africa | E87: primary | F87: locked | M87: =IF(OR($G87="",$H87="",$I87="",$J87="",$K87="",$L87="",$AL87="",$AM87=""),"",((($G87*(1-$AM87))-$H87-$I87-$J87-$K87-$L87)/$AL87)) | P87: =IF($O87<>"",$O87,$AN87) | AI87: =IFERROR(INDEX(Country_Context!$B$2:$B$64,MATCH($C87,Country_Context!$A$2:$A$64,0)),"") | AJ87: =IFERROR(INDEX(Country_Context!$C$2:$C$64,MATCH($C87,Country_Context!$A$2:$A$64,0)),"") | AK87: =IFERROR(INDEX(Country_Context!$D$2:$D$64,MATCH($C87,Country_Context!$A$2:$A$64,0)),"") | AL87: =IFERROR(INDEX(Country_Context!$E$2:$E$64,MATCH($C87,Country_Context!$A$2:$A$64,0)),"") | AM87: =IFERROR(INDEX(Country_Context!$F$2:$F$64,MATCH($C87,Country_Context!$A$2:$A$64,0)),"") | AN87: =IFERROR(INDEX(Country_Context!$G$2:$G$64,MATCH($C87,Country_Context!$A$2:$A$64,0)),"") | AO87: https://api.worldbank.org/v2/country/RWA/indicator/PA.NUS.PRVT.PP?format=json&mrv=30 | https://api.worldbank.org/v2/country/RWA/indicator/GC.TAX.TOTL.GD.ZS?format=json&mrv=30 | https://api.worldbank.org/v2/country/RWA/indicator/FD.AST.PRVT.GD.ZS?format=json&mrv=30 | AP87: Tier 3 | AQ87: 2024-12-31 | AR87: providers=world_bank; fields=ppp_private_consumption, tax_rate_assumption, household_debt_proxy | AW87: https://api.worldbank.org/v2/country/RWA/indicator/SI.POV.GINI?format=json&mrv=30 | AX87: Tier 3 | AY87: 2023-12-31 | AZ87: providers=world_bank; fields=gini_coefficient | BE87: https://api.worldbank.org/v2/country/RWA/indicator/NY.GDP.PCAP.PP.CD?format=json&mrv=30 | https://api.worldbank.org/v2/country/RWA/indicator/NY.GDP.MKTP.KD.ZG?format=json&mrv=30 | BF87: Tier 3 | BG87: 2024-12-31 | BH87: providers=world_bank; fields=gdp_per_capita_ppp, gdp_growth
A88: ma-casablanca | B88: Casablanca | C88: Morocco | D88: Africa | E88: primary | F88: provisional | M88: =IF(OR($G88="",$H88="",$I88="",$J88="",$K88="",$L88="",$AL88="",$AM88=""),"",((($G88*(1-$AM88))-$H88-$I88-$J88-$K88-$L88)/$AL88)) | P88: =IF($O88<>"",$O88,$AN88) | AI88: =IFERROR(INDEX(Country_Context!$B$2:$B$64,MATCH($C88,Country_Context!$A$2:$A$64,0)),"") | AJ88: =IFERROR(INDEX(Country_Context!$C$2:$C$64,MATCH($C88,Country_Context!$A$2:$A$64,0)),"") | AK88: =IFERROR(INDEX(Country_Context!$D$2:$D$64,MATCH($C88,Country_Context!$A$2:$A$64,0)),"") | AL88: =IFERROR(INDEX(Country_Context!$E$2:$E$64,MATCH($C88,Country_Context!$A$2:$A$64,0)),"") | AM88: =IFERROR(INDEX(Country_Context!$F$2:$F$64,MATCH($C88,Country_Context!$A$2:$A$64,0)),"") | AN88: =IFERROR(INDEX(Country_Context!$G$2:$G$64,MATCH($C88,Country_Context!$A$2:$A$64,0)),"") | AO88: https://api.worldbank.org/v2/country/MAR/indicator/PA.NUS.PRVT.PP?format=json&mrv=30 | https://api.worldbank.org/v2/country/MAR/indicator/GC.TAX.TOTL.GD.ZS?format=json&mrv=30 | https://api.worldbank.org/v2/country/MAR/indicator/FD.AST.PRVT.GD.ZS?format=json&mrv=30 | AP88: Tier 3 | AQ88: 2024-12-31 | AR88: providers=world_bank; fields=ppp_private_consumption, tax_rate_assumption, household_debt_proxy | AW88: https://api.worldbank.org/v2/country/MAR/indicator/SI.POV.GINI?format=json&mrv=30 | AX88: Tier 3 | AY88: 2013-12-31 | AZ88: providers=world_bank; fields=gini_coefficient | BE88: https://api.worldbank.org/v2/country/MAR/indicator/NY.GDP.PCAP.PP.CD?format=json&mrv=30 | https://api.worldbank.org/v2/country/MAR/indicator/NY.GDP.MKTP.KD.ZG?format=json&mrv=30 | BF88: Tier 3 | BG88: 2024-12-31 | BH88: providers=world_bank; fields=gdp_per_capita_ppp, gdp_growth
A89: mu-port-louis | B89: Port Louis | C89: Mauritius | D89: Africa | E89: secondary | F89: locked | M89: =IF(OR($G89="",$H89="",$I89="",$J89="",$K89="",$L89="",$AL89="",$AM89=""),"",((($G89*(1-$AM89))-$H89-$I89-$J89-$K89-$L89)/$AL89)) | P89: =IF($O89<>"",$O89,$AN89) | AI89: =IFERROR(INDEX(Country_Context!$B$2:$B$64,MATCH($C89,Country_Context!$A$2:$A$64,0)),"") | AJ89: =IFERROR(INDEX(Country_Context!$C$2:$C$64,MATCH($C89,Country_Context!$A$2:$A$64,0)),"") | AK89: =IFERROR(INDEX(Country_Context!$D$2:$D$64,MATCH($C89,Country_Context!$A$2:$A$64,0)),"") | AL89: =IFERROR(INDEX(Country_Context!$E$2:$E$64,MATCH($C89,Country_Context!$A$2:$A$64,0)),"") | AM89: =IFERROR(INDEX(Country_Context!$F$2:$F$64,MATCH($C89,Country_Context!$A$2:$A$64,0)),"") | AN89: =IFERROR(INDEX(Country_Context!$G$2:$G$64,MATCH($C89,Country_Context!$A$2:$A$64,0)),"") | AO89: https://api.worldbank.org/v2/country/MUS/indicator/PA.NUS.PRVT.PP?format=json&mrv=30 | https://api.worldbank.org/v2/country/MUS/indicator/GC.TAX.TOTL.GD.ZS?format=json&mrv=30 | https://api.worldbank.org/v2/country/MUS/indicator/FD.AST.PRVT.GD.ZS?format=json&mrv=30 | AP89: Tier 3 | AQ89: 2024-12-31 | AR89: providers=world_bank; fields=ppp_private_consumption, tax_rate_assumption, household_debt_proxy | AW89: https://api.worldbank.org/v2/country/MUS/indicator/SI.POV.GINI?format=json&mrv=30 | AX89: Tier 3 | AY89: 2017-12-31 | AZ89: providers=world_bank; fields=gini_coefficient | BE89: https://api.worldbank.org/v2/country/MUS/indicator/NY.GDP.PCAP.PP.CD?format=json&mrv=30 | https://api.worldbank.org/v2/country/MUS/indicator/NY.GDP.MKTP.KD.ZG?format=json&mrv=30 | BF89: Tier 3 | BG89: 2024-12-31 | BH89: providers=world_bank; fields=gdp_per_capita_ppp, gdp_growth
A90: bw-gaborone | B90: Gaborone | C90: Botswana | D90: Africa | E90: secondary | F90: locked | M90: =IF(OR($G90="",$H90="",$I90="",$J90="",$K90="",$L90="",$AL90="",$AM90=""),"",((($G90*(1-$AM90))-$H90-$I90-$J90-$K90-$L90)/$AL90)) | P90: =IF($O90<>"",$O90,$AN90) | AI90: =IFERROR(INDEX(Country_Context!$B$2:$B$64,MATCH($C90,Country_Context!$A$2:$A$64,0)),"") | AJ90: =IFERROR(INDEX(Country_Context!$C$2:$C$64,MATCH($C90,Country_Context!$A$2:$A$64,0)),"") | AK90: =IFERROR(INDEX(Country_Context!$D$2:$D$64,MATCH($C90,Country_Context!$A$2:$A$64,0)),"") | AL90: =IFERROR(INDEX(Country_Context!$E$2:$E$64,MATCH($C90,Country_Context!$A$2:$A$64,0)),"") | AM90: =IFERROR(INDEX(Country_Context!$F$2:$F$64,MATCH($C90,Country_Context!$A$2:$A$64,0)),"") | AN90: =IFERROR(INDEX(Country_Context!$G$2:$G$64,MATCH($C90,Country_Context!$A$2:$A$64,0)),"") | AO90: https://api.worldbank.org/v2/country/BWA/indicator/PA.NUS.PRVT.PP?format=json&mrv=30 | https://api.worldbank.org/v2/country/BWA/indicator/GC.TAX.TOTL.GD.ZS?format=json&mrv=30 | https://api.worldbank.org/v2/country/BWA/indicator/FD.AST.PRVT.GD.ZS?format=json&mrv=30 | AP90: Tier 3 | AQ90: 2024-12-31 | AR90: providers=world_bank; fields=ppp_private_consumption, tax_rate_assumption, household_debt_proxy | AW90: https://api.worldbank.org/v2/country/BWA/indicator/SI.POV.GINI?format=json&mrv=30 | AX90: Tier 3 | AY90: 2015-12-31 | AZ90: providers=world_bank; fields=gini_coefficient | BE90: https://api.worldbank.org/v2/country/BWA/indicator/NY.GDP.PCAP.PP.CD?format=json&mrv=30 | https://api.worldbank.org/v2/country/BWA/indicator/NY.GDP.MKTP.KD.ZG?format=json&mrv=30 | BF90: Tier 3 | BG90: 2024-12-31 | BH90: providers=world_bank; fields=gdp_per_capita_ppp, gdp_growth
A91: na-windhoek | B91: Windhoek | C91: Namibia | D91: Africa | E91: secondary | F91: locked | M91: =IF(OR($G91="",$H91="",$I91="",$J91="",$K91="",$L91="",$AL91="",$AM91=""),"",((($G91*(1-$AM91))-$H91-$I91-$J91-$K91-$L91)/$AL91)) | P91: =IF($O91<>"",$O91,$AN91) | AI91: =IFERROR(INDEX(Country_Context!$B$2:$B$64,MATCH($C91,Country_Context!$A$2:$A$64,0)),"") | AJ91: =IFERROR(INDEX(Country_Context!$C$2:$C$64,MATCH($C91,Country_Context!$A$2:$A$64,0)),"") | AK91: =IFERROR(INDEX(Country_Context!$D$2:$D$64,MATCH($C91,Country_Context!$A$2:$A$64,0)),"") | AL91: =IFERROR(INDEX(Country_Context!$E$2:$E$64,MATCH($C91,Country_Context!$A$2:$A$64,0)),"") | AM91: =IFERROR(INDEX(Country_Context!$F$2:$F$64,MATCH($C91,Country_Context!$A$2:$A$64,0)),"") | AN91: =IFERROR(INDEX(Country_Context!$G$2:$G$64,MATCH($C91,Country_Context!$A$2:$A$64,0)),"") | AO91: https://api.worldbank.org/v2/country/NAM/indicator/PA.NUS.PRVT.PP?format=json&mrv=30 | https://api.worldbank.org/v2/country/NAM/indicator/GC.TAX.TOTL.GD.ZS?format=json&mrv=30 | https://api.worldbank.org/v2/country/NAM/indicator/FD.AST.PRVT.GD.ZS?format=json&mrv=30 | AP91: Tier 3 | AQ91: 2024-12-31 | AR91: providers=world_bank; fields=ppp_private_consumption, tax_rate_assumption, household_debt_proxy | AW91: https://api.worldbank.org/v2/country/NAM/indicator/SI.POV.GINI?format=json&mrv=30 | AX91: Tier 3 | AY91: 2015-12-31 | AZ91: providers=world_bank; fields=gini_coefficient | BE91: https://api.worldbank.org/v2/country/NAM/indicator/NY.GDP.PCAP.PP.CD?format=json&mrv=30 | https://api.worldbank.org/v2/country/NAM/indicator/NY.GDP.MKTP.KD.ZG?format=json&mrv=30 | BF91: Tier 3 | BG91: 2024-12-31 | BH91: providers=world_bank; fields=gdp_per_capita_ppp, gdp_growth
A92: gh-accra | B92: Accra | C92: Ghana | D92: Africa | E92: secondary | F92: locked | M92: =IF(OR($G92="",$H92="",$I92="",$J92="",$K92="",$L92="",$AL92="",$AM92=""),"",((($G92*(1-$AM92))-$H92-$I92-$J92-$K92-$L92)/$AL92)) | P92: =IF($O92<>"",$O92,$AN92) | AI92: =IFERROR(INDEX(Country_Context!$B$2:$B$64,MATCH($C92,Country_Context!$A$2:$A$64,0)),"") | AJ92: =IFERROR(INDEX(Country_Context!$C$2:$C$64,MATCH($C92,Country_Context!$A$2:$A$64,0)),"") | AK92: =IFERROR(INDEX(Country_Context!$D$2:$D$64,MATCH($C92,Country_Context!$A$2:$A$64,0)),"") | AL92: =IFERROR(INDEX(Country_Context!$E$2:$E$64,MATCH($C92,Country_Context!$A$2:$A$64,0)),"") | AM92: =IFERROR(INDEX(Country_Context!$F$2:$F$64,MATCH($C92,Country_Context!$A$2:$A$64,0)),"") | AN92: =IFERROR(INDEX(Country_Context!$G$2:$G$64,MATCH($C92,Country_Context!$A$2:$A$64,0)),"") | AO92: https://api.worldbank.org/v2/country/GHA/indicator/PA.NUS.PRVT.PP?format=json&mrv=30 | https://api.worldbank.org/v2/country/GHA/indicator/GC.TAX.TOTL.GD.ZS?format=json&mrv=30 | https://api.worldbank.org/v2/country/GHA/indicator/FD.AST.PRVT.GD.ZS?format=json&mrv=30 | AP92: Tier 3 | AQ92: 2024-12-31 | AR92: providers=world_bank; fields=ppp_private_consumption, tax_rate_assumption, household_debt_proxy | AW92: https://api.worldbank.org/v2/country/GHA/indicator/SI.POV.GINI?format=json&mrv=30 | AX92: Tier 3 | AY92: 2016-12-31 | AZ92: providers=world_bank; fields=gini_coefficient | BE92: https://api.worldbank.org/v2/country/GHA/indicator/NY.GDP.PCAP.PP.CD?format=json&mrv=30 | https://api.worldbank.org/v2/country/GHA/indicator/NY.GDP.MKTP.KD.ZG?format=json&mrv=30 | BF92: Tier 3 | BG92: 2024-12-31 | BH92: providers=world_bank; fields=gdp_per_capita_ppp, gdp_growth
A93: sn-dakar | B93: Dakar | C93: Senegal | D93: Africa | E93: secondary | F93: provisional | M93: =IF(OR($G93="",$H93="",$I93="",$J93="",$K93="",$L93="",$AL93="",$AM93=""),"",((($G93*(1-$AM93))-$H93-$I93-$J93-$K93-$L93)/$AL93)) | P93: =IF($O93<>"",$O93,$AN93) | AI93: =IFERROR(INDEX(Country_Context!$B$2:$B$64,MATCH($C93,Country_Context!$A$2:$A$64,0)),"") | AJ93: =IFERROR(INDEX(Country_Context!$C$2:$C$64,MATCH($C93,Country_Context!$A$2:$A$64,0)),"") | AK93: =IFERROR(INDEX(Country_Context!$D$2:$D$64,MATCH($C93,Country_Context!$A$2:$A$64,0)),"") | AL93: =IFERROR(INDEX(Country_Context!$E$2:$E$64,MATCH($C93,Country_Context!$A$2:$A$64,0)),"") | AM93: =IFERROR(INDEX(Country_Context!$F$2:$F$64,MATCH($C93,Country_Context!$A$2:$A$64,0)),"") | AN93: =IFERROR(INDEX(Country_Context!$G$2:$G$64,MATCH($C93,Country_Context!$A$2:$A$64,0)),"") | AO93: https://api.worldbank.org/v2/country/SEN/indicator/PA.NUS.PRVT.PP?format=json&mrv=30 | https://api.worldbank.org/v2/country/SEN/indicator/GC.TAX.TOTL.GD.ZS?format=json&mrv=30 | https://api.worldbank.org/v2/country/SEN/indicator/FD.AST.PRVT.GD.ZS?format=json&mrv=30 | AP93: Tier 3 | AQ93: 2024-12-31 | AR93: providers=world_bank; fields=ppp_private_consumption, tax_rate_assumption, household_debt_proxy | AW93: https://api.worldbank.org/v2/country/SEN/indicator/SI.POV.GINI?format=json&mrv=30 | AX93: Tier 3 | AY93: 2021-12-31 | AZ93: providers=world_bank; fields=gini_coefficient | BE93: https://api.worldbank.org/v2/country/SEN/indicator/NY.GDP.PCAP.PP.CD?format=json&mrv=30 | https://api.worldbank.org/v2/country/SEN/indicator/NY.GDP.MKTP.KD.ZG?format=json&mrv=30 | BF93: Tier 3 | BG93: 2024-12-31 | BH93: providers=world_bank; fields=gdp_per_capita_ppp, gdp_growth
A94: nz-auckland | B94: Auckland | C94: New Zealand | D94: Oceania | E94: primary | F94: locked | M94: =IF(OR($G94="",$H94="",$I94="",$J94="",$K94="",$L94="",$AL94="",$AM94=""),"",((($G94*(1-$AM94))-$H94-$I94-$J94-$K94-$L94)/$AL94)) | P94: =IF($O94<>"",$O94,$AN94) | AI94: =IFERROR(INDEX(Country_Context!$B$2:$B$64,MATCH($C94,Country_Context!$A$2:$A$64,0)),"") | AJ94: =IFERROR(INDEX(Country_Context!$C$2:$C$64,MATCH($C94,Country_Context!$A$2:$A$64,0)),"") | AK94: =IFERROR(INDEX(Country_Context!$D$2:$D$64,MATCH($C94,Country_Context!$A$2:$A$64,0)),"") | AL94: =IFERROR(INDEX(Country_Context!$E$2:$E$64,MATCH($C94,Country_Context!$A$2:$A$64,0)),"") | AM94: =IFERROR(INDEX(Country_Context!$F$2:$F$64,MATCH($C94,Country_Context!$A$2:$A$64,0)),"") | AN94: =IFERROR(INDEX(Country_Context!$G$2:$G$64,MATCH($C94,Country_Context!$A$2:$A$64,0)),"") | AO94: https://api.worldbank.org/v2/country/NZL/indicator/PA.NUS.PRVT.PP?format=json&mrv=30 | https://api.worldbank.org/v2/country/NZL/indicator/GC.TAX.TOTL.GD.ZS?format=json&mrv=30 | https://api.worldbank.org/v2/country/NZL/indicator/FD.AST.PRVT.GD.ZS?format=json&mrv=30 | AP94: Tier 3 | AQ94: 2024-12-31 | AR94: providers=world_bank; fields=ppp_private_consumption, tax_rate_assumption, household_debt_proxy | BE94: https://api.worldbank.org/v2/country/NZL/indicator/NY.GDP.PCAP.PP.CD?format=json&mrv=30 | https://api.worldbank.org/v2/country/NZL/indicator/NY.GDP.MKTP.KD.ZG?format=json&mrv=30 | BF94: Tier 3 | BG94: 2024-12-31 | BH94: providers=world_bank; fields=gdp_per_capita_ppp, gdp_growth
A95: au-sydney | B95: Sydney | C95: Australia | D95: Oceania | E95: primary | F95: provisional | M95: =IF(OR($G95="",$H95="",$I95="",$J95="",$K95="",$L95="",$AL95="",$AM95=""),"",((($G95*(1-$AM95))-$H95-$I95-$J95-$K95-$L95)/$AL95)) | P95: =IF($O95<>"",$O95,$AN95) | AI95: =IFERROR(INDEX(Country_Context!$B$2:$B$64,MATCH($C95,Country_Context!$A$2:$A$64,0)),"") | AJ95: =IFERROR(INDEX(Country_Context!$C$2:$C$64,MATCH($C95,Country_Context!$A$2:$A$64,0)),"") | AK95: =IFERROR(INDEX(Country_Context!$D$2:$D$64,MATCH($C95,Country_Context!$A$2:$A$64,0)),"") | AL95: =IFERROR(INDEX(Country_Context!$E$2:$E$64,MATCH($C95,Country_Context!$A$2:$A$64,0)),"") | AM95: =IFERROR(INDEX(Country_Context!$F$2:$F$64,MATCH($C95,Country_Context!$A$2:$A$64,0)),"") | AN95: =IFERROR(INDEX(Country_Context!$G$2:$G$64,MATCH($C95,Country_Context!$A$2:$A$64,0)),"") | AO95: https://api.worldbank.org/v2/country/AUS/indicator/PA.NUS.PRVT.PP?format=json&mrv=30 | https://api.worldbank.org/v2/country/AUS/indicator/GC.TAX.TOTL.GD.ZS?format=json&mrv=30 | https://api.worldbank.org/v2/country/AUS/indicator/FD.AST.PRVT.GD.ZS?format=json&mrv=30 | AP95: Tier 3 | AQ95: 2024-12-31 | AR95: providers=world_bank; fields=ppp_private_consumption, tax_rate_assumption, household_debt_proxy | AW95: https://api.worldbank.org/v2/country/AUS/indicator/SI.POV.GINI?format=json&mrv=30 | AX95: Tier 3 | AY95: 2020-12-31 | AZ95: providers=world_bank; fields=gini_coefficient | BE95: https://api.worldbank.org/v2/country/AUS/indicator/NY.GDP.PCAP.PP.CD?format=json&mrv=30 | https://api.worldbank.org/v2/country/AUS/indicator/NY.GDP.MKTP.KD.ZG?format=json&mrv=30 | BF95: Tier 3 | BG95: 2024-12-31 | BH95: providers=world_bank; fields=gdp_per_capita_ppp, gdp_growth
A96: au-melbourne | B96: Melbourne | C96: Australia | D96: Oceania | E96: primary | F96: provisional | M96: =IF(OR($G96="",$H96="",$I96="",$J96="",$K96="",$L96="",$AL96="",$AM96=""),"",((($G96*(1-$AM96))-$H96-$I96-$J96-$K96-$L96)/$AL96)) | P96: =IF($O96<>"",$O96,$AN96) | AI96: =IFERROR(INDEX(Country_Context!$B$2:$B$64,MATCH($C96,Country_Context!$A$2:$A$64,0)),"") | AJ96: =IFERROR(INDEX(Country_Context!$C$2:$C$64,MATCH($C96,Country_Context!$A$2:$A$64,0)),"") | AK96: =IFERROR(INDEX(Country_Context!$D$2:$D$64,MATCH($C96,Country_Context!$A$2:$A$64,0)),"") | AL96: =IFERROR(INDEX(Country_Context!$E$2:$E$64,MATCH($C96,Country_Context!$A$2:$A$64,0)),"") | AM96: =IFERROR(INDEX(Country_Context!$F$2:$F$64,MATCH($C96,Country_Context!$A$2:$A$64,0)),"") | AN96: =IFERROR(INDEX(Country_Context!$G$2:$G$64,MATCH($C96,Country_Context!$A$2:$A$64,0)),"") | AO96: https://api.worldbank.org/v2/country/AUS/indicator/PA.NUS.PRVT.PP?format=json&mrv=30 | https://api.worldbank.org/v2/country/AUS/indicator/GC.TAX.TOTL.GD.ZS?format=json&mrv=30 | https://api.worldbank.org/v2/country/AUS/indicator/FD.AST.PRVT.GD.ZS?format=json&mrv=30 | AP96: Tier 3 | AQ96: 2024-12-31 | AR96: providers=world_bank; fields=ppp_private_consumption, tax_rate_assumption, household_debt_proxy | AW96: https://api.worldbank.org/v2/country/AUS/indicator/SI.POV.GINI?format=json&mrv=30 | AX96: Tier 3 | AY96: 2020-12-31 | AZ96: providers=world_bank; fields=gini_coefficient | BE96: https://api.worldbank.org/v2/country/AUS/indicator/NY.GDP.PCAP.PP.CD?format=json&mrv=30 | https://api.worldbank.org/v2/country/AUS/indicator/NY.GDP.MKTP.KD.ZG?format=json&mrv=30 | BF96: Tier 3 | BG96: 2024-12-31 | BH96: providers=world_bank; fields=gdp_per_capita_ppp, gdp_growth
A97: au-brisbane | B97: Brisbane | C97: Australia | D97: Oceania | E97: primary | F97: locked | M97: =IF(OR($G97="",$H97="",$I97="",$J97="",$K97="",$L97="",$AL97="",$AM97=""),"",((($G97*(1-$AM97))-$H97-$I97-$J97-$K97-$L97)/$AL97)) | P97: =IF($O97<>"",$O97,$AN97) | AI97: =IFERROR(INDEX(Country_Context!$B$2:$B$64,MATCH($C97,Country_Context!$A$2:$A$64,0)),"") | AJ97: =IFERROR(INDEX(Country_Context!$C$2:$C$64,MATCH($C97,Country_Context!$A$2:$A$64,0)),"") | AK97: =IFERROR(INDEX(Country_Context!$D$2:$D$64,MATCH($C97,Country_Context!$A$2:$A$64,0)),"") | AL97: =IFERROR(INDEX(Country_Context!$E$2:$E$64,MATCH($C97,Country_Context!$A$2:$A$64,0)),"") | AM97: =IFERROR(INDEX(Country_Context!$F$2:$F$64,MATCH($C97,Country_Context!$A$2:$A$64,0)),"") | AN97: =IFERROR(INDEX(Country_Context!$G$2:$G$64,MATCH($C97,Country_Context!$A$2:$A$64,0)),"") | AO97: https://api.worldbank.org/v2/country/AUS/indicator/PA.NUS.PRVT.PP?format=json&mrv=30 | https://api.worldbank.org/v2/country/AUS/indicator/GC.TAX.TOTL.GD.ZS?format=json&mrv=30 | https://api.worldbank.org/v2/country/AUS/indicator/FD.AST.PRVT.GD.ZS?format=json&mrv=30 | AP97: Tier 3 | AQ97: 2024-12-31 | AR97: providers=world_bank; fields=ppp_private_consumption, tax_rate_assumption, household_debt_proxy | AW97: https://api.worldbank.org/v2/country/AUS/indicator/SI.POV.GINI?format=json&mrv=30 | AX97: Tier 3 | AY97: 2020-12-31 | AZ97: providers=world_bank; fields=gini_coefficient | BE97: https://api.worldbank.org/v2/country/AUS/indicator/NY.GDP.PCAP.PP.CD?format=json&mrv=30 | https://api.worldbank.org/v2/country/AUS/indicator/NY.GDP.MKTP.KD.ZG?format=json&mrv=30 | BF97: Tier 3 | BG97: 2024-12-31 | BH97: providers=world_bank; fields=gdp_per_capita_ppp, gdp_growth
A98: nz-wellington | B98: Wellington | C98: New Zealand | D98: Oceania | E98: primary | F98: locked | M98: =IF(OR($G98="",$H98="",$I98="",$J98="",$K98="",$L98="",$AL98="",$AM98=""),"",((($G98*(1-$AM98))-$H98-$I98-$J98-$K98-$L98)/$AL98)) | P98: =IF($O98<>"",$O98,$AN98) | AI98: =IFERROR(INDEX(Country_Context!$B$2:$B$64,MATCH($C98,Country_Context!$A$2:$A$64,0)),"") | AJ98: =IFERROR(INDEX(Country_Context!$C$2:$C$64,MATCH($C98,Country_Context!$A$2:$A$64,0)),"") | AK98: =IFERROR(INDEX(Country_Context!$D$2:$D$64,MATCH($C98,Country_Context!$A$2:$A$64,0)),"") | AL98: =IFERROR(INDEX(Country_Context!$E$2:$E$64,MATCH($C98,Country_Context!$A$2:$A$64,0)),"") | AM98: =IFERROR(INDEX(Country_Context!$F$2:$F$64,MATCH($C98,Country_Context!$A$2:$A$64,0)),"") | AN98: =IFERROR(INDEX(Country_Context!$G$2:$G$64,MATCH($C98,Country_Context!$A$2:$A$64,0)),"") | AO98: https://api.worldbank.org/v2/country/NZL/indicator/PA.NUS.PRVT.PP?format=json&mrv=30 | https://api.worldbank.org/v2/country/NZL/indicator/GC.TAX.TOTL.GD.ZS?format=json&mrv=30 | https://api.worldbank.org/v2/country/NZL/indicator/FD.AST.PRVT.GD.ZS?format=json&mrv=30 | AP98: Tier 3 | AQ98: 2024-12-31 | AR98: providers=world_bank; fields=ppp_private_consumption, tax_rate_assumption, household_debt_proxy | BE98: https://api.worldbank.org/v2/country/NZL/indicator/NY.GDP.PCAP.PP.CD?format=json&mrv=30 | https://api.worldbank.org/v2/country/NZL/indicator/NY.GDP.MKTP.KD.ZG?format=json&mrv=30 | BF98: Tier 3 | BG98: 2024-12-31 | BH98: providers=world_bank; fields=gdp_per_capita_ppp, gdp_growth
A99: au-perth | B99: Perth | C99: Australia | D99: Oceania | E99: secondary | F99: locked | M99: =IF(OR($G99="",$H99="",$I99="",$J99="",$K99="",$L99="",$AL99="",$AM99=""),"",((($G99*(1-$AM99))-$H99-$I99-$J99-$K99-$L99)/$AL99)) | P99: =IF($O99<>"",$O99,$AN99) | AI99: =IFERROR(INDEX(Country_Context!$B$2:$B$64,MATCH($C99,Country_Context!$A$2:$A$64,0)),"") | AJ99: =IFERROR(INDEX(Country_Context!$C$2:$C$64,MATCH($C99,Country_Context!$A$2:$A$64,0)),"") | AK99: =IFERROR(INDEX(Country_Context!$D$2:$D$64,MATCH($C99,Country_Context!$A$2:$A$64,0)),"") | AL99: =IFERROR(INDEX(Country_Context!$E$2:$E$64,MATCH($C99,Country_Context!$A$2:$A$64,0)),"") | AM99: =IFERROR(INDEX(Country_Context!$F$2:$F$64,MATCH($C99,Country_Context!$A$2:$A$64,0)),"") | AN99: =IFERROR(INDEX(Country_Context!$G$2:$G$64,MATCH($C99,Country_Context!$A$2:$A$64,0)),"") | AO99: https://api.worldbank.org/v2/country/AUS/indicator/PA.NUS.PRVT.PP?format=json&mrv=30 | https://api.worldbank.org/v2/country/AUS/indicator/GC.TAX.TOTL.GD.ZS?format=json&mrv=30 | https://api.worldbank.org/v2/country/AUS/indicator/FD.AST.PRVT.GD.ZS?format=json&mrv=30 | AP99: Tier 3 | AQ99: 2024-12-31 | AR99: providers=world_bank; fields=ppp_private_consumption, tax_rate_assumption, household_debt_proxy | AW99: https://api.worldbank.org/v2/country/AUS/indicator/SI.POV.GINI?format=json&mrv=30 | AX99: Tier 3 | AY99: 2020-12-31 | AZ99: providers=world_bank; fields=gini_coefficient | BE99: https://api.worldbank.org/v2/country/AUS/indicator/NY.GDP.PCAP.PP.CD?format=json&mrv=30 | https://api.worldbank.org/v2/country/AUS/indicator/NY.GDP.MKTP.KD.ZG?format=json&mrv=30 | BF99: Tier 3 | BG99: 2024-12-31 | BH99: providers=world_bank; fields=gdp_per_capita_ppp, gdp_growth
A100: au-adelaide | B100: Adelaide | C100: Australia | D100: Oceania | E100: secondary | F100: locked | M100: =IF(OR($G100="",$H100="",$I100="",$J100="",$K100="",$L100="",$AL100="",$AM100=""),"",((($G100*(1-$AM100))-$H100-$I100-$J100-$K100-$L100)/$AL100)) | P100: =IF($O100<>"",$O100,$AN100) | AI100: =IFERROR(INDEX(Country_Context!$B$2:$B$64,MATCH($C100,Country_Context!$A$2:$A$64,0)),"") | AJ100: =IFERROR(INDEX(Country_Context!$C$2:$C$64,MATCH($C100,Country_Context!$A$2:$A$64,0)),"") | AK100: =IFERROR(INDEX(Country_Context!$D$2:$D$64,MATCH($C100,Country_Context!$A$2:$A$64,0)),"") | AL100: =IFERROR(INDEX(Country_Context!$E$2:$E$64,MATCH($C100,Country_Context!$A$2:$A$64,0)),"") | AM100: =IFERROR(INDEX(Country_Context!$F$2:$F$64,MATCH($C100,Country_Context!$A$2:$A$64,0)),"") | AN100: =IFERROR(INDEX(Country_Context!$G$2:$G$64,MATCH($C100,Country_Context!$A$2:$A$64,0)),"") | AO100: https://api.worldbank.org/v2/country/AUS/indicator/PA.NUS.PRVT.PP?format=json&mrv=30 | https://api.worldbank.org/v2/country/AUS/indicator/GC.TAX.TOTL.GD.ZS?format=json&mrv=30 | https://api.worldbank.org/v2/country/AUS/indicator/FD.AST.PRVT.GD.ZS?format=json&mrv=30 | AP100: Tier 3 | AQ100: 2024-12-31 | AR100: providers=world_bank; fields=ppp_private_consumption, tax_rate_assumption, household_debt_proxy | AW100: https://api.worldbank.org/v2/country/AUS/indicator/SI.POV.GINI?format=json&mrv=30 | AX100: Tier 3 | AY100: 2020-12-31 | AZ100: providers=world_bank; fields=gini_coefficient | BE100: https://api.worldbank.org/v2/country/AUS/indicator/NY.GDP.PCAP.PP.CD?format=json&mrv=30 | https://api.worldbank.org/v2/country/AUS/indicator/NY.GDP.MKTP.KD.ZG?format=json&mrv=30 | BF100: Tier 3 | BG100: 2024-12-31 | BH100: providers=world_bank; fields=gdp_per_capita_ppp, gdp_growth
A101: au-hobart | B101: Hobart | C101: Australia | D101: Oceania | E101: secondary | F101: locked | M101: =IF(OR($G101="",$H101="",$I101="",$J101="",$K101="",$L101="",$AL101="",$AM101=""),"",((($G101*(1-$AM101))-$H101-$I101-$J101-$K101-$L101)/$AL101)) | P101: =IF($O101<>"",$O101,$AN101) | AI101: =IFERROR(INDEX(Country_Context!$B$2:$B$64,MATCH($C101,Country_Context!$A$2:$A$64,0)),"") | AJ101: =IFERROR(INDEX(Country_Context!$C$2:$C$64,MATCH($C101,Country_Context!$A$2:$A$64,0)),"") | AK101: =IFERROR(INDEX(Country_Context!$D$2:$D$64,MATCH($C101,Country_Context!$A$2:$A$64,0)),"") | AL101: =IFERROR(INDEX(Country_Context!$E$2:$E$64,MATCH($C101,Country_Context!$A$2:$A$64,0)),"") | AM101: =IFERROR(INDEX(Country_Context!$F$2:$F$64,MATCH($C101,Country_Context!$A$2:$A$64,0)),"") | AN101: =IFERROR(INDEX(Country_Context!$G$2:$G$64,MATCH($C101,Country_Context!$A$2:$A$64,0)),"") | AO101: https://api.worldbank.org/v2/country/AUS/indicator/PA.NUS.PRVT.PP?format=json&mrv=30 | https://api.worldbank.org/v2/country/AUS/indicator/GC.TAX.TOTL.GD.ZS?format=json&mrv=30 | https://api.worldbank.org/v2/country/AUS/indicator/FD.AST.PRVT.GD.ZS?format=json&mrv=30 | AP101: Tier 3 | AQ101: 2024-12-31 | AR101: providers=world_bank; fields=ppp_private_consumption, tax_rate_assumption, household_debt_proxy | AW101: https://api.worldbank.org/v2/country/AUS/indicator/SI.POV.GINI?format=json&mrv=30 | AX101: Tier 3 | AY101: 2020-12-31 | AZ101: providers=world_bank; fields=gini_coefficient | BE101: https://api.worldbank.org/v2/country/AUS/indicator/NY.GDP.PCAP.PP.CD?format=json&mrv=30 | https://api.worldbank.org/v2/country/AUS/indicator/NY.GDP.MKTP.KD.ZG?format=json&mrv=30 | BF101: Tier 3 | BG101: 2024-12-31 | BH101: providers=world_bank; fields=gdp_per_capita_ppp, gdp_growth
A102: nz-christchurch | B102: Christchurch | C102: New Zealand | D102: Oceania | E102: secondary | F102: provisional | M102: =IF(OR($G102="",$H102="",$I102="",$J102="",$K102="",$L102="",$AL102="",$AM102=""),"",((($G102*(1-$AM102))-$H102-$I102-$J102-$K102-$L102)/$AL102)) | P102: =IF($O102<>"",$O102,$AN102) | AI102: =IFERROR(INDEX(Country_Context!$B$2:$B$64,MATCH($C102,Country_Context!$A$2:$A$64,0)),"") | AJ102: =IFERROR(INDEX(Country_Context!$C$2:$C$64,MATCH($C102,Country_Context!$A$2:$A$64,0)),"") | AK102: =IFERROR(INDEX(Country_Context!$D$2:$D$64,MATCH($C102,Country_Context!$A$2:$A$64,0)),"") | AL102: =IFERROR(INDEX(Country_Context!$E$2:$E$64,MATCH($C102,Country_Context!$A$2:$A$64,0)),"") | AM102: =IFERROR(INDEX(Country_Context!$F$2:$F$64,MATCH($C102,Country_Context!$A$2:$A$64,0)),"") | AN102: =IFERROR(INDEX(Country_Context!$G$2:$G$64,MATCH($C102,Country_Context!$A$2:$A$64,0)),"") | AO102: https://api.worldbank.org/v2/country/NZL/indicator/PA.NUS.PRVT.PP?format=json&mrv=30 | https://api.worldbank.org/v2/country/NZL/indicator/GC.TAX.TOTL.GD.ZS?format=json&mrv=30 | https://api.worldbank.org/v2/country/NZL/indicator/FD.AST.PRVT.GD.ZS?format=json&mrv=30 | AP102: Tier 3 | AQ102: 2024-12-31 | AR102: providers=world_bank; fields=ppp_private_consumption, tax_rate_assumption, household_debt_proxy | BE102: https://api.worldbank.org/v2/country/NZL/indicator/NY.GDP.PCAP.PP.CD?format=json&mrv=30 | https://api.worldbank.org/v2/country/NZL/indicator/NY.GDP.MKTP.KD.ZG?format=json&mrv=30 | BF102: Tier 3 | BG102: 2024-12-31 | BH102: providers=world_bank; fields=gdp_per_capita_ppp, gdp_growth
A103: fj-suva | B103: Suva | C103: Fiji | D103: Oceania | E103: secondary | F103: locked | M103: =IF(OR($G103="",$H103="",$I103="",$J103="",$K103="",$L103="",$AL103="",$AM103=""),"",((($G103*(1-$AM103))-$H103-$I103-$J103-$K103-$L103)/$AL103)) | P103: =IF($O103<>"",$O103,$AN103) | AI103: =IFERROR(INDEX(Country_Context!$B$2:$B$64,MATCH($C103,Country_Context!$A$2:$A$64,0)),"") | AJ103: =IFERROR(INDEX(Country_Context!$C$2:$C$64,MATCH($C103,Country_Context!$A$2:$A$64,0)),"") | AK103: =IFERROR(INDEX(Country_Context!$D$2:$D$64,MATCH($C103,Country_Context!$A$2:$A$64,0)),"") | AL103: =IFERROR(INDEX(Country_Context!$E$2:$E$64,MATCH($C103,Country_Context!$A$2:$A$64,0)),"") | AM103: =IFERROR(INDEX(Country_Context!$F$2:$F$64,MATCH($C103,Country_Context!$A$2:$A$64,0)),"") | AN103: =IFERROR(INDEX(Country_Context!$G$2:$G$64,MATCH($C103,Country_Context!$A$2:$A$64,0)),"") | AO103: https://api.worldbank.org/v2/country/FJI/indicator/PA.NUS.PRVT.PP?format=json&mrv=30 | https://api.worldbank.org/v2/country/FJI/indicator/GC.TAX.TOTL.GD.ZS?format=json&mrv=30 | https://api.worldbank.org/v2/country/FJI/indicator/FD.AST.PRVT.GD.ZS?format=json&mrv=30 | AP103: Tier 3 | AQ103: 2024-12-31 | AR103: providers=world_bank; fields=ppp_private_consumption, tax_rate_assumption, household_debt_proxy | AW103: https://api.worldbank.org/v2/country/FJI/indicator/SI.POV.GINI?format=json&mrv=30 | AX103: Tier 3 | AY103: 2019-12-31 | AZ103: providers=world_bank; fields=gini_coefficient | BE103: https://api.worldbank.org/v2/country/FJI/indicator/NY.GDP.PCAP.PP.CD?format=json&mrv=30 | https://api.worldbank.org/v2/country/FJI/indicator/NY.GDP.MKTP.KD.ZG?format=json&mrv=30 | BF103: Tier 3 | BG103: 2024-12-31 | BH103: providers=world_bank; fields=gdp_per_capita_ppp, gdp_growth

Sheet Norm_Stats
A1: input_key | B1: label | C1: source_column | D1: directionality | E1: coverage_weight | F1: p05 | G1: p95 | H1: notes
A2: di_ppp_raw | B2: Tax-adjusted PPP disposable income raw | C2: di_ppp_raw | D2: positive | E2: 1 | F2: =IF(COUNT(City_Inputs!$M$2:$M$103)>=2,PERCENTILE.INC(City_Inputs!$M$2:$M$103,0.05),"") | G2: =IF(COUNT(City_Inputs!$M$2:$M$103)>=2,PERCENTILE.INC(City_Inputs!$M$2:$M$103,0.95),"") | H2: Derived in City_Inputs from country context and essential-cost deductions.
A3: housing_burden_raw | B3: Housing burden raw | C3: housing_burden_raw | D3: negative | E3: 1 | F3: =IF(COUNT(City_Inputs!$N$2:$N$103)>=2,PERCENTILE.INC(City_Inputs!$N$2:$N$103,0.05),"") | G3: =IF(COUNT(City_Inputs!$N$2:$N$103)>=2,PERCENTILE.INC(City_Inputs!$N$2:$N$103,0.95),"") | H3: Higher housing share scores worse.
A4: household_debt_effective_raw | B4: Household debt effective raw | C4: household_debt_effective_raw | D4: negative | E4: 1 | F4: =IF(COUNT(City_Inputs!$P$2:$P$103)>=2,PERCENTILE.INC(City_Inputs!$P$2:$P$103,0.05),"") | G4: =IF(COUNT(City_Inputs!$P$2:$P$103)>=2,PERCENTILE.INC(City_Inputs!$P$2:$P$103,0.95),"") | H4: Uses country proxy where city debt burden is missing.
A5: working_time_pressure_raw | B5: Working time pressure raw | C5: working_time_pressure_raw | D5: negative | E5: 1 | F5: =IF(COUNT(City_Inputs!$Q$2:$Q$103)>=2,PERCENTILE.INC(City_Inputs!$Q$2:$Q$103,0.05),"") | G5: =IF(COUNT(City_Inputs!$Q$2:$Q$103)>=2,PERCENTILE.INC(City_Inputs!$Q$2:$Q$103,0.95),"") | H5: Higher weekly work burden scores worse.
A6: suicide_mental_strain_raw | B6: Suicide and mental strain raw | C6: suicide_mental_strain_raw | D6: negative | E6: 1 | F6: =IF(COUNT(City_Inputs!$R$2:$R$103)>=2,PERCENTILE.INC(City_Inputs!$R$2:$R$103,0.05),"") | G6: =IF(COUNT(City_Inputs!$R$2:$R$103)>=2,PERCENTILE.INC(City_Inputs!$R$2:$R$103,0.95),"") | H6: Higher suicide or strain proxy scores worse.
A7: personal_safety_raw | B7: Personal safety harm raw | C7: personal_safety_raw | D7: negative | E7: 1 | F7: =IF(COUNT(City_Inputs!$S$2:$S$103)>=2,PERCENTILE.INC(City_Inputs!$S$2:$S$103,0.05),"") | G7: =IF(COUNT(City_Inputs!$S$2:$S$103)>=2,PERCENTILE.INC(City_Inputs!$S$2:$S$103,0.95),"") | H7: Higher harm or victimization scores worse.
A8: transit_access_commute_raw | B8: Transit access and commute raw | C8: transit_access_commute_raw | D8: positive | E8: 1 | F8: =IF(COUNT(City_Inputs!$T$2:$T$103)>=2,PERCENTILE.INC(City_Inputs!$T$2:$T$103,0.05),"") | G8: =IF(COUNT(City_Inputs!$T$2:$T$103)>=2,PERCENTILE.INC(City_Inputs!$T$2:$T$103,0.95),"") | H8: Higher access/lower burden composite scores better.
A9: clean_air_raw | B9: Clean air raw | C9: clean_air_raw | D9: negative | E9: 1 | F9: =IF(COUNT(City_Inputs!$U$2:$U$103)>=2,PERCENTILE.INC(City_Inputs!$U$2:$U$103,0.05),"") | G9: =IF(COUNT(City_Inputs!$U$2:$U$103)>=2,PERCENTILE.INC(City_Inputs!$U$2:$U$103,0.95),"") | H9: Higher PM2.5 or pollution exposure scores worse.
A10: water_sanitation_utility_raw | B10: Water, sanitation, and utility reliability raw | C10: water_sanitation_utility_raw | D10: positive | E10: 1 | F10: =IF(COUNT(City_Inputs!$V$2:$V$103)>=2,PERCENTILE.INC(City_Inputs!$V$2:$V$103,0.05),"") | G10: =IF(COUNT(City_Inputs!$V$2:$V$103)>=2,PERCENTILE.INC(City_Inputs!$V$2:$V$103,0.95),"") | H10: Higher safe-service composite scores better.
A11: digital_infrastructure_raw | B11: Digital infrastructure raw | C11: digital_infrastructure_raw | D11: positive | E11: 1 | F11: =IF(COUNT(City_Inputs!$W$2:$W$103)>=2,PERCENTILE.INC(City_Inputs!$W$2:$W$103,0.05),"") | G11: =IF(COUNT(City_Inputs!$W$2:$W$103)>=2,PERCENTILE.INC(City_Inputs!$W$2:$W$103,0.95),"") | H11: Higher digital quality and affordability score better.
A12: healthcare_quality_raw | B12: Healthcare quality raw | C12: healthcare_quality_raw | D12: positive | E12: 1 | F12: =IF(COUNT(City_Inputs!$X$2:$X$103)>=2,PERCENTILE.INC(City_Inputs!$X$2:$X$103,0.05),"") | G12: =IF(COUNT(City_Inputs!$X$2:$X$103)>=2,PERCENTILE.INC(City_Inputs!$X$2:$X$103,0.95),"") | H12: Higher effective-care quality scores better.
A13: education_quality_raw | B13: Education quality raw | C13: education_quality_raw | D13: positive | E13: 1 | F13: =IF(COUNT(City_Inputs!$Y$2:$Y$103)>=2,PERCENTILE.INC(City_Inputs!$Y$2:$Y$103,0.05),"") | G13: =IF(COUNT(City_Inputs!$Y$2:$Y$103)>=2,PERCENTILE.INC(City_Inputs!$Y$2:$Y$103,0.95),"") | H13: Higher learning quality scores better.
A14: equal_opportunity_raw | B14: Equal opportunity raw | C14: equal_opportunity_raw | D14: positive | E14: 0.7 | F14: =IF(COUNT(City_Inputs!$Z$2:$Z$103)>=2,PERCENTILE.INC(City_Inputs!$Z$2:$Z$103,0.05),"") | G14: =IF(COUNT(City_Inputs!$Z$2:$Z$103)>=2,PERCENTILE.INC(City_Inputs!$Z$2:$Z$103,0.95),"") | H14: Primary opportunity component.
A15: gini_coefficient_context | B15: Gini coefficient context raw | C15: gini_coefficient_context | D15: negative | E15: 0.3 | F15: =IF(COUNT(City_Inputs!$AK$2:$AK$103)>=2,PERCENTILE.INC(City_Inputs!$AK$2:$AK$103,0.05),"") | G15: =IF(COUNT(City_Inputs!$AK$2:$AK$103)>=2,PERCENTILE.INC(City_Inputs!$AK$2:$AK$103,0.95),"") | H15: Country-context fairness component.
A16: hospitality_belonging_raw | B16: Hospitality and belonging raw | C16: hospitality_belonging_raw | D16: positive | E16: 1 | F16: =IF(COUNT(City_Inputs!$AA$2:$AA$103)>=2,PERCENTILE.INC(City_Inputs!$AA$2:$AA$103,0.05),"") | G16: =IF(COUNT(City_Inputs!$AA$2:$AA$103)>=2,PERCENTILE.INC(City_Inputs!$AA$2:$AA$103,0.95),"") | H16: Higher civic warmth and belonging scores better.
A17: tolerance_pluralism_raw | B17: Tolerance and pluralism raw | C17: tolerance_pluralism_raw | D17: positive | E17: 1 | F17: =IF(COUNT(City_Inputs!$AB$2:$AB$103)>=2,PERCENTILE.INC(City_Inputs!$AB$2:$AB$103,0.05),"") | G17: =IF(COUNT(City_Inputs!$AB$2:$AB$103)>=2,PERCENTILE.INC(City_Inputs!$AB$2:$AB$103,0.95),"") | H17: Higher coexistence and openness scores better.
A18: cultural_public_life_raw | B18: Cultural, historic, and public-life vitality raw | C18: cultural_public_life_raw | D18: positive | E18: 1 | F18: =IF(COUNT(City_Inputs!$AC$2:$AC$103)>=2,PERCENTILE.INC(City_Inputs!$AC$2:$AC$103,0.05),"") | G18: =IF(COUNT(City_Inputs!$AC$2:$AC$103)>=2,PERCENTILE.INC(City_Inputs!$AC$2:$AC$103,0.95),"") | H18: Higher everyday cultural vitality scores better.
A19: entrepreneurial_dynamism_raw | B19: Entrepreneurial dynamism raw | C19: entrepreneurial_dynamism_raw | D19: positive | E19: 1 | F19: =IF(COUNT(City_Inputs!$AD$2:$AD$103)>=2,PERCENTILE.INC(City_Inputs!$AD$2:$AD$103,0.05),"") | G19: =IF(COUNT(City_Inputs!$AD$2:$AD$103)>=2,PERCENTILE.INC(City_Inputs!$AD$2:$AD$103,0.95),"") | H19: Higher new-business dynamism scores better.
A20: innovation_research_intensity_raw | B20: Innovation and research intensity raw | C20: innovation_research_intensity_raw | D20: positive | E20: 1 | F20: =IF(COUNT(City_Inputs!$AE$2:$AE$103)>=2,PERCENTILE.INC(City_Inputs!$AE$2:$AE$103,0.05),"") | G20: =IF(COUNT(City_Inputs!$AE$2:$AE$103)>=2,PERCENTILE.INC(City_Inputs!$AE$2:$AE$103,0.95),"") | H20: Higher research strength scores better.
A21: investment_signal_raw | B21: Investment signal raw | C21: investment_signal_raw | D21: positive | E21: 0.5 | F21: =IF(COUNT(City_Inputs!$AF$2:$AF$103)>=2,PERCENTILE.INC(City_Inputs!$AF$2:$AF$103,0.05),"") | G21: =IF(COUNT(City_Inputs!$AF$2:$AF$103)>=2,PERCENTILE.INC(City_Inputs!$AF$2:$AF$103,0.95),"") | H21: Primary city-level productive-energy signal.
A22: gdp_per_capita_ppp_context | B22: GDP per capita PPP context raw | C22: gdp_per_capita_ppp_context | D22: positive | E22: 0.3 | F22: =IF(COUNT(City_Inputs!$AI$2:$AI$103)>=2,PERCENTILE.INC(City_Inputs!$AI$2:$AI$103,0.05),"") | G22: =IF(COUNT(City_Inputs!$AI$2:$AI$103)>=2,PERCENTILE.INC(City_Inputs!$AI$2:$AI$103,0.95),"") | H22: Capped country macro context.
A23: gdp_growth_context | B23: GDP growth context raw | C23: gdp_growth_context | D23: positive | E23: 0.2 | F23: =IF(COUNT(City_Inputs!$AJ$2:$AJ$103)>=2,PERCENTILE.INC(City_Inputs!$AJ$2:$AJ$103,0.05),"") | G23: =IF(COUNT(City_Inputs!$AJ$2:$AJ$103)>=2,PERCENTILE.INC(City_Inputs!$AJ$2:$AJ$103,0.95),"") | H23: Capped country momentum context.
A24: administrative_investment_friction_raw | B24: Administrative and investment friction raw | C24: administrative_investment_friction_raw | D24: negative | E24: 1 | F24: =IF(COUNT(City_Inputs!$AG$2:$AG$103)>=2,PERCENTILE.INC(City_Inputs!$AG$2:$AG$103,0.05),"") | G24: =IF(COUNT(City_Inputs!$AG$2:$AG$103)>=2,PERCENTILE.INC(City_Inputs!$AG$2:$AG$103,0.95),"") | H24: Higher business friction scores worse.

Sheet Scores
A1: city_id | B1: display_name | C1: country | D1: cohort | E1: manifest_status | F1: city_type | G1: pressure_disposable_income_ppp_score | H1: pressure_disposable_income_ppp_coverage | I1: pressure_housing_burden_score | J1: pressure_housing_burden_coverage | K1: pressure_household_debt_burden_score | L1: pressure_household_debt_burden_coverage | M1: pressure_working_time_pressure_score | N1: pressure_working_time_pressure_coverage | O1: pressure_suicide_mental_strain_score | P1: pressure_suicide_mental_strain_coverage | Q1: pressure_pillar_score | R1: pressure_pillar_coverage | S1: viability_personal_safety_score | T1: viability_personal_safety_coverage | U1: viability_transit_access_commute_score | V1: viability_transit_access_commute_coverage | W1: viability_clean_air_score | X1: viability_clean_air_coverage | Y1: viability_water_sanitation_utility_score | Z1: viability_water_sanitation_utility_coverage | AA1: viability_digital_infrastructure_score | AB1: viability_digital_infrastructure_coverage | AC1: viability_pillar_score | AD1: viability_pillar_coverage | AE1: capability_healthcare_quality_score | AF1: capability_healthcare_quality_coverage | AG1: capability_education_quality_score | AH1: capability_education_quality_coverage | AI1: capability_equal_opportunity_distributional_fairness_score | AJ1: capability_equal_opportunity_distributional_fairness_coverage | AK1: capability_pillar_score | AL1: capability_pillar_coverage | AM1: community_hospitality_belonging_score | AN1: community_hospitality_belonging_coverage | AO1: community_tolerance_pluralism_score | AP1: community_tolerance_pluralism_coverage | AQ1: community_cultural_historic_public_life_vitality_score | AR1: community_cultural_historic_public_life_vitality_coverage | AS1: community_pillar_score | AT1: community_pillar_coverage | AU1: creative_entrepreneurial_dynamism_score | AV1: creative_entrepreneurial_dynamism_coverage | AW1: creative_innovation_research_intensity_score | AX1: creative_innovation_research_intensity_coverage | AY1: creative_economic_vitality_productive_context_score | AZ1: creative_economic_vitality_productive_context_coverage | BA1: creative_administrative_investment_friction_score | BB1: creative_administrative_investment_friction_coverage | BC1: creative_pillar_score | BD1: creative_pillar_coverage | BE1: overall_weighted_coverage | BF1: coverage_grade | BG1: ranking_status | BH1: slic_score | BI1: rank | BJ1: visitor_flow_context_raw
